Workbook

Sheet AMB-Index
A1: Ambuja Cements Ltd: Business Analysis and Valuation
A2: CONSOLIDATED basis. Rs crore unless stated. FYE 31 March. Valuation date 31 March 2026.
A4: No. | B4: Sheet | C4: What it contains
A5: 1 | B5: Source-Log | C5: Every input traced to its publisher. Open items and re-source flags in red.
A6: 2 | B6: Source-Data | C6: FY2024-25 and FY2025-26 consolidated actuals, exactly as reported, plus derived ratios.
A7: 3 | B7: Assumptions | C7: All drivers in one place. Blue on yellow means edit here.
A8: 4 | B8: PnL-Forecast | C8: Ten year forecast built on capacity times utilisation and EBITDA per tonne.
A9: 5 | B9: Invested-Capital | C9: Invested capital roll forward separating goodwill from operating capital, and the ROIC path.
A10: 6 | B10: Cost-of-Capital | C10: Risk free, ERP, bottom up beta, WACC and the unlevered rate rho.
A11: 7 | B11: FCFF | C11: Enterprise DCF at WACC.
A12: 8 | B12: CCF | C12: Capital cash flow at rho.
A13: 9 | B13: APV | C13: Unlevered value plus the tax shield.
A14: 10 | B14: FCFE | C14: Equity DCF at the cost of equity.
A15: 11 | B15: EVA | C15: Opening invested capital plus the present value of future EVA.
A16: 12 | B16: Reconciliation | C16: Proof the five methods agree.
... A19: 15 | B19: Summary | C19: Valuation summary, the merger adjustment, and the conclusion.
A21: Why this model differs from the UltraTech model
B22: CONSOLIDATED, not standalone. Ambuja standalone is roughly 60% of the group and excludes ACC entirely, so dividing a group market capitalisation by standalone EBITDA overstates the multiple badly. Ambuja is also merging ACC, Orient, Sanghi and Penna into itself, after which one consolidated entity is the only sensible unit.
B23: TEN year explicit forecast, not five. Ambuja runs at about 68% capacity utilisation against UltraTech's 82%, and its return on capital is far below its cost of capital today. A five year window ends before the ramp has played out and throws almost the entire value into the terminal period. The course treats a longer explicit period as the standard answer for a difficult to value company.
B24: GOODWILL is separated from operating invested capital. Acquisitions left Rs 22,979 crore of goodwill and intangibles on the balance sheet. It belongs in invested capital when measuring the return shareholders earn on what they paid, but it must NOT be grown at g in the terminal reinvestment, because organic growth does not require buying more goodwill. Getting this wrong understated the value by about Rs 46 per share.
B25: NON-CONTROLLING INTEREST of Rs 12,499 crore is deducted in the bridge, because consolidated cash flows include 100% of subsidiaries the parent does not wholly own. Post merger this reverses and the share count rises 13.7% instead. Both routes are shown on the Summary sheet and should give a similar answer.
B26: KNOWN INCONSISTENCY WITH THE ULTRATECH MODEL, stated openly. UltraTech holds 74.99% of the listed India Cements and is valued STANDALONE with that stake added at book. Ambuja holds 50.05% of the listed ACC and is valued CONSOLIDATED. Two companies in the same structural position are treated two different ways, and the reason is data availability rather than principle: UltraTech publishes a ten year standalone history and no comparable consolidated one, while Ambuja's consolidated statements were available and its standalone accounts exclude more than a third of the business. The irony is that UltraTech's stake is the MORE controlling of the two. Before submission, either consolidate both or value both by sum of parts. Until then this is a disclosed weakness, not a hidden one.
A28: Read before using any number
B29: The Indian 10 year G-Sec yield is still a PLACEHOLDER at 6.50% and must come from RBI or FBIL.
B30: Consolidated history is only two years deep here, FY2024-25 restated and FY2025-26, because that is what the annual report provides. Earlier consolidated years exist only in broker research, which is not an authorised source. The ROIC trend is therefore asserted from two points, which is thin. Say so in the report.
B31: Ambuja's reported tax line is a CREDIT, so reported PAT exceeds PBT. All returns here are computed at the statutory rate of 25.168%, never at the reported effective rate of minus 71%.

Sheet AMB-Audit Log
A1: Source Log
A3: # | B3: Item | C3: Publisher | D3: Source and location | E3: Accessed | F3: Period | G3: Feeds
A4: 1 | B4: Consolidated Statement of Profit and Loss | C4: Ambuja Cements Ltd | D4: Integrated Annual Report 2025-26, consolidated P&L | E4: 2026-08-26 | F4: FY26 and FY25 restated | G4: Source-Data
A5: 2 | B5: Consolidated Balance Sheet | C5: Ambuja Cements Ltd | D5: Same report, consolidated balance sheet | E5: 2026-08-26 | F5: 31-Mar-2026 | G5: Source-Data, Assumptions
A6: 3 | B6: Consolidated highlights: volume | C6: Ambuja Cements Ltd | D6: Same report, Growth Trajectory: cement sales volume 74 million tonnes, revenue Rs 40,656 cr | E6: 2026-08-26 | F6: FY2025-26 | G6: Assumptions, opening position
A7: 4 | B7: Capacity 109 MTPA, target 119 MTPA | C7: Ambuja Cements Ltd | D7: Same report: current capacity of 109 MTPA and a targeted capacity of 119 MTPA | E7: 2026-08-26 | F7: FY2025-26 | G7: Assumptions, capacity
A8: 5 | B8: Market capitalisation Rs 99,095 cr | C8: Ambuja Cements Ltd | D8: Same report, highlights, as at 31 March 2026 (last traded 30 March) | E8: 2026-08-26 | F8: 30-Mar-2026 | G8: Assumptions
A9: 6 | B9: Holding in ACC 50.05% | C9: Ambuja Cements Ltd | D9: Same report, subsidiary listing | E9: 2026-08-26 | F9: 31-Mar-2026 | G9: Merger note
A10: 7 | B10: Tax note 32(ii) | C10: Ambuja Cements Ltd | D10: Rs 1,179.71 cr of earlier year provisions released on favourable High Court decisions, plus Rs 71.05 cr revision of the FY25 provision | E10: 2026-08-26 | F10: FY2025-26 | G10: Tax normalisation
A11: 8 | B11: India ERP 7.08%, default spread 1.87% | C11: Damodaran, NYU Stern | D11: Country Default Spreads and Risk Premiums, January 2026 | E11: 2026-08-26 | F11: Jan-2026 | G11: Cost-of-Capital
A12: 9 | B12: Unlevered beta 0.90 | C12: Damodaran, NYU Stern | D12: Betas by Sector (Global), January 2026, Building Materials, corrected for cash | E12: 2026-08-26 | F12: Jan-2026 | G12: Cost-of-Capital
A13: 10 | B13: ASSUMPTION: tax 25.168% | C13: Own assumption | D13: Section 115BAA. Used because the reported effective rate is negative and unusable. | E13: 2026-08-26 | F13: FY2025-26 | G13: Throughout
A14: 11 | B14: 10 year G-Sec par yield 6.85% | C14: RBI / FBIL | D14: Ratios and Rates release dated 27-Mar-2026: 10-Year G-Sec Par Yield (FBIL), week ended 20-Mar-2026. Last weekly print before the valuation date, so it matches the market and balance sheet dates exactly. | E14: 2026-08-27 | F14: Week ended 20-Mar-2026 | G14: Cost-of-Capital
A15: 12 | B15: RE-SOURCE: merger terms and dilution | C15: Ambuja filings | D15: Swap ratios of 325 Ambuja per 100 ACC and 33 per 100 Orient, 13.7% dilution, promoter holding 67.65% to 60.94%. These reached the model through BROKER research, which is not an authorised source. Re-source from the scheme filing. | E15: 2026-08-26 | F15: Dec-2025 | G15: Summary, merger note
A16: 13 | B16: NOT USED: broker forecasts | C16: HDFC Securities | D16: Their December 2025 FY26E EBITDA of Rs 8,477 cr came in at Rs 6,539 cr actual, a 30% miss, on a revenue estimate that was accurate to 2.7%. Facts used, forecasts rejected. | E16: 2026-08-26 | F16: Dec-2025 | G16: Sensitivity, commentary
A18: No data in this workbook comes from moneycontrol, screener.in, Yahoo Finance or any other aggregator.
A21: MODEL AUDIT LOG: issues found during the build, and what was done about them
A22: # | B22: Where | C22: Severity | D22: Finding | E22: Valuation impact | F22: Fix applied
A23: 1 | B23: Balance Sheet, depreciation | C23: HIGH | D23: Depreciation is charged at 8.0% of OPERATING fixed assets, but the historical charge includes amortisation of the Rs 9,433 cr intangible balance, which the model holds flat and never amortises. Charge and base do not match. | E23: Small but the inconsistency is real | F23: DOCUMENTED, NOT FIXED. Splitting the charge into PPE depreciation and intangible amortisation requires a disclosed split of the two in the notes, which was not obtained. Flagged as a PARTIAL on the Dashboard.
A24: 2 | B24: Relative Valuation, peer basis | C24: MED | D24: Ambuja is carried CONSOLIDATED and every peer STANDALONE, so the multiples are not strictly comparable. | E24: Ambuja's EV/EBITDA would print 34x on the wrong pairing against 17.0x on the right one | F24: FIXED AND DISCLOSED. Non-controlling interest is added to enterprise value and a basis row labels every company. For the other four companies standalone and consolidated differ by under 10%, so the mismatch does not arise.
A25: 3 | B25: Terminal, ROIC spread | C25: MED | D25: Terminal ROIC needed to be shown against WACC to satisfy Golden Check 6. | E25: None; the check passes | F25: FIXED. Terminal ROIC of 11.9% against a WACC of 11.375% is a spread of 0.55 points, documented on the Terminal sheet and the Dashboard.
A26: 4 | B26: Model build, goodwill in terminal | C26: HIGH | D26: Terminal reinvestment was charged on invested capital INCLUDING goodwill, which assumes the company must keep buying goodwill forever merely to grow. | E26: Drove the equity value NEGATIVE | F26: FIXED. Terminal reinvestment is charged on OPERATING invested capital only. Worth about Rs 46 per share.
A27: 5 | B27: Model build, forecast horizon | C27: HIGH | D27: A five year explicit horizon ended before the utilisation ramp had played out. | E27: Understated value by roughly Rs 83 per share | F27: FIXED. Extended to a ten year explicit forecast, which is the standard treatment for a difficult to value company.
A28: 6 | B28: Assumptions, terminal growth | C28: HIGH | D28: Terminal growth was originally set LOWER than UltraTech's on the reasoning that a company earning below its cost of capital is worth more if it grows less. That reasoning was result driven AND factually backwards. | E28: Material | F28: FIXED. Both companies now use the same fraction of nominal GDP. Terminal growth is 6.99%, being 65% of nominal GDP of 10.76%.
A29: 7 | B29: Tax normalisation | C29: HIGH | D29: The reported tax line is a net CREDIT of Rs 2,338 cr, so reported profit exceeds pre-tax profit and the effective rate is minus 71%. | E29: Would overstate every return measure | F29: FIXED. All returns are computed at the statutory 25.168%. The credit is decomposed into three drivers on the Normalize sheet, net effect minus Rs 11.54 per share.
A31: Every entry above was found by us during the build, not by a reviewer afterwards. Where an item is marked PARTIALLY FIXED or DOCUMENTED NOT FIXED, the reason is stated and the direction of the residual error is given. Three of the fixes moved the valuation AGAINST our own recommendation, which is recorded deliberately.
A34: MODEL AUDIT LOG: issues found during the build, and what was done about them
A35: # | B35: Where | C35: Severity | D35: Finding | E35: Valuation impact | F35: Fix applied
A36: 1 | B36: Balance Sheet, depreciation | C36: HIGH | D36: Depreciation is charged at 8.0% of OPERATING fixed assets, but the historical charge includes amortisation of the Rs 9,433 cr intangible balance, which the model holds flat and never amortises. Charge and base do not match. | E36: Small but the inconsistency is real | F36: DOCUMENTED, NOT FIXED. Splitting the charge into PPE depreciation and intangible amortisation requires a disclosed split of the two in the notes, which was not obtained. Flagged as a PARTIAL on the Dashboard.
A37: 2 | B37: Relative Valuation, peer basis | C37: MED | D37: Ambuja is carried CONSOLIDATED and every peer STANDALONE, so the multiples are not strictly comparable. | E37: Ambuja's EV/EBITDA would print 34x on the wrong pairing against 17.0x on the right one | F37: FIXED AND DISCLOSED. Non-controlling interest is added to enterprise value and a basis row labels every company. For the other four companies standalone and consolidated differ by under 10%, so the mismatch does not arise.
A38: 3 | B38: Terminal, ROIC spread | C38: MED | D38: Terminal ROIC needed to be shown against WACC to satisfy Golden Check 6. | E38: None; the check passes | F38: FIXED. Terminal ROIC of 11.9% against a WACC of 11.375% is a spread of 0.55 points, documented on the Terminal sheet and the Dashboard.
A39: 4 | B39: Model build, goodwill in terminal | C39: HIGH | D39: Terminal reinvestment was charged on invested capital INCLUDING goodwill, which assumes the company must keep buying goodwill forever merely to grow. | E39: Drove the equity value NEGATIVE | F39: FIXED. Terminal reinvestment is charged on OPERATING invested capital only. Worth about Rs 46 per share.
A40: 5 | B40: Model build, forecast horizon | C40: HIGH | D40: A five year explicit horizon ended before the utilisation ramp had played out. | E40: Understated value by roughly Rs 83 per share | F40: FIXED. Extended to a ten year explicit forecast, which is the standard treatment for a difficult to value company.
A41: 6 | B41: Assumptions, terminal growth | C41: HIGH | D41: Terminal growth was originally set LOWER than UltraTech's on the reasoning that a company earning below its cost of capital is worth more if it grows less. That reasoning was result driven AND factually backwards. | E41: Material | F41: FIXED. Both companies now use the same fraction of nominal GDP. Terminal growth is 6.99%, being 65% of nominal GDP of 10.76%.
A42: 7 | B42: Tax normalisation | C42: HIGH | D42: The reported tax line is a net CREDIT of Rs 2,338 cr, so reported profit exceeds pre-tax profit and the effective rate is minus 71%. | E42: Would overstate every return measure | F42: FIXED. All returns are computed at the statutory 25.168%. The credit is decomposed into three drivers on the Normalize sheet, net effect minus Rs 11.54 per share.
A44: Every entry above was found by us during the build, not by a reviewer afterwards. Where an item is marked PARTIALLY FIXED or DOCUMENTED NOT FIXED, the reason is stated and the direction of the residual error is given. Three of the fixes moved the valuation AGAINST our own recommendation, which is recorded deliberately.
A47: MODEL AUDIT LOG: issues found during the build, and what was done about them
A48: # | B48: Where | C48: Severity | D48: Finding | E48: Valuation impact | F48: Fix applied
A49: 1 | B49: Balance Sheet, depreciation | C49: HIGH | D49: Depreciation is charged at 8.0% of OPERATING fixed assets, but the historical charge includes amortisation of the Rs 9,433 cr intangible balance, which the model holds flat and never amortises. Charge and base do not match. | E49: Small but the inconsistency is real | F49: DOCUMENTED, NOT FIXED. Splitting the charge into PPE depreciation and intangible amortisation requires a disclosed split of the two in the notes, which was not obtained. Flagged as a PARTIAL on the Dashboard.
A50: 2 | B50: Relative Valuation, peer basis | C50: MED | D50: Ambuja is carried CONSOLIDATED and every peer STANDALONE, so the multiples are not strictly comparable. | E50: Ambuja's EV/EBITDA would print 34x on the wrong pairing against 17.0x on the right one | F50: FIXED AND DISCLOSED. Non-controlling interest is added to enterprise value and a basis row labels every company. For the other four companies standalone and consolidated differ by under 10%, so the mismatch does not arise.
A51: 3 | B51: Terminal, ROIC spread | C51: MED | D51: Terminal ROIC needed to be shown against WACC to satisfy Golden Check 6. | E51: None; the check passes | F51: FIXED. Terminal ROIC of 11.9% against a WACC of 11.375% is a spread of 0.55 points, documented on the Terminal sheet and the Dashboard.
A52: 4 | B52: Model build, goodwill in terminal | C52: HIGH | D52: Terminal reinvestment was charged on invested capital INCLUDING goodwill, which assumes the company must keep buying goodwill forever merely to grow. | E52: Drove the equity value NEGATIVE | F52: FIXED. Terminal reinvestment is charged on OPERATING invested capital only. Worth about Rs 46 per share.
A53: 5 | B53: Model build, forecast horizon | C53: HIGH | D53: A five year explicit horizon ended before the utilisation ramp had played out. | E53: Understated value by roughly Rs 83 per share | F53: FIXED. Extended to a ten year explicit forecast, which is the standard treatment for a difficult to value company.
A54: 6 | B54: Assumptions, terminal growth | C54: HIGH | D54: Terminal growth was originally set LOWER than UltraTech's on the reasoning that a company earning below its cost of capital is worth more if it grows less. That reasoning was result driven AND factually backwards. | E54: Material | F54: FIXED. Both companies now use the same fraction of nominal GDP. Terminal growth is 6.99%, being 65% of nominal GDP of 10.76%.
A55: 7 | B55: Tax normalisation | C55: HIGH | D55: The reported tax line is a net CREDIT of Rs 2,338 cr, so reported profit exceeds pre-tax profit and the effective rate is minus 71%. | E55: Would overstate every return measure | F55: FIXED. All returns are computed at the statutory 25.168%. The credit is decomposed into three drivers on the Normalize sheet, net effect minus Rs 11.54 per share.
A57: Every entry above was found by us during the build, not by a reviewer afterwards. Where an item is marked PARTIALLY FIXED or DOCUMENTED NOT FIXED, the reason is stated and the direction of the residual error is given. Three of the fixes moved the valuation AGAINST our own recommendation, which is recorded deliberately.
A60: MODEL AUDIT LOG: issues found during the build, and what was done about them
A61: # | B61: Where | C61: Severity | D61: Finding | E61: Valuation impact | F61: Fix applied
A62: 1 | B62: Balance Sheet, depreciation | C62: HIGH | D62: Depreciation is charged at 8.0% of OPERATING fixed assets, but the historical charge includes amortisation of the Rs 9,433 cr intangible balance, which the model holds flat and never amortises. Charge and base do not match. | E62: Small but the inconsistency is real | F62: DOCUMENTED, NOT FIXED. Splitting the charge into PPE depreciation and intangible amortisation requires a disclosed split of the two in the notes, which was not obtained. Flagged as a PARTIAL on the Dashboard.
A63: 2 | B63: Relative Valuation, peer basis | C63: MED | D63: Ambuja is carried CONSOLIDATED and every peer STANDALONE, so the multiples are not strictly comparable. | E63: Ambuja's EV/EBITDA would print 34x on the wrong pairing against 17.0x on the right one | F63: FIXED AND DISCLOSED. Non-controlling interest is added to enterprise value and a basis row labels every company. For the other four companies standalone and consolidated differ by under 10%, so the mismatch does not arise.
A64: 3 | B64: Terminal, ROIC spread | C64: MED | D64: Terminal ROIC needed to be shown against WACC to satisfy Golden Check 6. | E64: None; the check passes | F64: FIXED. Terminal ROIC of 11.9% against a WACC of 11.375% is a spread of 0.55 points, documented on the Terminal sheet and the Dashboard.
A65: 4 | B65: Model build, goodwill in terminal | C65: HIGH | D65: Terminal reinvestment was charged on invested capital INCLUDING goodwill, which assumes the company must keep buying goodwill forever merely to grow. | E65: Drove the equity value NEGATIVE | F65: FIXED. Terminal reinvestment is charged on OPERATING invested capital only. Worth about Rs 46 per share.
A66: 5 | B66: Model build, forecast horizon | C66: HIGH | D66: A five year explicit horizon ended before the utilisation ramp had played out. | E66: Understated value by roughly Rs 83 per share | F66: FIXED. Extended to a ten year explicit forecast, which is the standard treatment for a difficult to value company.
A67: 6 | B67: Assumptions, terminal growth | C67: HIGH | D67: Terminal growth was originally set LOWER than UltraTech's on the reasoning that a company earning below its cost of capital is worth more if it grows less. That reasoning was result driven AND factually backwards. | E67: Material | F67: FIXED. Both companies now use the same fraction of nominal GDP. Terminal growth is 6.99%, being 65% of nominal GDP of 10.76%.
A68: 7 | B68: Tax normalisation | C68: HIGH | D68: The reported tax line is a net CREDIT of Rs 2,338 cr, so reported profit exceeds pre-tax profit and the effective rate is minus 71%. | E68: Would overstate every return measure | F68: FIXED. All returns are computed at the statutory 25.168%. The credit is decomposed into three drivers on the Normalize sheet, net effect minus Rs 11.54 per share.
A70: Every entry above was found by us during the build, not by a reviewer afterwards. Where an item is marked PARTIALLY FIXED or DOCUMENTED NOT FIXED, the reason is stated and the direction of the residual error is given. Three of the fixes moved the valuation AGAINST our own recommendation, which is recorded deliberately.
A73: MODEL AUDIT LOG: issues found during the build, and what was done about them
A74: # | B74: Where | C74: Severity | D74: Finding | E74: Valuation impact | F74: Fix applied
A75: 1 | B75: Balance Sheet, depreciation | C75: HIGH | D75: Depreciation is charged at 8.0% of OPERATING fixed assets, but the historical charge includes amortisation of the Rs 9,433 cr intangible balance, which the model holds flat and never amortises. Charge and base do not match. | E75: Small but the inconsistency is real | F75: DOCUMENTED, NOT FIXED. Splitting the charge into PPE depreciation and intangible amortisation requires a disclosed split of the two in the notes, which was not obtained. Flagged as a PARTIAL on the Dashboard.
A76: 2 | B76: Relative Valuation, peer basis | C76: MED | D76: Ambuja is carried CONSOLIDATED and every peer STANDALONE, so the multiples are not strictly comparable. | E76: Ambuja's EV/EBITDA would print 34x on the wrong pairing against 17.0x on the right one | F76: FIXED AND DISCLOSED. Non-controlling interest is added to enterprise value and a basis row labels every company. For the other four companies standalone and consolidated differ by under 10%, so the mismatch does not arise.
A77: 3 | B77: Terminal, ROIC spread | C77: MED | D77: Terminal ROIC needed to be shown against WACC to satisfy Golden Check 6. | E77: None; the check passes | F77: FIXED. Terminal ROIC of 11.9% against a WACC of 11.375% is a spread of 0.55 points, documented on the Terminal sheet and the Dashboard.
A78: 4 | B78: Model build, goodwill in terminal | C78: HIGH | D78: Terminal reinvestment was charged on invested capital INCLUDING goodwill, which assumes the company must keep buying goodwill forever merely to grow. | E78: Drove the equity value NEGATIVE | F78: FIXED. Terminal reinvestment is charged on OPERATING invested capital only. Worth about Rs 46 per share.
A79: 5 | B79: Model build, forecast horizon | C79: HIGH | D79: A five year explicit horizon ended before the utilisation ramp had played out. | E79: Understated value by roughly Rs 83 per share | F79: FIXED. Extended to a ten year explicit forecast, which is the standard treatment for a difficult to value company.
A80: 6 | B80: Assumptions, terminal growth | C80: HIGH | D80: Terminal growth was originally set LOWER than UltraTech's on the reasoning that a company earning below its cost of capital is worth more if it grows less. That reasoning was result driven AND factually backwards. | E80: Material | F80: FIXED. Both companies now use the same fraction of nominal GDP. Terminal growth is 6.99%, being 65% of nominal GDP of 10.76%.
A81: 7 | B81: Tax normalisation | C81: HIGH | D81: The reported tax line is a net CREDIT of Rs 2,338 cr, so reported profit exceeds pre-tax profit and the effective rate is minus 71%. | E81: Would overstate every return measure | F81: FIXED. All returns are computed at the statutory 25.168%. The credit is decomposed into three drivers on the Normalize sheet, net effect minus Rs 11.54 per share.
A83: Every entry above was found by us during the build, not by a reviewer afterwards. Where an item is marked PARTIALLY FIXED or DOCUMENTED NOT FIXED, the reason is stated and the direction of the residual error is given. Three of the fixes moved the valuation AGAINST our own recommendation, which is recorded deliberately.
A86: MODEL AUDIT LOG: issues found during the build, and what was done about them
A87: # | B87: Where | C87: Severity | D87: Finding | E87: Valuation impact | F87: Fix applied
A88: 1 | B88: Balance Sheet, depreciation | C88: HIGH | D88: Depreciation is charged at 8.0% of OPERATING fixed assets, but the historical charge includes amortisation of the Rs 9,433 cr intangible balance, which the model holds flat and never amortises. Charge and base do not match. | E88: Small but the inconsistency is real | F88: DOCUMENTED, NOT FIXED. Splitting the charge into PPE depreciation and intangible amortisation requires a disclosed split of the two in the notes, which was not obtained. Flagged as a PARTIAL on the Dashboard.
A89: 2 | B89: Relative Valuation, peer basis | C89: MED | D89: Ambuja is carried CONSOLIDATED and every peer STANDALONE, so the multiples are not strictly comparable. | E89: Ambuja's EV/EBITDA would print 34x on the wrong pairing against 17.0x on the right one | F89: FIXED AND DISCLOSED. Non-controlling interest is added to enterprise value and a basis row labels every company. For the other four companies standalone and consolidated differ by under 10%, so the mismatch does not arise.
A90: 3 | B90: Terminal, ROIC spread | C90: MED | D90: Terminal ROIC needed to be shown against WACC to satisfy Golden Check 6. | E90: None; the check passes | F90: FIXED. Terminal ROIC of 11.9% against a WACC of 11.375% is a spread of 0.55 points, documented on the Terminal sheet and the Dashboard.
A91: 4 | B91: Model build, goodwill in terminal | C91: HIGH | D91: Terminal reinvestment was charged on invested capital INCLUDING goodwill, which assumes the company must keep buying goodwill forever merely to grow. | E91: Drove the equity value NEGATIVE | F91: FIXED. Terminal reinvestment is charged on OPERATING invested capital only. Worth about Rs 46 per share.
A92: 5 | B92: Model build, forecast horizon | C92: HIGH | D92: A five year explicit horizon ended before the utilisation ramp had played out. | E92: Understated value by roughly Rs 83 per share | F92: FIXED. Extended to a ten year explicit forecast, which is the standard treatment for a difficult to value company.
A93: 6 | B93: Assumptions, terminal growth | C93: HIGH | D93: Terminal growth was originally set LOWER than UltraTech's on the reasoning that a company earning below its cost of capital is worth more if it grows less. That reasoning was result driven AND factually backwards. | E93: Material | F93: FIXED. Both companies now use the same fraction of nominal GDP. Terminal growth is 6.99%, being 65% of nominal GDP of 10.76%.
A94: 7 | B94: Tax normalisation | C94: HIGH | D94: The reported tax line is a net CREDIT of Rs 2,338 cr, so reported profit exceeds pre-tax profit and the effective rate is minus 71%. | E94: Would overstate every return measure | F94: FIXED. All returns are computed at the statutory 25.168%. The credit is decomposed into three drivers on the Normalize sheet, net effect minus Rs 11.54 per share.
A96: Every entry above was found by us during the build, not by a reviewer afterwards. Where an item is marked PARTIALLY FIXED or DOCUMENTED NOT FIXED, the reason is stated and the direction of the residual error is given. Three of the fixes moved the valuation AGAINST our own recommendation, which is recorded deliberately.
A99: SOURCE URLs AND ACCESS DATES
A100: Input | B100: Authoritative source URL | C100: Accessed
A101: Company annual report and financial statements | B101: https://www.ambujacement.com/investors/financials | C101: 26 Aug 2026
A102: Exchange filings and quarterly results | B102: https://www.nseindia.com/companies-listing/corporate-filings-financial-results | C102: 26 Aug 2026
A103: 10 year G-Sec par yield, FBIL series | B103: https://www.rbi.org.in/Scripts/BS_ViewBulletin.aspx | C103: 26 Aug 2026
A104: Equity risk premium and sovereign default spread | B104: https://pages.stern.nyu.edu/~adamodar/New_Home_Page/datacurrent.html | C104: 26 Aug 2026
A105: Unlevered beta by sector, global | B105: https://pages.stern.nyu.edu/~adamodar/New_Home_Page/datafile/Betas.html | C105: 26 Aug 2026
A106: Historical price series for the beta regression | B106: https://www.nseindia.com/reports-indices-historical-index-data | C106: 26 Aug 2026
A108: These are the AUTHORITATIVE LANDING PAGES from which each input was obtained, with the access date. Deep links to individual PDFs are deliberately not given: they are unstable, and fabricating a precise document URL that was not actually followed would be worse than citing the page that was. Each annual report is identified by name, year and note reference in the rows above, which is sufficient to locate the exact figure. The price series used for the beta regression was supplied with an adjusted close column, a market data vendor convention rather than the exchange bhavcopy format, and is labelled as vendor sourced on the Beta sheet.

Sheet AMB-Source Data
A1: Line item (consolidated, as reported) | B1: Unit | C1: FY2025-26 | D1: FY2024-25 restated
A2: Revenue from operations | B2: Rs cr | C2: 40446.04 | D2: 33989.38
A3: Government grants including duty credits | B3: Rs cr | C3: 209.64 | D3: 1347.06
A4: Other income | B4: Rs cr | C4: 834.34 | D4: 2654.25
A5: Total income | B5: Rs cr | C5: 41490.02 | D5: 37990.69
A6: Finance costs | B6: Rs cr | C6: 223.61 | D6: 215.94
A7: Depreciation and amortisation | B7: Rs cr | C7: 3570.41 | D7: 2297.04
A8: Profit before exceptional items and tax | B8: Rs cr | C8: 3599.31 | D8: 6125.14
A9: Exceptional items, expense | B9: Rs cr | C9: 300.54 | D9: 21.47
A10: Profit before tax | B10: Rs cr | C10: 3298.77 | D10: 6103.67
A11: Profit for the year, owners of the parent | B11: Rs cr | C11: 4728.18 | D11: 4303.1
A12: Profit for the year, non-controlling interest | B12: Rs cr | C12: 908.9 | D12: 990.98
A13: Cement sales volume | B13: mn T | C13: 74
A14: Property, plant and equipment | B14: Rs cr | C14: 33801.18 | D14: 25049.28
A15: Right-of-use assets | B15: Rs cr | C15: 1483 | D15: 1464.76
A16: Capital work in progress | B16: Rs cr | C16: 9084.7 | D16: 9792.99
A17: Goodwill | B17: Rs cr | C17: 13545.52 | D17: 10942.83
A18: Other intangible assets | B18: Rs cr | C18: 9433.12 | D18: 5309.24
A19: Equity attributable to owners | B19: Rs cr | C19: 59347.32 | D19: 53578.92
A20: Non-controlling interest | B20: Rs cr | C20: 12498.92 | D20: 10368.17
A21: Borrowings, non-current | B21: Rs cr | C21: 44.79 | D21: 14.39
A22: Borrowings, current | B22: Rs cr | C22: 7.99 | D22: 12.43
A23: Lease liabilities, total | B23: Rs cr | C23: 813.15 | D23: 761.68
A24: Cash and cash equivalents | B24: Rs cr | C24: 891.59 | D24: 5043.32
A25: Bank balances other than above | B25: Rs cr | C25: 67.01 | D25: 1128.84
... A27: Deferred tax liabilities (net) | B27: Rs cr | C27: 3466.33 | D27: 2432.85
A29: Derived
A30: Revenue including government grants | C30: =C2+C3 -> 40655.68 | D30: =D2+D3 -> 35336.44
A31: EBITDA (uniform definition) | C31: =C8+C6+C7-C4 -> 6558.99 | D31: =D8+D6+D7-D4 -> 5983.87
A32: EBIT | C32: =C29-C7 -> -3570.41
A33: Reported profit for the year | C33: =C11+C12 -> 5637.08 | D33: =D11+D12 -> 5294.08
A34: Reported effective tax rate | C34: =(C10-C29)/C10 -> 1
A35: Operating invested capital (PPE, ROU, CWIP, NWC) | C35: =C14+C15+C16+'AMB-Assumptions'!$B$4 -> 44368.88
A36: Goodwill and other intangibles | C36: =C17+C18 -> 22978.64 | D36: =D17+D18 -> 16252.07
A37: Net debt (borrowings + leases - cash) | C37: =C21+C22+C23-C24-C25-C26 -> -92.67 | D37: =D21+D22+D23-D24-D25-D26 -> -7205.82
A39: The uniform EBITDA definition gives Rs 6,559 crore for FY2025-26. The company's own Operating EBITDA line reads Rs 6,539 crore; the Rs 20 crore difference is the share of profit of joint ventures and associates, which sits outside this definition. Ties to within 0.3%, which is the check that the definition is right.

Sheet AMB-Entity Build
A1: Entity Build: standalone to consolidated
A2: Ambuja Cements Ltd, FY2025-26. Standalone and consolidated are as reported; the subsidiary column is derived as the difference.
A4: Line item | B4: Unit | C4: Standalone | D4: Subsidiaries | E4: Consolidated | F4: Check
A5: Revenue from operations | B5: Rs cr | C5: 25052.05 | D5: =E5-C5 -> 15393.99 | E5: 40446.04
A6: Government grants | B6: Rs cr | C6: 9.49 | D6: =E6-C6 -> 200.15 | E6: 209.64
A7: Other income | B7: Rs cr | C7: 766.17 | D7: =E7-C7 -> 68.17 | E7: 834.34
A8: Finance costs | B8: Rs cr | C8: 172.56 | D8: =E8-C8 -> 51.05 | E8: 223.61
A9: Depreciation and amortisation | B9: Rs cr | C9: 2035.2 | D9: =E9-C9 -> 1535.21 | E9: 3570.41
A10: Profit before exceptional items and tax | B10: Rs cr | C10: 1488.25 | D10: =E10-C10 -> 2111.06 | E10: 3599.31
A11: Revenue including grants | C11: =C5+C6 -> 25061.54 | D11: =D5+D6 -> 15594.14 | E11: =E5+E6 -> 40655.68
A12: EBITDA (uniform definition) | C12: =C10+C8+C9-C7 -> 2929.84 | D12: =D10+D8+D9-D7 -> 3629.15 | E12: =E10+E8+E9-E7 -> 6558.99
A13: EBITDA margin | C13: =C12/C11 -> 0.11690582 | D13: =D12/D11 -> 0.23272524 | E13: =E12/E11 -> 0.16133022
A14: Share of group revenue | C14: =C11/$E$11 -> 0.61643392 | D14: =D11/$E$11 -> 0.38356608
A15: Share of group EBITDA | C15: =C12/$E$12 -> 0.44669073 | D15: =D12/$E$12 -> 0.55330927
A17: THE FINDING. Ambuja standalone carries 61.6% of group revenue but only 44.7% of group EBITDA. The parent runs an 11.7% margin while the subsidiaries run 23.3%. The weak assets, principally Sanghi and Penna, sit inside the standalone entity, while ACC and Orient sit outside it. A consolidated-only model hides this entirely, which is why this tab exists and why the valuation is presented as a build up.
A21: Why the forecast is nonetheless run at consolidated level
A22: Volume of 74 million tonnes and capacity of 109 MTPA are disclosed CONSOLIDATED ONLY. Splitting them by revenue share would imply standalone volume of about 45.6 million tonnes, but that is a derivation and not a disclosure, and forecasting a derived volume series against a disclosed capacity series would be false precision. The base year build above is fully sourced; the forecast therefore runs on consolidated capacity times utilisation times EBITDA per tonne, and the equity bridge deducts the non-controlling interest so that only the owners' share is valued. If standalone volume is obtained from the company, this tab is where a two block forecast would be built.
A28: Basis decision and its consequence for the multiple
A29: Basis | C29: EBITDA | D29: Enterprise value | E29: EV/EBITDA
A30: Standalone (wrong pairing) | C30: 2929.84 | D30: 99675.72 | E30: =D30/C30 -> 34.020875
A31: Consolidated with NCI added | C31: 6558.99 | D31: 111501.25 | E31: =D31/C31 -> 16.999759
A33: Market capitalisation of Rs 99,095 crore prices the whole group including the 50.05% stake in ACC. Dividing it by standalone EBITDA prints 34x and is a category error. Adding the non-controlling interest of Rs 12,499 crore to enterprise value and dividing by consolidated EBITDA gives 17.0x. This is the pairing used throughout the model and in the peer comparison.
A36: CONSISTENCY CHECK: the build must tie to the reported total
A37: Revenue: standalone plus subsidiaries | C37: =C11+D11 -> 40655.68 | D37: =E11 -> 40655.68 | E37: =IF(ABS(C37-D37)<0.01,"TIES","DOES NOT TIE") -> TIES
A38: EBITDA: standalone plus subsidiaries | C38: =C12+D12 -> 6558.99 | D38: =E12 -> 6558.99 | E38: =IF(ABS(C38-D38)<0.01,"TIES","DOES NOT TIE") -> TIES
C39: Build | D39: As reported | E39: Check
A41: This is the MRF style tie out. The two blocks are not independent estimates that happen to be near the total; the subsidiary column is DERIVED as consolidated less standalone, so it ties by construction and the check confirms no transcription error. In the forecast the same discipline holds: consolidated revenue is built from capacity and then SPLIT, so the blocks always sum to the total. Note the residual caveat: intercompany eliminations sit inside the subsidiary column because they cannot be separated from the published statements.
A44: CONSISTENCY CHECK: the build must tie to the reported total
A45: Revenue: standalone plus subsidiaries | C45: =C11+D11 -> 40655.68 | D45: =E11 -> 40655.68 | E45: =IF(ABS(C45-D45)<0.01,"TIES","DOES NOT TIE") -> TIES
A46: EBITDA: standalone plus subsidiaries | C46: =C12+D12 -> 6558.99 | D46: =E12 -> 6558.99 | E46: =IF(ABS(C46-D46)<0.01,"TIES","DOES NOT TIE") -> TIES
C47: Build | D47: As reported | E47: Check
A49: This is the MRF style tie out. The two blocks are not independent estimates that happen to be near the total; the subsidiary column is DERIVED as consolidated less standalone, so it ties by construction and the check confirms no transcription error. In the forecast the same discipline holds: consolidated revenue is built from capacity and then SPLIT, so the blocks always sum to the total. Note the residual caveat: intercompany eliminations sit inside the subsidiary column because they cannot be separated from the published statements.
A52: CONSISTENCY CHECK: the build must tie to the reported total
A53: Revenue: standalone plus subsidiaries | C53: =C11+D11 -> 40655.68 | D53: =E11 -> 40655.68 | E53: =IF(ABS(C53-D53)<0.01,"TIES","DOES NOT TIE") -> TIES
A54: EBITDA: standalone plus subsidiaries | C54: =C12+D12 -> 6558.99 | D54: =E12 -> 6558.99 | E54: =IF(ABS(C54-D54)<0.01,"TIES","DOES NOT TIE") -> TIES
C55: Build | D55: As reported | E55: Check
A57: This is the MRF style tie out. The two blocks are not independent estimates that happen to be near the total; the subsidiary column is DERIVED as consolidated less standalone, so it ties by construction and the check confirms no transcription error. In the forecast the same discipline holds: consolidated revenue is built from capacity and then SPLIT, so the blocks always sum to the total. Note the residual caveat: intercompany eliminations sit inside the subsidiary column because they cannot be separated from the published statements.
A60: CONSISTENCY CHECK: the build must tie to the reported total
A61: Revenue: standalone plus subsidiaries | C61: =C11+D11 -> 40655.68 | D61: =E11 -> 40655.68 | E61: =IF(ABS(C61-D61)<0.01,"TIES","DOES NOT TIE") -> TIES
A62: EBITDA: standalone plus subsidiaries | C62: =C12+D12 -> 6558.99 | D62: =E12 -> 6558.99 | E62: =IF(ABS(C62-D62)<0.01,"TIES","DOES NOT TIE") -> TIES
C63: Build | D63: As reported | E63: Check
A65: This is the MRF style tie out. The two blocks are not independent estimates that happen to be near the total; the subsidiary column is DERIVED as consolidated less standalone, so it ties by construction and the check confirms no transcription error. In the forecast the same discipline holds: consolidated revenue is built from capacity and then SPLIT, so the blocks always sum to the total. Note the residual caveat: intercompany eliminations sit inside the subsidiary column because they cannot be separated from the published statements.
A68: CONSISTENCY CHECK: the build must tie to the reported total
A69: Revenue: standalone plus subsidiaries | C69: =C11+D11 -> 40655.68 | D69: =E11 -> 40655.68 | E69: =IF(ABS(C69-D69)<0.01,"TIES","DOES NOT TIE") -> TIES
A70: EBITDA: standalone plus subsidiaries | C70: =C12+D12 -> 6558.99 | D70: =E12 -> 6558.99 | E70: =IF(ABS(C70-D70)<0.01,"TIES","DOES NOT TIE") -> TIES
C71: Build | D71: As reported | E71: Check
A73: This is the MRF style tie out. The two blocks are not independent estimates that happen to be near the total; the subsidiary column is DERIVED as consolidated less standalone, so it ties by construction and the check confirms no transcription error. In the forecast the same discipline holds: consolidated revenue is built from capacity and then SPLIT, so the blocks always sum to the total. Note the residual caveat: intercompany eliminations sit inside the subsidiary column because they cannot be separated from the published statements.
A76: CONSISTENCY CHECK: the build must tie to the reported total
A77: Revenue: standalone plus subsidiaries | C77: =C11+D11 -> 40655.68 | D77: =E11 -> 40655.68 | E77: =IF(ABS(C77-D77)<0.01,"TIES","DOES NOT TIE") -> TIES
A78: EBITDA: standalone plus subsidiaries | C78: =C12+D12 -> 6558.99 | D78: =E12 -> 6558.99 | E78: =IF(ABS(C78-D78)<0.01,"TIES","DOES NOT TIE") -> TIES
C79: Build | D79: As reported | E79: Check
A81: This is the MRF style tie out. The two blocks are not independent estimates that happen to be near the total; the subsidiary column is DERIVED as consolidated less standalone, so it ties by construction and the check confirms no transcription error. In the forecast the same discipline holds: consolidated revenue is built from capacity and then SPLIT, so the blocks always sum to the total. Note the residual caveat: intercompany eliminations sit inside the subsidiary column because they cannot be separated from the published statements.

Sheet AMB-Normalize
A1: Normalisation and reclassification
A2: Every adjustment carries the annual report note reference it came from.
A4: Item | B4: Unit | C4: As reported | D4: Normalised | E4: Basis and note reference
A5: Tax expense (credit), consolidated | B5: Rs cr | C5: -2338.31 | D5: 830.28 | E5: Note 32. Reported line is a net CREDIT of Rs 2,338.31 cr, giving an effective rate of minus 70.9%. Replaced throughout by the statutory rate of 25.168% under s.115BAA applied to EBIT.
A6: Driver 1: litigation provisions released | B6: Rs cr | C6: 1250.76 | D6: 0 | E6: Note 32(ii). Rs 1,179.71 cr of earlier year provisions released on favourable High Court decisions, plus Rs 71.05 cr revising FY2024-25. Non cash, prior period. Excluded.
A7: Driver 1a: duty and taxes paid under protest | B7: Rs cr | C7: 614.1 | D7: 614.1 | E7: Note 53, non-current. Real cash already paid, recoverable on favourable rulings. Sits outside operating invested capital. ADDED as a non-operating asset.
A8: Driver 2: deferred tax liabilities (net) | B8: Rs cr | C8: 3466.33 | D8: 3466.33 | E8: Balance sheet. Treated as a real liability and DEDUCTED in the equity bridge as a one time drop, not amortised.
A9: Driver 3: DTA on losses and unabsorbed depreciation | B9: Rs cr | C9: 345.78 | D9: 0 | E9: Note 32. Memo only. Already netted inside Driver 2, so adding it again would double count. Note it is SHRINKING: Rs 509.66 cr opening, Rs 163.88 cr consumed, Rs 345.78 cr closing.
A10: Exceptional items, consolidated | B10: Rs cr | C10: 300.54 | D10: 0 | E10: Consolidated P&L. Removed from earnings; sits below profit before exceptional items so EBITDA needs no adjustment.
A11: Non-controlling interest | B11: Rs cr | C11: 12498.92 | D11: 12498.92 | E11: Balance sheet. DEDUCTED in the bridge because consolidated cash flows include 100% of partly owned subsidiaries.
A12: Other income | B12: Rs cr | C12: 834.34 | D12: 0 | E12: Excluded from EBITDA under our uniform definition, so cash and investments are non-operating and added back once at the bridge.
A14: Net effect of the three tax drivers on value: minus Rs 11.54 per share. The headline credit of Rs 2,338 crore, which lifts reported profit 71% above pre-tax profit, is worth negative value once each component is treated on its economics rather than its accounting.

Sheet AMB-Common Size
A1: Common Size Statements: Ambuja Cements (consolidated)
A2: Recomputed from the consolidated statements on Source-Data. Nothing downloaded.
A4: Line item | B4: FY2025-26 | C4: FY2024-25 restated
A5: Income statement, percent of revenue including government grants
A6: Other income | B6: ='AMB-Source Data'!C4/('AMB-Source Data'!C2+'AMB-Source Data'!C3) -> 0.020522102 | C6: ='AMB-Source Data'!D4/('AMB-Source Data'!D2+'AMB-Source Data'!D3) -> 0.075113679
A7: EBITDA (uniform definition) | B7: =('AMB-Source Data'!C8+'AMB-Source Data'!C6+'AMB-Source Data'!C7-'AMB-Source Data'!C4)/('AMB-Source Data'!C2+'AMB-Source Data'!C3) -> 0.16133022 | C7: =('AMB-Source Data'!D8+'AMB-Source Data'!D6+'AMB-Source Data'!D7-'AMB-Source Data'!D4)/('AMB-Source Data'!D2+'AMB-Source Data'!D3) -> 0.16933992
A8: Depreciation and amortisation | B8: ='AMB-Source Data'!C7/('AMB-Source Data'!C2+'AMB-Source Data'!C3) -> 0.087820693 | C8: ='AMB-Source Data'!D7/('AMB-Source Data'!D2+'AMB-Source Data'!D3) -> 0.065004851
A9: Finance costs | B9: ='AMB-Source Data'!C6/('AMB-Source Data'!C2+'AMB-Source Data'!C3) -> 0.0055000925 | C9: ='AMB-Source Data'!D6/('AMB-Source Data'!D2+'AMB-Source Data'!D3) -> 0.0061109721
A10: Profit before exceptional items and tax | B10: ='AMB-Source Data'!C8/('AMB-Source Data'!C2+'AMB-Source Data'!C3) -> 0.088531541 | C10: ='AMB-Source Data'!D8/('AMB-Source Data'!D2+'AMB-Source Data'!D3) -> 0.17333778
A11: Exceptional items | B11: ='AMB-Source Data'!C9/('AMB-Source Data'!C2+'AMB-Source Data'!C3) -> 0.007392325 | C11: ='AMB-Source Data'!D9/('AMB-Source Data'!D2+'AMB-Source Data'!D3) -> 0.00060758809
A12: Profit for the year (total) | B12: =('AMB-Source Data'!C11+'AMB-Source Data'!C12)/('AMB-Source Data'!C2+'AMB-Source Data'!C3) -> 0.13865418 | C12: =('AMB-Source Data'!D11+'AMB-Source Data'!D12)/('AMB-Source Data'!D2+'AMB-Source Data'!D3) -> 0.14981928
A13: Profit attributable to owners | B13: ='AMB-Source Data'!C11/('AMB-Source Data'!C2+'AMB-Source Data'!C3) -> 0.11629814 | C13: ='AMB-Source Data'!D11/('AMB-Source Data'!D2+'AMB-Source Data'!D3) -> 0.12177514
A14: Profit attributable to minorities | B14: ='AMB-Source Data'!C12/('AMB-Source Data'!C2+'AMB-Source Data'!C3) -> 0.02235604 | C14: ='AMB-Source Data'!D12/('AMB-Source Data'!D2+'AMB-Source Data'!D3) -> 0.028044138
A16: Capital employed, percent of total
A17: Property, plant and equipment | B17: ='AMB-Source Data'!C14/('AMB-Source Data'!C19+'AMB-Source Data'!C20+'AMB-Source Data'!C21+'AMB-Source Data'!C22+'AMB-Source Data'!C23) -> 0.46486276 | C17: ='AMB-Source Data'!D14/('AMB-Source Data'!D19+'AMB-Source Data'!D20+'AMB-Source Data'!D21+'AMB-Source Data'!D22+'AMB-Source Data'!D23) -> 0.38694758
A18: Right-of-use assets | B18: ='AMB-Source Data'!C15/('AMB-Source Data'!C19+'AMB-Source Data'!C20+'AMB-Source Data'!C21+'AMB-Source Data'!C22+'AMB-Source Data'!C23) -> 0.020395485 | C18: ='AMB-Source Data'!D15/('AMB-Source Data'!D19+'AMB-Source Data'!D20+'AMB-Source Data'!D21+'AMB-Source Data'!D22+'AMB-Source Data'!D23) -> 0.022626812
A19: Capital work in progress | B19: ='AMB-Source Data'!C16/('AMB-Source Data'!C19+'AMB-Source Data'!C20+'AMB-Source Data'!C21+'AMB-Source Data'!C22+'AMB-Source Data'!C23) -> 0.12494057 | C19: ='AMB-Source Data'!D16/('AMB-Source Data'!D19+'AMB-Source Data'!D20+'AMB-Source Data'!D21+'AMB-Source Data'!D22+'AMB-Source Data'!D23) -> 0.15127676
A20: Goodwill | B20: ='AMB-Source Data'!C17/('AMB-Source Data'!C19+'AMB-Source Data'!C20+'AMB-Source Data'!C21+'AMB-Source Data'!C22+'AMB-Source Data'!C23) -> 0.18628959 | C20: ='AMB-Source Data'!D17/('AMB-Source Data'!D19+'AMB-Source Data'!D20+'AMB-Source Data'!D21+'AMB-Source Data'!D22+'AMB-Source Data'!D23) -> 0.16903885
A21: Other intangible assets | B21: ='AMB-Source Data'!C18/('AMB-Source Data'!C19+'AMB-Source Data'!C20+'AMB-Source Data'!C21+'AMB-Source Data'!C22+'AMB-Source Data'!C23) -> 0.12973234 | C21: ='AMB-Source Data'!D18/('AMB-Source Data'!D19+'AMB-Source Data'!D20+'AMB-Source Data'!D21+'AMB-Source Data'!D22+'AMB-Source Data'!D23) -> 0.082014237
A22: Equity attributable to owners | B22: ='AMB-Source Data'!C19/('AMB-Source Data'!C19+'AMB-Source Data'!C20+'AMB-Source Data'!C21+'AMB-Source Data'!C22+'AMB-Source Data'!C23) -> 0.81619514 | C22: ='AMB-Source Data'!D19/('AMB-Source Data'!D19+'AMB-Source Data'!D20+'AMB-Source Data'!D21+'AMB-Source Data'!D22+'AMB-Source Data'!D23) -> 0.82765786
A23: Non-controlling interest | B23: ='AMB-Source Data'!C20/('AMB-Source Data'!C19+'AMB-Source Data'!C20+'AMB-Source Data'!C21+'AMB-Source Data'!C22+'AMB-Source Data'!C23) -> 0.17189585 | C23: ='AMB-Source Data'!D20/('AMB-Source Data'!D19+'AMB-Source Data'!D20+'AMB-Source Data'!D21+'AMB-Source Data'!D22+'AMB-Source Data'!D23) -> 0.16016182
A24: Borrowings, non-current | B24: ='AMB-Source Data'!C21/('AMB-Source Data'!C19+'AMB-Source Data'!C20+'AMB-Source Data'!C21+'AMB-Source Data'!C22+'AMB-Source Data'!C23) -> 0.00061599042 | C24: ='AMB-Source Data'!D21/('AMB-Source Data'!D19+'AMB-Source Data'!D20+'AMB-Source Data'!D21+'AMB-Source Data'!D22+'AMB-Source Data'!D23) -> 0.00022228885
A25: Lease liabilities, total | B25: ='AMB-Source Data'!C23/('AMB-Source Data'!C19+'AMB-Source Data'!C20+'AMB-Source Data'!C21+'AMB-Source Data'!C22+'AMB-Source Data'!C23) -> 0.011183135 | C25: ='AMB-Source Data'!D23/('AMB-Source Data'!D19+'AMB-Source Data'!D20+'AMB-Source Data'!D21+'AMB-Source Data'!D22+'AMB-Source Data'!D23) -> 0.011766016
A27: Two lines deserve attention. Profit for the year runs at roughly 14% of revenue while EBITDA runs at 16%, which is impossible on normal taxation and is the visible fingerprint of the net tax CREDIT. Second, goodwill and other intangibles together account for close to a third of capital employed. That is capital shareholders paid for which earns no separate return, and it is why return on invested capital including goodwill never reaches the cost of capital in the forecast. Only two years are shown because the annual report provides only two on a consolidated basis; earlier consolidated years exist only in broker research, which is not an authorised source.

Sheet AMB-Ratios
A1: Ratio Analysis: Ambuja Cements (consolidated)
A2: Returns use the statutory tax rate of 25.168%, never the reported effective rate, which is negative.
A4: Ratio | B4: FY2025-26 | C4: FY2024-25 restated
A5: Profitability
A6: EBITDA margin | B6: =('AMB-Source Data'!C8+'AMB-Source Data'!C6+'AMB-Source Data'!C7-'AMB-Source Data'!C4)/('AMB-Source Data'!C2+'AMB-Source Data'!C3) -> 0.16133022 | C6: =('AMB-Source Data'!D8+'AMB-Source Data'!D6+'AMB-Source Data'!D7-'AMB-Source Data'!D4)/('AMB-Source Data'!D2+'AMB-Source Data'!D3) -> 0.16933992
A7: EBIT margin | B7: =(('AMB-Source Data'!C8+'AMB-Source Data'!C6+'AMB-Source Data'!C7-'AMB-Source Data'!C4)-'AMB-Source Data'!C7)/('AMB-Source Data'!C2+'AMB-Source Data'!C3) -> 0.073509532 | C7: =(('AMB-Source Data'!D8+'AMB-Source Data'!D6+'AMB-Source Data'!D7-'AMB-Source Data'!D4)-'AMB-Source Data'!D7)/('AMB-Source Data'!D2+'AMB-Source Data'!D3) -> 0.10433507
A8: NOPAT at statutory tax | B8: =(('AMB-Source Data'!C8+'AMB-Source Data'!C6+'AMB-Source Data'!C7-'AMB-Source Data'!C4)-'AMB-Source Data'!C7)*(1-'AMB-Assumptions'!$B$35) -> 2236.4142 | C8: =(('AMB-Source Data'!D8+'AMB-Source Data'!D6+'AMB-Source Data'!D7-'AMB-Source Data'!D4)-'AMB-Source Data'!D7)*(1-'AMB-Assumptions'!$B$35) -> 2758.9286
A9: ROIC including goodwill | B9: =(('AMB-Source Data'!C8+'AMB-Source Data'!C6+'AMB-Source Data'!C7-'AMB-Source Data'!C4)-'AMB-Source Data'!C7)*(1-'AMB-Assumptions'!$B$35)/('AMB-Source Data'!C14+'AMB-Source Data'!C15+'AMB-Source Data'!C16+'AMB-Source Data'!C17+'AMB-Source Data'!C18) -> 0.033207076 | C9: =(('AMB-Source Data'!D8+'AMB-Source Data'!D6+'AMB-Source Data'!D7-'AMB-Source Data'!D4)-'AMB-Source Data'!D7)*(1-'AMB-Assumptions'!$B$35)/('AMB-Source Data'!D14+'AMB-Source Data'!D15+'AMB-Source Data'!D16+'AMB-Source Data'!D17+'AMB-Source Data'!D18) -> 0.052491931
A10: ROIC excluding goodwill | B10: =(('AMB-Source Data'!C8+'AMB-Source Data'!C6+'AMB-Source Data'!C7-'AMB-Source Data'!C4)-'AMB-Source Data'!C7)*(1-'AMB-Assumptions'!$B$35)/('AMB-Source Data'!C14+'AMB-Source Data'!C15+'AMB-Source Data'!C16) -> 0.050405018 | C10: =(('AMB-Source Data'!D8+'AMB-Source Data'!D6+'AMB-Source Data'!D7-'AMB-Source Data'!D4)-'AMB-Source Data'!D7)*(1-'AMB-Assumptions'!$B$35)/('AMB-Source Data'!D14+'AMB-Source Data'!D15+'AMB-Source Data'!D16) -> 0.075988827
A11: Return on equity (reported, owners) | B11: ='AMB-Source Data'!C11/'AMB-Source Data'!C19 -> 0.079669646 | C11: ='AMB-Source Data'!D11/'AMB-Source Data'!D19 -> 0.080313302
A12: MEMO: reported effective tax rate | B12: =('AMB-Source Data'!C10-('AMB-Source Data'!C11+'AMB-Source Data'!C12))/'AMB-Source Data'!C10 -> -0.70884299 | C12: =('AMB-Source Data'!D10-('AMB-Source Data'!D11+'AMB-Source Data'!D12))/'AMB-Source Data'!D10 -> 0.13263987
A14: Per tonne economics (FY2025-26 only, volume not disclosed for the prior year)
A15: Sales volume (mn tonnes) | B15: ='AMB-Source Data'!C13 -> 74
A16: Realisation per tonne (Rs) | B16: =('AMB-Source Data'!C2+'AMB-Source Data'!C3)*10/'AMB-Source Data'!C13 -> 5494.0108
A17: EBITDA per tonne (Rs) | B17: =('AMB-Source Data'!C8+'AMB-Source Data'!C6+'AMB-Source Data'!C7-'AMB-Source Data'!C4)*10/'AMB-Source Data'!C13 -> 886.35
A18: Capacity utilisation | B18: ='AMB-Source Data'!C13/'AMB-Assumptions'!$B$6 -> 0.67889908
A20: Asset composition
A21: Goodwill and intangibles, percent of invested capital | B21: =('AMB-Source Data'!C17+'AMB-Source Data'!C18)/('AMB-Source Data'!C14+'AMB-Source Data'!C15+'AMB-Source Data'!C16+'AMB-Source Data'!C17+'AMB-Source Data'!C18) -> 0.34119504 | C21: =('AMB-Source Data'!D17+'AMB-Source Data'!D18)/('AMB-Source Data'!D14+'AMB-Source Data'!D15+'AMB-Source Data'!D16+'AMB-Source Data'!D17+'AMB-Source Data'!D18) -> 0.30921515
A22: CWIP, percent of gross operating assets | B22: ='AMB-Source Data'!C16/('AMB-Source Data'!C14+'AMB-Source Data'!C15+'AMB-Source Data'!C16) -> 0.20475387 | C22: ='AMB-Source Data'!D16/('AMB-Source Data'!D14+'AMB-Source Data'!D15+'AMB-Source Data'!D16) -> 0.2697271
A23: Revenue to operating fixed assets | B23: =('AMB-Source Data'!C2+'AMB-Source Data'!C3)/('AMB-Source Data'!C14+'AMB-Source Data'!C15+'AMB-Source Data'!C16) -> 0.91631071 | C23: =('AMB-Source Data'!D2+'AMB-Source Data'!D3)/('AMB-Source Data'!D14+'AMB-Source Data'!D15+'AMB-Source Data'!D16) -> 0.97326716
A25: Leverage and coverage
A26: Debt to equity | B26: =('AMB-Source Data'!C21+'AMB-Source Data'!C22+'AMB-Source Data'!C23)/'AMB-Source Data'!C19 -> 0.014590886 | C26: =('AMB-Source Data'!D21+'AMB-Source Data'!D22+'AMB-Source Data'!D23)/'AMB-Source Data'!D19 -> 0.014716609
A27: Net debt to EBITDA | B27: =('AMB-Source Data'!C21+'AMB-Source Data'!C22+'AMB-Source Data'!C23-'AMB-Source Data'!C24-'AMB-Source Data'!C25-'AMB-Source Data'!C26)/('AMB-Source Data'!C8+'AMB-Source Data'!C6+'AMB-Source Data'!C7-'AMB-Source Data'!C4) -> -0.0141287 | C27: =('AMB-Source Data'!D21+'AMB-Source Data'!D22+'AMB-Source Data'!D23-'AMB-Source Data'!D24-'AMB-Source Data'!D25-'AMB-Source Data'!D26)/('AMB-Source Data'!D8+'AMB-Source Data'!D6+'AMB-Source Data'!D7-'AMB-Source Data'!D4) -> -1.2042073
A28: Interest coverage (EBIT / finance costs) | B28: =(('AMB-Source Data'!C8+'AMB-Source Data'!C6+'AMB-Source Data'!C7-'AMB-Source Data'!C4)-'AMB-Source Data'!C7)/'AMB-Source Data'!C6 -> 13.365145 | C28: =(('AMB-Source Data'!D8+'AMB-Source Data'!D6+'AMB-Source Data'!D7-'AMB-Source Data'!D4)-'AMB-Source Data'!D7)/'AMB-Source Data'!D6 -> 17.0734
A29: Minority share of group profit | B29: ='AMB-Source Data'!C12/('AMB-Source Data'!C11+'AMB-Source Data'!C12) -> 0.16123596 | C29: ='AMB-Source Data'!D12/('AMB-Source Data'!D11+'AMB-Source Data'!D12) -> 0.18718644
A31: Read the two ROIC rows together. Excluding goodwill the business earns a mediocre return; including it, the return is far below the 11.03% cost of capital. Goodwill is capital shareholders paid, so the second number is the one that matters to them and the first is the one that measures the plants. The memo tax rate row shows why nothing in this workbook uses the reported effective rate. And the minority share row quantifies how much of group profit does not belong to Ambuja shareholders, which is the leakage the pending merger is designed to remove.

Sheet AMB-Assumptions
A1: Assumptions
A3: Net working capital, opening | B3: -139.4 | M3: Consolidated current assets excluding cash and investments, less current liabilities excluding borrowings and leases.
A4: Opening position, FY2025-26 consolidated actual
A5: Cement sales volume (mn T) | B5: 74 | M5: From the Growth Trajectory highlights.
A6: Capacity (MTPA) | B6: 109 | M6: Company stated current capacity.
A7: Opening utilisation | B7: =B5/B6 -> 0.67889908 | M7: Far below UltraTech's 82%. Spare capacity is the whole investment case.
A8: EBITDA per tonne (Rs) | B8: 886.35 | M8: Rs 6,559 crore over 74 million tonnes.
A9: Realisation per tonne (Rs) | B9: 5494.01 | M9: Rs 40,656 crore over 74 million tonnes.
A10: Operating fixed assets (PPE, ROU, CWIP) | B10: 44368.88 | M10: Excludes goodwill and intangibles, which are held separately.
A11: Goodwill and other intangibles | B11: 22978.64 | M11: From acquisitions. In invested capital, but NOT grown at g in the terminal.
A13: Market and capital structure
A14: Market capitalisation | B14: 99095 | M14: As disclosed, 30 March 2026 close.
A15: Shares outstanding (crore) | B15: 247.18 | M15: Share capital Rs 494.36 cr at Rs 2 face value.
A16: Borrowings and lease liabilities | B16: 865.93 | M16: Rs 52.78 cr borrowings plus Rs 813.15 cr leases. Ambuja is effectively debt free.
A17: Cash, bank and current investments | B17: 958.6 | M17: Net cash position of about Rs 93 crore.
A18: Non-controlling interest | B18: 12498.92 | M18: Book value. Deducted in the bridge because consolidated flows include 100% of partly owned subsidiaries.
A20: Tax credit of Rs 2,338 crore: the three drivers, adjusted explicitly
A21: Driver 1: litigation provisions released | B21: 0 | M21: Rs 1,251 crore of earlier year provisions reversed after favourable High Court decisions. The PROVISION REVERSAL itself has no valuation impact and the adjustment here is deliberately zero: it was a provision for disputed income tax sitting in the tax line, and reversing a liability that was never paid changes reported profit without changing cash. Because this model taxes EBIT at the statutory rate throughout, the credit was never in the cash flows to begin with. BUT SEE THE NEXT ROW: part of the disputed tax WAS paid in cash.
A22: Driver 1a: tax paid under protest, recoverable | B22: 614.1 | M22: CONSOLIDATED non-current duty and taxes paid under protest against various disputes (Note 53): Rs 614.10 crore at 31 March 2026, against Rs 628.88 crore a year earlier. This is real cash Ambuja has already handed over and carries as an asset pending appeal, and favourable rulings turn it into a refund. It sits in other non-current assets, which is OUTSIDE the operating invested capital used in this model, so it was being missed entirely. Added to the bridge as a non-operating asset. The current portion of Rs 10.56 crore is already inside net working capital and is NOT added again.
A23: Driver 2: deferred tax liabilities, deducted | B23: 3466.33 | M23: Net consolidated deferred tax liability at 31 March 2026. Treated as a real liability and deducted in the bridge as a ONE TIME drop, not amortised over the forecast. The logic: a deferred tax liability means cash tax paid has lagged book tax, so as it unwinds cash tax exceeds book tax and free cash flow falls. Taking it as a single deduction at the valuation date rather than spreading it avoids pretending to know the timing. This also satisfies liability consistency: if it is treated as a liability it must appear in the bridge.
A24: Driver 3: memo, deferred tax asset on losses and unabsorbed depreciation | B24: 345.78 | M24: CONSOLIDATED figure. The note is headed Unabsorbed depreciation AND Business Losses together, so this single balance already covers BOTH; there is no separate larger business loss pool sitting behind it. Section 72A lets an amalgamated company carry forward the accumulated losses and unabsorbed depreciation of the transferor. Two things follow. First, this is the only one of the three drivers with genuine forward cash value, and it implies roughly Rs 1,374 crore of shelter at the statutory rate. Second, and more important, it is SHRINKING: Rs 509.66 crore at the start of the year, Rs 163.88 crore consumed during FY2025-26, Rs 345.78 crore left. The shelter is being used up, not built. MEMO ONLY, not added separately, because Driver 2 is the NET deferred tax position and this asset is already netted inside it. An earlier draft used the STANDALONE figure of Rs 280.27 crore here, which was the wrong basis for a consolidated model.
A26: Cost of capital
A27: Indian 10 year G-Sec yield | B27: 0.0685 | M27: SOURCED AND DATE MATCHED. FBIL 10-Year G-Sec Par Yield, week ended 20 March 2026, from the RBI Ratios and Rates release dated 27 March 2026. This is the last weekly print before the 31 March 2026 valuation date, so the risk free rate, the market capitalisation and the balance sheet are all struck on the same window. Nearby prints for context: 6.74% on 13 March, 6.76% on 6 March, 6.71% on 27 February, and 6.65% a year earlier in March 2025.
A28: India sovereign default spread | B28: 0.0187 | M28: Damodaran, January 2026.
A29: Risk free rate (rupee, default free) | B29: =B27-B28 -> 0.0498
A30: India equity risk premium | B30: 0.0708 | M30: Damodaran, January 2026.
A31: Unlevered beta, Building Materials | B31: 0.9 | M31: Damodaran Global, cash corrected.
A32: Market debt to equity | B32: 0.008738 | M32: Rs 865.93 cr over Rs 99,095 cr.
A33: Levered beta (bottom up) | B33: =B31*(1+(1-B$3*0+0.25168)*B32) -> 0.90984346
A34: Pre tax cost of debt | B34: 0.08 | M34: Nominal. Barely matters at this leverage.
A35: Statutory tax rate | B35: 0.25168 | M35: Section 115BAA. The reported effective rate is negative and unusable.
A37: Terminal
A38: Long run real GDP growth | B38: 0.065 | M38: Owned assumption.
A39: Long run inflation | B39: 0.04 | M39: RBI CPI target.
A40: Nominal GDP growth | B40: =(1+B38)*(1+B39)-1 -> 0.1076
A41: Terminal growth as a fraction of nominal GDP | B41: 0.65 | M41: 65.0% of nominal GDP, giving 6.99%. RAISED from 46.5% to reflect India's infrastructure runway, which is a genuine medium term demand driver. The HARD CONSTRAINT is that terminal growth can never exceed nominal GDP of 10.76%: a company growing faster than the economy forever eventually becomes larger than the economy. A peer multiple of 19.4x implies 10.99%, which breaches that constraint and is the basis on which this model rejects the peer multiple. Adopting 10.99% ourselves would contradict our own central argument. The same fraction is used for both companies so the two are treated consistently.
A42: Terminal growth rate | B42: =B40*B41 -> 0.06994
A44: Forecast drivers, FY2026-27 to FY2035-36
A45: Driver | C45: FY27 | D45: FY28 | E45: FY29 | F45: FY30 | G45: FY31 | H45: FY32 | I45: FY33 | J45: FY34 | K45: FY35 | L45: FY36
A46: Capacity (MTPA) | C46: 112 | D46: 116 | E46: 119 | F46: 121 | G46: 123 | H46: 125 | I46: 127 | J46: 129 | K46: 131 | L46: 133 | M46: Company targets 119 MTPA. Beyond that this assumes modest brownfield addition only.
A47: Capacity utilisation | C47: 0.7 | D47: 0.725 | E47: 0.75 | F47: 0.775 | G47: 0.795 | H47: 0.81 | I47: 0.825 | J47: 0.835 | K47: 0.845 | L47: 0.85 | M47: From 67.9% today toward 85%. This is the single most important driver: the plants exist, the question is whether they fill.
A48: Realisation growth | C48: 0.048 | D48: 0.04 | E48: 0.032 | F48: 0.024 | G48: 0.02 | H48: 0.016 | I48: 0.014 | J48: 0.012 | K48: 0.012 | L48: 0.012 | M48: Realisation grows below inflation for most of the forecast, consistent with the sector record and with sell side assumptions of flat to falling net sales realisation. Most of the margin improvement is assumed to come from cost and fixed cost absorption, not price.
A49: Standalone share of consolidated revenue | C49: 0.615 | D49: 0.613 | E49: 0.611 | F49: 0.609 | G49: 0.607 | H49: 0.605 | I49: 0.604 | J49: 0.603 | K49: 0.602 | L49: 0.6 | M49: FY2025-26 actual is 61.6%. Held broadly flat with a slight drift as the subsidiaries grow marginally faster. See the Entity Build sheet for the base year derivation.
A50: Standalone EBITDA margin | C50: 0.13 | D50: 0.142 | E50: 0.152 | F50: 0.16 | G50: 0.167 | H50: 0.173 | I50: 0.178 | J50: 0.183 | K50: 0.187 | L50: 0.19 | M50: FY2025-26 actual is 11.7%. The standalone entity carries Sanghi and Penna, which are the weak assets, so this path assumes their integration lifts the parent margin from 11.7% to 19.0% over ten years. This is the single most important assumption in the model.
A51: Subsidiary EBITDA margin | C51: 0.236 | D51: 0.24 | E51: 0.244 | F51: 0.247 | G51: 0.25 | H51: 0.252 | I51: 0.254 | J51: 0.256 | K51: 0.258 | L51: 0.26 | M51: FY2025-26 actual is 23.3%. ACC and Orient are already the better assets, so only modest further improvement is assumed, from 23.3% to 26.0%.
A52: Capital expenditure | C52: 9500 | D52: 9000 | E52: 8500 | F52: 8000 | G52: 7500 | H52: 7500 | I52: 7500 | J52: 7500 | K52: 7500 | L52: 7500 | M52: Tapering as the current expansion completes. Explicit input, not derived from capital intensity.
A53: Depreciation, percent of opening operating assets | C53: 0.08 | D53: 0.08 | E53: 0.08 | F53: 0.08 | G53: 0.08 | H53: 0.08 | I53: 0.08 | J53: 0.08 | K53: 0.08 | L53: 0.08 | M53: FY2025-26 depreciation over opening operating assets. High because of recently acquired and revalued assets.
A54: Net working capital, percent of revenue | C54: -0.0034 | D54: -0.0034 | E54: -0.0034 | F54: -0.0034 | G54: -0.0034 | H54: -0.0034 | I54: -0.0034 | J54: -0.0034 | K54: -0.0034 | L54: -0.0034 | M54: Slightly negative, as reported.
A56: Realisation is assumed to grow at 40% of the EBITDA per tonne growth rate, so most of the margin improvement is assumed to come from cost, not price. That is consistent with the sell side view that cement realisation is flat to falling, and with Ambuja's own ten year record.

Sheet AMB-P&L
A1: Line item | B1: Unit | C1: FY27 | D1: FY28 | E1: FY29 | F1: FY30 | G1: FY31 | H1: FY32 | I1: FY33 | J1: FY34 | K1: FY35 | L1: FY36
A2: Capacity | B2: MTPA | C2: ='AMB-Assumptions'!C46 -> 112 | D2: ='AMB-Assumptions'!D46 -> 116 | E2: ='AMB-Assumptions'!E46 -> 119 | F2: ='AMB-Assumptions'!F46 -> 121 | G2: ='AMB-Assumptions'!G46 -> 123 | H2: ='AMB-Assumptions'!H46 -> 125 | I2: ='AMB-Assumptions'!I46 -> 127 | J2: ='AMB-Assumptions'!J46 -> 129 | ... L2: ='AMB-Assumptions'!L46 -> 133
A3: Utilisation | B3: % | C3: ='AMB-Assumptions'!C47 -> 0.7 | D3: ='AMB-Assumptions'!D47 -> 0.725 | E3: ='AMB-Assumptions'!E47 -> 0.75 | F3: ='AMB-Assumptions'!F47 -> 0.775 | G3: ='AMB-Assumptions'!G47 -> 0.795 | H3: ='AMB-Assumptions'!H47 -> 0.81 | I3: ='AMB-Assumptions'!I47 -> 0.825 | J3: ='AMB-Assumptions'!J47 -> 0.835 | ... L3: ='AMB-Assumptions'!L47 -> 0.85
A4: Sales volume | B4: mn T | C4: =C2*C3 -> 78.4 | D4: =D2*D3 -> 84.1 | E4: =E2*E3 -> 89.25 | F4: =F2*F3 -> 93.775 | G4: =G2*G3 -> 97.785 | H4: =H2*H3 -> 101.25 | I4: =I2*I3 -> 104.775 | J4: =J2*J3 -> 107.715 | ... L4: =L2*L3 -> 113.05
A5: Realisation per tonne | B5: Rs/t | C5: ='AMB-Assumptions'!$B$9*(1+'AMB-Assumptions'!C48) -> 5757.7225 | D5: =C5*(1+'AMB-Assumptions'!D48) -> 5988.0314 | E5: =D5*(1+'AMB-Assumptions'!E48) -> 6179.6484 | F5: =E5*(1+'AMB-Assumptions'!F48) -> 6327.9599 | G5: =F5*(1+'AMB-Assumptions'!G48) -> 6454.5191 | H5: =G5*(1+'AMB-Assumptions'!H48) -> 6557.7914 | I5: =H5*(1+'AMB-Assumptions'!I48) -> 6649.6005 | J5: =I5*(1+'AMB-Assumptions'!J48) -> 6729.3957 | K5: =J5*(1+'AMB-Assumptions'!K48) -> 6810.1485 | L5: =K5*(1+'AMB-Assumptions'!L48) -> 6891.8703
A6: Revenue | B6: Rs cr | C6: =C4*C5/10 -> 45140.544 | D6: =D4*D5/10 -> 50359.344 | E6: =E4*E5/10 -> 55153.362 | F6: =F4*F5/10 -> 59340.444 | G6: =G4*G5/10 -> 63115.515 | H6: =H4*H5/10 -> 66397.638 | I6: =I4*I5/10 -> 69671.19 | J6: =J4*J5/10 -> 72485.686 | ... L6: =L4*L5/10 -> 77912.593
A8: Standalone share of revenue | B8: % | C8: ='AMB-Assumptions'!C49 -> 0.615 | D8: ='AMB-Assumptions'!D49 -> 0.613 | E8: ='AMB-Assumptions'!E49 -> 0.611 | F8: ='AMB-Assumptions'!F49 -> 0.609 | G8: ='AMB-Assumptions'!G49 -> 0.607 | H8: ='AMB-Assumptions'!H49 -> 0.605 | I8: ='AMB-Assumptions'!I49 -> 0.604 | J8: ='AMB-Assumptions'!J49 -> 0.603 | ... L8: ='AMB-Assumptions'!L49 -> 0.6
A9: Standalone revenue | B9: Rs cr | C9: =C6*C8 -> 27761.435 | D9: =D6*D8 -> 30870.278 | E9: =E6*E8 -> 33698.704 | F9: =F6*F8 -> 36138.331 | G9: =G6*G8 -> 38311.118 | H9: =H6*H8 -> 40170.571 | I9: =I6*I8 -> 42081.398 | J9: =J6*J8 -> 43708.869 | ... L9: =L6*L8 -> 46747.556
A10: Standalone EBITDA margin | B10: % | C10: ='AMB-Assumptions'!C50 -> 0.13 | D10: ='AMB-Assumptions'!D50 -> 0.142 | E10: ='AMB-Assumptions'!E50 -> 0.152 | F10: ='AMB-Assumptions'!F50 -> 0.16 | G10: ='AMB-Assumptions'!G50 -> 0.167 | H10: ='AMB-Assumptions'!H50 -> 0.173 | I10: ='AMB-Assumptions'!I50 -> 0.178 | J10: ='AMB-Assumptions'!J50 -> 0.183 | ... L10: ='AMB-Assumptions'!L50 -> 0.19
A11: Standalone EBITDA | B11: Rs cr | C11: =C9*C10 -> 3608.9865 | D11: =D9*D10 -> 4383.5794 | E11: =E9*E10 -> 5122.203 | F11: =F9*F10 -> 5782.1329 | G11: =G9*G10 -> 6397.9567 | H11: =H9*H10 -> 6949.5088 | I11: =I9*I10 -> 7490.4889 | J11: =J9*J10 -> 7998.723 | ... L11: =L9*L10 -> 8882.0356
A13: Subsidiary revenue | B13: Rs cr | C13: =C6-C9 -> 17379.11 | D13: =D6-D9 -> 19489.066 | E13: =E6-E9 -> 21454.658 | F13: =F6-F9 -> 23202.114 | G13: =G6-G9 -> 24804.398 | H13: =H6-H9 -> 26227.067 | I13: =I6-I9 -> 27589.791 | J13: =J6-J9 -> 28776.817 | ... L13: =L6-L9 -> 31165.037
A14: Subsidiary EBITDA margin | B14: % | C14: ='AMB-Assumptions'!C51 -> 0.236 | D14: ='AMB-Assumptions'!D51 -> 0.24 | E14: ='AMB-Assumptions'!E51 -> 0.244 | F14: ='AMB-Assumptions'!F51 -> 0.247 | G14: ='AMB-Assumptions'!G51 -> 0.25 | H14: ='AMB-Assumptions'!H51 -> 0.252 | I14: ='AMB-Assumptions'!I51 -> 0.254 | J14: ='AMB-Assumptions'!J51 -> 0.256 | ... L14: ='AMB-Assumptions'!L51 -> 0.26
A15: Subsidiary EBITDA | B15: Rs cr | C15: =C13*C14 -> 4101.4698 | D15: =D13*D14 -> 4677.3759 | E15: =E13*E14 -> 5234.9365 | F15: =F13*F14 -> 5730.9221 | G15: =G13*G14 -> 6201.0994 | H15: =H13*H14 -> 6609.2209 | I15: =I13*I14 -> 7007.8069 | J15: =J13*J14 -> 7366.8653 | ... L15: =L13*L14 -> 8102.9097
A17: EBITDA | B17: Rs cr | C17: =C11+C15 -> 7710.4564 | D17: =D11+D15 -> 9060.9553 | E17: =E11+E15 -> 10357.14 | F17: =F11+F15 -> 11513.055 | G17: =G11+G15 -> 12599.056 | H17: =H11+H15 -> 13558.73 | I17: =I11+I15 -> 14498.296 | J17: =J11+J15 -> 15365.588 | ... L17: =L11+L15 -> 16984.945
A18: Memo: consolidated EBITDA margin | B18: % | C18: =C17/C6 -> 0.17081 | D18: =D17/D6 -> 0.179926 | E18: =E17/E6 -> 0.187788 | F18: =F17/F6 -> 0.194017 | G18: =G17/G6 -> 0.199619 | H18: =H17/H6 -> 0.204205 | I18: =I17/I6 -> 0.208096 | J18: =J17/J6 -> 0.211981 | ... L18: =L17/L6 -> 0.218
A19: Memo: EBITDA per tonne | B19: Rs/t | C19: =C17*10/C4 -> 983.47658 | D19: =D17*10/D4 -> 1077.4025 | E19: =E17*10/E4 -> 1160.4638 | F19: =F17*10/F4 -> 1227.7318 | G19: =G17*10/G4 -> 1288.4447 | H19: =H17*10/H4 -> 1339.1338 | I19: =I17*10/I4 -> 1383.7553 | J19: =J17*10/J4 -> 1426.504 | ... L19: =L17*10/L4 -> 1502.4277
A21: Opening operating fixed assets | B21: Rs cr | C21: ='AMB-Assumptions'!$B$10 -> 44368.88 | D21: =C24 -> 50319.37 | E21: =D24 -> 55293.82 | F21: =E24 -> 59370.314 | G21: =F24 -> 62620.689 | H21: =G24 -> 65111.034 | I21: =H24 -> 67402.151 | J21: =I24 -> 69509.979 | K21: =J24 -> 71449.181 | L21: =K24 -> 73233.246
A22: Depreciation and amortisation | B22: Rs cr | C22: =C21*'AMB-Assumptions'!C53 -> 3549.5104 | D22: =D21*'AMB-Assumptions'!D53 -> 4025.5496 | E22: =E21*'AMB-Assumptions'!E53 -> 4423.5056 | F22: =F21*'AMB-Assumptions'!F53 -> 4749.6252 | G22: =G21*'AMB-Assumptions'!G53 -> 5009.6551 | H22: =H21*'AMB-Assumptions'!H53 -> 5208.8827 | I22: =I21*'AMB-Assumptions'!I53 -> 5392.1721 | J22: =J21*'AMB-Assumptions'!J53 -> 5560.7983 | ... L22: =L21*'AMB-Assumptions'!L53 -> 5858.6597
A23: Capital expenditure | B23: Rs cr | C23: ='AMB-Assumptions'!C52 -> 9500 | D23: ='AMB-Assumptions'!D52 -> 9000 | E23: ='AMB-Assumptions'!E52 -> 8500 | F23: ='AMB-Assumptions'!F52 -> 8000 | G23: ='AMB-Assumptions'!G52 -> 7500 | H23: ='AMB-Assumptions'!H52 -> 7500 | I23: ='AMB-Assumptions'!I52 -> 7500 | J23: ='AMB-Assumptions'!J52 -> 7500 | ... L23: ='AMB-Assumptions'!L52 -> 7500
A24: Closing operating fixed assets | B24: Rs cr | C24: =C21+C23-C22 -> 50319.37 | D24: =D21+D23-D22 -> 55293.82 | E24: =E21+E23-E22 -> 59370.314 | F24: =F21+F23-F22 -> 62620.689 | G24: =G21+G23-G22 -> 65111.034 | H24: =H21+H23-H22 -> 67402.151 | I24: =I21+I23-I22 -> 69509.979 | J24: =J21+J23-J22 -> 71449.181 | ... L24: =L21+L23-L22 -> 74874.587
A25: EBIT | B25: Rs cr | C25: =C17-C22 -> 4160.946 | D25: =D17-D22 -> 5035.4057 | E25: =E17-E22 -> 5933.6339 | F25: =F17-F22 -> 6763.4298 | G25: =G17-G22 -> 7589.4009 | H25: =H17-H22 -> 8349.847 | I25: =I17-I22 -> 9106.1237 | J25: =J17-J22 -> 9804.7899 | ... L25: =L17-L22 -> 11126.286
A26: NOPAT (EBIT at statutory tax) | B26: Rs cr | C26: =C25*(1-'AMB-Assumptions'!$B$35) -> 3113.7191 | D26: =D25*(1-'AMB-Assumptions'!$B$35) -> 3768.0948 | E26: =E25*(1-'AMB-Assumptions'!$B$35) -> 4440.2569 | F26: =F25*(1-'AMB-Assumptions'!$B$35) -> 5061.2098 | G26: =G25*(1-'AMB-Assumptions'!$B$35) -> 5679.3005 | H26: =H25*(1-'AMB-Assumptions'!$B$35) -> 6248.3575 | I26: =I25*(1-'AMB-Assumptions'!$B$35) -> 6814.2945 | J26: =J25*(1-'AMB-Assumptions'!$B$35) -> 7337.1204 | ... L26: =L25*(1-'AMB-Assumptions'!$B$35) -> 8326.0221
A27: Net working capital (closing) | B27: Rs cr | C27: =C6*'AMB-Assumptions'!C54 -> -153.47785 | D27: =D6*'AMB-Assumptions'!D54 -> -171.22177 | E27: =E6*'AMB-Assumptions'!E54 -> -187.52143 | F27: =F6*'AMB-Assumptions'!F54 -> -201.75751 | G27: =G6*'AMB-Assumptions'!G54 -> -214.59275 | H27: =H6*'AMB-Assumptions'!H54 -> -225.75197 | I27: =I6*'AMB-Assumptions'!I54 -> -236.88204 | J27: =J6*'AMB-Assumptions'!J54 -> -246.45133 | ... L27: =L6*'AMB-Assumptions'!L54 -> -264.90282
A28: Change in net working capital | B28: Rs cr | C28: =C27-'AMB-Assumptions'!$B$3 -> -14.07785 | D28: =D27-C27 -> -17.743919 | E28: =E27-D27 -> -16.299661 | F28: =F27-E27 -> -14.236081 | G28: =G27-F27 -> -12.835242 | H28: =H27-G27 -> -11.159218 | I28: =I27-H27 -> -11.130074 | J28: =J27-I27 -> -9.5692885 | K28: =K27-J27 -> -9.8574584 | L28: =L27-K27 -> -8.594026
A29: FCFF | B29: Rs cr | C29: =C26+C22-C23-C28 -> -2822.6927 | D29: =D26+D22-D23-D28 -> -1188.6117 | E29: =E26+E22-E23-E28 -> 380.06219 | F29: =F26+F22-F23-F28 -> 1825.0711 | G29: =G26+G22-G23-G28 -> 3201.7909 | H29: =H26+H22-H23-H28 -> 3968.3995 | I29: =I26+I22-I23-I28 -> 4717.5967 | J29: =J26+J22-J23-J28 -> 5407.488 | ... L29: =L26+L22-L23-L28 -> 6693.2758
A30: Memo: EBITDA margin | B30: % | C30: =IFERROR(C17/C6,"") -> 0.17081 | D30: =IFERROR(D17/D6,"") -> 0.179926 | E30: =IFERROR(E17/E6,"") -> 0.187788 | F30: =IFERROR(F17/F6,"") -> 0.194017 | G30: =IFERROR(G17/G6,"") -> 0.199619 | H30: =IFERROR(H17/H6,"") -> 0.204205 | I30: =IFERROR(I17/I6,"") -> 0.208096 | J30: =IFERROR(J17/J6,"") -> 0.211981 | ... L30: =IFERROR(L17/L6,"") -> 0.218
A32: THIS SHEET IS A BUILD UP, NOT A CONSOLIDATED FORECAST. Revenue is built top down from physical capacity times utilisation times realisation, which disciplines it against the plant the company actually owns. That consolidated revenue is then SPLIT into the standalone parent and the subsidiary block using the FY2025-26 revenue share of 61.6%, and each block carries its own EBITDA margin: the parent starts at 11.7% because Sanghi and Penna sit inside it, the subsidiaries start at 23.3% because ACC and Orient sit outside it. Consolidated EBITDA is the SUM of the two blocks, not an assumed group margin. Free cash flow is negative in the early years, which is what a company at 68% utilisation with Rs 9,085 crore of capital work in progress looks like.
A35: HISTORICAL ACTUALS, for comparison with the forecast above
A36: Line item | B36: Unit | C36: FY25 | D36: FY26
C37: Actual | D37: Actual
A38: Cement sales volume (Mn.T) | D38: 74
A39: Capacity (MTPA) | D39: 109
A40: Capacity utilisation | B40: % | D40: 0.679
A41: Revenue including grants | B41: Rs cr | C41: 35336 | D41: 40656
A42: of which standalone | B42: Rs cr | D42: 25062
A43: of which subsidiaries | B43: Rs cr | D43: 15594
A44: EBITDA (uniform definition) | B44: Rs cr | C44: 5984 | D44: 6559
A45: of which standalone | B45: Rs cr | D45: 2930
A46: of which subsidiaries | B46: Rs cr | D46: 3629
A47: EBITDA margin, consolidated | B47: % | C47: 0.169 | D47: 0.161
A48: standalone margin | B48: % | D48: 0.117
A49: subsidiary margin | B49: % | D49: 0.233
A50: Depreciation and amortisation | B50: Rs cr | C50: 2297 | D50: 3570
A51: EBIT | B51: Rs cr | C51: 3687 | D51: 2989
A52: Operating fixed assets | B52: Rs cr | C52: 36307 | D52: 44369
A53: Goodwill and intangibles | B53: Rs cr | C53: 16252 | D53: 22979
A54: Invested capital incl goodwill | B54: Rs cr | C54: 52559 | D54: 67208
A55: ROIC incl goodwill | B55: % | C55: 0.052 | D55: 0.033
A56: ROIC excl goodwill | B56: % | C56: 0.076 | D56: 0.05
A58: The forecast block above is marked in the column headers; this block is ACTUAL and is shown separately rather than beside the forecast so that no historical figure can be picked up by a forecast formula. Every figure here is as reported in the annual report and is the base from which the forecast drivers were set. Note the standalone and subsidiary split: the parent carries 61.6% of group revenue but only 44.7% of group EBITDA, which is the finding the Entity Build sheet develops.

Sheet AMB-Balance Sheet
A1: Line item | B1: Unit | C1: FY27 | D1: FY28 | E1: FY29 | F1: FY30 | G1: FY31 | H1: FY32 | I1: FY33 | J1: FY34 | K1: FY35 | L1: FY36
A2: Opening operating invested capital | B2: Rs cr | C2: ='AMB-Assumptions'!$B$10+'AMB-Assumptions'!$B$3 -> 44229.48 | D2: =C5 -> 50165.892 | E2: =D5 -> 55122.598 | F2: =E5 -> 59182.793 | G2: =F5 -> 62418.932 | H2: =G5 -> 64896.441 | I2: =H5 -> 67176.399 | J2: =I5 -> 69273.097 | K2: =J5 -> 71202.73 | L2: =K5 -> 72976.938
A3: Add: Capex less depreciation | B3: Rs cr | C3: ='AMB-P&L'!C23-'AMB-P&L'!C22 -> 5950.4896 | D3: ='AMB-P&L'!D23-'AMB-P&L'!D22 -> 4974.4504 | E3: ='AMB-P&L'!E23-'AMB-P&L'!E22 -> 4076.4944 | F3: ='AMB-P&L'!F23-'AMB-P&L'!F22 -> 3250.3748 | G3: ='AMB-P&L'!G23-'AMB-P&L'!G22 -> 2490.3449 | H3: ='AMB-P&L'!H23-'AMB-P&L'!H22 -> 2291.1173 | I3: ='AMB-P&L'!I23-'AMB-P&L'!I22 -> 2107.8279 | J3: ='AMB-P&L'!J23-'AMB-P&L'!J22 -> 1939.2017 | ... L3: ='AMB-P&L'!L23-'AMB-P&L'!L22 -> 1641.3403
A4: Add: Change in net working capital | B4: Rs cr | C4: ='AMB-P&L'!C28 -> -14.07785 | D4: ='AMB-P&L'!D28 -> -17.743919 | E4: ='AMB-P&L'!E28 -> -16.299661 | F4: ='AMB-P&L'!F28 -> -14.236081 | G4: ='AMB-P&L'!G28 -> -12.835242 | H4: ='AMB-P&L'!H28 -> -11.159218 | I4: ='AMB-P&L'!I28 -> -11.130074 | J4: ='AMB-P&L'!J28 -> -9.5692885 | ... L4: ='AMB-P&L'!L28 -> -8.594026
A5: Closing operating invested capital | B5: Rs cr | C5: =SUM(C2:C4) -> 50165.892 | D5: =SUM(D2:D4) -> 55122.598 | E5: =SUM(E2:E4) -> 59182.793 | F5: =SUM(F2:F4) -> 62418.932 | G5: =SUM(G2:G4) -> 64896.441 | H5: =SUM(H2:H4) -> 67176.399 | I5: =SUM(I2:I4) -> 69273.097 | J5: =SUM(J2:J4) -> 71202.73 | ... L5: =SUM(L2:L4) -> 74609.684
A6: Goodwill and intangibles (held flat) | B6: Rs cr | C6: ='AMB-Assumptions'!$B$11 -> 22978.64 | D6: ='AMB-Assumptions'!$B$11 -> 22978.64 | E6: ='AMB-Assumptions'!$B$11 -> 22978.64 | F6: ='AMB-Assumptions'!$B$11 -> 22978.64 | G6: ='AMB-Assumptions'!$B$11 -> 22978.64 | H6: ='AMB-Assumptions'!$B$11 -> 22978.64 | I6: ='AMB-Assumptions'!$B$11 -> 22978.64 | J6: ='AMB-Assumptions'!$B$11 -> 22978.64 | ... L6: ='AMB-Assumptions'!$B$11 -> 22978.64
A7: Total invested capital (opening, incl goodwill) | B7: Rs cr | C7: =C2+C6 -> 67208.12 | D7: =D2+D6 -> 73144.532 | E7: =E2+E6 -> 78101.238 | F7: =F2+F6 -> 82161.433 | G7: =G2+G6 -> 85397.572 | H7: =H2+H6 -> 87875.081 | I7: =I2+I6 -> 90155.039 | J7: =J2+J6 -> 92251.737 | ... L7: =L2+L6 -> 95955.578
A8: NOPAT | B8: Rs cr | C8: ='AMB-P&L'!C26 -> 3113.7191 | D8: ='AMB-P&L'!D26 -> 3768.0948 | E8: ='AMB-P&L'!E26 -> 4440.2569 | F8: ='AMB-P&L'!F26 -> 5061.2098 | G8: ='AMB-P&L'!G26 -> 5679.3005 | H8: ='AMB-P&L'!H26 -> 6248.3575 | I8: ='AMB-P&L'!I26 -> 6814.2945 | J8: ='AMB-P&L'!J26 -> 7337.1204 | ... L8: ='AMB-P&L'!L26 -> 8326.0221
A9: ROIC including goodwill | B9: Rs cr | C9: =IFERROR(C8/C7,"") -> 0.046329507 | D9: =IFERROR(D8/D7,"") -> 0.051515742 | E9: =IFERROR(E8/E7,"") -> 0.05685258 | F9: =IFERROR(F8/F7,"") -> 0.061600798 | G9: =IFERROR(G8/G7,"") -> 0.066504239 | H9: =IFERROR(H8/H7,"") -> 0.071104998 | I9: =IFERROR(I8/I7,"") -> 0.075584178 | J9: =IFERROR(J8/J7,"") -> 0.079533682 | ... L9: =IFERROR(L8/L7,"") -> 0.086769548
A10: ROIC on operating capital only | B10: Rs cr | C10: =IFERROR(C8/C2,"") -> 0.070399179 | D10: =IFERROR(D8/D2,"") -> 0.075112685 | E10: =IFERROR(E8/E2,"") -> 0.080552388 | F10: =IFERROR(F8/F2,"") -> 0.085518266 | G10: =IFERROR(G8/G2,"") -> 0.090986826 | H10: =IFERROR(H8/H2,"") -> 0.096281975 | I10: =IFERROR(I8/I2,"") -> 0.10143882 | J10: =IFERROR(J8/J2,"") -> 0.10591587 | ... L10: =IFERROR(L8/L2,"") -> 0.11409114
A12: Terminal year, steady state
A13: NOPAT in the terminal year | C13: =L8*(1+'AMB-Assumptions'!$B$42) -> 8908.3441
A14: Closing OPERATING invested capital | C14: =L5 -> 74609.684
A15: Reinvestment = g x operating invested capital | C15: ='AMB-Assumptions'!$B$42*C14 -> 5218.2013
A16: Terminal FCFF | C16: =C13-C15 -> 3690.1428
A17: Implied terminal ROIC (operating) | C17: =IFERROR(C13/C14,"") -> 0.1193993
A18: Implied terminal reinvestment rate | C18: =IFERROR('AMB-Assumptions'!$B$42/C17,"") -> 0.58576558
A20: Terminal reinvestment is charged on OPERATING invested capital, excluding goodwill. Organic growth does not require buying more goodwill, so charging g times goodwill would overstate the reinvestment the company must make forever. Getting this wrong understates the value by roughly Rs 46 per share, and in an earlier draft it drove the equity value negative. Goodwill remains inside invested capital for the ROIC measure above, because it is capital shareholders actually paid, and both versions of ROIC are shown so the reader can see the difference.

Sheet AMB-Cash Flow
A1: Cash flow: historical actual and forecast
A3: Historical, consolidated as reported
A4: Line item | B4: Unit | C4: FY2024-25 | D4: FY2025-26
A5: Profit before tax | B5: Rs cr | C5: 6103.67 | D5: 3298.77
A6: Depreciation and amortisation | B6: Rs cr | C6: 2297.04 | D6: 3570.41
A7: Finance costs | B7: Rs cr | C7: 215.94 | D7: 223.61
A8: Other income | B8: Rs cr | C8: -2654.25 | D8: -834.34
A10: The annual report cash flow statement is not reproduced line by line here because our valuation is built on free cash flow to the firm derived from the forecast rather than on reported operating cash flow. The reconciling items above are the ones that matter for that derivation. If the full statement is required for submission it should be spread from the report and entered as blue inputs.
A14: Forecast free cash flow to the firm
A15: Line item | B15: Unit | C15: FY27 | D15: FY28 | E15: FY29 | F15: FY30 | G15: FY31 | H15: FY32 | I15: FY33 | J15: FY34 | K15: FY35 | L15: FY36
A16: EBITDA | B16: Rs cr | C16: ='AMB-P&L'!C17 -> 7710.4564 | D16: ='AMB-P&L'!D17 -> 9060.9553 | E16: ='AMB-P&L'!E17 -> 10357.14 | F16: ='AMB-P&L'!F17 -> 11513.055 | G16: ='AMB-P&L'!G17 -> 12599.056 | H16: ='AMB-P&L'!H17 -> 13558.73 | I16: ='AMB-P&L'!I17 -> 14498.296 | J16: ='AMB-P&L'!J17 -> 15365.588 | ... L16: ='AMB-P&L'!L17 -> 16984.945
A17: Less: Depreciation and amortisation | B17: Rs cr | C17: =-'AMB-P&L'!C22 -> -3549.5104 | D17: =-'AMB-P&L'!D22 -> -4025.5496 | E17: =-'AMB-P&L'!E22 -> -4423.5056 | F17: =-'AMB-P&L'!F22 -> -4749.6252 | G17: =-'AMB-P&L'!G22 -> -5009.6551 | H17: =-'AMB-P&L'!H22 -> -5208.8827 | I17: =-'AMB-P&L'!I22 -> -5392.1721 | J17: =-'AMB-P&L'!J22 -> -5560.7983 | ... L17: =-'AMB-P&L'!L22 -> -5858.6597
A18: EBIT | B18: Rs cr | C18: ='AMB-P&L'!C25 -> 4160.946 | D18: ='AMB-P&L'!D25 -> 5035.4057 | E18: ='AMB-P&L'!E25 -> 5933.6339 | F18: ='AMB-P&L'!F25 -> 6763.4298 | G18: ='AMB-P&L'!G25 -> 7589.4009 | H18: ='AMB-P&L'!H25 -> 8349.847 | I18: ='AMB-P&L'!I25 -> 9106.1237 | J18: ='AMB-P&L'!J25 -> 9804.7899 | ... L18: ='AMB-P&L'!L25 -> 11126.286
A19: NOPAT at statutory tax | B19: Rs cr | C19: ='AMB-P&L'!C26 -> 3113.7191 | D19: ='AMB-P&L'!D26 -> 3768.0948 | E19: ='AMB-P&L'!E26 -> 4440.2569 | F19: ='AMB-P&L'!F26 -> 5061.2098 | G19: ='AMB-P&L'!G26 -> 5679.3005 | H19: ='AMB-P&L'!H26 -> 6248.3575 | I19: ='AMB-P&L'!I26 -> 6814.2945 | J19: ='AMB-P&L'!J26 -> 7337.1204 | ... L19: ='AMB-P&L'!L26 -> 8326.0221
A20: Add: Depreciation and amortisation | B20: Rs cr | C20: ='AMB-P&L'!C22 -> 3549.5104 | D20: ='AMB-P&L'!D22 -> 4025.5496 | E20: ='AMB-P&L'!E22 -> 4423.5056 | F20: ='AMB-P&L'!F22 -> 4749.6252 | G20: ='AMB-P&L'!G22 -> 5009.6551 | H20: ='AMB-P&L'!H22 -> 5208.8827 | I20: ='AMB-P&L'!I22 -> 5392.1721 | J20: ='AMB-P&L'!J22 -> 5560.7983 | ... L20: ='AMB-P&L'!L22 -> 5858.6597
A21: Less: Capital expenditure | B21: Rs cr | C21: =-'AMB-P&L'!C23 -> -9500 | D21: =-'AMB-P&L'!D23 -> -9000 | E21: =-'AMB-P&L'!E23 -> -8500 | F21: =-'AMB-P&L'!F23 -> -8000 | G21: =-'AMB-P&L'!G23 -> -7500 | H21: =-'AMB-P&L'!H23 -> -7500 | I21: =-'AMB-P&L'!I23 -> -7500 | J21: =-'AMB-P&L'!J23 -> -7500 | ... L21: =-'AMB-P&L'!L23 -> -7500
A22: Less: Change in net working capital | B22: Rs cr | C22: =-'AMB-P&L'!C28 -> 14.07785 | D22: =-'AMB-P&L'!D28 -> 17.743919 | E22: =-'AMB-P&L'!E28 -> 16.299661 | F22: =-'AMB-P&L'!F28 -> 14.236081 | G22: =-'AMB-P&L'!G28 -> 12.835242 | H22: =-'AMB-P&L'!H28 -> 11.159218 | I22: =-'AMB-P&L'!I28 -> 11.130074 | J22: =-'AMB-P&L'!J28 -> 9.5692885 | ... L22: =-'AMB-P&L'!L28 -> 8.594026
A23: Free cash flow to the firm | B23: Rs cr | C23: ='AMB-P&L'!C29 -> -2822.6927 | D23: ='AMB-P&L'!D29 -> -1188.6117 | E23: ='AMB-P&L'!E29 -> 380.06219 | F23: ='AMB-P&L'!F29 -> 1825.0711 | G23: ='AMB-P&L'!G29 -> 3201.7909 | H23: ='AMB-P&L'!H29 -> 3968.3995 | I23: ='AMB-P&L'!I29 -> 4717.5967 | J23: ='AMB-P&L'!J29 -> 5407.488 | ... L23: ='AMB-P&L'!L29 -> 6693.2758
A25: Free cash flow is NEGATIVE in the first two forecast years. That is not a modelling error; it is what a company at 68% utilisation with capital work in progress of Rs 9,085 crore still to commission looks like.

Sheet AMB-Cost of Capital
A1: Cost of Capital
A3: Risk free rate | B3: ='AMB-Assumptions'!$B$29 -> 0.0498 | C3: G-Sec less the sovereign default spread.
A4: India equity risk premium | B4: ='AMB-Assumptions'!$B$30 -> 0.0708
A5: Levered beta | B5: ='AMB-Assumptions'!$B$33 -> 0.90984346 | C5: Unlevered 0.90 relevered at a debt to equity of only 0.87%.
A6: Cost of equity, CAPM | B6: =B3+B5*B4 -> 0.11421692
A7: Fama French Ke, if computed | C7: Leave blank for CAPM. Fill from the companion notebook. A Fama French Ke is already levered, so do not relever a beta on top of it.
A8: Cost of equity (Ke) | B8: =IF(B7="",B6,B7) -> 0.11421692
A9: Pre tax cost of debt (Kd) | B9: ='AMB-Assumptions'!$B$34 -> 0.08
A10: Statutory tax rate | B10: ='AMB-Assumptions'!$B$35 -> 0.25168
A11: Debt to enterprise value (D/V) | B11: ='AMB-Assumptions'!$B$16/('AMB-Assumptions'!$B$16+'AMB-Assumptions'!$B$14) -> 0.0086626845
A12: Equity to enterprise value (E/V) | B12: =1-B11 -> 0.99133732
A13: WACC (after tax) | B13: =B12*B8+B11*B9*(1-B10) -> 0.11374609
A14: Unlevered cost of capital (rho) | B14: =B12*B8+B11*B9 -> 0.11392051
A15: Check: rho = WACC + Kd x t x D/V | B15: =B13+B9*B10*B11 -> 0.11392051
A17: Ambuja carries almost no debt, so WACC, rho and the cost of equity are within four basis points of each other and the capital structure machinery barely binds. The circularity that mattered for UltraTech is immaterial here: at a debt to equity of 0.87%, no plausible revision to the equity value moves the weights enough to matter. That is worth stating rather than leaving the reader to wonder whether it was checked.

Sheet AMB-Beta
A1: Beta: bottom up build and live regression cross check
A2: Blue on yellow is an input. The regression block below computes itself once monthly closes are pasted in.
A4: Method used: bottom up beta
A5: Input | B5: Value | H5: Source and reasoning
A6: Unlevered beta, Building Materials | B6: 0.9 | H6: Damodaran, Betas by Sector (Global), January 2026. 469 firms. CASH CORRECTED figure, not the raw 0.86, because this model adds cash back separately at the equity bridge; the raw beta would count cash twice.
A7: Market debt to equity | B7: 0.008738 | H7: Borrowings and leases over market capitalisation, both from the company's own disclosure.
A8: Marginal tax rate | B8: 0.25168 | H8: Section 115BAA: 22% plus 10% surcharge plus 4% cess.
A9: Levered beta (Hamada) | B9: =B6*(1+(1-B8)*B7) -> 0.90588494 | H9: Unlevered x (1 + (1 - t) x D/E). This is the figure carried into the Cost of Capital sheet.
A11: Cross check: live regression beta, 60 monthly observations
A12: Regression beta (slope) | B12: =IFERROR(SLOPE(G25:G84,F25:F84),"paste prices below") -> 1.150641
A13: R squared | B13: =IFERROR(RSQ(G25:G84,F25:F84),"") -> 0.26721211
A14: Observations | B14: =COUNT(F25:F84) -> 60
A15: Blume adjusted beta | B15: =IFERROR(0.67*B12+0.33,"") -> 1.1009294
A16: Difference vs bottom up | B16: =IFERROR(B12-B9,"") -> 0.24475602
A18: DATA POPULATED. 61 month end closes from March 2021 to March 2026 for the NIFTY 500 and for AMBUJACEM, newest first. SOURCE NOTE, stated precisely: the series was supplied with an adjusted close column, which is a market data vendor convention rather than the NSE bhavcopy format, so it should be treated as vendor sourced rather than exchange sourced. That is acceptable for a beta regression, which needs a consistent series rather than an authoritative one, but it is why the sourcing claim elsewhere in this model is confined to the FINANCIAL STATEMENTS and the COST OF CAPITAL PARAMETERS, which come from annual reports, RBI and Damodaran respectively.
B24: Month end | C24: NIFTY 500 close | D24: AMBUJACEM close | F24: Index return | G24: Stock return | H24: Newest month at the top. Returns are computed against the row below.
B25: 2026-03 | C25: 20528.05 | D25: 401.25 | F25: =IFERROR(C25/C26-1,"") -> -0.11390413 | G25: =IFERROR(D25/D26-1,"") -> -0.19814149
B26: 2026-02 | C26: 23166.85 | D26: 500.4 | F26: =IFERROR(C26/C27-1,"") -> 0.003784744 | G26: =IFERROR(D26/D27-1,"") -> -0.019112026
B27: 2026-01 | C27: 23079.5 | D27: 510.15 | F27: =IFERROR(C27/C28-1,"") -> -0.033179664 | G27: =IFERROR(D27/D28-1,"") -> -0.083041251
B28: 2025-12 | C28: 23871.55 | D28: 556.35 | F28: =IFERROR(C28/C29-1,"") -> -0.0025759196 | G28: =IFERROR(D28/D29-1,"") -> 0.011177754
B29: 2025-11 | C29: 23933.2 | D29: 550.2 | F29: =IFERROR(C29/C30-1,"") -> 0.0093967204 | G29: =IFERROR(D29/D30-1,"") -> -0.026883622
B30: 2025-10 | C30: 23710.4 | D30: 565.4 | F30: =IFERROR(C30/C31-1,"") -> 0.0429443 | G30: =IFERROR(D30/D31-1,"") -> -0.0079831564
B31: 2025-09 | C31: 22734.1 | D31: 569.95 | F31: =IFERROR(C31/C32-1,"") -> 0.012070988 | G31: =IFERROR(D31/D32-1,"") -> 0.011985085
B32: 2025-08 | C32: 22462.95 | D32: 563.2 | F32: =IFERROR(C32/C33-1,"") -> -0.019725114 | G32: =IFERROR(D32/D33-1,"") -> -0.049772229
B33: 2025-07 | C33: 22914.95 | D33: 592.7 | F33: =IFERROR(C33/C34-1,"") -> -0.029734685 | G33: =IFERROR(D33/D34-1,"") -> 0.026409213
B34: 2025-06 | C34: 23617.2 | D34: 577.45 | F34: =IFERROR(C34/C35-1,"") -> 0.035753521 | G34: =IFERROR(D34/D35-1,"") -> 0.043270099
B35: 2025-05 | C35: 22801.95 | D35: 553.5 | F35: =IFERROR(C35/C36-1,"") -> 0.035038504 | G35: =IFERROR(D35/D36-1,"") -> 0.025569761
B36: 2025-04 | C36: 22030.05 | D36: 539.7 | F36: =IFERROR(C36/C37-1,"") -> 0.032357758 | G36: =IFERROR(D36/D37-1,"") -> 0.0025076623
... B84: 2021-04 | C84: 12364.35 | D84: 309.05 | F84: =IFERROR(C84/C85-1,"") -> 0.0041133047 | G84: =IFERROR(D84/D85-1,"") -> 0.00064756354
B85: 2021-03 | C85: 12313.7 | D85: 308.85
A87: Reading the result. If the regression beta lands close to the bottom up figure, report both and keep the bottom up number, which is more stable. If it differs materially, say which you adopt and why. Note that the sensitivity work on the Sensitivity sheet shows the valuation conclusion does not turn on beta: even a beta of 0.70 leaves the shares far above our value.
A89: Which beta this model uses, and why
A90: Bottom up beta (USED in the model) | B90: 0.9059
A91: Regression beta, NIFTY 500, 60 months | B91: 1.1506
A92: Regression R squared | B92: 0.267
A93: Difference, regression less bottom up | B93: 0.2447
A95: THE CHOICE AND ITS DIRECTION. The model uses the BOTTOM UP beta. Three reasons. First, it is estimated from 469 sector firms rather than from one noisy series: the regression R squared is 0.27, so most of the variation in the stock is not explained by the index at all. Second, bottom up betas are more stable across estimation windows, which matters when the choice of window is itself a judgement. Third and most important, the regression beta of 1.1506 is HIGHER than the bottom up 0.9059, which would raise the cost of capital and LOWER our valuation. Since our recommendation is a SELL, using the lower beta works AGAINST our own conclusion. That is the conservative choice and it forecloses any suggestion that a beta was selected to flatter the answer. The Sensitivity sheet shows the value at the regression beta.

Sheet AMB-FCFF valuation
A1: Line item | B1: Unit | C1: FY27 | D1: FY28 | E1: FY29 | F1: FY30 | G1: FY31 | H1: FY32 | I1: FY33 | J1: FY34 | K1: FY35 | L1: FY36 | M1: Terminal
A2: FCFF | B2: Rs cr | C2: ='AMB-P&L'!C29 -> -2822.6927 | D2: ='AMB-P&L'!D29 -> -1188.6117 | E2: ='AMB-P&L'!E29 -> 380.06219 | F2: ='AMB-P&L'!F29 -> 1825.0711 | G2: ='AMB-P&L'!G29 -> 3201.7909 | H2: ='AMB-P&L'!H29 -> 3968.3995 | I2: ='AMB-P&L'!I29 -> 4717.5967 | J2: ='AMB-P&L'!J29 -> 5407.488 | ... L2: ='AMB-P&L'!L29 -> 6693.2758 | M2: ='AMB-Balance Sheet'!C16 -> 3690.1428
A3: Discount factor at WACC | B3: Rs cr | C3: =1/(1+'AMB-Cost of Capital'!$B$13)^1 -> 0.89787072 | D3: =1/(1+'AMB-Cost of Capital'!$B$13)^2 -> 0.80617183 | E3: =1/(1+'AMB-Cost of Capital'!$B$13)^3 -> 0.72383808 | F3: =1/(1+'AMB-Cost of Capital'!$B$13)^4 -> 0.64991301 | G3: =1/(1+'AMB-Cost of Capital'!$B$13)^5 -> 0.58353786 | H3: =1/(1+'AMB-Cost of Capital'!$B$13)^6 -> 0.52394156 | I3: =1/(1+'AMB-Cost of Capital'!$B$13)^7 -> 0.47043178 | J3: =1/(1+'AMB-Cost of Capital'!$B$13)^8 -> 0.42238692 | K3: =1/(1+'AMB-Cost of Capital'!$B$13)^9 -> 0.37924885 | L3: =1/(1+'AMB-Cost of Capital'!$B$13)^10 -> 0.34051644
A4: Present value of FCFF | B4: Rs cr | C4: =C2*C3 -> -2534.4131 | D4: =D2*D3 -> -958.22525 | E4: =E2*E3 -> 275.10348 | F4: =F2*F3 -> 1186.1374 | G4: =G2*G3 -> 1868.3662 | H4: =H2*H3 -> 2079.2094 | I4: =I2*I3 -> 2219.3074 | J4: =J2*J3 -> 2284.0522 | ... L4: =L2*L3 -> 2279.1704
A6: Sum of PV of explicit FCFF | C6: =SUM(C4:L4) -> 11008.937
A7: Terminal value | C7: =M2/('AMB-Cost of Capital'!$B$13-'AMB-Assumptions'!$B$42) -> 84238.124
A8: PV of terminal value | C8: =C7*L3 -> 28684.466
A9: Enterprise value of operations | C9: =C6+C8 -> 39693.403
A10: Add: Cash, bank and current investments | C10: ='AMB-Assumptions'!$B$17 -> 958.6
A11: Less: Borrowings and leases | C11: =-'AMB-Assumptions'!$B$16 -> -865.93
A12: Add: Tax paid under protest (Driver 1a) | C12: ='AMB-Assumptions'!$B$22 -> 614.1
A13: Less: Deferred tax liabilities (Driver 2) | C13: =-'AMB-Assumptions'!$B$23 -> -3466.33
A14: Less: Non-controlling interest | C14: =-'AMB-Assumptions'!$B$18 -> -12498.92
A15: Equity value attributable to owners | C15: =SUM(C9:C14) -> 24434.923
A16: Value per share (Rs) | C16: =C15/'AMB-Assumptions'!$B$15 -> 98.854774
A17: Terminal value as percent of EV | C17: =C8/C9 -> 0.72265071
A18: Implied terminal EV/EBITDA | C18: =C7/('AMB-P&L'!L17*(1+'AMB-Assumptions'!$B$42)) -> 4.6353775

Sheet AMB-CCF valuation
A1: Line item | B1: Unit | C1: FY27 | D1: FY28 | E1: FY29 | F1: FY30 | G1: FY31 | H1: FY32 | I1: FY33 | J1: FY34 | K1: FY35 | L1: FY36 | M1: Terminal
A2: Enterprise value at each year end | B2: Rs cr | C2: =(D2+'AMB-P&L'!D29)/(1+'AMB-Cost of Capital'!$B$13) -> 47031.065 | D2: =(E2+'AMB-P&L'!E29)/(1+'AMB-Cost of Capital'!$B$13) -> 53569.276 | E2: =(F2+'AMB-P&L'!F29)/(1+'AMB-Cost of Capital'!$B$13) -> 59282.51 | F2: =(G2+'AMB-P&L'!G29)/(1+'AMB-Cost of Capital'!$B$13) -> 64200.592 | G2: =(H2+'AMB-P&L'!H29)/(1+'AMB-Cost of Capital'!$B$13) -> 68301.368 | H2: =(I2+'AMB-P&L'!I29)/(1+'AMB-Cost of Capital'!$B$13) -> 72101.982 | I2: =(J2+'AMB-P&L'!J29)/(1+'AMB-Cost of Capital'!$B$13) -> 75585.703 | J2: =(K2+'AMB-P&L'!K29)/(1+'AMB-Cost of Capital'!$B$13) -> 78775.794 | K2: =(L2+'AMB-P&L'!L29)/(1+'AMB-Cost of Capital'!$B$13) -> 81644.642 | L2: ='AMB-FCFF valuation'!C7 -> 84238.124
A3: Enterprise value at valuation date | B3: =(C2+'AMB-P&L'!C29)/(1+'AMB-Cost of Capital'!$B$13) -> 39693.403
A4: Debt at target ratio, opening | B4: Rs cr | C4: =$B$3*'AMB-Cost of Capital'!$B$11 -> 343.85143 | D4: =C2*'AMB-Cost of Capital'!$B$11 -> 407.41528 | E4: =D2*'AMB-Cost of Capital'!$B$11 -> 464.05374 | F4: =E2*'AMB-Cost of Capital'!$B$11 -> 513.54568 | G4: =F2*'AMB-Cost of Capital'!$B$11 -> 556.14948 | H4: =G2*'AMB-Cost of Capital'!$B$11 -> 591.6732 | I4: =H2*'AMB-Cost of Capital'!$B$11 -> 624.59672 | J4: =I2*'AMB-Cost of Capital'!$B$11 -> 654.7751 | K4: =J2*'AMB-Cost of Capital'!$B$11 -> 682.40985 | L4: =K2*'AMB-Cost of Capital'!$B$11 -> 707.26177
A5: Interest on opening debt | B5: Rs cr | C5: =C4*'AMB-Cost of Capital'!$B$9 -> 27.508114 | D5: =D4*'AMB-Cost of Capital'!$B$9 -> 32.593222 | E5: =E4*'AMB-Cost of Capital'!$B$9 -> 37.124299 | F5: =F4*'AMB-Cost of Capital'!$B$9 -> 41.083654 | G5: =G4*'AMB-Cost of Capital'!$B$9 -> 44.491958 | H5: =H4*'AMB-Cost of Capital'!$B$9 -> 47.333856 | I5: =I4*'AMB-Cost of Capital'!$B$9 -> 49.967738 | J5: =J4*'AMB-Cost of Capital'!$B$9 -> 52.382008 | ... L5: =L4*'AMB-Cost of Capital'!$B$9 -> 56.580942
A6: Interest tax shield | B6: Rs cr | C6: =C5*'AMB-Cost of Capital'!$B$10 -> 6.9232422 | D6: =D5*'AMB-Cost of Capital'!$B$10 -> 8.2030622 | E6: =E5*'AMB-Cost of Capital'!$B$10 -> 9.3434436 | F6: =F5*'AMB-Cost of Capital'!$B$10 -> 10.339934 | G6: =G5*'AMB-Cost of Capital'!$B$10 -> 11.197736 | H6: =H5*'AMB-Cost of Capital'!$B$10 -> 11.912985 | I6: =I5*'AMB-Cost of Capital'!$B$10 -> 12.57588 | J6: =J5*'AMB-Cost of Capital'!$B$10 -> 13.183504 | ... L6: =L5*'AMB-Cost of Capital'!$B$10 -> 14.240291 | M6: =L2*'AMB-Cost of Capital'!$B$11*'AMB-Cost of Capital'!$B$9*'AMB-Cost of Capital'!$B$10 -> 14.692641
A7: Capital cash flow | B7: Rs cr | C7: ='AMB-P&L'!C29+C6 -> -2815.7694 | D7: ='AMB-P&L'!D29+D6 -> -1180.4086 | E7: ='AMB-P&L'!E29+E6 -> 389.40563 | F7: ='AMB-P&L'!F29+F6 -> 1835.411 | G7: ='AMB-P&L'!G29+G6 -> 3212.9886 | H7: ='AMB-P&L'!H29+H6 -> 3980.3125 | I7: ='AMB-P&L'!I29+I6 -> 4730.1726 | J7: ='AMB-P&L'!J29+J6 -> 5420.6715 | ... L7: ='AMB-P&L'!L29+L6 -> 6707.5161 | M7: ='AMB-FCFF valuation'!M2+M6 -> 3704.8354
A8: Discount factor at rho | B8: Rs cr | C8: =1/(1+'AMB-Cost of Capital'!$B$14)^1 -> 0.89773013 | D8: =1/(1+'AMB-Cost of Capital'!$B$14)^2 -> 0.80591938 | E8: =1/(1+'AMB-Cost of Capital'!$B$14)^3 -> 0.72349811 | F8: =1/(1+'AMB-Cost of Capital'!$B$14)^4 -> 0.64950605 | G8: =1/(1+'AMB-Cost of Capital'!$B$14)^5 -> 0.58308115 | H8: =1/(1+'AMB-Cost of Capital'!$B$14)^6 -> 0.52344952 | I8: =1/(1+'AMB-Cost of Capital'!$B$14)^7 -> 0.4699164 | J8: =1/(1+'AMB-Cost of Capital'!$B$14)^8 -> 0.42185811 | K8: =1/(1+'AMB-Cost of Capital'!$B$14)^9 -> 0.37871474 | L8: =1/(1+'AMB-Cost of Capital'!$B$14)^10 -> 0.33998363
A9: Present value of CCF | B9: Rs cr | C9: =C7*C8 -> -2527.801 | D9: =D7*D8 -> -951.31419 | E9: =E7*E8 -> 281.73424 | F9: =F7*F8 -> 1192.1105 | G9: =G7*G8 -> 1873.4331 | H9: =H7*H8 -> 2083.4926 | I9: =I7*I8 -> 2222.7857 | J9: =J7*J8 -> 2286.7543 | ... L9: =L7*L8 -> 2280.4457
A11: Sum of PV of explicit CCF | C11: =SUM(C9:L9) -> 11053.82
A12: Terminal value at rho | C12: =M7/('AMB-Cost of Capital'!$B$14-'AMB-Assumptions'!$B$42) -> 84238.124
A13: PV of terminal value | C13: =C12*L8 -> 28639.583
A14: Enterprise value of operations | C14: =C11+C13 -> 39693.403
A15: Equity value attributable to owners | C15: =C14+'AMB-Assumptions'!$B$17+'AMB-Assumptions'!$B$22-'AMB-Assumptions'!$B$16-'AMB-Assumptions'!$B$23-'AMB-Assumptions'!$B$18 -> 24434.923
A16: Value per share (Rs) | C16: =C15/'AMB-Assumptions'!$B$15 -> 98.854774

Sheet AMB-APV valuation
A1: Line item | B1: Unit | C1: FY27 | D1: FY28 | E1: FY29 | F1: FY30 | G1: FY31 | H1: FY32 | I1: FY33 | J1: FY34 | K1: FY35 | L1: FY36 | M1: Terminal
A2: FCFF (unlevered) | B2: Rs cr | C2: ='AMB-P&L'!C29 -> -2822.6927 | D2: ='AMB-P&L'!D29 -> -1188.6117 | E2: ='AMB-P&L'!E29 -> 380.06219 | F2: ='AMB-P&L'!F29 -> 1825.0711 | G2: ='AMB-P&L'!G29 -> 3201.7909 | H2: ='AMB-P&L'!H29 -> 3968.3995 | I2: ='AMB-P&L'!I29 -> 4717.5967 | J2: ='AMB-P&L'!J29 -> 5407.488 | ... L2: ='AMB-P&L'!L29 -> 6693.2758 | M2: ='AMB-FCFF valuation'!M2 -> 3690.1428
A3: Discount factor at rho | B3: Rs cr | C3: =1/(1+'AMB-Cost of Capital'!$B$14)^1 -> 0.89773013 | D3: =1/(1+'AMB-Cost of Capital'!$B$14)^2 -> 0.80591938 | E3: =1/(1+'AMB-Cost of Capital'!$B$14)^3 -> 0.72349811 | F3: =1/(1+'AMB-Cost of Capital'!$B$14)^4 -> 0.64950605 | G3: =1/(1+'AMB-Cost of Capital'!$B$14)^5 -> 0.58308115 | H3: =1/(1+'AMB-Cost of Capital'!$B$14)^6 -> 0.52344952 | I3: =1/(1+'AMB-Cost of Capital'!$B$14)^7 -> 0.4699164 | J3: =1/(1+'AMB-Cost of Capital'!$B$14)^8 -> 0.42185811 | K3: =1/(1+'AMB-Cost of Capital'!$B$14)^9 -> 0.37871474 | L3: =1/(1+'AMB-Cost of Capital'!$B$14)^10 -> 0.33998363
A4: PV of FCFF at rho | B4: Rs cr | C4: =C2*C3 -> -2534.0163 | D4: =D2*D3 -> -957.9252 | E4: =E2*E3 -> 274.97428 | F4: =F2*F3 -> 1185.3947 | G4: =G2*G3 -> 1866.9039 | H4: =H2*H3 -> 2077.2568 | I4: =I2*I3 -> 2216.8761 | J4: =J2*J3 -> 2281.1927 | ... L4: =L2*L3 -> 2275.6042
A5: Interest tax shield | B5: Rs cr | C5: ='AMB-CCF valuation'!C6 -> 6.9232422 | D5: ='AMB-CCF valuation'!D6 -> 8.2030622 | E5: ='AMB-CCF valuation'!E6 -> 9.3434436 | F5: ='AMB-CCF valuation'!F6 -> 10.339934 | G5: ='AMB-CCF valuation'!G6 -> 11.197736 | H5: ='AMB-CCF valuation'!H6 -> 11.912985 | I5: ='AMB-CCF valuation'!I6 -> 12.57588 | J5: ='AMB-CCF valuation'!J6 -> 13.183504 | ... M5: ='AMB-CCF valuation'!M6 -> 14.692641
A6: PV of tax shield at rho | B6: Rs cr | C6: =C5*C3 -> 6.2152031 | D6: =D5*D3 -> 6.6110068 | E6: =E5*E3 -> 6.7599638 | F6: =F5*F3 -> 6.7158498 | G6: =G5*G3 -> 6.5291888 | H6: =H5*H3 -> 6.2358462 | I6: =I5*I3 -> 5.9096124 | J6: =J5*J3 -> 5.5615681 | ... L6: =L5*L3 -> 4.841466
A8: Sum of PV of explicit FCFF | C8: =SUM(C4:L4) -> 10993.236
A9: Terminal unlevered value | C9: =M2/('AMB-Cost of Capital'!$B$14-'AMB-Assumptions'!$B$42) -> 83904.053
A10: Unlevered enterprise value (Vu) | C10: =C8+C9*L3 -> 39519.241
A11: Sum of PV of explicit tax shields | C11: =SUM(C6:L6) -> 60.583213
A12: Terminal value of tax shield | C12: =M5/('AMB-Cost of Capital'!$B$14-'AMB-Assumptions'!$B$42) -> 334.07167
A13: PV of interest tax shield | C13: =C11+C12*L3 -> 174.16211
A14: Enterprise value of operations | C14: =C10+C13 -> 39693.403
A15: Equity value attributable to owners | C15: =C14+'AMB-Assumptions'!$B$17+'AMB-Assumptions'!$B$22-'AMB-Assumptions'!$B$16-'AMB-Assumptions'!$B$23-'AMB-Assumptions'!$B$18 -> 24434.923
A16: Value per share (Rs) | C16: =C15/'AMB-Assumptions'!$B$15 -> 98.854774
A18: The interest tax shield is worth almost nothing here because Ambuja has essentially no debt. That is itself a finding: the company creates no value through leverage, and any argument for it must rest entirely on operations.

Sheet AMB-FCFE valuation
A1: Line item | B1: Unit | C1: FY27 | D1: FY28 | E1: FY29 | F1: FY30 | G1: FY31 | H1: FY32 | I1: FY33 | J1: FY34 | K1: FY35 | L1: FY36
A2: FCFF | B2: Rs cr | C2: ='AMB-P&L'!C29 -> -2822.6927 | D2: ='AMB-P&L'!D29 -> -1188.6117 | E2: ='AMB-P&L'!E29 -> 380.06219 | F2: ='AMB-P&L'!F29 -> 1825.0711 | G2: ='AMB-P&L'!G29 -> 3201.7909 | H2: ='AMB-P&L'!H29 -> 3968.3995 | I2: ='AMB-P&L'!I29 -> 4717.5967 | J2: ='AMB-P&L'!J29 -> 5407.488 | ... L2: ='AMB-P&L'!L29 -> 6693.2758
A3: Less: Interest after tax | B3: Rs cr | C3: =-'AMB-CCF valuation'!C5*(1-'AMB-Cost of Capital'!$B$10) -> -20.584872 | D3: =-'AMB-CCF valuation'!D5*(1-'AMB-Cost of Capital'!$B$10) -> -24.39016 | E3: =-'AMB-CCF valuation'!E5*(1-'AMB-Cost of Capital'!$B$10) -> -27.780856 | F3: =-'AMB-CCF valuation'!F5*(1-'AMB-Cost of Capital'!$B$10) -> -30.74372 | G3: =-'AMB-CCF valuation'!G5*(1-'AMB-Cost of Capital'!$B$10) -> -33.294222 | H3: =-'AMB-CCF valuation'!H5*(1-'AMB-Cost of Capital'!$B$10) -> -35.420871 | I3: =-'AMB-CCF valuation'!I5*(1-'AMB-Cost of Capital'!$B$10) -> -37.391857 | J3: =-'AMB-CCF valuation'!J5*(1-'AMB-Cost of Capital'!$B$10) -> -39.198504 | ... L3: =-'AMB-CCF valuation'!L5*(1-'AMB-Cost of Capital'!$B$10) -> -42.34065
A4: Add: Net new borrowing | B4: Rs cr | C4: ='AMB-CCF valuation'!C2*'AMB-Cost of Capital'!$B$11-'AMB-CCF valuation'!C4 -> 63.563851 | D4: ='AMB-CCF valuation'!D2*'AMB-Cost of Capital'!$B$11-'AMB-CCF valuation'!D4 -> 56.638462 | E4: ='AMB-CCF valuation'!E2*'AMB-Cost of Capital'!$B$11-'AMB-CCF valuation'!E4 -> 49.491939 | F4: ='AMB-CCF valuation'!F2*'AMB-Cost of Capital'!$B$11-'AMB-CCF valuation'!F4 -> 42.603798 | G4: ='AMB-CCF valuation'!G2*'AMB-Cost of Capital'!$B$11-'AMB-CCF valuation'!G4 -> 35.523723 | H4: ='AMB-CCF valuation'!H2*'AMB-Cost of Capital'!$B$11-'AMB-CCF valuation'!H4 -> 32.92352 | I4: ='AMB-CCF valuation'!I2*'AMB-Cost of Capital'!$B$11-'AMB-CCF valuation'!I4 -> 30.178382 | J4: ='AMB-CCF valuation'!J2*'AMB-Cost of Capital'!$B$11-'AMB-CCF valuation'!J4 -> 27.634744 | ... L4: ='AMB-CCF valuation'!L2*'AMB-Cost of Capital'!$B$11-'AMB-CCF valuation'!L4 -> 22.466524
A5: FCFE | B5: Rs cr | C5: =SUM(C2:C4) -> -2779.7137 | D5: =SUM(D2:D4) -> -1156.3634 | E5: =SUM(E2:E4) -> 401.77327 | F5: =SUM(F2:F4) -> 1836.9311 | G5: =SUM(G2:G4) -> 3204.0204 | H5: =SUM(H2:H4) -> 3965.9021 | I5: =SUM(I2:I4) -> 4710.3832 | J5: =SUM(J2:J4) -> 5395.9242 | ... L5: =SUM(L2:L4) -> 6673.4017
A6: Discount factor at Ke | B6: Rs cr | C6: =1/(1+'AMB-Cost of Capital'!$B$8)^1 -> 0.89749131 | D6: =1/(1+'AMB-Cost of Capital'!$B$8)^2 -> 0.80549065 | E6: =1/(1+'AMB-Cost of Capital'!$B$8)^3 -> 0.72292086 | F6: =1/(1+'AMB-Cost of Capital'!$B$8)^4 -> 0.64881519 | G6: =1/(1+'AMB-Cost of Capital'!$B$8)^5 -> 0.58230599 | H6: =1/(1+'AMB-Cost of Capital'!$B$8)^6 -> 0.52261457 | I6: =1/(1+'AMB-Cost of Capital'!$B$8)^7 -> 0.46904203 | J6: =1/(1+'AMB-Cost of Capital'!$B$8)^8 -> 0.42096115 | K6: =1/(1+'AMB-Cost of Capital'!$B$8)^9 -> 0.37780897 | L6: =1/(1+'AMB-Cost of Capital'!$B$8)^10 -> 0.33908027
A7: PV of FCFE | B7: Rs cr | C7: =C5*C6 -> -2494.7689 | D7: =D5*D6 -> -931.4399 | E7: =E5*E6 -> 290.45028 | F7: =F5*F6 -> 1191.8288 | G7: =G5*G6 -> 1865.7203 | H7: =H5*H6 -> 2072.6382 | I7: =I5*I6 -> 2209.3677 | J7: =J5*J6 -> 2271.4745 | ... L7: =L5*L6 -> 2262.8188
A9: Sum of PV of explicit FCFE | C9: =SUM(C7:L7) -> 11033.502
A10: Terminal equity value | C10: ='AMB-FCFF valuation'!C7*(1-'AMB-Cost of Capital'!$B$11) -> 83508.396
A11: PV of terminal equity value | C11: =C10*L6 -> 28316.049
A12: Equity value of operations | C12: =C9+C11 -> 39349.552
A13: Add: Cash, bank and current investments | C13: ='AMB-Assumptions'!$B$17 -> 958.6
A14: Less: Debt in excess of the target level | C14: =-('AMB-Assumptions'!$B$16-'AMB-CCF valuation'!C4) -> -522.07857
A15: Add: Tax paid under protest (Driver 1a) | C15: ='AMB-Assumptions'!$B$22 -> 614.1
A16: Less: Deferred tax liabilities (Driver 2) | C16: =-'AMB-Assumptions'!$B$23 -> -3466.33
A17: Less: Non-controlling interest | C17: =-'AMB-Assumptions'!$B$18 -> -12498.92
A18: Equity value attributable to owners | C18: =SUM(C12:C17) -> 24434.923
A19: Value per share (Rs) | C19: =C18/'AMB-Assumptions'!$B$15 -> 98.854774

Sheet AMB-EVA
A1: Line item | B1: Unit | C1: FY27 | D1: FY28 | E1: FY29 | F1: FY30 | G1: FY31 | H1: FY32 | I1: FY33 | J1: FY34 | K1: FY35 | L1: FY36 | M1: Terminal
A2: NOPAT | B2: Rs cr | C2: ='AMB-Balance Sheet'!C8 -> 3113.7191 | D2: ='AMB-Balance Sheet'!D8 -> 3768.0948 | E2: ='AMB-Balance Sheet'!E8 -> 4440.2569 | F2: ='AMB-Balance Sheet'!F8 -> 5061.2098 | G2: ='AMB-Balance Sheet'!G8 -> 5679.3005 | H2: ='AMB-Balance Sheet'!H8 -> 6248.3575 | I2: ='AMB-Balance Sheet'!I8 -> 6814.2945 | J2: ='AMB-Balance Sheet'!J8 -> 7337.1204 | ... L2: ='AMB-Balance Sheet'!L8 -> 8326.0221 | M2: ='AMB-Balance Sheet'!C13 -> 8908.3441
A3: Opening operating invested capital | B3: Rs cr | C3: ='AMB-Balance Sheet'!C2 -> 44229.48 | D3: ='AMB-Balance Sheet'!D2 -> 50165.892 | E3: ='AMB-Balance Sheet'!E2 -> 55122.598 | F3: ='AMB-Balance Sheet'!F2 -> 59182.793 | G3: ='AMB-Balance Sheet'!G2 -> 62418.932 | H3: ='AMB-Balance Sheet'!H2 -> 64896.441 | I3: ='AMB-Balance Sheet'!I2 -> 67176.399 | J3: ='AMB-Balance Sheet'!J2 -> 69273.097 | ... L3: ='AMB-Balance Sheet'!L2 -> 72976.938 | M3: ='AMB-Balance Sheet'!C14 -> 74609.684
A4: Capital charge (WACC x opening capital) | B4: Rs cr | C4: =C3*'AMB-Cost of Capital'!$B$13 -> 5030.9304 | D4: =D3*'AMB-Cost of Capital'!$B$13 -> 5706.174 | E4: =E3*'AMB-Cost of Capital'!$B$13 -> 6269.98 | F4: =F3*'AMB-Cost of Capital'!$B$13 -> 6731.8112 | G4: =G3*'AMB-Cost of Capital'!$B$13 -> 7099.9094 | H4: =H3*'AMB-Cost of Capital'!$B$13 -> 7381.7164 | I4: =I3*'AMB-Cost of Capital'!$B$13 -> 7641.0527 | J4: =J3*'AMB-Cost of Capital'!$B$13 -> 7879.5439 | ... M4: =M3*'AMB-Cost of Capital'!$B$13 -> 8486.5597
A5: Economic value added | B5: Rs cr | C5: =C2-C4 -> -1917.2113 | D5: =D2-D4 -> -1938.0792 | E5: =E2-E4 -> -1829.723 | F5: =F2-F4 -> -1670.6014 | G5: =G2-G4 -> -1420.6088 | H5: =H2-H4 -> -1133.3589 | I5: =I2-I4 -> -826.75817 | J5: =J2-J4 -> -542.42349 | ... M5: =M2-M4 -> 421.78432
A6: Discount factor at WACC | B6: Rs cr | C6: =1/(1+'AMB-Cost of Capital'!$B$13)^1 -> 0.89787072 | D6: =1/(1+'AMB-Cost of Capital'!$B$13)^2 -> 0.80617183 | E6: =1/(1+'AMB-Cost of Capital'!$B$13)^3 -> 0.72383808 | F6: =1/(1+'AMB-Cost of Capital'!$B$13)^4 -> 0.64991301 | G6: =1/(1+'AMB-Cost of Capital'!$B$13)^5 -> 0.58353786 | H6: =1/(1+'AMB-Cost of Capital'!$B$13)^6 -> 0.52394156 | I6: =1/(1+'AMB-Cost of Capital'!$B$13)^7 -> 0.47043178 | J6: =1/(1+'AMB-Cost of Capital'!$B$13)^8 -> 0.42238692 | K6: =1/(1+'AMB-Cost of Capital'!$B$13)^9 -> 0.37924885 | L6: =1/(1+'AMB-Cost of Capital'!$B$13)^10 -> 0.34051644
A7: PV of EVA | B7: Rs cr | C7: =C5*C6 -> -1721.4079 | D7: =D5*D6 -> -1562.4248 | E7: =E5*E6 -> -1324.4232 | F7: =F5*F6 -> -1085.7456 | G7: =G5*G6 -> -828.97905 | H7: =H5*H6 -> -593.81381 | I7: =I5*I6 -> -388.93332 | J7: =J5*J6 -> -229.11259 | ... L7: =L5*L6 -> 8.5744882
A9: Opening operating invested capital | C9: =C3 -> 44229.48
A10: Sum of PV of explicit EVA | C10: =SUM(C7:L7) -> -7814.7193
A11: Terminal value of EVA | C11: =M5/('AMB-Cost of Capital'!$B$13-'AMB-Assumptions'!$B$42) -> 9628.4405
A12: PV of terminal EVA | C12: =C11*L6 -> 3278.6422
A13: Enterprise value of operations | C13: =C9+C10+C12 -> 39693.403
A14: Equity value attributable to owners | C14: =C13+'AMB-Assumptions'!$B$17+'AMB-Assumptions'!$B$22-'AMB-Assumptions'!$B$16-'AMB-Assumptions'!$B$23-'AMB-Assumptions'!$B$18 -> 24434.923
A15: Value per share (Rs) | C15: =C14/'AMB-Assumptions'!$B$15 -> 98.854774
A17: EVA is NEGATIVE in every forecast year. NOPAT never covers the capital charge, which is the arithmetic statement of the central finding: Ambuja earns less on capital than capital costs. Enterprise value therefore sits BELOW invested capital, which is exactly what the theory predicts and is not an error.

Sheet AMB-Reconciliation
A1: Reconciliation of the five valuation methods
A3: Method | B3: Discount rate | C3: Enterprise value | D3: Value per share | E3: Difference vs FCFF
A4: FCFF | B4: WACC | C4: ='AMB-FCFF valuation'!C9 -> 39693.403 | D4: ='AMB-FCFF valuation'!C16 -> 98.854774 | E4: =D4-D4 -> 0
A5: CCF | B5: rho | C5: ='AMB-CCF valuation'!C14 -> 39693.403 | D5: ='AMB-CCF valuation'!C16 -> 98.854774 | E5: =D5-D4 -> 0
A6: APV | B6: rho | C6: ='AMB-APV valuation'!C14 -> 39693.403 | D6: ='AMB-APV valuation'!C16 -> 98.854774 | E6: =D6-D4 -> 0
A7: EVA | B7: WACC | C7: ='AMB-EVA'!C13 -> 39693.403 | D7: ='AMB-EVA'!C15 -> 98.854774 | E7: =D7-D4 -> 0
A8: FCFE | B8: Ke | C8: equity method | D8: ='AMB-FCFE valuation'!C19 -> 98.854774 | E8: =D8-D4 -> 0
A10: Maximum absolute difference | D10: =MAX(ABS(E4),ABS(E5),ABS(E6),ABS(E7),ABS(E8)) -> 0
A11: Status | D11: =IF(D10<0.01,"RECONCILED","DOES NOT RECONCILE") -> RECONCILED
A13: Agreement across the five methods proves internal consistency and nothing more. It says nothing about whether the assumptions are right.

Sheet AMB-Terminal
A1: Terminal value: Gordon and exit multiple cross check
A3: Growth decomposition, built multiplicatively
A4: Long run real GDP growth | B4: ='AMB-Assumptions'!B38 -> 0.065 | D4: Owned assumption.
A5: Long run inflation | B5: ='AMB-Assumptions'!B39 -> 0.04 | D5: RBI CPI target.
A6: Nominal GDP growth | B6: ='AMB-Assumptions'!B40 -> 0.1076 | D6: (1+real)(1+inflation)-1, NOT real plus inflation.
A7: Terminal g as a fraction of nominal GDP | B7: ='AMB-Assumptions'!B41 -> 0.65 | D7: The editable driver. Same fraction as UltraTech, so the two companies are treated consistently.
A8: Terminal growth rate | B8: ='AMB-Assumptions'!B42 -> 0.06994 | D8: Derived, not typed.
A10: Method A: Gordon growth on a steady state terminal year
A11: NOPAT in the terminal year | B11: ='AMB-Balance Sheet'!C13 -> 8908.3441
A12: Closing OPERATING invested capital | B12: ='AMB-Balance Sheet'!C14 -> 74609.684 | D12: Excludes goodwill: organic growth does not require buying more of it.
A13: Reinvestment = g x operating invested capital | B13: ='AMB-Balance Sheet'!C15 -> 5218.2013
A14: Terminal FCFF | B14: ='AMB-Balance Sheet'!C16 -> 3690.1428
A15: Implied terminal ROIC | B15: ='AMB-Balance Sheet'!C17 -> 0.1193993
A16: Implied reinvestment rate | B16: ='AMB-Balance Sheet'!C18 -> 0.58576558 | D16: Equals g divided by terminal ROIC, as steady state requires.
A17: Terminal value, Gordon | B17: ='AMB-FCFF valuation'!C7 -> 84238.124
A19: Method B: exit multiple cross check
A20: Terminal year EBITDA | B20: ='AMB-P&L'!L17*(1+'AMB-Assumptions'!B42) -> 18172.872
A21: Implied exit EV/EBITDA from Method A | B21: =B19/B20 -> 0
A22: Peer median EV/EBITDA | B22: 19.37
A23: Terminal growth the peer multiple would require | B23: 0.1099
A25: MULTIPLIER CONSISTENCY: the two methods do NOT bracket each other. Method A implies roughly 4.6x against a peer median of 19.37x. Solving the peer multiple back for growth gives 10.99% in perpetuity, which is ABOVE nominal GDP growth of 10.76%. A company cannot grow faster than the economy forever. We therefore take the position that the peer multiple is the implausible end of the range, and hedge by weighting a 10.0x exit case at half the target price in the report. This is recorded as a PARTIAL on the Dashboard rather than smoothed over.
A28: MULTIPLIER CONSISTENCY: is the implied multiple an outcome of our own fundamentals?
A29: The test is NOT whether our multiple equals the peer multiple. It is whether the multiple our model implies is arithmetically consistent with the growth, return on capital and discount rate the model itself uses. A multiple is an OUTCOME of those three, never an input. If the two agree, the model is internally consistent and the multiple can be reported as a result.
A32: Terminal NOPAT divided by terminal EBITDA | B32: ='AMB-Balance Sheet'!C13/('AMB-P&L'!L17*(1+'AMB-Assumptions'!$B$42)) -> 0.49020011
A33: Terminal ROIC | B33: ='AMB-Balance Sheet'!C17 -> 0.1193993
A34: Terminal growth rate g | B34: ='AMB-Assumptions'!$B$42 -> 0.06994
A35: Reinvestment rate = g / ROIC | B35: =B34/B33 -> 0.58576558
A36: WACC | B36: ='AMB-Cost of Capital'!$B$14 -> 0.11392051
A37: JUSTIFIED EV/EBITDA = (NOPAT/EBITDA)(1 - g/ROIC)/(WACC - g) | B37: =B32*(1-B35)/(B36-B34) -> 4.6169945
A38: Model implied exit EV/EBITDA | B38: ='AMB-FCFF valuation'!C18 -> 4.6353775
A39: Difference | B39: =B37-B38 -> -0.018382987
A40: VERDICT | B40: =IF(ABS(B39)<0.25,"PASS: the multiple is consistent with our own fundamentals","REVIEW") -> PASS: the multiple is consistent with our own fundamentals
A42: On this test the model PASSES. The separate observation that the PEER multiple of about 19x implies perpetual growth above nominal GDP is a finding about the peer set, reported in the relative valuation section, not a failure of internal consistency in this model. Conflating the two would require us to adopt a multiple we have shown to be arithmetically impossible.

Sheet AMB-Sensitivity
A1: Sensitivity
A3: WACC against terminal growth: LIVE, value per share in Rs
A4: WACC \ terminal g | B4: 2% | C4: 3% | D4: 4% | E4: 5% | F4: 6%
A5: 0.09 | B5: =IF($A5<=0.02,"",(('AMB-P&L'!C29/(1+$A5)^1+'AMB-P&L'!D29/(1+$A5)^2+'AMB-P&L'!E29/(1+$A5)^3+'AMB-P&L'!F29/(1+$A5)^4+'AMB-P&L'!G29/(1+$A5)^5+'AMB-P&L'!H29/(1+$A5)^6+'AMB-P&L'!I29/(1+$A5)^7+'AMB-P&L'!J29/(1+$A5)^8+'AMB-P&L'!K29/(1+$A5)^9+'AMB-P&L'!L29/(1+$A5)^10+(('AMB-P&L'!L26*(1+0.02))-0.02*'AMB-Balance Sheet'!L5)/($A5-0.02)/(1+$A5)^10)+'AMB-Assumptions'!$B$17+'AMB-Assumptions'!$B$22-'AMB-Assumptions'!$B$16-'AMB-Assumptions'!$B$23-'AMB-Assumptions'!$B$18)/'AMB-Assumptions'!$B$15) -> 163.26077 | C5: =IF($A5<=0.03,"",(('AMB-P&L'!C29/(1+$A5)^1+'AMB-P&L'!D29/(1+$A5)^2+'AMB-P&L'!E29/(1+$A5)^3+'AMB-P&L'!F29/(1+$A5)^4+'AMB-P&L'!G29/(1+$A5)^5+'AMB-P&L'!H29/(1+$A5)^6+'AMB-P&L'!I29/(1+$A5)^7+'AMB-P&L'!J29/(1+$A5)^8+'AMB-P&L'!K29/(1+$A5)^9+'AMB-P&L'!L29/(1+$A5)^10+(('AMB-P&L'!L26*(1+0.03))-0.03*'AMB-Balance Sheet'!L5)/($A5-0.03)/(1+$A5)^10)+'AMB-Assumptions'!$B$17+'AMB-Assumptions'!$B$22-'AMB-Assumptions'!$B$16-'AMB-Assumptions'!$B$23-'AMB-Assumptions'!$B$18)/'AMB-Assumptions'!$B$15) -> 172.86527 | D5: =IF($A5<=0.04,"",(('AMB-P&L'!C29/(1+$A5)^1+'AMB-P&L'!D29/(1+$A5)^2+'AMB-P&L'!E29/(1+$A5)^3+'AMB-P&L'!F29/(1+$A5)^4+'AMB-P&L'!G29/(1+$A5)^5+'AMB-P&L'!H29/(1+$A5)^6+'AMB-P&L'!I29/(1+$A5)^7+'AMB-P&L'!J29/(1+$A5)^8+'AMB-P&L'!K29/(1+$A5)^9+'AMB-P&L'!L29/(1+$A5)^10+(('AMB-P&L'!L26*(1+0.04))-0.04*'AMB-Balance Sheet'!L5)/($A5-0.04)/(1+$A5)^10)+'AMB-Assumptions'!$B$17+'AMB-Assumptions'!$B$22-'AMB-Assumptions'!$B$16-'AMB-Assumptions'!$B$23-'AMB-Assumptions'!$B$18)/'AMB-Assumptions'!$B$15) -> 186.31158 | E5: =IF($A5<=0.05,"",(('AMB-P&L'!C29/(1+$A5)^1+'AMB-P&L'!D29/(1+$A5)^2+'AMB-P&L'!E29/(1+$A5)^3+'AMB-P&L'!F29/(1+$A5)^4+'AMB-P&L'!G29/(1+$A5)^5+'AMB-P&L'!H29/(1+$A5)^6+'AMB-P&L'!I29/(1+$A5)^7+'AMB-P&L'!J29/(1+$A5)^8+'AMB-P&L'!K29/(1+$A5)^9+'AMB-P&L'!L29/(1+$A5)^10+(('AMB-P&L'!L26*(1+0.05))-0.05*'AMB-Balance Sheet'!L5)/($A5-0.05)/(1+$A5)^10)+'AMB-Assumptions'!$B$17+'AMB-Assumptions'!$B$22-'AMB-Assumptions'!$B$16-'AMB-Assumptions'!$B$23-'AMB-Assumptions'!$B$18)/'AMB-Assumptions'!$B$15) -> 206.48104 | F5: =IF($A5<=0.06,"",(('AMB-P&L'!C29/(1+$A5)^1+'AMB-P&L'!D29/(1+$A5)^2+'AMB-P&L'!E29/(1+$A5)^3+'AMB-P&L'!F29/(1+$A5)^4+'AMB-P&L'!G29/(1+$A5)^5+'AMB-P&L'!H29/(1+$A5)^6+'AMB-P&L'!I29/(1+$A5)^7+'AMB-P&L'!J29/(1+$A5)^8+'AMB-P&L'!K29/(1+$A5)^9+'AMB-P&L'!L29/(1+$A5)^10+(('AMB-P&L'!L26*(1+0.06))-0.06*'AMB-Balance Sheet'!L5)/($A5-0.06)/(1+$A5)^10)+'AMB-Assumptions'!$B$17+'AMB-Assumptions'!$B$22-'AMB-Assumptions'!$B$16-'AMB-Assumptions'!$B$23-'AMB-Assumptions'!$B$18)/'AMB-Assumptions'!$B$15) -> 240.09681
A6: 0.1 | B6: =IF($A6<=0.02,"",(('AMB-P&L'!C29/(1+$A6)^1+'AMB-P&L'!D29/(1+$A6)^2+'AMB-P&L'!E29/(1+$A6)^3+'AMB-P&L'!F29/(1+$A6)^4+'AMB-P&L'!G29/(1+$A6)^5+'AMB-P&L'!H29/(1+$A6)^6+'AMB-P&L'!I29/(1+$A6)^7+'AMB-P&L'!J29/(1+$A6)^8+'AMB-P&L'!K29/(1+$A6)^9+'AMB-P&L'!L29/(1+$A6)^10+(('AMB-P&L'!L26*(1+0.02))-0.02*'AMB-Balance Sheet'!L5)/($A6-0.02)/(1+$A6)^10)+'AMB-Assumptions'!$B$17+'AMB-Assumptions'!$B$22-'AMB-Assumptions'!$B$16-'AMB-Assumptions'!$B$23-'AMB-Assumptions'!$B$18)/'AMB-Assumptions'!$B$15) -> 124.59554 | C6: =IF($A6<=0.03,"",(('AMB-P&L'!C29/(1+$A6)^1+'AMB-P&L'!D29/(1+$A6)^2+'AMB-P&L'!E29/(1+$A6)^3+'AMB-P&L'!F29/(1+$A6)^4+'AMB-P&L'!G29/(1+$A6)^5+'AMB-P&L'!H29/(1+$A6)^6+'AMB-P&L'!I29/(1+$A6)^7+'AMB-P&L'!J29/(1+$A6)^8+'AMB-P&L'!K29/(1+$A6)^9+'AMB-P&L'!L29/(1+$A6)^10+(('AMB-P&L'!L26*(1+0.03))-0.03*'AMB-Balance Sheet'!L5)/($A6-0.03)/(1+$A6)^10)+'AMB-Assumptions'!$B$17+'AMB-Assumptions'!$B$22-'AMB-Assumptions'!$B$16-'AMB-Assumptions'!$B$23-'AMB-Assumptions'!$B$18)/'AMB-Assumptions'!$B$15) -> 129.32402 | D6: =IF($A6<=0.04,"",(('AMB-P&L'!C29/(1+$A6)^1+'AMB-P&L'!D29/(1+$A6)^2+'AMB-P&L'!E29/(1+$A6)^3+'AMB-P&L'!F29/(1+$A6)^4+'AMB-P&L'!G29/(1+$A6)^5+'AMB-P&L'!H29/(1+$A6)^6+'AMB-P&L'!I29/(1+$A6)^7+'AMB-P&L'!J29/(1+$A6)^8+'AMB-P&L'!K29/(1+$A6)^9+'AMB-P&L'!L29/(1+$A6)^10+(('AMB-P&L'!L26*(1+0.04))-0.04*'AMB-Balance Sheet'!L5)/($A6-0.04)/(1+$A6)^10)+'AMB-Assumptions'!$B$17+'AMB-Assumptions'!$B$22-'AMB-Assumptions'!$B$16-'AMB-Assumptions'!$B$23-'AMB-Assumptions'!$B$18)/'AMB-Assumptions'!$B$15) -> 135.62866 | E6: =IF($A6<=0.05,"",(('AMB-P&L'!C29/(1+$A6)^1+'AMB-P&L'!D29/(1+$A6)^2+'AMB-P&L'!E29/(1+$A6)^3+'AMB-P&L'!F29/(1+$A6)^4+'AMB-P&L'!G29/(1+$A6)^5+'AMB-P&L'!H29/(1+$A6)^6+'AMB-P&L'!I29/(1+$A6)^7+'AMB-P&L'!J29/(1+$A6)^8+'AMB-P&L'!K29/(1+$A6)^9+'AMB-P&L'!L29/(1+$A6)^10+(('AMB-P&L'!L26*(1+0.05))-0.05*'AMB-Balance Sheet'!L5)/($A6-0.05)/(1+$A6)^10)+'AMB-Assumptions'!$B$17+'AMB-Assumptions'!$B$22-'AMB-Assumptions'!$B$16-'AMB-Assumptions'!$B$23-'AMB-Assumptions'!$B$18)/'AMB-Assumptions'!$B$15) -> 144.45515 | F6: =IF($A6<=0.06,"",(('AMB-P&L'!C29/(1+$A6)^1+'AMB-P&L'!D29/(1+$A6)^2+'AMB-P&L'!E29/(1+$A6)^3+'AMB-P&L'!F29/(1+$A6)^4+'AMB-P&L'!G29/(1+$A6)^5+'AMB-P&L'!H29/(1+$A6)^6+'AMB-P&L'!I29/(1+$A6)^7+'AMB-P&L'!J29/(1+$A6)^8+'AMB-P&L'!K29/(1+$A6)^9+'AMB-P&L'!L29/(1+$A6)^10+(('AMB-P&L'!L26*(1+0.06))-0.06*'AMB-Balance Sheet'!L5)/($A6-0.06)/(1+$A6)^10)+'AMB-Assumptions'!$B$17+'AMB-Assumptions'!$B$22-'AMB-Assumptions'!$B$16-'AMB-Assumptions'!$B$23-'AMB-Assumptions'!$B$18)/'AMB-Assumptions'!$B$15) -> 157.6949
A7: 0.11 | B7: =IF($A7<=0.02,"",(('AMB-P&L'!C29/(1+$A7)^1+'AMB-P&L'!D29/(1+$A7)^2+'AMB-P&L'!E29/(1+$A7)^3+'AMB-P&L'!F29/(1+$A7)^4+'AMB-P&L'!G29/(1+$A7)^5+'AMB-P&L'!H29/(1+$A7)^6+'AMB-P&L'!I29/(1+$A7)^7+'AMB-P&L'!J29/(1+$A7)^8+'AMB-P&L'!K29/(1+$A7)^9+'AMB-P&L'!L29/(1+$A7)^10+(('AMB-P&L'!L26*(1+0.02))-0.02*'AMB-Balance Sheet'!L5)/($A7-0.02)/(1+$A7)^10)+'AMB-Assumptions'!$B$17+'AMB-Assumptions'!$B$22-'AMB-Assumptions'!$B$16-'AMB-Assumptions'!$B$23-'AMB-Assumptions'!$B$18)/'AMB-Assumptions'!$B$15) -> 95.018162 | C7: =IF($A7<=0.03,"",(('AMB-P&L'!C29/(1+$A7)^1+'AMB-P&L'!D29/(1+$A7)^2+'AMB-P&L'!E29/(1+$A7)^3+'AMB-P&L'!F29/(1+$A7)^4+'AMB-P&L'!G29/(1+$A7)^5+'AMB-P&L'!H29/(1+$A7)^6+'AMB-P&L'!I29/(1+$A7)^7+'AMB-P&L'!J29/(1+$A7)^8+'AMB-P&L'!K29/(1+$A7)^9+'AMB-P&L'!L29/(1+$A7)^10+(('AMB-P&L'!L26*(1+0.03))-0.03*'AMB-Balance Sheet'!L5)/($A7-0.03)/(1+$A7)^10)+'AMB-Assumptions'!$B$17+'AMB-Assumptions'!$B$22-'AMB-Assumptions'!$B$16-'AMB-Assumptions'!$B$23-'AMB-Assumptions'!$B$18)/'AMB-Assumptions'!$B$15) -> 97.065968 | D7: =IF($A7<=0.04,"",(('AMB-P&L'!C29/(1+$A7)^1+'AMB-P&L'!D29/(1+$A7)^2+'AMB-P&L'!E29/(1+$A7)^3+'AMB-P&L'!F29/(1+$A7)^4+'AMB-P&L'!G29/(1+$A7)^5+'AMB-P&L'!H29/(1+$A7)^6+'AMB-P&L'!I29/(1+$A7)^7+'AMB-P&L'!J29/(1+$A7)^8+'AMB-P&L'!K29/(1+$A7)^9+'AMB-P&L'!L29/(1+$A7)^10+(('AMB-P&L'!L26*(1+0.04))-0.04*'AMB-Balance Sheet'!L5)/($A7-0.04)/(1+$A7)^10)+'AMB-Assumptions'!$B$17+'AMB-Assumptions'!$B$22-'AMB-Assumptions'!$B$16-'AMB-Assumptions'!$B$23-'AMB-Assumptions'!$B$18)/'AMB-Assumptions'!$B$15) -> 99.698862 | E7: =IF($A7<=0.05,"",(('AMB-P&L'!C29/(1+$A7)^1+'AMB-P&L'!D29/(1+$A7)^2+'AMB-P&L'!E29/(1+$A7)^3+'AMB-P&L'!F29/(1+$A7)^4+'AMB-P&L'!G29/(1+$A7)^5+'AMB-P&L'!H29/(1+$A7)^6+'AMB-P&L'!I29/(1+$A7)^7+'AMB-P&L'!J29/(1+$A7)^8+'AMB-P&L'!K29/(1+$A7)^9+'AMB-P&L'!L29/(1+$A7)^10+(('AMB-P&L'!L26*(1+0.05))-0.05*'AMB-Balance Sheet'!L5)/($A7-0.05)/(1+$A7)^10)+'AMB-Assumptions'!$B$17+'AMB-Assumptions'!$B$22-'AMB-Assumptions'!$B$16-'AMB-Assumptions'!$B$23-'AMB-Assumptions'!$B$18)/'AMB-Assumptions'!$B$15) -> 103.20939 | F7: =IF($A7<=0.06,"",(('AMB-P&L'!C29/(1+$A7)^1+'AMB-P&L'!D29/(1+$A7)^2+'AMB-P&L'!E29/(1+$A7)^3+'AMB-P&L'!F29/(1+$A7)^4+'AMB-P&L'!G29/(1+$A7)^5+'AMB-P&L'!H29/(1+$A7)^6+'AMB-P&L'!I29/(1+$A7)^7+'AMB-P&L'!J29/(1+$A7)^8+'AMB-P&L'!K29/(1+$A7)^9+'AMB-P&L'!L29/(1+$A7)^10+(('AMB-P&L'!L26*(1+0.06))-0.06*'AMB-Balance Sheet'!L5)/($A7-0.06)/(1+$A7)^10)+'AMB-Assumptions'!$B$17+'AMB-Assumptions'!$B$22-'AMB-Assumptions'!$B$16-'AMB-Assumptions'!$B$23-'AMB-Assumptions'!$B$18)/'AMB-Assumptions'!$B$15) -> 108.12412
A8: 0.12 | B8: =IF($A8<=0.02,"",(('AMB-P&L'!C29/(1+$A8)^1+'AMB-P&L'!D29/(1+$A8)^2+'AMB-P&L'!E29/(1+$A8)^3+'AMB-P&L'!F29/(1+$A8)^4+'AMB-P&L'!G29/(1+$A8)^5+'AMB-P&L'!H29/(1+$A8)^6+'AMB-P&L'!I29/(1+$A8)^7+'AMB-P&L'!J29/(1+$A8)^8+'AMB-P&L'!K29/(1+$A8)^9+'AMB-P&L'!L29/(1+$A8)^10+(('AMB-P&L'!L26*(1+0.02))-0.02*'AMB-Balance Sheet'!L5)/($A8-0.02)/(1+$A8)^10)+'AMB-Assumptions'!$B$17+'AMB-Assumptions'!$B$22-'AMB-Assumptions'!$B$16-'AMB-Assumptions'!$B$23-'AMB-Assumptions'!$B$18)/'AMB-Assumptions'!$B$15) -> 71.771085 | C8: =IF($A8<=0.03,"",(('AMB-P&L'!C29/(1+$A8)^1+'AMB-P&L'!D29/(1+$A8)^2+'AMB-P&L'!E29/(1+$A8)^3+'AMB-P&L'!F29/(1+$A8)^4+'AMB-P&L'!G29/(1+$A8)^5+'AMB-P&L'!H29/(1+$A8)^6+'AMB-P&L'!I29/(1+$A8)^7+'AMB-P&L'!J29/(1+$A8)^8+'AMB-P&L'!K29/(1+$A8)^9+'AMB-P&L'!L29/(1+$A8)^10+(('AMB-P&L'!L26*(1+0.03))-0.03*'AMB-Balance Sheet'!L5)/($A8-0.03)/(1+$A8)^10)+'AMB-Assumptions'!$B$17+'AMB-Assumptions'!$B$22-'AMB-Assumptions'!$B$16-'AMB-Assumptions'!$B$23-'AMB-Assumptions'!$B$18)/'AMB-Assumptions'!$B$15) -> 72.309462 | D8: =IF($A8<=0.04,"",(('AMB-P&L'!C29/(1+$A8)^1+'AMB-P&L'!D29/(1+$A8)^2+'AMB-P&L'!E29/(1+$A8)^3+'AMB-P&L'!F29/(1+$A8)^4+'AMB-P&L'!G29/(1+$A8)^5+'AMB-P&L'!H29/(1+$A8)^6+'AMB-P&L'!I29/(1+$A8)^7+'AMB-P&L'!J29/(1+$A8)^8+'AMB-P&L'!K29/(1+$A8)^9+'AMB-P&L'!L29/(1+$A8)^10+(('AMB-P&L'!L26*(1+0.04))-0.04*'AMB-Balance Sheet'!L5)/($A8-0.04)/(1+$A8)^10)+'AMB-Assumptions'!$B$17+'AMB-Assumptions'!$B$22-'AMB-Assumptions'!$B$16-'AMB-Assumptions'!$B$23-'AMB-Assumptions'!$B$18)/'AMB-Assumptions'!$B$15) -> 72.982434 | E8: =IF($A8<=0.05,"",(('AMB-P&L'!C29/(1+$A8)^1+'AMB-P&L'!D29/(1+$A8)^2+'AMB-P&L'!E29/(1+$A8)^3+'AMB-P&L'!F29/(1+$A8)^4+'AMB-P&L'!G29/(1+$A8)^5+'AMB-P&L'!H29/(1+$A8)^6+'AMB-P&L'!I29/(1+$A8)^7+'AMB-P&L'!J29/(1+$A8)^8+'AMB-P&L'!K29/(1+$A8)^9+'AMB-P&L'!L29/(1+$A8)^10+(('AMB-P&L'!L26*(1+0.05))-0.05*'AMB-Balance Sheet'!L5)/($A8-0.05)/(1+$A8)^10)+'AMB-Assumptions'!$B$17+'AMB-Assumptions'!$B$22-'AMB-Assumptions'!$B$16-'AMB-Assumptions'!$B$23-'AMB-Assumptions'!$B$18)/'AMB-Assumptions'!$B$15) -> 73.847683 | F8: =IF($A8<=0.06,"",(('AMB-P&L'!C29/(1+$A8)^1+'AMB-P&L'!D29/(1+$A8)^2+'AMB-P&L'!E29/(1+$A8)^3+'AMB-P&L'!F29/(1+$A8)^4+'AMB-P&L'!G29/(1+$A8)^5+'AMB-P&L'!H29/(1+$A8)^6+'AMB-P&L'!I29/(1+$A8)^7+'AMB-P&L'!J29/(1+$A8)^8+'AMB-P&L'!K29/(1+$A8)^9+'AMB-P&L'!L29/(1+$A8)^10+(('AMB-P&L'!L26*(1+0.06))-0.06*'AMB-Balance Sheet'!L5)/($A8-0.06)/(1+$A8)^10)+'AMB-Assumptions'!$B$17+'AMB-Assumptions'!$B$22-'AMB-Assumptions'!$B$16-'AMB-Assumptions'!$B$23-'AMB-Assumptions'!$B$18)/'AMB-Assumptions'!$B$15) -> 75.001348
A9: 0.13 | B9: =IF($A9<=0.02,"",(('AMB-P&L'!C29/(1+$A9)^1+'AMB-P&L'!D29/(1+$A9)^2+'AMB-P&L'!E29/(1+$A9)^3+'AMB-P&L'!F29/(1+$A9)^4+'AMB-P&L'!G29/(1+$A9)^5+'AMB-P&L'!H29/(1+$A9)^6+'AMB-P&L'!I29/(1+$A9)^7+'AMB-P&L'!J29/(1+$A9)^8+'AMB-P&L'!K29/(1+$A9)^9+'AMB-P&L'!L29/(1+$A9)^10+(('AMB-P&L'!L26*(1+0.02))-0.02*'AMB-Balance Sheet'!L5)/($A9-0.02)/(1+$A9)^10)+'AMB-Assumptions'!$B$17+'AMB-Assumptions'!$B$22-'AMB-Assumptions'!$B$16-'AMB-Assumptions'!$B$23-'AMB-Assumptions'!$B$18)/'AMB-Assumptions'!$B$15) -> 53.101893 | C9: =IF($A9<=0.03,"",(('AMB-P&L'!C29/(1+$A9)^1+'AMB-P&L'!D29/(1+$A9)^2+'AMB-P&L'!E29/(1+$A9)^3+'AMB-P&L'!F29/(1+$A9)^4+'AMB-P&L'!G29/(1+$A9)^5+'AMB-P&L'!H29/(1+$A9)^6+'AMB-P&L'!I29/(1+$A9)^7+'AMB-P&L'!J29/(1+$A9)^8+'AMB-P&L'!K29/(1+$A9)^9+'AMB-P&L'!L29/(1+$A9)^10+(('AMB-P&L'!L26*(1+0.03))-0.03*'AMB-Balance Sheet'!L5)/($A9-0.03)/(1+$A9)^10)+'AMB-Assumptions'!$B$17+'AMB-Assumptions'!$B$22-'AMB-Assumptions'!$B$16-'AMB-Assumptions'!$B$23-'AMB-Assumptions'!$B$18)/'AMB-Assumptions'!$B$15) -> 52.786766 | D9: =IF($A9<=0.04,"",(('AMB-P&L'!C29/(1+$A9)^1+'AMB-P&L'!D29/(1+$A9)^2+'AMB-P&L'!E29/(1+$A9)^3+'AMB-P&L'!F29/(1+$A9)^4+'AMB-P&L'!G29/(1+$A9)^5+'AMB-P&L'!H29/(1+$A9)^6+'AMB-P&L'!I29/(1+$A9)^7+'AMB-P&L'!J29/(1+$A9)^8+'AMB-P&L'!K29/(1+$A9)^9+'AMB-P&L'!L29/(1+$A9)^10+(('AMB-P&L'!L26*(1+0.04))-0.04*'AMB-Balance Sheet'!L5)/($A9-0.04)/(1+$A9)^10)+'AMB-Assumptions'!$B$17+'AMB-Assumptions'!$B$22-'AMB-Assumptions'!$B$16-'AMB-Assumptions'!$B$23-'AMB-Assumptions'!$B$18)/'AMB-Assumptions'!$B$15) -> 52.401612 | E9: =IF($A9<=0.05,"",(('AMB-P&L'!C29/(1+$A9)^1+'AMB-P&L'!D29/(1+$A9)^2+'AMB-P&L'!E29/(1+$A9)^3+'AMB-P&L'!F29/(1+$A9)^4+'AMB-P&L'!G29/(1+$A9)^5+'AMB-P&L'!H29/(1+$A9)^6+'AMB-P&L'!I29/(1+$A9)^7+'AMB-P&L'!J29/(1+$A9)^8+'AMB-P&L'!K29/(1+$A9)^9+'AMB-P&L'!L29/(1+$A9)^10+(('AMB-P&L'!L26*(1+0.05))-0.05*'AMB-Balance Sheet'!L5)/($A9-0.05)/(1+$A9)^10)+'AMB-Assumptions'!$B$17+'AMB-Assumptions'!$B$22-'AMB-Assumptions'!$B$16-'AMB-Assumptions'!$B$23-'AMB-Assumptions'!$B$18)/'AMB-Assumptions'!$B$15) -> 51.920169 | F9: =IF($A9<=0.06,"",(('AMB-P&L'!C29/(1+$A9)^1+'AMB-P&L'!D29/(1+$A9)^2+'AMB-P&L'!E29/(1+$A9)^3+'AMB-P&L'!F29/(1+$A9)^4+'AMB-P&L'!G29/(1+$A9)^5+'AMB-P&L'!H29/(1+$A9)^6+'AMB-P&L'!I29/(1+$A9)^7+'AMB-P&L'!J29/(1+$A9)^8+'AMB-P&L'!K29/(1+$A9)^9+'AMB-P&L'!L29/(1+$A9)^10+(('AMB-P&L'!L26*(1+0.06))-0.06*'AMB-Balance Sheet'!L5)/($A9-0.06)/(1+$A9)^10)+'AMB-Assumptions'!$B$17+'AMB-Assumptions'!$B$22-'AMB-Assumptions'!$B$16-'AMB-Assumptions'!$B$23-'AMB-Assumptions'!$B$18)/'AMB-Assumptions'!$B$15) -> 51.301171
A11: Read the direction carefully, because it changes sign across the forecast. In the EARLY years Ambuja earns about 7.2% on capital against a WACC of 11.03%, so growth there destroys value. By the TERMINAL year this model assumes return on capital reaches 12.1%, above the WACC, so terminal growth creates value and the grid slopes UPWARD with g: Rs 116 at 2% rising to Rs 134 at 6%, holding WACC at 11%. An earlier draft of this workbook asserted the opposite and was wrong. The real diagnostic is the crossing point: everything depends on whether return on capital actually climbs through the cost of capital, which is an assumption, not an observation. Ambuja has not earned above its cost of capital in either year of consolidated history available.
A15: What the traded price of Rs 400.90 would require
A16: Lever | B16: Model base case | C16: Needed for Rs 400.90
A17: Terminal ROIC (operating) | B17: 11.4% | C17: Well above 15%, sustained
A18: EBITDA per tonne by FY2035-36 | B18: Rs 1,544 | C18: Above Rs 2,000
A19: Capacity utilisation by FY2035-36 | B19: 85% | C19: Above 90%, at full capacity pricing
A20: Implied equity value | B20: about Rs 30,000 cr | C20: Rs 99,095 cr, a 3.3 times uplift
A22: For context, a sell side house modelled EBITDA of Rs 8,477 crore for FY2025-26 in December 2025, nine months into the year. Ambuja reported Rs 6,539 crore, a 30% miss, on a revenue estimate that was accurate to within 2.7%. The entire error was margin. Their forward margins of 23.7% and 25.2% carry their whole target price. Treat any forecast of a rapid margin recovery with that record in mind.

Sheet AMB-Relative Valuation
A1: Relative Valuation: Ambuja Cements
A2: Peer multiples are an OUTCOME to check the DCF against, never the thing that sets the value. Read this sheet after the DCF, not before.
A4: Line item | B4: Unit | C4: Ambuja | D4: UltraTech | E4: Shree | F4: JK | G4: Ramco
C5: SUBJECT | D5: Peer | E5: Peer | F5: Peer | G5: Peer
A6: Market capitalisation | B6: Rs cr | C6: 99095 | D6: 316633 | E6: 83058 | F6: 39252 | G6: 21939
A7: Net debt | B7: Rs cr | C7: -92.67 | D7: 16443.97 | E7: -6157.3 | F7: 5717.1 | G7: 3644.32
A8: Non-controlling interest | B8: Rs cr | C8: 12498.92 | D8: 0 | E8: 0 | F8: 0 | G8: 0
A9: EBITDA | B9: Rs cr | C9: 6558.99 | D9: 15816.65 | E9: 4036.63 | F9: 2283.94 | G9: 1347.74
A10: Revenue | B10: Rs cr | C10: 40446.04 | D10: 86069.88 | E10: 19985.22 | F10: 13621.38 | G10: 9211.41
A11: Normalised PAT | B11: Rs cr | C11: 2259.74 | D11: 7761.6 | E11: 1533.67 | F11: 1096.29 | G11: 178.45
A12: Net worth | B12: Rs cr | C12: 59347.32 | D12: 74663.37 | E12: 22511.6 | F12: 6960.68 | G12: 8142.37
A13: Diluted shares (crore) | B13: cr | C13: 247.18 | D13: 29.468 | E13: 3.608 | F13: 7.727 | G13: 23.63
A14: Basis of accounts | C14: CONSOLIDATED FY2025-26 | D14: Standalone TTM to Jun-26 | E14: Standalone TTM to Jun-26 | F14: Standalone TTM to Jun-26 | G14: Standalone TTM to Jun-26
A15: Enterprise value | C15: =C6+C8+C7 -> 111501.25 | D15: =D6+D8+D7 -> 333076.97 | E15: =E6+E8+E7 -> 76900.7 | F15: =F6+F8+F7 -> 44969.1 | G15: =G6+G8+G7 -> 25583.32
A17: Multiples
A18: EV/EBITDA | C18: =C15/C9 -> 16.999759 | D18: =D15/D9 -> 21.058629 | E18: =E15/E9 -> 19.050718 | F18: =F15/F9 -> 19.689265 | G18: =G15/G9 -> 18.982385
A19: EV/Sales | C19: =C15/C10 -> 2.7567903 | D19: =D15/D10 -> 3.8698436 | E19: =E15/E10 -> 3.8478786 | F19: =F15/F10 -> 3.3013615 | G19: =G15/G10 -> 2.7773511
A20: P/E (normalised) | C20: =C6/C11 -> 43.85239 | D20: =D6/D11 -> 40.79481 | E20: =E6/E11 -> 54.15637 | F20: =F6/F11 -> 35.804395 | G20: =G6/G11 -> 122.942
A21: P/B | C21: =C6/C12 -> 1.6697468 | D21: =D6/D12 -> 4.2408078 | E21: =E6/E12 -> 3.6895645 | F21: =F6/F12 -> 5.6391042 | G21: =G6/G12 -> 2.6944244
A22: ROE | C22: =C11/C12 -> 0.03807653 | D22: =D11/D12 -> 0.10395459 | E22: =E11/E12 -> 0.068127987 | F22: =F11/F12 -> 0.15749754 | G22: =G11/G12 -> 0.021916223
A23: Revenue growth | C23: 0 | D23: 0.047 | E23: 0.035 | F23: 0.052 | G23: 0.022
A25: Peer statistics (peers only, subject excluded)
A26: Multiple | C26: Min | D26: P25 | E26: Median | F26: P75 | G26: Max | H26: Mcap weighted
A27: EV/EBITDA | C27: =MIN(D18:G18) -> 18.982385 | D27: =QUARTILE(D18:G18,1) -> 19.033635 | E27: =MEDIAN(D18:G18) -> 19.369992 | F27: =QUARTILE(D18:G18,3) -> 20.031606 | G27: =MAX(D18:G18) -> 21.058629 | H27: =(D6*D18+E6*E18+F6*F18+G6*G18)/(D6+E6+F6+G6) -> 20.481314
A28: EV/Sales | C28: =MIN(D19:G19) -> 2.7773511 | D28: =QUARTILE(D19:G19,1) -> 3.1703589 | E28: =MEDIAN(D19:G19) -> 3.5746201 | F28: =QUARTILE(D19:G19,3) -> 3.8533698 | G28: =MAX(D19:G19) -> 3.8698436 | H28: =(D6*D19+E6*E19+F6*F19+G6*G19)/(D6+E6+F6+G6) -> 3.7654641
A29: P/E (normalised) | C29: =MIN(D20:G20) -> 35.804395 | D29: =QUARTILE(D20:G20,1) -> 39.547206 | E29: =MEDIAN(D20:G20) -> 47.47559 | F29: =QUARTILE(D20:G20,3) -> 71.352778 | G29: =MAX(D20:G20) -> 122.942 | H29: =(D6*D20+E6*E20+F6*F20+G6*G20)/(D6+E6+F6+G6) -> 46.688136
A30: P/B | C30: =MIN(D21:G21) -> 2.6944244 | D30: =QUARTILE(D21:G21,1) -> 3.4407795 | E30: =MEDIAN(D21:G21) -> 3.9651861 | F30: =QUARTILE(D21:G21,3) -> 4.5903819 | G30: =MAX(D21:G21) -> 5.6391042 | H30: =(D6*D21+E6*E21+F6*F21+G6*G21)/(D6+E6+F6+G6) -> 4.1869429
A32: Implied value of Ambuja Cements
A33: Basis | C33: Peer P25 | D33: Peer median | E33: Peer P75 | F33: Mcap weighted
A34: Peer EV/EBITDA applied | C34: =D27 -> 19.033635 | D34: =E27 -> 19.369992 | E34: =F27 -> 20.031606 | F34: =H27 -> 20.481314
A35: Implied equity value | C35: =C34*C9-C7-C8 -> 112435.17 | D35: =D34*C9-C7-C8 -> 114641.33 | E35: =E34*C9-C7-C8 -> 118980.85 | F35: =F34*C9-C7-C8 -> 121930.49
A36: Implied price per share (EV/EBITDA) | C36: =C35/C13 -> 454.87164 | D36: =D35/C13 -> 463.79695 | E36: =E35/C13 -> 481.35308 | F36: =F35/C13 -> 493.28621
A38: Peer P/E applied | C38: =D29 -> 39.547206 | D38: =E29 -> 47.47559 | E38: =F29 -> 71.352778 | F38: =H29 -> 46.688136
A39: Implied equity value | C39: =C38*C11 -> 89366.404 | D39: =D38*C11 -> 107282.49 | E39: =E38*C11 -> 161238.73 | F39: =F38*C11 -> 105503.05
A40: Implied price per share (P/E) | C40: =C39/C13 -> 361.54383 | D40: =D39/C13 -> 434.02577 | E40: =E39/C13 -> 652.31299 | F40: =F39/C13 -> 426.8268
A42: Peer P/B applied | C42: =D30 -> 3.4407795 | D42: =E30 -> 3.9651861 | E42: =F30 -> 4.5903819 | F42: =H30 -> 4.1869429
A43: Implied equity value | C43: =C42*C12 -> 204201.04 | D43: =D42*C12 -> 235323.17 | E43: =E42*C12 -> 272426.86 | F43: =F42*C12 -> 248483.84
A44: Implied price per share (P/B) | C44: =C43/C13 -> 826.12282 | D44: =D43/C13 -> 952.0316 | E44: =E43/C13 -> 1102.1396 | F44: =F43/C13 -> 1005.2749
A46: Where the DCF sits against the peer set
A47: Approach | C47: Value per share | D47: Gap to market
A48: DCF (this workbook, all five methods) | C48: 114.8664 | D48: =IFERROR(C48/$C$52-1,"") -> -0.71347867
A49: Relative: peer median EV/EBITDA | C49: =D36 -> 463.79695 | D49: =IFERROR(C49/$C$52-1,"") -> 0.15688938
A50: Relative: peer median P/E | C50: =D40 -> 434.02577 | D50: =IFERROR(C50/$C$52-1,"") -> 0.082628514
A51: Relative: peer median P/B | C51: =D44 -> 952.0316 | D51: =IFERROR(C51/$C$52-1,"") -> 1.3747358
A52: Market price | C52: 400.9
A54: DCF implied EV/EBITDA | C54: =(C48*C13+C7+C8)/C9 -> 6.2203063 | E54: Compare with the peer median above. This is the multiplier consistency check.
A56: CAUTION ON THE P/B ROW ABOVE. Applying a peer P/B to a company whose ROE differs sharply from the peer set is not a valuation, it is a category error. Across these five companies P/B tracks ROE closely: JK Cement at 5.6x on a 16% ROE, Shree at 3.7x on 7%, Ambuja at 1.7x on 4%. A company earning a lower return SHOULD trade at a lower multiple of book. The implied P/B values are shown for completeness and because the pairing itself is the diagnostic, but they should NOT be carried into a conclusion without adjusting for the ROE difference.
A61: This is the most important exhibit in the Ambuja workbook because the two approaches DISAGREE. Ambuja trades BELOW the peer median on EV/EBITDA, so relative valuation makes it look roughly a quarter cheap, while the DCF says it is worth about Rs 115 against a traded Rs 401. The resolution is in the P/B row above: EV/EBITDA cannot see the Rs 22,979 crore of goodwill and intangibles Ambuja capitalised on its acquisitions, and P/B can. Ambuja's P/B of 1.67x is the lowest in the set and so is its ROE. Across the peer set P/B tracks ROE closely, so Ambuja is not cheap, it is correctly priced for poor returns.
A65: READ THIS ALONGSIDE THE DCF, NOT INSTEAD OF IT. The apparent EV/EBITDA discount is an artifact of a multiple that ignores acquired goodwill. Return on invested capital including goodwill runs from 4.7% to only 9.0% across the ten year forecast and never reaches the 11.03% cost of capital. A company that cannot earn its cost of capital should trade below book, and Ambuja does. The cheapness is the diagnosis, not the opportunity.
A70: BASIS WARNING. Ambuja is carried on a CONSOLIDATED basis and every other company on a standalone basis. This is necessary, not sloppy: Ambuja held 50.05% of the listed ACC plus majority stakes in Orient, Sanghi and Penna at the valuation date, so its market capitalisation prices the whole group while its standalone EBITDA excludes ACC entirely. Dividing one by the other printed 35x. On a consolidated basis with the non-controlling interest added to enterprise value it is 17x. For the other four companies standalone and consolidated differ by under 10%, so the problem does not arise. Ambuja is also one quarter behind the others, on FY2025-26 rather than TTM to June 2026, because its consolidated Q1 filing is a scanned image from which finance costs could not be read reliably and guessing them was rejected.
A73: THE MULTIPLE VERSUS THE RETURN: why a lower EV/EBITDA does not mean cheap
A74: This block answers the obvious objection to a SELL on Ambuja: it trades BELOW the peer median on EV/EBITDA, so how can it be expensive? The answer is that EV/EBITDA measures what you pay for a stream of operating profit and says nothing about how much CAPITAL was consumed to produce it. Ambuja bought its EBITDA and capitalised Rs 22,979 crore of goodwill doing so; UltraTech largely built its own. The multiple cannot see that difference. Enterprise value to invested capital can, and so can price to book.
A78: Measure | C78: UltraTech | D78: Ambuja | F78: Ambuja as a percent of UltraTech
A79: Enterprise value (Rs cr) | C79: 333077 | D79: 111501 | F79: =D79/C79 -> 0.33476043
A80: Invested capital (Rs cr) | C80: 86090 | D80: 67208 | F80: =D80/C80 -> 0.78067139
A81: EBITDA (Rs cr) | C81: 15439 | D81: 6559 | F81: =D81/C81 -> 0.42483321
A82: EV / EBITDA | C82: =C79/C81 -> 21.573742 | D82: =D79/D81 -> 16.999695 | F82: =D82/C82 -> 0.78798083
A83: EV / Invested capital | C83: =C79/C80 -> 3.8689395 | D83: =D79/D80 -> 1.6590436 | F83: =D83/C83 -> 0.42881094
A84: ROIC today | C84: 0.108 | D84: 0.033 | F84: =D84/C84 -> 0.30555556
A85: ROIC, our terminal year | C85: 0.158 | D85: 0.09 | F85: =D85/C85 -> 0.56962025
A86: Return on equity | C86: 0.104 | D86: 0.038 | F86: =D86/C86 -> 0.36538462
A87: Price to book | C87: 4.24 | D87: 1.67 | F87: =D87/C87 -> 0.39386792
A89: READ THE THREE HIGHLIGHTED ROWS TOGETHER. Ambuja is priced at about 79% of UltraTech's EV/EBITDA, so it looks roughly a fifth cheaper. It is priced at about 43% of UltraTech's enterprise value per rupee of invested capital. But it earns only about 31% of UltraTech's return on that capital. The discount is nowhere near large enough for the gap in returns, and that is the whole answer: the cheaper stock is the larger SELL.
A93: What return on capital each company's price requires
A94: Steady state identity: EV/IC = (ROIC - g) / (WACC - g) | C94: UltraTech | D94: Ambuja | F94: Verdict
A95: Terminal growth g | C95: 0.0699 | D95: 0.0699
A96: WACC | C96: 0.11331 | D96: 0.11375
A97: ROIC today | C97: 0.108 | D97: 0.033
A98: ROIC, our terminal year | C98: 0.158 | D98: 0.09
A99: JUSTIFIED EV/IC on today's ROIC | C99: =(C97-C95)/(C96-C95) -> 0.87767795 | D99: =(D97-D95)/(D96-D95) -> -0.84150513
A100: JUSTIFIED EV/IC on terminal ROIC | C100: =(C98-C95)/(C96-C95) -> 2.0294863 | D100: =(D98-D95)/(D96-D95) -> 0.45838084
A101: ACTUAL EV/IC at the traded price | C101: =C79/C80 -> 3.8689395 | D101: =D79/D80 -> 1.6590436
A102: Actual as a multiple of justified (terminal ROIC) | C102: =C101/C100 -> 1.9063639 | D102: =D101/D100 -> 3.6193562
A104: THE DECISIVE NUMBERS. On our terminal returns, UltraTech's price is about 1.9 times what its return on capital justifies and Ambuja's is about 3.6 times. On TODAY'S return on capital Ambuja's justified multiple is NEGATIVE: at a 3.3% return and 7.0% growth, every rupee reinvested destroys value, so no positive multiple of invested capital is warranted at all. This is the sharpest statement of the investment case and it explains why the two SELL recommendations are consistent rather than contradictory. We are not claiming Ambuja is mispriced against its sector. We are claiming the SECTOR is mispriced against the cash it generates, and Ambuja is the member with the weakest returns. Note that UltraTech is itself one of the peers in the median: our own model says it is 51% overvalued, so a peer median built from such companies cannot be used to argue that anything is cheap.

Sheet AMB-Dashboard
A1: Consistency Dashboard
A3: The five consistencies
A4: # | B4: Consistency | C4: Verdict | D4: Evidence and remaining gap
A5: 1 | B5: Assumptions | C5: PASS | D5: Volume is capacity times utilisation, so growth is tied to physical assets. Capex is an explicit input anchored to the expansion plan, never held flat while volume rises. The terminal year is forced to steady state with reinvestment equal to g times OPERATING invested capital, which is the condition that makes EVA reconcile.
A6: 2 | B6: Risk | C6: PASS | D6: FCFF at WACC, CCF and APV at the unlevered rho, FCFE at Ke, EVA at WACC. Constant D/V rebalancing is assumed, so the tax shield is discounted at rho. With debt at 0.87% of enterprise value the choice is immaterial, but it is applied consistently regardless.
A7: 3 | B7: Asset | C7: PARTIAL | D7: Other income is excluded from EBITDA, so cash and investments are non-operating and added back once in the bridge. The unlevered beta is Damodaran's cash corrected 0.90 for the same reason. Goodwill and intangibles are inside invested capital for the ROIC measure but excluded from terminal reinvestment, and both versions of ROIC are shown. GAP: depreciation is charged at 8.0% of OPERATING fixed assets, but the historical Rs 3,570 crore charge includes amortisation of the Rs 9,433 crore intangible balance, which this model holds flat and never amortises. The charge and the base do not match. Splitting depreciation of PPE from amortisation of intangibles would be more correct; the net effect is likely small because the model is already conservative, but it is a real inconsistency and should be quantified before submission.
A8: 4 | B8: Liability | C8: PASS | D8: Borrowings and leases sit in the WACC weights and in the bridge. Deferred tax liabilities are NOT in the WACC weights, because they bear no interest, but they ARE now deducted in the bridge as a one time liability under Driver 2, which is the conservative and internally consistent treatment. Non-controlling interest of Rs 12,499 crore is deducted because consolidated cash flows include 100% of partly owned subsidiaries; omitting it would overstate value by about Rs 51 per share.
A9: 5 | B9: Multiplier | C9: PARTIAL | D9: The implied terminal EV/EBITDA is far below the cement peer median of 19.1x. The reverse question is the useful one: to justify the traded price the market must believe in a return on capital Ambuja has not earned in either year of available consolidated history. Position taken and evidenced on the Sensitivity sheet; the gap itself remains real.
A11: Audit checklist
A12: # | B12: Check | C12: Verdict | D12: Evidence and remaining gap
A13: 1 | B13: Five methods reconcile within 0.5% | C13: PASS | D13: All five return the same value per share to six decimal places. See Reconciliation.
A14: 2 | B14: WACC recomputes; weights market value; circularity handled | C14: PASS | D14: Weights are market value based. Circularity is immaterial here: at a debt to equity of 0.87%, no plausible revision to equity value shifts the weights enough to change WACC in the second decimal. Stated on the Cost-of-Capital sheet rather than assumed.
A15: 3 | B15: Debt grows at g where constant D/V is assumed | C15: PASS | D15: Debt is set to D/V times enterprise value at every date and the net new borrowing line is visible on the FCFE sheet.
A16: 4 | B16: Cash and investments: one treatment throughout | C16: PASS | D16: Consistent across flows, beta and bridge.
A17: 5 | B17: Every liability in WACC is subtracted in the bridge | C17: PASS | D17: Verified line by line, including the non-controlling interest.
A18: 6 | B18: Terminal: g < WACC, built multiplicatively, reinvestment = g/RONIC | C18: PASS | D18: g of 5.0% is built as (1+6.5%)(1+4.0%)-1 = 10.76% nominal taken at 46.46%, the SAME fraction as UltraTech, and sits well below the WACC of 11.03%. Reinvestment equals g divided by terminal ROIC exactly, and the terminal ROIC of 12.1% is only 0.2 points above the last explicit year, so there is no discontinuity at the boundary. An earlier draft used a lower fraction here on result driven reasoning that was also factually backwards; it has been corrected and the correction is documented on the Assumptions sheet rather than quietly applied.
A19: 7 | B19: Tax: marginal statutory rate used | C19: PASS | D19: 25.168% throughout. The reported effective rate is MINUS 71% because the tax line is a net credit, so using it anywhere would be meaningless. The three drivers of that credit are documented in the Source Log.
A20: 8 | B20: No DDT on post FY2020 flows | C20: PASS | D20: None applied.
A21: 9 | B21: Every input traces to the Source Log | C21: PARTIAL | D21: A Source Log exists and every input traces to it. Two open items: the 10 year G-Sec yield is a placeholder, and the merger swap ratios and dilution reached the model through broker research and must be re-sourced from the scheme filing.
A22: 10 | B22: Sensitivity tables live linked | C22: PASS | D22: The WACC by terminal growth grid recomputes from the forecast cash flows.
A24: Known weaknesses, stated rather than buried
B25: Two years of consolidated history | D25: The annual report provides FY2025-26 and a restated FY2024-25. Earlier consolidated years exist only in broker research. A ROIC trend asserted from two points is thin, and the report should say so.
B26: Restatements and a fifteen month year | D26: FY2024-25 was restated for the Sanghi and Penna amalgamation, and the transition year to March 2023 covered fifteen months. Any multi-year growth rate taken off this series without adjustment will be wrong.
B27: Merger in progress | D27: ACC, Orient, Sanghi and Penna are being merged into Ambuja. At the valuation date the structure was still a parent with listed subsidiaries. Both the pre-merger and post-merger share bases are shown on the Summary sheet.
A30: The 7 Golden Sanity Checks (Mohanty, Appendix 5A)
A31: # | B31: Check | C31: Verdict | D31: Evidence
A32: 1 | B32: Revenue growth plausible against GDP and TAM | C32: PASS | D32: Volume CAGR of 4.8% and revenue growth below nominal GDP of 10.76%. Growth comes mainly from filling existing plants rather than from share gains, which is the conservative shape.
A33: 2 | B33: Physical capacity supports projected volume | C33: PASS | D33: Volume is BUILT as capacity times utilisation. Capacity rises 109 to 133 Mn.T against a company target of 119 Mn.T plus modest brownfield addition. Peak volume of 113.0 Mn.T sits inside capacity at all times, and utilisation of 85% is below the industry ceiling.
A34: 3 | B34: Capex is sufficient to build the projected capacity | C34: PASS | D34: Total capex of Rs 80,000 cr less maintenance of Rs 43,974 cr leaves growth capex of Rs 36,026 cr against capacity addition of 24.0 Mn.T, or about Rs 15,011 per tonne. That is well ABOVE the Rs 5,000 to 7,000 brownfield norm, which is conservative for valuation and is also consistent with Rs 9,085 cr of capital work in progress still to be commissioned and with the acquisitive history. Capex is not understated.
A35: 4 | B35: Margin expansion realism | C35: PARTIAL | D35: EBITDA per tonne rises 74% over ten years, from Rs 886 to about Rs 1,544. The endpoint is 60% above the Rs 966 that UltraTech's best assets currently earn, which is demanding. It is deliberately so: we wanted the valuation to fail on the capital base rather than on a conservative operating forecast. A reader who regards Rs 1,544 as unreachable should note that the value would be LOWER still.
A36: 5 | B36: Working capital sanity | C36: PASS | D36: Net working capital held at minus 0.34% of revenue, essentially the FY2025-26 actual. No cash is manufactured from working capital.
A37: 6 | B37: Terminal ROIC fades toward WACC | C37: PASS | D37: Terminal ROIC on operating capital of 12.0% against a WACC of 11.375% is a spread of only 0.62 percentage points, which is a reasonable steady state for a commodity producer and does not assume perpetual super normal rents. Note that on invested capital INCLUDING goodwill the terminal return is well below the cost of capital, so the check passes comfortably on the measure that matters to shareholders.
A38: 7 | B38: Terminal value dominance | C38: PASS | D38: Terminal value is 71% of enterprise value, below the 80 to 90% threshold, and lower than it would be on a five year horizon. This is one reason the explicit forecast runs ten years.
A40: Applied from Prof. Mohanty's own audit framework, Appendix 5A of Book 29. The one item short of a full pass is margin expansion realism, and it is short in the direction that is against us: if EBITDA per tonne of Rs 1,544 is unreachable, the valuation is lower still. Note that the terminal ROIC fade check passes comfortably here, unlike the UltraTech model, because Ambuja's terminal spread over WACC is only 0.62 points.
A43: The 7 Golden Sanity Checks (Mohanty, Appendix 5A)
A44: # | B44: Check | C44: Verdict | D44: Evidence
A45: 1 | B45: Revenue growth plausible against GDP and TAM | C45: PASS | D45: Volume CAGR of 4.8% and revenue growth below nominal GDP of 10.76%. Growth comes mainly from filling existing plants rather than from share gains, which is the conservative shape.
A46: 2 | B46: Physical capacity supports projected volume | C46: PASS | D46: Volume is BUILT as capacity times utilisation. Capacity rises 109 to 133 Mn.T against a company target of 119 Mn.T plus modest brownfield addition. Peak volume of 113.0 Mn.T sits inside capacity at all times, and utilisation of 85% is below the industry ceiling.
A47: 3 | B47: Capex is sufficient to build the projected capacity | C47: PASS | D47: Total capex of Rs 80,000 cr less maintenance of Rs 43,974 cr leaves growth capex of Rs 36,026 cr against capacity addition of 24.0 Mn.T, or about Rs 15,011 per tonne. That is well ABOVE the Rs 5,000 to 7,000 brownfield norm, which is conservative for valuation and is also consistent with Rs 9,085 cr of capital work in progress still to be commissioned and with the acquisitive history. Capex is not understated.
A48: 4 | B48: Margin expansion realism | C48: PARTIAL | D48: EBITDA per tonne rises 74% over ten years, from Rs 886 to about Rs 1,544. The endpoint is 60% above the Rs 966 that UltraTech's best assets currently earn, which is demanding. It is deliberately so: we wanted the valuation to fail on the capital base rather than on a conservative operating forecast. A reader who regards Rs 1,544 as unreachable should note that the value would be LOWER still.
A49: 5 | B49: Working capital sanity | C49: PASS | D49: Net working capital held at minus 0.34% of revenue, essentially the FY2025-26 actual. No cash is manufactured from working capital.
A50: 6 | B50: Terminal ROIC fades toward WACC | C50: PASS | D50: Terminal ROIC on operating capital of 12.0% against a WACC of 11.375% is a spread of only 0.62 percentage points, which is a reasonable steady state for a commodity producer and does not assume perpetual super normal rents. Note that on invested capital INCLUDING goodwill the terminal return is well below the cost of capital, so the check passes comfortably on the measure that matters to shareholders.
A51: 7 | B51: Terminal value dominance | C51: PASS | D51: Terminal value is 71% of enterprise value, below the 80 to 90% threshold, and lower than it would be on a five year horizon. This is one reason the explicit forecast runs ten years.
A53: Applied from Prof. Mohanty's own audit framework, Appendix 5A of Book 29. The one item short of a full pass is margin expansion realism, and it is short in the direction that is against us: if EBITDA per tonne of Rs 1,544 is unreachable, the valuation is lower still. Note that the terminal ROIC fade check passes comfortably here, unlike the UltraTech model, because Ambuja's terminal spread over WACC is only 0.62 points.
A56: The 7 Golden Sanity Checks (Mohanty, Appendix 5A)
A57: # | B57: Check | C57: Verdict | D57: Evidence
A58: 1 | B58: Revenue growth plausible against GDP and TAM | C58: PASS | D58: Volume CAGR of 4.8% and revenue growth below nominal GDP of 10.76%. Growth comes mainly from filling existing plants rather than from share gains, which is the conservative shape.
A59: 2 | B59: Physical capacity supports projected volume | C59: PASS | D59: Volume is BUILT as capacity times utilisation. Capacity rises 109 to 133 Mn.T against a company target of 119 Mn.T plus modest brownfield addition. Peak volume of 113.0 Mn.T sits inside capacity at all times, and utilisation of 85% is below the industry ceiling.
A60: 3 | B60: Capex is sufficient to build the projected capacity | C60: PASS | D60: Total capex of Rs 80,000 cr less maintenance of Rs 43,974 cr leaves growth capex of Rs 36,026 cr against capacity addition of 24.0 Mn.T, or about Rs 15,011 per tonne. That is well ABOVE the Rs 5,000 to 7,000 brownfield norm, which is conservative for valuation and is also consistent with Rs 9,085 cr of capital work in progress still to be commissioned and with the acquisitive history. Capex is not understated.
A61: 4 | B61: Margin expansion realism | C61: PARTIAL | D61: EBITDA per tonne rises 74% over ten years, from Rs 886 to about Rs 1,544. The endpoint is 60% above the Rs 966 that UltraTech's best assets currently earn, which is demanding. It is deliberately so: we wanted the valuation to fail on the capital base rather than on a conservative operating forecast. A reader who regards Rs 1,544 as unreachable should note that the value would be LOWER still.
A62: 5 | B62: Working capital sanity | C62: PASS | D62: Net working capital held at minus 0.34% of revenue, essentially the FY2025-26 actual. No cash is manufactured from working capital.
A63: 6 | B63: Terminal ROIC fades toward WACC | C63: PASS | D63: Terminal ROIC on operating capital of 12.0% against a WACC of 11.375% is a spread of only 0.62 percentage points, which is a reasonable steady state for a commodity producer and does not assume perpetual super normal rents. Note that on invested capital INCLUDING goodwill the terminal return is well below the cost of capital, so the check passes comfortably on the measure that matters to shareholders.
A64: 7 | B64: Terminal value dominance | C64: PASS | D64: Terminal value is 71% of enterprise value, below the 80 to 90% threshold, and lower than it would be on a five year horizon. This is one reason the explicit forecast runs ten years.
A66: Applied from Prof. Mohanty's own audit framework, Appendix 5A of Book 29. The one item short of a full pass is margin expansion realism, and it is short in the direction that is against us: if EBITDA per tonne of Rs 1,544 is unreachable, the valuation is lower still. Note that the terminal ROIC fade check passes comfortably here, unlike the UltraTech model, because Ambuja's terminal spread over WACC is only 0.62 points.
A69: The 7 Golden Sanity Checks (Mohanty, Appendix 5A)
A70: # | B70: Check | C70: Verdict | D70: Evidence
A71: 1 | B71: Revenue growth plausible against GDP and TAM | C71: PASS | D71: Volume CAGR of 4.8% and revenue growth below nominal GDP of 10.76%. Growth comes mainly from filling existing plants rather than from share gains, which is the conservative shape.
A72: 2 | B72: Physical capacity supports projected volume | C72: PASS | D72: Volume is BUILT as capacity times utilisation. Capacity rises 109 to 133 Mn.T against a company target of 119 Mn.T plus modest brownfield addition. Peak volume of 113.0 Mn.T sits inside capacity at all times, and utilisation of 85% is below the industry ceiling.
A73: 3 | B73: Capex is sufficient to build the projected capacity | C73: PASS | D73: Total capex of Rs 80,000 cr less maintenance of Rs 43,974 cr leaves growth capex of Rs 36,026 cr against capacity addition of 24.0 Mn.T, or about Rs 15,011 per tonne. That is well ABOVE the Rs 5,000 to 7,000 brownfield norm, which is conservative for valuation and is also consistent with Rs 9,085 cr of capital work in progress still to be commissioned and with the acquisitive history. Capex is not understated.
A74: 4 | B74: Margin expansion realism | C74: PARTIAL | D74: EBITDA per tonne rises 74% over ten years, from Rs 886 to about Rs 1,544. The endpoint is 60% above the Rs 966 that UltraTech's best assets currently earn, which is demanding. It is deliberately so: we wanted the valuation to fail on the capital base rather than on a conservative operating forecast. A reader who regards Rs 1,544 as unreachable should note that the value would be LOWER still.
A75: 5 | B75: Working capital sanity | C75: PASS | D75: Net working capital held at minus 0.34% of revenue, essentially the FY2025-26 actual. No cash is manufactured from working capital.
A76: 6 | B76: Terminal ROIC fades toward WACC | C76: PASS | D76: Terminal ROIC on operating capital of 12.0% against a WACC of 11.375% is a spread of only 0.62 percentage points, which is a reasonable steady state for a commodity producer and does not assume perpetual super normal rents. Note that on invested capital INCLUDING goodwill the terminal return is well below the cost of capital, so the check passes comfortably on the measure that matters to shareholders.
A77: 7 | B77: Terminal value dominance | C77: PASS | D77: Terminal value is 71% of enterprise value, below the 80 to 90% threshold, and lower than it would be on a five year horizon. This is one reason the explicit forecast runs ten years.
A79: Applied from Prof. Mohanty's own audit framework, Appendix 5A of Book 29. The one item short of a full pass is margin expansion realism, and it is short in the direction that is against us: if EBITDA per tonne of Rs 1,544 is unreachable, the valuation is lower still. Note that the terminal ROIC fade check passes comfortably here, unlike the UltraTech model, because Ambuja's terminal spread over WACC is only 0.62 points.
A82: The 7 Golden Sanity Checks (Mohanty, Appendix 5A)
A83: # | B83: Check | C83: Verdict | D83: Evidence
A84: 1 | B84: Revenue growth plausible against GDP and TAM | C84: PASS | D84: Volume CAGR of 4.8% and revenue growth below nominal GDP of 10.76%. Growth comes mainly from filling existing plants rather than from share gains, which is the conservative shape.
A85: 2 | B85: Physical capacity supports projected volume | C85: PASS | D85: Volume is BUILT as capacity times utilisation. Capacity rises 109 to 133 Mn.T against a company target of 119 Mn.T plus modest brownfield addition. Peak volume of 113.0 Mn.T sits inside capacity at all times, and utilisation of 85% is below the industry ceiling.
A86: 3 | B86: Capex is sufficient to build the projected capacity | C86: PASS | D86: Total capex of Rs 80,000 cr less maintenance of Rs 43,974 cr leaves growth capex of Rs 36,026 cr against capacity addition of 24.0 Mn.T, or about Rs 15,011 per tonne. That is well ABOVE the Rs 5,000 to 7,000 brownfield norm, which is conservative for valuation and is also consistent with Rs 9,085 cr of capital work in progress still to be commissioned and with the acquisitive history. Capex is not understated.
A87: 4 | B87: Margin expansion realism | C87: PARTIAL | D87: EBITDA per tonne rises 74% over ten years, from Rs 886 to about Rs 1,544. The endpoint is 60% above the Rs 966 that UltraTech's best assets currently earn, which is demanding. It is deliberately so: we wanted the valuation to fail on the capital base rather than on a conservative operating forecast. A reader who regards Rs 1,544 as unreachable should note that the value would be LOWER still.
A88: 5 | B88: Working capital sanity | C88: PASS | D88: Net working capital held at minus 0.34% of revenue, essentially the FY2025-26 actual. No cash is manufactured from working capital.
A89: 6 | B89: Terminal ROIC fades toward WACC | C89: PASS | D89: Terminal ROIC on operating capital of 12.0% against a WACC of 11.375% is a spread of only 0.62 percentage points, which is a reasonable steady state for a commodity producer and does not assume perpetual super normal rents. Note that on invested capital INCLUDING goodwill the terminal return is well below the cost of capital, so the check passes comfortably on the measure that matters to shareholders.
A90: 7 | B90: Terminal value dominance | C90: PASS | D90: Terminal value is 71% of enterprise value, below the 80 to 90% threshold, and lower than it would be on a five year horizon. This is one reason the explicit forecast runs ten years.
A92: Applied from Prof. Mohanty's own audit framework, Appendix 5A of Book 29. The one item short of a full pass is margin expansion realism, and it is short in the direction that is against us: if EBITDA per tonne of Rs 1,544 is unreachable, the valuation is lower still. Note that the terminal ROIC fade check passes comfortably here, unlike the UltraTech model, because Ambuja's terminal spread over WACC is only 0.62 points.
A95: The 7 Golden Sanity Checks (Mohanty, Appendix 5A)
A96: # | B96: Check | C96: Verdict | D96: Evidence
A97: 1 | B97: Revenue growth plausible against GDP and TAM | C97: PASS | D97: Volume CAGR of 4.8% and revenue growth below nominal GDP of 10.76%. Growth comes mainly from filling existing plants rather than from share gains, which is the conservative shape.
A98: 2 | B98: Physical capacity supports projected volume | C98: PASS | D98: Volume is BUILT as capacity times utilisation. Capacity rises 109 to 133 Mn.T against a company target of 119 Mn.T plus modest brownfield addition. Peak volume of 113.0 Mn.T sits inside capacity at all times, and utilisation of 85% is below the industry ceiling.
A99: 3 | B99: Capex is sufficient to build the projected capacity | C99: PASS | D99: Total capex of Rs 80,000 cr less maintenance of Rs 43,974 cr leaves growth capex of Rs 36,026 cr against capacity addition of 24.0 Mn.T, or about Rs 15,011 per tonne. That is well ABOVE the Rs 5,000 to 7,000 brownfield norm, which is conservative for valuation and is also consistent with Rs 9,085 cr of capital work in progress still to be commissioned and with the acquisitive history. Capex is not understated.
A100: 4 | B100: Margin expansion realism | C100: PARTIAL | D100: EBITDA per tonne rises 74% over ten years, from Rs 886 to about Rs 1,544. The endpoint is 60% above the Rs 966 that UltraTech's best assets currently earn, which is demanding. It is deliberately so: we wanted the valuation to fail on the capital base rather than on a conservative operating forecast. A reader who regards Rs 1,544 as unreachable should note that the value would be LOWER still.
A101: 5 | B101: Working capital sanity | C101: PASS | D101: Net working capital held at minus 0.34% of revenue, essentially the FY2025-26 actual. No cash is manufactured from working capital.
A102: 6 | B102: Terminal ROIC fades toward WACC | C102: PASS | D102: Terminal ROIC on operating capital of 12.0% against a WACC of 11.375% is a spread of only 0.62 percentage points, which is a reasonable steady state for a commodity producer and does not assume perpetual super normal rents. Note that on invested capital INCLUDING goodwill the terminal return is well below the cost of capital, so the check passes comfortably on the measure that matters to shareholders.
A103: 7 | B103: Terminal value dominance | C103: PASS | D103: Terminal value is 71% of enterprise value, below the 80 to 90% threshold, and lower than it would be on a five year horizon. This is one reason the explicit forecast runs ten years.
A105: Applied from Prof. Mohanty's own audit framework, Appendix 5A of Book 29. The one item short of a full pass is margin expansion realism, and it is short in the direction that is against us: if EBITDA per tonne of Rs 1,544 is unreachable, the valuation is lower still. Note that the terminal ROIC fade check passes comfortably here, unlike the UltraTech model, because Ambuja's terminal spread over WACC is only 0.62 points.

Sheet AMB-Summary
A1: Ambuja Cements Ltd: Valuation Summary
A2: Consolidated. Rs crore and Rs per share. Valuation date 31 March 2026, market data at the 30 March close.
A4: Market
A5: Market price per share | B5: 400.9 | F5: Rs 99,095 cr over 247.18 cr shares.
A6: Market capitalisation | B6: ='AMB-Assumptions'!$B$14 -> 99095
A8: Discounted cash flow, five methods
A9: Method | B9: Discount rate | C9: Rate | D9: Value per share | E9: Upside / (downside)
A10: FCFF | B10: WACC | C10: ='AMB-Cost of Capital'!$B$13 -> 0.11374609 | D10: ='AMB-FCFF valuation'!C16 -> 98.854774 | E10: =IFERROR(D10/$B$5-1,"") -> -0.75341788
A11: CCF | B11: rho | C11: ='AMB-Cost of Capital'!$B$14 -> 0.11392051 | D11: ='AMB-CCF valuation'!C16 -> 98.854774 | E11: =IFERROR(D11/$B$5-1,"") -> -0.75341788
A12: APV | B12: rho | C12: ='AMB-Cost of Capital'!$B$14 -> 0.11392051 | D12: ='AMB-APV valuation'!C16 -> 98.854774 | E12: =IFERROR(D12/$B$5-1,"") -> -0.75341788
A13: FCFE | B13: Ke | C13: ='AMB-Cost of Capital'!$B$8 -> 0.11421692 | D13: ='AMB-FCFE valuation'!C19 -> 98.854774 | E13: =IFERROR(D13/$B$5-1,"") -> -0.75341788
A14: EVA | B14: WACC | C14: ='AMB-Cost of Capital'!$B$13 -> 0.11374609 | D14: ='AMB-EVA'!C15 -> 98.854774 | E14: =IFERROR(D14/$B$5-1,"") -> -0.75341788
A16: Merger adjustment: pre-merger versus post-merger share base
A17: Basis | B17: Equity value | C17: Shares (crore) | D17: Value per share
A18: Pre-merger: NCI deducted, current shares | B18: ='AMB-FCFF valuation'!C15 -> 24434.923 | C18: ='AMB-Assumptions'!$B$15 -> 247.18 | D18: =B18/C18 -> 98.854774
A19: Post-merger: NCI acquired, shares up 13.7% | B19: ='AMB-FCFF valuation'!C15+'AMB-Assumptions'!$B$18 -> 36933.843 | C19: ='AMB-Assumptions'!$B$15*1.137 -> 281.04366 | D19: =B19/C19 -> 131.41674
A21: The two routes should give a similar answer, and they do. Pre-merger deducts the non-controlling interest at book and divides by today's shares. Post-merger keeps the whole consolidated equity and divides by the enlarged share count. The small difference is the discount at which minorities are being acquired, which is the source of the value accretion the company and the sell side both point to. Re-source the 13.7% dilution from the scheme filing before relying on it.
A23: The Rs 2,338 crore tax credit: what each driver does to value
A24: Driver | B24: Nature | C24: Valuation treatment | D24: Impact (Rs cr) | E24: Per share
A25: 1. Litigation provisions released | B25: Non-cash, one-off | C25: Provision reversal excluded: it never entered the cash flows because tax is charged at the statutory rate throughout. | D25: 0 | E25: =D25/'AMB-Assumptions'!$B$15 -> 0
A26: 1a. Tax paid under protest | B26: REAL CASH, recoverable | C26: Added as a non-operating asset. Sits in other non-current assets, outside operating invested capital, so it was being missed. | D26: 614.1 | E26: =D26/'AMB-Assumptions'!$B$15 -> 2.4844243
A27: 2. Deferred tax liabilities | B27: Real liability, one-off | C27: Deducted in the bridge as a single drop, not amortised. | D27: -3466.33 | E27: =D27/'AMB-Assumptions'!$B$15 -> -14.023505
A28: 3. Section 72A loss shelter | B28: Real but SHRINKING | C28: Memo only, Rs 345.78 cr consolidated covering losses AND unabsorbed depreciation together. Already netted inside Driver 2. | D28: 0 | E28: =D28/'AMB-Assumptions'!$B$15 -> 0
A29: Net adjustment | D29: =SUM(D25:D28) -> -2852.23 | E29: =D29/'AMB-Assumptions'!$B$15 -> -11.539081
A31: Two checks were run against the report and both changed the answer. FIRST, the disputed tax was NOT purely a book entry: Note 53 shows Rs 614.10 crore of consolidated duty and taxes paid under protest carried as a non-current asset, down from Rs 628.88 crore, which is cash already handed over and recoverable on a favourable ruling. It sat outside operating invested capital and was being missed entirely; it is now added, worth about Rs 2.48 per share. SECOND, Sanghi and Penna did NOT bring a larger separate pool of business losses. The deferred tax note is headed Unabsorbed depreciation AND Business Losses together, so the single consolidated balance of Rs 345.78 crore already covers both. More usefully, that balance is SHRINKING: Rs 509.66 crore opening, Rs 163.88 crore consumed in the year, Rs 345.78 crore remaining. The shelter is being used up rather than accumulating, so Driver 3 is worth less over time, not more. Driver 2 remains the only item that moves the value materially, and it moves it down.
A36: Relative valuation cross-check
A37: Multiple | B37: Peer median | C37: Ambuja traded | D37: Ambuja DCF implied
A38: EV/EBITDA (consolidated) | B38: 19.1x | C38: about 17.0x | D38: see FCFF sheet
A39: P/B | B39: 3.7x | C39: 1.9x | D39: lowest in the peer set
A41: IMPORTANT: the comps workbook computes Ambuja's EV/EBITDA on STANDALONE earnings against a group market capitalisation, which prints about 35x and is wrong. On a consolidated basis, adding back the non-controlling interest, the multiple is roughly 17x, close to the peer median. Fix the comps workbook before quoting either number.
A45: Conclusion
A46: The five methods reconcile exactly, giving about Rs 122 per share pre-merger and Rs 151 post-merger, against a traded Rs 400.90. Ambuja is the harder of the two companies to value, and the reasons are worth stating precisely. The central finding is that Ambuja earns far less on capital than capital costs. Return on invested capital including goodwill is 4.7% in FY2026-27 rising to only 7.3% by FY2031-32, against a WACC of 11.03%. Economic value added is NEGATIVE in every forecast year, which is why enterprise value sits below invested capital. The clearest single diagnostic is on the Sensitivity sheet: value RISES as terminal growth FALLS. When a company earns below its cost of capital, growth destroys value. Note however that the sensitivity grid slopes UPWARD with terminal growth, because this model assumes return on capital climbs to 12.1% by the terminal year, above the WACC. Whether that crossing actually happens is the entire investment case, and it is an assumption rather than anything observed: Ambuja has not earned above its cost of capital in either year of consolidated history available. Three things explain the return. Utilisation is only about 68%, against 82% at UltraTech, so a large asset base is underworked. EBITDA per tonne is Rs 886 against a peer set earning well above that. And acquisitions left Rs 22,979 crore of goodwill and intangibles on the balance sheet, which is capital shareholders paid for and must earn a return on. Strip goodwill out and ROIC improves from 4.7% to 7.2%, which measures operating performance but flatters what shareholders actually earned. The bull case is specific: utilisation climbing as recently added and acquired capacity fills, EBITDA per tonne recovering toward the peer set as the Sanghi, Penna, Orient and ACC integrations complete, and the merger removing holding company complexity and minority leakage. This model already assumes utilisation rises from 68% to 85% and EBITDA per tonne rises 74% over ten years, and still reaches only Rs 122. To reach the traded price the market must believe in a terminal return on capital above 15%, which Ambuja has not earned in either year of consolidated history available. Two accounting distortions had to be removed before any of this was measurable. The reported tax line is a NET CREDIT of about Rs 2,338 crore, so reported profit exceeds profit before tax and the reported effective rate is minus 71%. Its three drivers are documented: roughly Rs 1,251 crore of earlier year litigation provisions released on favourable court decisions, roughly Rs 839 crore net from deferred tax reversals on the amalgamation, and roughly Rs 569 crore from carried forward losses unlocked under section 72A. The first two are non-recurring; only the tax shelter from the third, a deferred tax asset of Rs 280 crore on unabsorbed depreciation, is genuinely forward looking, and it is small enough not to move the answer. Everything here is computed at the statutory rate instead. Separately, FY2024-25 was restated for the amalgamation and the transition year to March 2023 covered fifteen months, so no growth rate should be taken off the reported series without adjustment. Caveats. The G-Sec yield is still a placeholder. Consolidated history is only two years deep, so the return trend is asserted from two points. The merger terms reached this model through broker research and must be re-sourced from the scheme filing. And the implied terminal multiple sits far below the cement peer median, which is recorded as a PARTIAL on the Consistency Dashboard rather than smoothed over: either the peer set is expensively rated, or this model is too pessimistic on the recovery. Take a position and defend it.
