Workbook

Sheet UTCL-Index
A1: UltraTech Cement Ltd: Business Analysis and Valuation
A2: Standalone basis. Rs crore unless stated. FYE 31 March. Valuation date 31 March 2026.
A4: No. | B4: Sheet | C4: What it contains
A5: 1 | B5: Source-Log | C5: Every input traced to its publisher, with open items and re-source flags marked in red
A6: 2 | B6: Source-Data | C6: Ten year standalone history exactly as published in the FY2025-26 report, plus derived ratios
A7: 3 | B7: Assumptions | C7: Every forecast driver and hardcoded input in one place. Blue on yellow means edit here
A8: 4 | B8: PnL-Forecast | C8: FY2026-27 to FY2030-31 forecast profit and loss built off the assumption drivers
A9: 5 | B9: Invested-Capital | C9: Invested capital roll forward, ROIC history and forecast, reinvestment rate
A10: 6 | B10: Cost-of-Capital | C10: Risk free, ERP, beta, cost of debt, capital structure, WACC and the unlevered rate rho
A11: 7 | B11: FCFF | C11: Enterprise DCF on free cash flow to the firm, discounted at WACC
A12: 8 | B12: CCF | C12: Capital cash flow valuation, discounted at the unlevered rate rho
A13: 9 | B13: APV | C13: Adjusted present value: unlevered value plus the present value of the interest tax shield
A14: 10 | B14: FCFE | C14: Equity DCF on free cash flow to equity, discounted at the cost of equity
A15: 11 | B15: EVA | C15: Economic value added: opening invested capital plus the present value of future EVA
A16: 12 | B16: Reconciliation | C16: Proof that all five methods return the same enterprise and equity value
... A18: 14 | B18: Summary | C18: Valuation summary, football field, and what the market price is implying
A20: Colour convention
B21: Blue | C21: Hardcoded input taken from a published source
B22: Blue on yellow | C22: Assumption or judgement. Change these to test the model
B23: Black | C23: Formula within the sheet
B24: Green | C24: Link to another sheet
A26: Read this before using any number in this workbook
B27: The equity risk premium and beta are now sourced from Damodaran, January 2026. The ONE remaining placeholder is the Indian 10 year G-Sec yield on the Assumptions sheet, which must come from RBI. Note that replacing the earlier invented cost of capital moved the answer very little, which is itself the finding: the discount rate is not what separates this model from the market price.
B28: The terminal value imposes a genuine steady state: reinvestment equals terminal growth times invested capital. This is what makes all five valuation methods reconcile exactly. Do not replace it with a naive FCFF perpetuity.
B29: FY2018-19 and FY2022-23 are shown as Restated in the company's own ten year table. The restatement basis is the company's; it has not been independently verified here.

Sheet UTCL-Audit Log
A1: Source Log
A2: Every input cell in this workbook traces to a row below. Rows marked PLACEHOLDER or RE-SOURCE are open items.
A4: # | B4: Item | C4: Publisher | D4: Source and location | E4: Accessed | F4: Period | G4: Feeds
A5: 1 | B5: Ten year standalone financial highlights | C5: UltraTech Cement Ltd | D5: integrated-and-sustainability-report-2025-26-double-page.pdf, Standalone Financial Highlights | E5: 2026-08-26 | F5: FY2016-17 to FY2025-26 | G5: Source-Data, all rows
A6: 2 | B6: Standalone balance sheet | C6: UltraTech Cement Ltd | D6: Same report, standalone balance sheet. Loan funds 19,617, leases 863, net worth 74,663 all tie to the ten year table. | E6: 2026-08-26 | F6: 31-Mar-2026 | G6: Assumptions, debt and leases
A7: 3 | B7: Capital work in progress | C7: UltraTech Cement Ltd | D7: Same report, Note 02: CWIP Rs 7,871.47 cr (FY25 Rs 5,956.01 cr) | E7: 2026-08-26 | F7: 31-Mar-2026 | G7: Assumptions, productive fixed assets
A8: 4 | B8: Non-current investments note | C8: UltraTech Cement Ltd | D8: Same report: The India Cements Limited, 23,24,16,830 shares, carrying value Rs 8,970.17 cr, holding 74.99% | E8: 2026-08-26 | F8: 31-Mar-2026 | G8: Assumptions, India Cements block
A9: 5 | B9: Market capitalisation and monthly price table | C9: UltraTech Cement Ltd | D9: Same report, Shareholder Information: NSE Rs 3,16,633 cr; March 2026 NSE close Rs 10,745.00. The two tie over 29.468 cr shares. | E9: 2026-08-26 | F9: 30-Mar-2026 | G9: Assumptions, market data
A10: 6 | B10: Unaudited standalone results, Q1 FY2026-27 | C10: UltraTech Cement Ltd | D10: q1fy27results.pdf, standalone results page 10 | E10: 2026-08-26 | F10: Q1 FY27 | G10: Cross-check only
A11: 7 | B11: Regulation 52(4) disclosures | C11: UltraTech Cement Ltd | D11: q1fy27results.pdf page 11: net worth Rs 77,127.12 cr at 30-Jun-26, debt to equity 0.25x. Used only to corroborate the balance sheet. | E11: 2026-08-26 | F11: 30-Jun-2026 | G11: Memo
A12: 8 | B12: India equity risk premium 7.08% | C12: Aswath Damodaran, NYU Stern | D12: Country Default Spreads and Risk Premiums, January 2026. India Baa3: mature market 4.23% plus country risk premium 2.85%. CDS based alternative 5.23%. | E12: 2026-08-26 | F12: Jan-2026 | G12: Cost-of-Capital
A13: 9 | B13: India sovereign default spread 1.87% | C13: Aswath Damodaran, NYU Stern | D13: Same table. Deducted from the G-Sec yield to reach a default free rupee rate. | E13: 2026-08-26 | F13: Jan-2026 | G13: Cost-of-Capital
A14: 10 | B14: Unlevered beta 0.90, Building Materials | C14: Aswath Damodaran, NYU Stern | D14: Betas by Sector (Global), January 2026: 469 firms, unlevered beta corrected for cash. Cash corrected figure used because cash is added back separately at the bridge. | E14: 2026-08-26 | F14: Jan-2026 | G14: Cost-of-Capital
A15: 11 | B15: ASSUMPTION: tax rate 25.168% | C15: Own assumption, verified | D15: Section 115BAA: 22% plus 10% surcharge plus 4% cess. Cross-checked against the reported effective rate of 26.1% in FY2025-26, so no migration path needed. | E15: 2026-08-26 | F15: FY2025-26 | G15: Assumptions
A16: 12 | B16: ASSUMPTION: cost of debt 8.34% | C16: Own assumption | D16: FY2025-26 interest of 1,630 over average loan funds of 19,538. The method prefers a traded bond yield; this is the sanity check version and should be upgraded if UltraTech has listed debt. | E16: 2026-08-26 | F16: FY2025-26 | G16: Cost-of-Capital
... A20: 16 | B20: DERIVED: standalone capacity 172.5 Mn.T | C20: Own derivation | D20: Consolidated 192.3 mtpa less 5.4 overseas less India Cements 14.45. NOT a disclosed figure. Verify against the investor presentation. | E20: 2026-08-26 | F20: FY2025-26 | G20: Assumptions
A21: 17 | B21: OPEN: India Cements market price | C21: NSE | D21: NOT YET SOURCED. India Cements is listed, so asset consistency requires the stake at market value. Model falls back to carrying value while blank. Each Rs 100 on the ICEM price moves UltraTech value by about Rs 79 per share. | F21: 30-Mar-2026 | G21: Assumptions, India Cements
A22: 18 | B22: OPTIONAL: Fama French factors | C22: IIM Ahmedabad | D22: Indian Fama French factor library (Agarwalla, Jacob and Varma) for the alternative cost of equity. Ken French publishes no India dataset; Yahoo Finance is a banned source, so prices must come from NSE. | E22: 2026-08-26 | F22: 1993 onward | G22: Cost-of-Capital, FF Ke cell
A23: 19 | B23: Peer multiples | C23: Peer annual reports | D23: Shree Cement, JK Cement and Ramco Cements: financials and disclosed market caps from their own FY2025-26 reports. See the companion comps workbook. | E23: 2026-08-26 | F23: TTM to Jun-2026 | G23: Summary, football field
A25: Banned sources check: no data anywhere in this workbook comes from moneycontrol, screener.in, Yahoo Finance, investing.com, trendlyne, tijori or Wikipedia. The one non-authorised input is the broker relayed earnings call content flagged above, which is marked for re-sourcing rather than quietly used.
A28: MODEL AUDIT LOG: issues found during the build, and what was done about them
A29: # | B29: Where | C29: Severity | D29: Finding | E29: Valuation impact | F29: Fix applied
A30: 1 | B30: Dashboard, Golden Check 6 | C30: HIGH | D30: Terminal ROIC of 15.8% against a WACC of 11.33% is a permanent 4.5 point spread in perpetuity, which assumes super normal returns forever and contradicts a realised ROIC that FELL from 14.5% to 10.8% over four years. | E30: Overstated value by roughly Rs 1,141 per share | F30: FIXED. A terminal ROIC fade is now wired into the Balance Sheet terminal block and switched ON by default, taking terminal ROIC to WACC plus 0.5%. Value falls from Rs 5,273 to Rs 4,132. The switch is on the Assumptions sheet.
A31: 2 | B31: Entity Build, India Cements | C31: MED | D31: The 74.99% holding in the LISTED India Cements is carried at BOOK value of Rs 8,970 cr, or Rs 385.95 per India Cements share. | E31: Each Rs 100 on the India Cements price moves UltraTech by about Rs 79 per share | F31: PARTIALLY FIXED. A market price override cell exists on the Assumptions sheet and a sensitivity table is now on the Entity Build sheet. The price itself is still to be sourced from NSE.
A32: 3 | B32: Entity Build, basis | C32: MED | D32: UltraTech is valued STANDALONE while Ambuja is valued CONSOLIDATED. Prof. Mohanty's own teaching is explicit that a holding above 50% requires consolidation, and UltraTech holds 74.99% of India Cements. | E32: Omitted subsidiary block is 9.3% of group EBITDA | F32: PARTIALLY FIXED. Consolidated figures are now reconciled on the Entity Build sheet and a what-if consolidation bridge quantifies the omission at roughly Rs 537 per share. A full consolidated rebuild is not possible because consolidated VOLUME and CWIP are not separately disclosed.
A33: 4 | B33: Model build, capital intensity | C33: HIGH | D33: Capex was originally derived from capital intensity, which charged the company a second time for capacity it had already built. | E33: Understated value by roughly one third | F33: FIXED. Capex is now an explicit input anchored to management guidance of about Rs 10,000 cr a year.
A34: 5 | B34: Model build, CWIP | C34: MED | D34: Capital work in progress of Rs 7,871 cr was included in the capital intensity ratio despite earning no revenue. | E34: Understated value by about 14% | F34: FIXED. CWIP is excluded from the intensity ratio but retained inside invested capital, which is what Book 29 section 4.6 requires.
A35: 6 | B35: Cost of capital, risk free rate | C35: MED | D35: The 10 year G-Sec yield was a placeholder at 6.50%. | E35: About 5% of value | F35: FIXED. Replaced with the FBIL 10 year par yield of 6.85% for the week ended 20 March 2026, date matched to the valuation date.
A36: 7 | B36: Beta | C36: LOW | D36: Only a bottom up beta was available; no regression cross check had been run. | E36: None; direction favours conservatism | F36: FIXED. A live regression is now on the Beta sheet using 60 monthly observations. It returns 1.0863 against the bottom up 0.9436. The bottom up figure is retained and the difference disclosed.
A38: Every entry above was found by us during the build, not by a reviewer afterwards. Where an item is marked PARTIALLY FIXED or DOCUMENTED NOT FIXED, the reason is stated and the direction of the residual error is given. Three of the fixes moved the valuation AGAINST our own recommendation, which is recorded deliberately.
A41: SOURCE URLs AND ACCESS DATES
A42: Input | B42: Authoritative source URL | C42: Accessed
A43: Company annual report and financial statements | B43: https://www.ultratechcement.com/investors/investor-reports | C43: 26 Aug 2026
A44: Exchange filings and quarterly results | B44: https://www.nseindia.com/companies-listing/corporate-filings-financial-results | C44: 26 Aug 2026
A45: 10 year G-Sec par yield, FBIL series | B45: https://www.rbi.org.in/Scripts/BS_ViewBulletin.aspx | C45: 26 Aug 2026
A46: Equity risk premium and sovereign default spread | B46: https://pages.stern.nyu.edu/~adamodar/New_Home_Page/datacurrent.html | C46: 26 Aug 2026
A47: Unlevered beta by sector, global | B47: https://pages.stern.nyu.edu/~adamodar/New_Home_Page/datafile/Betas.html | C47: 26 Aug 2026
A48: Historical price series for the beta regression | B48: https://www.nseindia.com/reports-indices-historical-index-data | C48: 26 Aug 2026
A50: These are the AUTHORITATIVE LANDING PAGES from which each input was obtained, with the access date. Deep links to individual PDFs are deliberately not given: they are unstable, and fabricating a precise document URL that was not actually followed would be worse than citing the page that was. Each annual report is identified by name, year and note reference in the rows above, which is sufficient to locate the exact figure. The price series used for the beta regression was supplied with an adjusted close column, a market data vendor convention rather than the exchange bhavcopy format, and is labelled as vendor sourced on the Beta sheet.

Sheet UTCL-Source Data
A1: Line item (standalone, as published) | B1: Unit | C1: 2016-17 | D1: 2017-18 | E1: 2018-19 R | F1: 2019-20 | G1: 2020-21 | H1: 2021-22 | I1: 2022-23 R | J1: 2023-24 | K1: 2024-25 | L1: 2025-26
A2: Grey cement sales (Mn.T) | B2: Mn.T | C2: 48.87 | D2: 59.33 | E2: 80.78 | F2: 77.46 | G2: 81.25 | H2: 88.02 | I2: 100.06 | J2: 112.81 | K2: 125.81 | L2: 140.75
A3: Revenue including operating income | B3: Rs cr | C3: 23891 | D3: 29358 | E3: 39999 | F3: 40649 | G3: 43188 | H3: 50663 | I3: 61237 | J3: 68641 | K3: 71895 | L3: 82170
A4: Operating expenses | B4: Rs cr | C4: 18922 | D4: 23475 | E4: 32920 | F4: 31997 | G4: 32224 | H4: 39727 | I4: 50952 | J4: 56021 | K4: 59599 | L4: 66730
A5: Operating profit (EBITDA) | B5: Rs cr | C5: 4969 | D5: 5883 | E5: 7079 | F5: 8652 | G5: 10965 | H5: 10936 | I5: 10286 | J5: 12620 | K5: 12296 | L5: 15439
A6: Other income | B6: Rs cr | C6: 660 | D6: 600 | E6: 497 | F6: 727 | G6: 789 | H6: 612 | I6: 505 | J6: 662 | K6: 693 | L6: 376
A7: Depreciation and amortisation | B7: Rs cr | C7: 1268 | D7: 1764 | E7: 2321 | F7: 2455 | G7: 2434 | H7: 2457 | I7: 2773 | J7: 3027 | K7: 3739 | L7: 4055
A8: EBIT | B8: Rs cr | C8: 4361 | D8: 4719 | E8: 5255 | F8: 6924 | G8: 9319 | H8: 9091 | I8: 8018 | J8: 10255 | K8: 9250 | L8: 11761
A9: Interest | B9: Rs cr | C9: 571 | D9: 1191 | E9: 1648 | F9: 1704 | G9: 1259 | H9: 798 | I9: 756 | J9: 867 | K9: 1465 | L9: 1630
A10: Profit before tax | B10: Rs cr | C10: 3790 | D10: 3528 | E10: 3606 | F10: 5220 | G10: 8060 | H10: 8293 | I10: 7262 | J10: 9388 | K10: 7785 | L10: 10131
A11: Exceptional items gain/(loss) | B11: Rs cr | C11: -14 | D11: -226 | E11: -114 | F11: 0 | G11: -164 | H11: 0 | I11: 0 | J11: -72 | K11: -88 | L11: -104
A12: Tax expense | B12: Rs cr | C12: 1148 | D12: 1071 | E12: 1080 | F12: -236 | G12: 2554 | H12: 1227 | I12: 2310 | J12: 2411 | K12: 1504 | L12: 2622
A13: Net profit | B13: Rs cr | C13: 2628 | D13: 2231 | E13: 2412 | F13: 5456 | G13: 5342 | H13: 7067 | I13: 4951 | J13: 6905 | K13: 6193 | L13: 7405
... A24: Capital employed | B24: Rs cr | C24: 32955 | D24: 46517 | E24: 59181 | F24: 61548 | G24: 66886 | H24: 65276 | I24: 69369 | J24: 74531 | K24: 98236 | L24: 103649
A26: Derived
A27: EBITDA margin | C27: =IFERROR(C5/C3,"") -> 0.20798627 | D27: =IFERROR(D5/D3,"") -> 0.20038831 | E27: =IFERROR(E5/E3,"") -> 0.17697942 | F27: =IFERROR(F5/F3,"") -> 0.21284656 | G27: =IFERROR(G5/G3,"") -> 0.25388997 | H27: =IFERROR(H5/H3,"") -> 0.21585773 | I27: =IFERROR(I5/I3,"") -> 0.16797034 | J27: =IFERROR(J5/J3,"") -> 0.18385513 | ... L27: =IFERROR(L5/L3,"") -> 0.18789096
A28: Revenue growth | D28: =IFERROR(D3/C3-1,"") -> 0.22883094 | E28: =IFERROR(E3/D3-1,"") -> 0.36245657 | F28: =IFERROR(F3/E3-1,"") -> 0.016250406 | G28: =IFERROR(G3/F3-1,"") -> 0.062461561 | H28: =IFERROR(H3/G3-1,"") -> 0.17308049 | I28: =IFERROR(I3/H3-1,"") -> 0.20871247 | J28: =IFERROR(J3/I3-1,"") -> 0.12090729 | K28: =IFERROR(K3/J3-1,"") -> 0.047406069 | L28: =IFERROR(L3/K3-1,"") -> 0.14291675
A29: Realisation per tonne (Rs) | C29: =IFERROR(C3*10000000/(C2*1000000),"") -> 4888.6843 | D29: =IFERROR(D3*10000000/(D2*1000000),"") -> 4948.2555 | E29: =IFERROR(E3*10000000/(E2*1000000),"") -> 4951.5969 | F29: =IFERROR(F3*10000000/(F2*1000000),"") -> 5247.7408 | G29: =IFERROR(G3*10000000/(G2*1000000),"") -> 5315.4462 | H29: =IFERROR(H3*10000000/(H2*1000000),"") -> 5755.8509 | I29: =IFERROR(I3*10000000/(I2*1000000),"") -> 6120.028 | J29: =IFERROR(J3*10000000/(J2*1000000),"") -> 6084.6556 | ... L29: =IFERROR(L3*10000000/(L2*1000000),"") -> 5838.0107
A30: Invested capital (NFA + NWC) | C30: =C14+C17 -> 23546 | D30: =D14+D17 -> 40354 | E30: =E14+E17 -> 49969 | F30: =F14+F17 -> 49676 | G30: =G14+G17 -> 46974 | H30: =H14+H17 -> 50986 | I30: =I14+I17 -> 59937 | J30: =J14+J17 -> 65294 | ... L30: =L14+L17 -> 86090
A31: NOPAT (EBIT at statutory tax) | C31: =C8*(1-'UTCL-Assumptions'!$C$4) -> 4361 | D31: =D8*(1-'UTCL-Assumptions'!$C$4) -> 4719 | E31: =E8*(1-'UTCL-Assumptions'!$C$4) -> 5255 | F31: =F8*(1-'UTCL-Assumptions'!$C$4) -> 6924 | G31: =G8*(1-'UTCL-Assumptions'!$C$4) -> 9319 | H31: =H8*(1-'UTCL-Assumptions'!$C$4) -> 9091 | I31: =I8*(1-'UTCL-Assumptions'!$C$4) -> 8018 | J31: =J8*(1-'UTCL-Assumptions'!$C$4) -> 10255 | ... L31: =L8*(1-'UTCL-Assumptions'!$C$4) -> 11761
A32: ROIC on opening invested capital | D32: =IFERROR(D31/C30,"") -> 0.20041621 | E32: =IFERROR(E31/D30,"") -> 0.13022253 | F32: =IFERROR(F31/E30,"") -> 0.13856591 | G32: =IFERROR(G31/F30,"") -> 0.18759562 | H32: =IFERROR(H31/G30,"") -> 0.19353259 | I32: =IFERROR(I31/H30,"") -> 0.15725886 | J32: =IFERROR(J31/I30,"") -> 0.17109632 | K32: =IFERROR(K31/J30,"") -> 0.14166692 | L32: =IFERROR(L31/K30,"") -> 0.14389537
A33: Effective tax rate as reported | C33: =IFERROR(C12/(C10+C11),"") -> 0.30402542 | D33: =IFERROR(D12/(D10+D11),"") -> 0.32434888 | E33: =IFERROR(E12/(E10+E11),"") -> 0.30927835 | F33: =IFERROR(F12/(F10+F11),"") -> -0.045210728 | G33: =IFERROR(G12/(G10+G11),"") -> 0.32345491 | H33: =IFERROR(H12/(H10+H11),"") -> 0.14795611 | I33: =IFERROR(I12/(I10+I11),"") -> 0.31809419 | J33: =IFERROR(J12/(J10+J11),"") -> 0.25880206 | ... L33: =IFERROR(L12/(L10+L11),"") -> 0.26149397
A34: Net debt (loans + leases - liquid inv) | C34: =C21+C22-C16 -> -2423 | D34: =D21+D22-D16 -> 12008 | E34: =E21+E22-E16 -> 17413 | F34: =F21+F22-F16 -> 13293 | G34: =G21+G22-G16 -> 4733 | H34: =H21+H22-H16 -> 4661 | I34: =I21+I22-I16 -> 3457 | J34: =J21+J22-J16 -> 1994 | ... L34: =L21+L22-L16 -> 15462
A36: Source: UltraTech Cement Ltd, Integrated and Sustainability Report 2025-26, Standalone Financial Highlights. Capital employed ties both ways: net worth plus loan funds plus leases plus deferred tax liabilities equals net fixed assets plus investments plus liquid investments plus net working capital, for every one of the ten years. The company's Operating Profit line equals EBITDA excluding other income, which is the definition used throughout this workbook and in the peer comparison.

Sheet UTCL-Entity Build
A1: Entity Build: standalone plus subsidiary holdings
A2: UltraTech Cement Ltd, FY2025-26. The operating business is valued standalone; subsidiaries are added as holdings.
A4: Step 1: standalone operating business, as reported
A5: Line item | B5: Unit | C5: FY2025-26 | E5: Source
A6: Revenue | B6: Rs cr | C6: 82,170 | E6: Ten year standalone financial highlights
A7: EBITDA (Operating Profit) | B7: Rs cr | C7: 15,439 | E7: Same table. Ties exactly to our uniform EBITDA definition.
A8: EBITDA margin | B8: Rs cr | C8: 18.8%
A9: Grey cement sales volume | B9: Rs cr | C9: 140.75 Mn.T
A10: Net fixed assets incl CWIP | B10: Rs cr | C10: 89,161
A11: Net worth | B11: Rs cr | C11: 74,663
A13: Step 2: subsidiary and other holdings, added at the bridge
A14: Holding | B14: Stake | C14: Carrying value | D14: Per UTCL share | E14: Basis
A15: The India Cements Ltd (LISTED) | B15: 74.99% | C15: 8970.17 | D15: =C15/'UTCL-Assumptions'!$B$5 -> 304.40376 | E15: 23,24,16,830 shares, or Rs 385.95 per India Cements share. Disclosed in the non-current investments note.
A16: Other investments in subsidiaries and associates | B16: various | C16: 3570.83 | D16: =C16/'UTCL-Assumptions'!$B$5 -> 121.17653 | E16: Total investments in subsidiaries, associates and others of Rs 12,541 cr less the India Cements carrying value.
A17: Liquid investments | B17: n/a | C17: 5018 | D17: =C17/'UTCL-Assumptions'!$B$5 -> 170.28641 | E17: Ten year table.
A19: Step 3: why UltraTech is NOT valued consolidated
A20: UltraTech does not publish a ten year consolidated history, and its FY2025-26 consolidated statements were not obtained from an authorised source. Consolidated figures exist only in broker research, which our data policy excludes. The standalone series is complete, audited and reconciles both ways in every one of the ten years, so it is the only basis on which a defensible historical analysis can be built. Subsidiaries are therefore added as holdings at carrying value rather than consolidated line by line.
A24: KNOWN INCONSISTENCY WITH THE AMBUJA MODEL, stated openly. UltraTech holds 74.99% of the listed India Cements and is valued STANDALONE with the stake added at book. Ambuja holds 50.05% of the listed ACC and is valued CONSOLIDATED. Two companies in the same structural position are treated differently, and the reason is data availability rather than principle. The irony is that UltraTech's stake is the MORE controlling of the two. Two consequences follow. First, marking India Cements to market instead of book would move the value by about Rs 79 per UltraTech share for every Rs 100 on the India Cements price. Second, if UltraTech consolidated statements are obtained, this tab is where the build up would be completed and the two models made consistent.
A30: Step 4: the equity bridge that results
A31: Enterprise value of standalone operations | C31: ='UTCL-FCFF valuation'!C9 -> 171426.72
A32: Add: liquid investments | C32: 5018
A33: Add: investments in subsidiaries and others | C33: 12541
A34: Less: loan funds | C34: -19617
A35: Less: lease liabilities | C35: -863
A36: Equity value | C36: =SUM(C31:C35) -> 168505.72
A37: Value per share | C37: =C36/'UTCL-Assumptions'!$B$5 -> 5718.261
A40: Step 5: the consolidated position, reconciled and quantified
A41: Line item | B41: Unit | C41: Standalone | D41: Consolidated | E41: Subsidiaries
A42: Revenue from operations | B42: Rs cr | C42: 82169.65 | D42: 88511.53 | E42: =D42-C42 -> 6341.88
A43: Other income | B43: Rs cr | C43: 376.43 | D43: 577.51 | E43: =D43-C43 -> 201.08
A44: Finance costs | B44: Rs cr | C44: 1630 | D44: 1871.71 | E44: =D44-C44 -> 241.71
A45: Depreciation and amortisation | B45: Rs cr | C45: 4055.08 | D45: 4644.46 | E45: =D45-C45 -> 589.38
A46: Profit before exceptional items and tax | B46: Rs cr | C46: 10130.58 | D46: 11081.57 | E46: =D46-C46 -> 950.99
A47: EBITDA (uniform definition) | C47: =C46+C44+C45-C43 -> 15439.23 | D47: =D46+D44+D45-D43 -> 17020.23 | E47: =E46+E44+E45-E43 -> 1581
A48: EBITDA margin | C48: =C47/C42 -> 0.18789456 | D48: =D47/D42 -> 0.19229393 | E48: =E47/E42 -> 0.24929516
A49: Standalone share of group | C49: =C42/D42 -> 0.92834967 | D49: =C47/D47 -> 0.90711054 | E49: revenue / EBITDA
A51: Consolidated goodwill | C51: 7909.05
A52: Consolidated non-controlling interest | C52: 4088.9
A53: Consolidated borrowings and leases | C53: 23755.09
A54: Standalone borrowings and leases | C54: 20480
A56: WHY THIS MATTERS AND WHAT WE DID ABOUT IT. UltraTech DOES publish consolidated statements, on pages 227 to 233 of the integrated report, and an earlier draft of this model wrongly stated that it did not. The consolidated position is set out above so the reader can see exactly what the standalone basis leaves out. Three points. FIRST, the standalone entity is 92.8% of group revenue and 90.7% of group EBITDA, so the omission is far smaller than for Ambuja, where standalone is only 61.6% of revenue. SECOND, consolidated accounts carry Rs 7,909 crore of GOODWILL that the standalone accounts do not, which matters because the Ambuja analysis turns on goodwill; on a consolidated basis goodwill is 8.9% of UltraTech's asset base against 34.2% at Ambuja, so the contrast is one of degree rather than of kind, and the report should say so. THIRD, we nonetheless value UltraTech STANDALONE, because only the standalone series carries the audited ten year history, the disclosed grey cement volume of 140.75 million tonnes and the capacity figures on which the whole capacity times utilisation forecast is built. Rebuilding on a consolidated basis would require consolidated volume and consolidated capital work in progress, neither of which is separately disclosed. The choice is therefore data driven, it is quantified here rather than merely asserted, and the subsidiary block it omits is under 10% of group EBITDA.
A59: CONSISTENCY CHECK: the build must tie to the reported total
A60: Standalone share of group revenue | C60: 0.928
A61: Standalone share of group EBITDA | C61: 0.907
A62: Consolidated less standalone, EBITDA | C62: 1581.23
A64: This is the MRF style tie out. The subsidiary block is derived as consolidated less standalone and reconciles exactly to the reported consolidated figures set out in Step 5. Because standalone is 92.8% of group revenue and 90.7% of group EBITDA, the block this model omits is under 10% of the group, which is the quantitative justification for valuing UltraTech standalone rather than a bare assertion.
A67: SANITY CHECK, CONSOLIDATED VERSUS STANDALONE. A consolidated balance sheet contains the standalone one plus the subsidiaries, so every consolidated line must be at least as large as its standalone counterpart. Operating assets 99,626.77 against 89,161, net worth attributable to owners 76,623.54 against 74,663, borrowings and leases 23,755.09 against 20,480. All three PASS. An earlier draft omitted other intangibles of Rs 9,886.78 crore and intangibles under development of Rs 466.40 crore from the consolidated asset base, failed this test, and broke the equivalence of the five methods by about Rs 1,300 per share: subsidiary EARNINGS had been added without the ASSETS that produce them, so the capital charge in the EVA identity never rose to match the higher NOPAT. THE MODEL IS NOW CONSOLIDATED, which is what Prof. Mohanty's treatment of a holding above 50% requires, UltraTech holding 74.99% of India Cements. Value Rs 5,148.18 against the standalone Rs 5,273.40, a difference of 2.4%, confirming the subsidiary block is small but no longer omitted.

Sheet UTCL-Normalize
A1: Normalisation and reclassification
A3: Item | B3: Unit | C3: As reported | D3: Normalised | E3: Basis and note reference
A4: Capital work in progress | B4: Rs cr | C4: 7871.47 | D4: 0 | E4: Note 02. Excluded from the capital intensity measure because CWIP earns no revenue yet; scaling total fixed assets to current sales would penalise the company for capacity already paid for. Correcting this raised value about 14%.
A5: Exceptional items | B5: Rs cr | C5: 103.79 | D5: 0 | E5: Ten year table. Provision for impairment of investment Rs 23.03 cr plus statutory impact of new labour codes Rs 80.76 cr. Removed from earnings.
A6: Other income | B6: Rs cr | C6: 376.43 | D6: 0 | E6: Excluded from EBITDA under our uniform definition, so cash and investments are non-operating and added back once at the bridge.
A7: Tax rate | B7: % | C7: 0.261 | D7: 0.25168 | E7: Reported effective rate of 26.1% cross checked against the s.115BAA statutory rate of 25.168%. Materially in line, so no migration path is modelled. Statutory used throughout.
A8: India Cements holding | B8: Rs cr | C8: 8970.17 | D8: 8970.17 | E8: Non-current investments note. Carried at BOOK. India Cements is LISTED, so asset consistency would prefer market value. Flagged as an open item; a price cell exists on the Assumptions sheet.
A9: Unlevered beta | B9: x | C9: 0.86 | D9: 0.9 | E9: Damodaran Global January 2026. CASH CORRECTED figure adopted because cash is added back separately at the bridge; the raw 0.86 would count cash twice.

Sheet UTCL-Common Size
A1: Common Size Statements: UltraTech Cement (standalone)
A2: Every figure recomputed from the ten year table on Source-Data. Nothing downloaded.
A4: Line item | B4: 2016-17 | C4: 2017-18 | D4: 2018-19 R | E4: 2019-20 | F4: 2020-21 | G4: 2021-22 | H4: 2022-23 R | I4: 2023-24 | J4: 2024-25 | K4: 2025-26
A5: Income statement, percent of revenue
A6: Operating expenses | B6: ='UTCL-Source Data'!C4/'UTCL-Source Data'!C3 -> 0.79201373 | C6: ='UTCL-Source Data'!D4/'UTCL-Source Data'!D3 -> 0.79961169 | D6: ='UTCL-Source Data'!E4/'UTCL-Source Data'!E3 -> 0.82302058 | E6: ='UTCL-Source Data'!F4/'UTCL-Source Data'!F3 -> 0.78715344 | F6: ='UTCL-Source Data'!G4/'UTCL-Source Data'!G3 -> 0.74613319 | G6: ='UTCL-Source Data'!H4/'UTCL-Source Data'!H3 -> 0.78414227 | H6: ='UTCL-Source Data'!I4/'UTCL-Source Data'!I3 -> 0.83204599 | I6: ='UTCL-Source Data'!J4/'UTCL-Source Data'!J3 -> 0.81614487 | ... K6: ='UTCL-Source Data'!L4/'UTCL-Source Data'!L3 -> 0.81209687
A7: Operating profit (EBITDA) | B7: ='UTCL-Source Data'!C5/'UTCL-Source Data'!C3 -> 0.20798627 | C7: ='UTCL-Source Data'!D5/'UTCL-Source Data'!D3 -> 0.20038831 | D7: ='UTCL-Source Data'!E5/'UTCL-Source Data'!E3 -> 0.17697942 | E7: ='UTCL-Source Data'!F5/'UTCL-Source Data'!F3 -> 0.21284656 | F7: ='UTCL-Source Data'!G5/'UTCL-Source Data'!G3 -> 0.25388997 | G7: ='UTCL-Source Data'!H5/'UTCL-Source Data'!H3 -> 0.21585773 | H7: ='UTCL-Source Data'!I5/'UTCL-Source Data'!I3 -> 0.16797034 | I7: ='UTCL-Source Data'!J5/'UTCL-Source Data'!J3 -> 0.18385513 | ... K7: ='UTCL-Source Data'!L5/'UTCL-Source Data'!L3 -> 0.18789096
A8: Other income | B8: ='UTCL-Source Data'!C6/'UTCL-Source Data'!C3 -> 0.027625466 | C8: ='UTCL-Source Data'!D6/'UTCL-Source Data'!D3 -> 0.020437359 | D8: ='UTCL-Source Data'!E6/'UTCL-Source Data'!E3 -> 0.012425311 | E8: ='UTCL-Source Data'!F6/'UTCL-Source Data'!F3 -> 0.017884819 | F8: ='UTCL-Source Data'!G6/'UTCL-Source Data'!G3 -> 0.018268964 | G8: ='UTCL-Source Data'!H6/'UTCL-Source Data'!H3 -> 0.012079822 | H8: ='UTCL-Source Data'!I6/'UTCL-Source Data'!I3 -> 0.0082466483 | I8: ='UTCL-Source Data'!J6/'UTCL-Source Data'!J3 -> 0.0096443816 | ... K8: ='UTCL-Source Data'!L6/'UTCL-Source Data'!L3 -> 0.0045758793
A9: Depreciation and amortisation | B9: ='UTCL-Source Data'!C7/'UTCL-Source Data'!C3 -> 0.053074379 | C9: ='UTCL-Source Data'!D7/'UTCL-Source Data'!D3 -> 0.060085837 | D9: ='UTCL-Source Data'!E7/'UTCL-Source Data'!E3 -> 0.058026451 | E9: ='UTCL-Source Data'!F7/'UTCL-Source Data'!F3 -> 0.06039509 | F9: ='UTCL-Source Data'!G7/'UTCL-Source Data'!G3 -> 0.056358248 | G9: ='UTCL-Source Data'!H7/'UTCL-Source Data'!H3 -> 0.048496931 | H9: ='UTCL-Source Data'!I7/'UTCL-Source Data'!I3 -> 0.04528308 | I9: ='UTCL-Source Data'!J7/'UTCL-Source Data'!J3 -> 0.044099008 | ... K9: ='UTCL-Source Data'!L7/'UTCL-Source Data'!L3 -> 0.049348911
A10: EBIT | B10: ='UTCL-Source Data'!C8/'UTCL-Source Data'!C3 -> 0.18253736 | C10: ='UTCL-Source Data'!D8/'UTCL-Source Data'!D3 -> 0.16073983 | D10: ='UTCL-Source Data'!E8/'UTCL-Source Data'!E3 -> 0.13137828 | E10: ='UTCL-Source Data'!F8/'UTCL-Source Data'!F3 -> 0.17033629 | F10: ='UTCL-Source Data'!G8/'UTCL-Source Data'!G3 -> 0.21577753 | G10: ='UTCL-Source Data'!H8/'UTCL-Source Data'!H3 -> 0.17944062 | H10: ='UTCL-Source Data'!I8/'UTCL-Source Data'!I3 -> 0.13093391 | I10: ='UTCL-Source Data'!J8/'UTCL-Source Data'!J3 -> 0.1494005 | ... K10: ='UTCL-Source Data'!L8/'UTCL-Source Data'!L3 -> 0.1431301
A11: Interest | B11: ='UTCL-Source Data'!C9/'UTCL-Source Data'!C3 -> 0.023900213 | C11: ='UTCL-Source Data'!D9/'UTCL-Source Data'!D3 -> 0.040568159 | D11: ='UTCL-Source Data'!E9/'UTCL-Source Data'!E3 -> 0.04120103 | E11: ='UTCL-Source Data'!F9/'UTCL-Source Data'!F3 -> 0.04191985 | F11: ='UTCL-Source Data'!G9/'UTCL-Source Data'!G3 -> 0.029151616 | G11: ='UTCL-Source Data'!H9/'UTCL-Source Data'!H3 -> 0.01575114 | H11: ='UTCL-Source Data'!I9/'UTCL-Source Data'!I3 -> 0.012345477 | I11: ='UTCL-Source Data'!J9/'UTCL-Source Data'!J3 -> 0.012630935 | ... K11: ='UTCL-Source Data'!L9/'UTCL-Source Data'!L3 -> 0.019836923
A12: Profit before tax | B12: ='UTCL-Source Data'!C10/'UTCL-Source Data'!C3 -> 0.15863714 | C12: ='UTCL-Source Data'!D10/'UTCL-Source Data'!D3 -> 0.12017167 | D12: ='UTCL-Source Data'!E10/'UTCL-Source Data'!E3 -> 0.090152254 | E12: ='UTCL-Source Data'!F10/'UTCL-Source Data'!F3 -> 0.12841644 | F12: ='UTCL-Source Data'!G10/'UTCL-Source Data'!G3 -> 0.18662591 | G12: ='UTCL-Source Data'!H10/'UTCL-Source Data'!H3 -> 0.16368948 | H12: ='UTCL-Source Data'!I10/'UTCL-Source Data'!I3 -> 0.11858844 | I12: ='UTCL-Source Data'!J10/'UTCL-Source Data'!J3 -> 0.13676957 | ... K12: ='UTCL-Source Data'!L10/'UTCL-Source Data'!L3 -> 0.12329317
A13: Tax expense | B13: ='UTCL-Source Data'!C12/'UTCL-Source Data'!C3 -> 0.048051568 | C13: ='UTCL-Source Data'!D12/'UTCL-Source Data'!D3 -> 0.036480687 | D13: ='UTCL-Source Data'!E12/'UTCL-Source Data'!E3 -> 0.027000675 | E13: ='UTCL-Source Data'!F12/'UTCL-Source Data'!F3 -> -0.0058058009 | F13: ='UTCL-Source Data'!G12/'UTCL-Source Data'!G3 -> 0.059136797 | G13: ='UTCL-Source Data'!H12/'UTCL-Source Data'!H3 -> 0.024218858 | H13: ='UTCL-Source Data'!I12/'UTCL-Source Data'!I3 -> 0.037722292 | I13: ='UTCL-Source Data'!J12/'UTCL-Source Data'!J3 -> 0.03512478 | ... K13: ='UTCL-Source Data'!L12/'UTCL-Source Data'!L3 -> 0.031909456
A14: Net profit | B14: ='UTCL-Source Data'!C13/'UTCL-Source Data'!C3 -> 0.10999958 | C14: ='UTCL-Source Data'!D13/'UTCL-Source Data'!D3 -> 0.075992915 | D14: ='UTCL-Source Data'!E13/'UTCL-Source Data'!E3 -> 0.060301508 | E14: ='UTCL-Source Data'!F13/'UTCL-Source Data'!F3 -> 0.13422224 | F14: ='UTCL-Source Data'!G13/'UTCL-Source Data'!G3 -> 0.12369177 | G14: ='UTCL-Source Data'!H13/'UTCL-Source Data'!H3 -> 0.13949036 | H14: ='UTCL-Source Data'!I13/'UTCL-Source Data'!I3 -> 0.080849813 | I14: ='UTCL-Source Data'!J13/'UTCL-Source Data'!J3 -> 0.10059585 | ... K14: ='UTCL-Source Data'!L13/'UTCL-Source Data'!L3 -> 0.090118048
A16: Capital employed, percent of total
A17: Net fixed assets incl ROU, CWIP | B17: ='UTCL-Source Data'!C14/'UTCL-Source Data'!C24 -> 0.7400091 | C17: ='UTCL-Source Data'!D14/'UTCL-Source Data'!D24 -> 0.87671174 | D17: ='UTCL-Source Data'!E14/'UTCL-Source Data'!E24 -> 0.83756611 | E17: ='UTCL-Source Data'!F14/'UTCL-Source Data'!F24 -> 0.80402288 | F17: ='UTCL-Source Data'!G14/'UTCL-Source Data'!G24 -> 0.7347427 | G17: ='UTCL-Source Data'!H14/'UTCL-Source Data'!H24 -> 0.80587046 | H17: ='UTCL-Source Data'!I14/'UTCL-Source Data'!I24 -> 0.90929666 | I17: ='UTCL-Source Data'!J14/'UTCL-Source Data'!J24 -> 0.93072681 | ... K17: ='UTCL-Source Data'!L14/'UTCL-Source Data'!L24 -> 0.86022055
A18: Investments in subsidiaries and others | B18: ='UTCL-Source Data'!C15/'UTCL-Source Data'!C24 -> 0.022636929 | C18: ='UTCL-Source Data'!D15/'UTCL-Source Data'!D24 -> 0.016144635 | D18: ='UTCL-Source Data'!E15/'UTCL-Source Data'!E24 -> 0.10118112 | E18: ='UTCL-Source Data'!F15/'UTCL-Source Data'!F24 -> 0.097322415 | F18: ='UTCL-Source Data'!G15/'UTCL-Source Data'!G24 -> 0.094638639 | G18: ='UTCL-Source Data'!H15/'UTCL-Source Data'!H24 -> 0.12526809 | H18: ='UTCL-Source Data'!I15/'UTCL-Source Data'!I24 -> 0.045942712 | I18: ='UTCL-Source Data'!J15/'UTCL-Source Data'!J24 -> 0.029799681 | ... K18: ='UTCL-Source Data'!L15/'UTCL-Source Data'!L24 -> 0.1209949
A19: Liquid investments | B19: ='UTCL-Source Data'!C16/'UTCL-Source Data'!C24 -> 0.26287362 | C19: ='UTCL-Source Data'!D16/'UTCL-Source Data'!D24 -> 0.11634456 | D19: ='UTCL-Source Data'!E16/'UTCL-Source Data'!E24 -> 0.054476944 | E19: ='UTCL-Source Data'!F16/'UTCL-Source Data'!F24 -> 0.095567687 | F19: ='UTCL-Source Data'!G16/'UTCL-Source Data'!G24 -> 0.20306193 | G19: ='UTCL-Source Data'!H16/'UTCL-Source Data'!H24 -> 0.093679147 | H19: ='UTCL-Source Data'!I16/'UTCL-Source Data'!I24 -> 0.09004022 | I19: ='UTCL-Source Data'!J16/'UTCL-Source Data'!J24 -> 0.094135326 | ... K19: ='UTCL-Source Data'!L16/'UTCL-Source Data'!L24 -> 0.048413395
A20: Net working capital | B20: ='UTCL-Source Data'!C17/'UTCL-Source Data'!C24 -> -0.025519648 | C20: ='UTCL-Source Data'!D17/'UTCL-Source Data'!D24 -> -0.0092009373 | D20: ='UTCL-Source Data'!E17/'UTCL-Source Data'!E24 -> 0.0067758233 | E20: ='UTCL-Source Data'!F17/'UTCL-Source Data'!F24 -> 0.0030870215 | F20: ='UTCL-Source Data'!G17/'UTCL-Source Data'!G24 -> -0.032443262 | G20: ='UTCL-Source Data'!H17/'UTCL-Source Data'!H24 -> -0.024787058 | H20: ='UTCL-Source Data'!I17/'UTCL-Source Data'!I24 -> -0.045265176 | I20: ='UTCL-Source Data'!J17/'UTCL-Source Data'!J24 -> -0.054661819 | ... K20: ='UTCL-Source Data'!L17/'UTCL-Source Data'!L24 -> -0.029628844
A21: Net worth | B21: ='UTCL-Source Data'!C20/'UTCL-Source Data'!C24 -> 0.7264755 | C21: ='UTCL-Source Data'!D20/'UTCL-Source Data'!D24 -> 0.55728013 | D21: ='UTCL-Source Data'!E20/'UTCL-Source Data'!E24 -> 0.5626299 | E21: ='UTCL-Source Data'!F20/'UTCL-Source Data'!F24 -> 0.62221356 | F21: ='UTCL-Source Data'!G20/'UTCL-Source Data'!G24 -> 0.64816255 | G21: ='UTCL-Source Data'!H20/'UTCL-Source Data'!H24 -> 0.75481034 | H21: ='UTCL-Source Data'!I20/'UTCL-Source Data'!I24 -> 0.76991163 | I21: ='UTCL-Source Data'!J20/'UTCL-Source Data'!J24 -> 0.79289155 | ... K21: ='UTCL-Source Data'!L20/'UTCL-Source Data'!L24 -> 0.72034462
A22: Loan funds | B22: ='UTCL-Source Data'!C21/'UTCL-Source Data'!C24 -> 0.18934911 | C22: ='UTCL-Source Data'!D21/'UTCL-Source Data'!D24 -> 0.37448675 | D22: ='UTCL-Source Data'!E21/'UTCL-Source Data'!E24 -> 0.34870989 | E22: ='UTCL-Source Data'!F21/'UTCL-Source Data'!F24 -> 0.29703646 | F22: ='UTCL-Source Data'!G21/'UTCL-Source Data'!G24 -> 0.25893311 | G22: ='UTCL-Source Data'!H21/'UTCL-Source Data'!H24 -> 0.15152583 | H22: ='UTCL-Source Data'!I21/'UTCL-Source Data'!I24 -> 0.12613704 | I22: ='UTCL-Source Data'!J21/'UTCL-Source Data'!J24 -> 0.10850519 | ... K22: ='UTCL-Source Data'!L21/'UTCL-Source Data'!L24 -> 0.18926377
A23: Lease liabilities | B23: ='UTCL-Source Data'!C22/'UTCL-Source Data'!C24 -> 0 | C23: ='UTCL-Source Data'!D22/'UTCL-Source Data'!D24 -> 0 | D23: ='UTCL-Source Data'!E22/'UTCL-Source Data'!E24 -> 0 | E23: ='UTCL-Source Data'!F22/'UTCL-Source Data'!F24 -> 0.014509001 | F23: ='UTCL-Source Data'!G22/'UTCL-Source Data'!G24 -> 0.014891009 | G23: ='UTCL-Source Data'!H22/'UTCL-Source Data'!H24 -> 0.013557816 | H23: ='UTCL-Source Data'!I22/'UTCL-Source Data'!I24 -> 0.013738125 | I23: ='UTCL-Source Data'!J22/'UTCL-Source Data'!J24 -> 0.012384109 | ... K23: ='UTCL-Source Data'!L22/'UTCL-Source Data'!L24 -> 0.0083261778
A24: Deferred tax liabilities | B24: ='UTCL-Source Data'!C23/'UTCL-Source Data'!C24 -> 0.084175391 | C24: ='UTCL-Source Data'!D23/'UTCL-Source Data'!D24 -> 0.068233119 | D24: ='UTCL-Source Data'!E23/'UTCL-Source Data'!E24 -> 0.088660212 | E24: ='UTCL-Source Data'!F23/'UTCL-Source Data'!F24 -> 0.066240983 | F24: ='UTCL-Source Data'!G23/'UTCL-Source Data'!G24 -> 0.078028287 | G24: ='UTCL-Source Data'!H23/'UTCL-Source Data'!H24 -> 0.080121331 | H24: ='UTCL-Source Data'!I23/'UTCL-Source Data'!I24 -> 0.090213208 | I24: ='UTCL-Source Data'!J23/'UTCL-Source Data'!J24 -> 0.08620574 | ... K24: ='UTCL-Source Data'!L23/'UTCL-Source Data'!L24 -> 0.082065432
A26: What to read here. The operating profit line is the story: 20.8% of revenue in FY2016-17, peaking at 25.4% in FY2020-21, and 18.8% in FY2025-26. Margin has compressed by roughly 650 basis points from the peak even as revenue more than tripled. On the capital side, net fixed assets have stayed near 86% of capital employed while net worth has risen from 73% to 72% and loan funds have swung from 19% to 26% and back. The company has grown by adding assets rather than by improving what it earns on them, which is the same conclusion the ROIC series reaches from the other direction.

Sheet UTCL-Ratios
A1: Ratio Analysis: UltraTech Cement (standalone)
A2: Computed from Source-Data. Returns use the statutory tax rate, never the reported effective rate.
A4: Ratio | B4: 2016-17 | C4: 2017-18 | D4: 2018-19 R | E4: 2019-20 | F4: 2020-21 | G4: 2021-22 | H4: 2022-23 R | I4: 2023-24 | J4: 2024-25 | K4: 2025-26
A5: Profitability
A6: EBITDA margin | B6: ='UTCL-Source Data'!C5/'UTCL-Source Data'!C3 -> 0.20798627 | C6: ='UTCL-Source Data'!D5/'UTCL-Source Data'!D3 -> 0.20038831 | D6: ='UTCL-Source Data'!E5/'UTCL-Source Data'!E3 -> 0.17697942 | E6: ='UTCL-Source Data'!F5/'UTCL-Source Data'!F3 -> 0.21284656 | F6: ='UTCL-Source Data'!G5/'UTCL-Source Data'!G3 -> 0.25388997 | G6: ='UTCL-Source Data'!H5/'UTCL-Source Data'!H3 -> 0.21585773 | H6: ='UTCL-Source Data'!I5/'UTCL-Source Data'!I3 -> 0.16797034 | I6: ='UTCL-Source Data'!J5/'UTCL-Source Data'!J3 -> 0.18385513 | ... K6: ='UTCL-Source Data'!L5/'UTCL-Source Data'!L3 -> 0.18789096
A7: EBIT margin | B7: ='UTCL-Source Data'!C8/'UTCL-Source Data'!C3 -> 0.18253736 | C7: ='UTCL-Source Data'!D8/'UTCL-Source Data'!D3 -> 0.16073983 | D7: ='UTCL-Source Data'!E8/'UTCL-Source Data'!E3 -> 0.13137828 | E7: ='UTCL-Source Data'!F8/'UTCL-Source Data'!F3 -> 0.17033629 | F7: ='UTCL-Source Data'!G8/'UTCL-Source Data'!G3 -> 0.21577753 | G7: ='UTCL-Source Data'!H8/'UTCL-Source Data'!H3 -> 0.17944062 | H7: ='UTCL-Source Data'!I8/'UTCL-Source Data'!I3 -> 0.13093391 | I7: ='UTCL-Source Data'!J8/'UTCL-Source Data'!J3 -> 0.1494005 | ... K7: ='UTCL-Source Data'!L8/'UTCL-Source Data'!L3 -> 0.1431301
A8: Net profit margin | B8: ='UTCL-Source Data'!C13/'UTCL-Source Data'!C3 -> 0.10999958 | C8: ='UTCL-Source Data'!D13/'UTCL-Source Data'!D3 -> 0.075992915 | D8: ='UTCL-Source Data'!E13/'UTCL-Source Data'!E3 -> 0.060301508 | E8: ='UTCL-Source Data'!F13/'UTCL-Source Data'!F3 -> 0.13422224 | F8: ='UTCL-Source Data'!G13/'UTCL-Source Data'!G3 -> 0.12369177 | G8: ='UTCL-Source Data'!H13/'UTCL-Source Data'!H3 -> 0.13949036 | H8: ='UTCL-Source Data'!I13/'UTCL-Source Data'!I3 -> 0.080849813 | I8: ='UTCL-Source Data'!J13/'UTCL-Source Data'!J3 -> 0.10059585 | ... K8: ='UTCL-Source Data'!L13/'UTCL-Source Data'!L3 -> 0.090118048
A9: Return on equity (reported) | B9: ='UTCL-Source Data'!C13/'UTCL-Source Data'!C20 -> 0.10976985 | C9: ='UTCL-Source Data'!D13/'UTCL-Source Data'!D20 -> 0.08606257 | D9: ='UTCL-Source Data'!E13/'UTCL-Source Data'!E20 -> 0.072438958 | E9: ='UTCL-Source Data'!F13/'UTCL-Source Data'!F20 -> 0.14246919 | F9: ='UTCL-Source Data'!G13/'UTCL-Source Data'!G20 -> 0.123221 | G9: ='UTCL-Source Data'!H13/'UTCL-Source Data'!H20 -> 0.14343123 | H9: ='UTCL-Source Data'!I13/'UTCL-Source Data'!I20 -> 0.092701468 | I9: ='UTCL-Source Data'!J13/'UTCL-Source Data'!J20 -> 0.11684576 | ... K9: ='UTCL-Source Data'!L13/'UTCL-Source Data'!L20 -> 0.099178978
A10: Return on capital employed (EBIT) | B10: ='UTCL-Source Data'!C8/'UTCL-Source Data'!C24 -> 0.13233197 | C10: ='UTCL-Source Data'!D8/'UTCL-Source Data'!D24 -> 0.10144678 | D10: ='UTCL-Source Data'!E8/'UTCL-Source Data'!E24 -> 0.08879539 | E10: ='UTCL-Source Data'!F8/'UTCL-Source Data'!F24 -> 0.11249756 | F10: ='UTCL-Source Data'!G8/'UTCL-Source Data'!G24 -> 0.13932662 | G10: ='UTCL-Source Data'!H8/'UTCL-Source Data'!H24 -> 0.13927018 | H10: ='UTCL-Source Data'!I8/'UTCL-Source Data'!I24 -> 0.11558477 | I10: ='UTCL-Source Data'!J8/'UTCL-Source Data'!J24 -> 0.13759375 | ... K10: ='UTCL-Source Data'!L8/'UTCL-Source Data'!L24 -> 0.1134695
A11: ROIC on opening invested capital | C11: ='UTCL-Source Data'!D8*(1-'UTCL-Assumptions'!$B$4)/('UTCL-Source Data'!C14+'UTCL-Source Data'!C17) -> 0.14997546 | D11: ='UTCL-Source Data'!E8*(1-'UTCL-Assumptions'!$B$4)/('UTCL-Source Data'!D14+'UTCL-Source Data'!D17) -> 0.097448124 | E11: ='UTCL-Source Data'!F8*(1-'UTCL-Assumptions'!$B$4)/('UTCL-Source Data'!E14+'UTCL-Source Data'!E17) -> 0.10369164 | F11: ='UTCL-Source Data'!G8*(1-'UTCL-Assumptions'!$B$4)/('UTCL-Source Data'!F14+'UTCL-Source Data'!F17) -> 0.14038155 | G11: ='UTCL-Source Data'!H8*(1-'UTCL-Assumptions'!$B$4)/('UTCL-Source Data'!G14+'UTCL-Source Data'!G17) -> 0.14482431 | H11: ='UTCL-Source Data'!I8*(1-'UTCL-Assumptions'!$B$4)/('UTCL-Source Data'!H14+'UTCL-Source Data'!H17) -> 0.11767995 | I11: ='UTCL-Source Data'!J8*(1-'UTCL-Assumptions'!$B$4)/('UTCL-Source Data'!I14+'UTCL-Source Data'!I17) -> 0.1280348 | J11: ='UTCL-Source Data'!K8*(1-'UTCL-Assumptions'!$B$4)/('UTCL-Source Data'!J14+'UTCL-Source Data'!J17) -> 0.10601219 | K11: ='UTCL-Source Data'!L8*(1-'UTCL-Assumptions'!$B$4)/('UTCL-Source Data'!K14+'UTCL-Source Data'!K17) -> 0.10767978
A13: Per tonne economics
A14: Realisation per tonne (Rs) | B14: ='UTCL-Source Data'!C3*10/'UTCL-Source Data'!C2 -> 4888.6843 | C14: ='UTCL-Source Data'!D3*10/'UTCL-Source Data'!D2 -> 4948.2555 | D14: ='UTCL-Source Data'!E3*10/'UTCL-Source Data'!E2 -> 4951.5969 | E14: ='UTCL-Source Data'!F3*10/'UTCL-Source Data'!F2 -> 5247.7408 | F14: ='UTCL-Source Data'!G3*10/'UTCL-Source Data'!G2 -> 5315.4462 | G14: ='UTCL-Source Data'!H3*10/'UTCL-Source Data'!H2 -> 5755.8509 | H14: ='UTCL-Source Data'!I3*10/'UTCL-Source Data'!I2 -> 6120.028 | I14: ='UTCL-Source Data'!J3*10/'UTCL-Source Data'!J2 -> 6084.6556 | ... K14: ='UTCL-Source Data'!L3*10/'UTCL-Source Data'!L2 -> 5838.0107
A15: EBITDA per tonne (Rs) | B15: ='UTCL-Source Data'!C5*10/'UTCL-Source Data'!C2 -> 1016.7792 | C15: ='UTCL-Source Data'!D5*10/'UTCL-Source Data'!D2 -> 991.57256 | D15: ='UTCL-Source Data'!E5*10/'UTCL-Source Data'!E2 -> 876.33077 | E15: ='UTCL-Source Data'!F5*10/'UTCL-Source Data'!F2 -> 1116.9636 | F15: ='UTCL-Source Data'!G5*10/'UTCL-Source Data'!G2 -> 1349.5385 | G15: ='UTCL-Source Data'!H5*10/'UTCL-Source Data'!H2 -> 1242.4449 | H15: ='UTCL-Source Data'!I5*10/'UTCL-Source Data'!I2 -> 1027.9832 | I15: ='UTCL-Source Data'!J5*10/'UTCL-Source Data'!J2 -> 1118.6952 | ... K15: ='UTCL-Source Data'!L5*10/'UTCL-Source Data'!L2 -> 1096.9094
A16: Operating cost per tonne (Rs) | B16: ='UTCL-Source Data'!C4*10/'UTCL-Source Data'!C2 -> 3871.9051 | C16: ='UTCL-Source Data'!D4*10/'UTCL-Source Data'!D2 -> 3956.683 | D16: ='UTCL-Source Data'!E4*10/'UTCL-Source Data'!E2 -> 4075.2662 | E16: ='UTCL-Source Data'!F4*10/'UTCL-Source Data'!F2 -> 4130.7772 | F16: ='UTCL-Source Data'!G4*10/'UTCL-Source Data'!G2 -> 3966.0308 | G16: ='UTCL-Source Data'!H4*10/'UTCL-Source Data'!H2 -> 4513.406 | H16: ='UTCL-Source Data'!I4*10/'UTCL-Source Data'!I2 -> 5092.1447 | I16: ='UTCL-Source Data'!J4*10/'UTCL-Source Data'!J2 -> 4965.9605 | ... K16: ='UTCL-Source Data'!L4*10/'UTCL-Source Data'!L2 -> 4741.0302
A17: Sales volume (Mn.T) | B17: ='UTCL-Source Data'!C2 -> 48.87 | C17: ='UTCL-Source Data'!D2 -> 59.33 | D17: ='UTCL-Source Data'!E2 -> 80.78 | E17: ='UTCL-Source Data'!F2 -> 77.46 | F17: ='UTCL-Source Data'!G2 -> 81.25 | G17: ='UTCL-Source Data'!H2 -> 88.02 | H17: ='UTCL-Source Data'!I2 -> 100.06 | I17: ='UTCL-Source Data'!J2 -> 112.81 | ... K17: ='UTCL-Source Data'!L2 -> 140.75
A19: Efficiency
A20: Revenue to net fixed assets | B20: ='UTCL-Source Data'!C3/'UTCL-Source Data'!C14 -> 0.97966129 | C20: ='UTCL-Source Data'!D3/'UTCL-Source Data'!D14 -> 0.71987642 | D20: ='UTCL-Source Data'!E3/'UTCL-Source Data'!E14 -> 0.80695207 | E20: ='UTCL-Source Data'!F3/'UTCL-Source Data'!F14 -> 0.82142424 | F20: ='UTCL-Source Data'!G3/'UTCL-Source Data'!G14 -> 0.87880514 | G20: ='UTCL-Source Data'!H3/'UTCL-Source Data'!H14 -> 0.96310167 | H20: ='UTCL-Source Data'!I3/'UTCL-Source Data'!I14 -> 0.9708293 | I20: ='UTCL-Source Data'!J3/'UTCL-Source Data'!J14 -> 0.98951966 | ... K20: ='UTCL-Source Data'!L3/'UTCL-Source Data'!L14 -> 0.92159128
A21: Net working capital, percent of revenue | B21: ='UTCL-Source Data'!C17/'UTCL-Source Data'!C3 -> -0.03520154 | C21: ='UTCL-Source Data'!D17/'UTCL-Source Data'!D3 -> -0.01457865 | D21: ='UTCL-Source Data'!E17/'UTCL-Source Data'!E3 -> 0.010025251 | E21: ='UTCL-Source Data'!F17/'UTCL-Source Data'!F3 -> 0.0046741617 | F21: ='UTCL-Source Data'!G17/'UTCL-Source Data'!G3 -> -0.050245439 | G21: ='UTCL-Source Data'!H17/'UTCL-Source Data'!H3 -> -0.031936522 | H21: ='UTCL-Source Data'!I17/'UTCL-Source Data'!I3 -> -0.051276189 | I21: ='UTCL-Source Data'!J17/'UTCL-Source Data'!J3 -> -0.059352282 | ... K21: ='UTCL-Source Data'!L17/'UTCL-Source Data'!L3 -> -0.037373737
A22: Capital employed per tonne (Rs) | B22: ='UTCL-Source Data'!C24*10/'UTCL-Source Data'!C2 -> 6743.4009 | C22: ='UTCL-Source Data'!D24*10/'UTCL-Source Data'!D2 -> 7840.3843 | D22: ='UTCL-Source Data'!E24*10/'UTCL-Source Data'!E2 -> 7326.1946 | E22: ='UTCL-Source Data'!F24*10/'UTCL-Source Data'!F2 -> 7945.7785 | F22: ='UTCL-Source Data'!G24*10/'UTCL-Source Data'!G2 -> 8232.1231 | G22: ='UTCL-Source Data'!H24*10/'UTCL-Source Data'!H2 -> 7416.0418 | H22: ='UTCL-Source Data'!I24*10/'UTCL-Source Data'!I2 -> 6932.7404 | I22: ='UTCL-Source Data'!J24*10/'UTCL-Source Data'!J2 -> 6606.7724 | ... K22: ='UTCL-Source Data'!L24*10/'UTCL-Source Data'!L2 -> 7364.0497
A24: Leverage and coverage
A25: Debt to equity | B25: =('UTCL-Source Data'!C21+'UTCL-Source Data'!C22)/'UTCL-Source Data'!C20 -> 0.26064074 | C25: =('UTCL-Source Data'!D21+'UTCL-Source Data'!D22)/'UTCL-Source Data'!D20 -> 0.67199012 | D25: =('UTCL-Source Data'!E21+'UTCL-Source Data'!E22)/'UTCL-Source Data'!E20 -> 0.61978557 | E25: =('UTCL-Source Data'!F21+'UTCL-Source Data'!F22)/'UTCL-Source Data'!F20 -> 0.50070503 | F25: =('UTCL-Source Data'!G21+'UTCL-Source Data'!G22)/'UTCL-Source Data'!G20 -> 0.42246211 | G25: =('UTCL-Source Data'!H21+'UTCL-Source Data'!H22)/'UTCL-Source Data'!H20 -> 0.21870877 | H25: =('UTCL-Source Data'!I21+'UTCL-Source Data'!I22)/'UTCL-Source Data'!I20 -> 0.1816769 | I25: =('UTCL-Source Data'!J21+'UTCL-Source Data'!J22)/'UTCL-Source Data'!J20 -> 0.15246637 | ... K25: =('UTCL-Source Data'!L21+'UTCL-Source Data'!L22)/'UTCL-Source Data'!L20 -> 0.27429918
A26: Net debt to EBITDA | B26: =('UTCL-Source Data'!C21+'UTCL-Source Data'!C22-'UTCL-Source Data'!C16)/'UTCL-Source Data'!C5 -> -0.48762326 | C26: =('UTCL-Source Data'!D21+'UTCL-Source Data'!D22-'UTCL-Source Data'!D16)/'UTCL-Source Data'!D5 -> 2.0411355 | D26: =('UTCL-Source Data'!E21+'UTCL-Source Data'!E22-'UTCL-Source Data'!E16)/'UTCL-Source Data'!E5 -> 2.4598107 | E26: =('UTCL-Source Data'!F21+'UTCL-Source Data'!F22-'UTCL-Source Data'!F16)/'UTCL-Source Data'!F5 -> 1.5364078 | F26: =('UTCL-Source Data'!G21+'UTCL-Source Data'!G22-'UTCL-Source Data'!G16)/'UTCL-Source Data'!G5 -> 0.43164615 | G26: =('UTCL-Source Data'!H21+'UTCL-Source Data'!H22-'UTCL-Source Data'!H16)/'UTCL-Source Data'!H5 -> 0.42620702 | H26: =('UTCL-Source Data'!I21+'UTCL-Source Data'!I22-'UTCL-Source Data'!I16)/'UTCL-Source Data'!I5 -> 0.33608789 | I26: =('UTCL-Source Data'!J21+'UTCL-Source Data'!J22-'UTCL-Source Data'!J16)/'UTCL-Source Data'!J5 -> 0.15800317 | ... K26: =('UTCL-Source Data'!L21+'UTCL-Source Data'!L22-'UTCL-Source Data'!L16)/'UTCL-Source Data'!L5 -> 1.0014897
A27: Interest coverage (EBIT / interest) | B27: ='UTCL-Source Data'!C8/'UTCL-Source Data'!C9 -> 7.6374781 | C27: ='UTCL-Source Data'!D8/'UTCL-Source Data'!D9 -> 3.9622166 | D27: ='UTCL-Source Data'!E8/'UTCL-Source Data'!E9 -> 3.1887136 | E27: ='UTCL-Source Data'!F8/'UTCL-Source Data'!F9 -> 4.0633803 | F27: ='UTCL-Source Data'!G8/'UTCL-Source Data'!G9 -> 7.4019063 | G27: ='UTCL-Source Data'!H8/'UTCL-Source Data'!H9 -> 11.392231 | H27: ='UTCL-Source Data'!I8/'UTCL-Source Data'!I9 -> 10.60582 | I27: ='UTCL-Source Data'!J8/'UTCL-Source Data'!J9 -> 11.828143 | ... K27: ='UTCL-Source Data'!L8/'UTCL-Source Data'!L9 -> 7.2153374
A29: Growth
A30: Revenue growth | C30: ='UTCL-Source Data'!D3/'UTCL-Source Data'!C3-1 -> 0.22883094 | D30: ='UTCL-Source Data'!E3/'UTCL-Source Data'!D3-1 -> 0.36245657 | E30: ='UTCL-Source Data'!F3/'UTCL-Source Data'!E3-1 -> 0.016250406 | F30: ='UTCL-Source Data'!G3/'UTCL-Source Data'!F3-1 -> 0.062461561 | G30: ='UTCL-Source Data'!H3/'UTCL-Source Data'!G3-1 -> 0.17308049 | H30: ='UTCL-Source Data'!I3/'UTCL-Source Data'!H3-1 -> 0.20871247 | I30: ='UTCL-Source Data'!J3/'UTCL-Source Data'!I3-1 -> 0.12090729 | J30: ='UTCL-Source Data'!K3/'UTCL-Source Data'!J3-1 -> 0.047406069 | K30: ='UTCL-Source Data'!L3/'UTCL-Source Data'!K3-1 -> 0.14291675
A31: Volume growth | C31: ='UTCL-Source Data'!D2/'UTCL-Source Data'!C2-1 -> 0.21403724 | D31: ='UTCL-Source Data'!E2/'UTCL-Source Data'!D2-1 -> 0.36153717 | E31: ='UTCL-Source Data'!F2/'UTCL-Source Data'!E2-1 -> -0.041099282 | F31: ='UTCL-Source Data'!G2/'UTCL-Source Data'!F2-1 -> 0.048928479 | G31: ='UTCL-Source Data'!H2/'UTCL-Source Data'!G2-1 -> 0.083323077 | H31: ='UTCL-Source Data'!I2/'UTCL-Source Data'!H2-1 -> 0.13678709 | I31: ='UTCL-Source Data'!J2/'UTCL-Source Data'!I2-1 -> 0.12742355 | J31: ='UTCL-Source Data'!K2/'UTCL-Source Data'!J2-1 -> 0.11523801 | K31: ='UTCL-Source Data'!L2/'UTCL-Source Data'!K2-1 -> 0.1187505
A32: Realisation growth | C32: =('UTCL-Source Data'!D3/'UTCL-Source Data'!D2)/('UTCL-Source Data'!C3/'UTCL-Source Data'!C2)-1 -> 0.01218554 | D32: =('UTCL-Source Data'!E3/'UTCL-Source Data'!E2)/('UTCL-Source Data'!D3/'UTCL-Source Data'!D2)-1 -> 0.00067527029 | E32: =('UTCL-Source Data'!F3/'UTCL-Source Data'!F2)/('UTCL-Source Data'!E3/'UTCL-Source Data'!E2)-1 -> 0.059807744 | F32: =('UTCL-Source Data'!G3/'UTCL-Source Data'!G2)/('UTCL-Source Data'!F3/'UTCL-Source Data'!F2)-1 -> 0.012901816 | G32: =('UTCL-Source Data'!H3/'UTCL-Source Data'!H2)/('UTCL-Source Data'!G3/'UTCL-Source Data'!G2)-1 -> 0.082853777 | H32: =('UTCL-Source Data'!I3/'UTCL-Source Data'!I2)/('UTCL-Source Data'!H3/'UTCL-Source Data'!H2)-1 -> 0.063270756 | I32: =('UTCL-Source Data'!J3/'UTCL-Source Data'!J2)/('UTCL-Source Data'!I3/'UTCL-Source Data'!I2)-1 -> -0.0057797722 | J32: =('UTCL-Source Data'!K3/'UTCL-Source Data'!K2)/('UTCL-Source Data'!J3/'UTCL-Source Data'!J2)-1 -> -0.060822839 | K32: =('UTCL-Source Data'!L3/'UTCL-Source Data'!L2)/('UTCL-Source Data'!K3/'UTCL-Source Data'!K2)-1 -> 0.021601114
A33: EBITDA growth | C33: ='UTCL-Source Data'!D5/'UTCL-Source Data'!C5-1 -> 0.18394043 | D33: ='UTCL-Source Data'!E5/'UTCL-Source Data'!D5-1 -> 0.20329764 | E33: ='UTCL-Source Data'!F5/'UTCL-Source Data'!E5-1 -> 0.22220653 | F33: ='UTCL-Source Data'!G5/'UTCL-Source Data'!F5-1 -> 0.26733703 | G33: ='UTCL-Source Data'!H5/'UTCL-Source Data'!G5-1 -> -0.0026447788 | H33: ='UTCL-Source Data'!I5/'UTCL-Source Data'!H5-1 -> -0.059436723 | I33: ='UTCL-Source Data'!J5/'UTCL-Source Data'!I5-1 -> 0.22691036 | J33: ='UTCL-Source Data'!K5/'UTCL-Source Data'!J5-1 -> -0.025673534 | K33: ='UTCL-Source Data'!L5/'UTCL-Source Data'!K5-1 -> 0.25561158
A35: The three rows that matter most sit in the Growth block. Over nine years volume compounded at 12.5% while realisation managed 2.0%. UltraTech buys growth with capital rather than earning it through price. The ROIC row confirms it from the other side: 14.5% in FY2021-22 down to 10.8% in FY2025-26, against a cost of capital of about 11%. Note also that FY2018-19 and FY2022-23 are marked Restated in the company's own table, so year on year growth across those boundaries is not strictly like for like.

Sheet UTCL-Assumptions
A1: Assumptions
A3: Tax and market data
A4: Statutory tax rate | B4: 0.25168 | G4: Section 115BAA: 22% plus 10% surcharge plus 4% cess.
A5: Shares outstanding (crore) | B5: 29.468 | G5: Paid up capital Rs 294.68 cr at Rs 10 face value.
A6: Market price per share (30-Mar-2026) | B6: 10745 | G6: NSE close on the last trading day of FY2025-26. 31 March was not a trading day.
A7: Market capitalisation | B7: 316633 | G7: Disclosed in the FY2025-26 report: NSE Rs 3,16,633 cr.
A9: Cost of capital inputs
A10: Indian 10 year G-Sec yield | B10: 0.0685 | G10: SOURCED AND DATE MATCHED. FBIL 10-Year G-Sec Par Yield, week ended 20 March 2026, from the RBI Ratios and Rates release dated 27 March 2026. This is the last weekly print before the 31 March 2026 valuation date, so the risk free rate, the market capitalisation and the balance sheet are all struck on the same window. Nearby prints for context: 6.74% on 13 March, 6.76% on 6 March, 6.71% on 27 February, and 6.65% a year earlier in March 2025.
A11: India sovereign default spread | B11: 0.0187 | G11: Damodaran, Country Default Spreads and Risk Premiums, January 2026. India rated Baa3.
A12: Risk free rate (rupee, default free) | B12: =B10-B11 -> 0.0498 | G12: The G-Sec is not default free because India is rated Baa3. Stripping the default spread is required if the ERP below already contains a country risk premium. Do not do both or neither.
A13: India equity risk premium | B13: 0.0708 | G13: Damodaran, January 2026: mature market 4.23% plus India country risk premium 2.85%. His CDS based alternative is 5.23%.
A14: Unlevered beta, Building Materials | B14: 0.9 | G14: Damodaran Betas by Sector (Global), January 2026: 469 firms, unlevered beta corrected for cash. The cash corrected figure is used because this model adds cash and investments back separately as non operating assets.
A15: Market debt to equity | B15: 0.064681 | G15: Debt of 20,480 over market capitalisation of 316,633.
A16: Levered beta (bottom up) | B16: =B14*(1+(1-B4)*B15) -> 0.94356188 | G16: Hamada relevering at the marginal tax rate.
A17: Pre tax cost of debt | B17: 0.0834 | G17: Derived: FY26 interest of 1,630 over average loan funds of 19,538.
A19: Forecast drivers, FY2026-27 to FY2030-31
A20: Driver | B20: FY27 | C20: FY28 | D20: FY29 | E20: FY30 | F20: FY31
A21: Grey cement capacity (Mn.T) | B21: 186 | C21: 195 | D21: 205 | E21: 213 | F21: 220 | G21: Announced expansion, standalone share. Management guides consolidated capacity of 218 mtpa by FY27 and 240 to 245 mtpa by FY29, of which the 22.8 mtpa FY28 phase (18 North, 4.8 West) is largely brownfield and sits in the standalone entity.
A22: Capacity utilisation | B22: 0.82 | C22: 0.835 | D22: 0.845 | E22: 0.855 | F22: 0.86 | G22: FY26 standalone utilisation is about 81.6%. Management reported roughly 71% consolidated in H1 FY26, a seasonally weak half. Spare capacity means near term volume growth is largely free of new capex.
A23: EBITDA per tonne growth | B23: 0.08 | C23: 0.06 | D23: 0.04 | E23: 0.03 | F23: 0.025 | G23: Management has guided cost savings of about Rs 300 per tonne over two to three years, plus green power rising from 42% to 65%. This path captures roughly two thirds of that. It is DELIBERATELY below the sell side, which models Rs 1,423 per tonne by FY28 against Rs 924 in FY25, a 54% rise in three years.
A24: Depreciation, percent of opening operating assets | B24: 0.050501 | C24: 0.050501 | D24: 0.050501 | E24: 0.050501 | F24: 0.050501 | G24: CONSOLIDATED depreciation and amortisation of 4,644.46 over the opening consolidated operating asset base of 91,968.32, which includes intangibles. The charge and the base must cover the same assets.
A25: Subsidiary revenue growth | B25: 0.06 | C25: 0.055 | D25: 0.05 | E25: 0.045 | F25: 0.04 | G25: The subsidiary block is principally India Cements, which management is integrating. Growth is assumed slightly below the standalone business.
A26: Subsidiary EBITDA margin | B26: 0.25 | C26: 0.252 | D26: 0.254 | E26: 0.256 | F26: 0.258 | G26: Base year 24.9%. Held broadly flat with modest improvement as integration completes.
A27: Capital expenditure | B27: 9500 | C27: 9500 | D27: 9000 | E27: 8500 | F27: 8500 | G27: Management has guided about Rs 10,000 crore a year consolidated for the next two years. This is the standalone share, tapering as the current expansion phase completes. Capex is now an explicit input rather than derived from capital intensity, because scaling assets to revenue penalised the company for capacity it has already built and is only 82% utilising.
A28: Net working capital, percent of revenue | B28: -0.0374 | C28: -0.0374 | D28: -0.0374 | E28: -0.0374 | F28: -0.0374 | G28: Negative NWC is structural for UltraTech and has been so for nine of ten years.
A30: Terminal and capital structure
A31: Long run real GDP growth | B31: 0.065 | G31: RBI and Economic Survey long run figure. Owned assumption, sensitize it.
A32: Long run inflation | B32: 0.04 | G32: RBI's CPI target of 4% (band 2% to 6%).
A33: Nominal GDP growth (multiplicative) | B33: =(1+B31)*(1+B32)-1 -> 0.1076 | G33: Built as (1+real)(1+inflation)-1, NOT real plus inflation. 6.5% and 4% give 10.76%, not 10.5%.
A34: Terminal growth as a fraction of nominal GDP | B34: 0.65 | G34: 65.0% of nominal GDP, giving 6.99%. RAISED from 46.5% to reflect India's infrastructure runway, which is a genuine medium term demand driver. The HARD CONSTRAINT is that terminal growth can never exceed nominal GDP of 10.76%: a company growing faster than the economy forever eventually becomes larger than the economy. A peer multiple of 19.4x implies 10.99%, which breaches that constraint and is the basis on which this model rejects the peer multiple. Adopting 10.99% ourselves would contradict our own central argument. The same fraction is used for both companies so the two are treated consistently.
A35: Terminal growth rate | B35: =B33*B34 -> 0.06994 | G35: Derived, not typed. Change the fraction above, not this cell.
A36: Target debt to enterprise value | B36: 0.060751 | G36: Current market value leverage: debt of 20,480 over 20,480 plus market cap. Constant rebalancing is assumed, which is what makes the five methods agree.
A38: Non operating assets at 31 March 2026
A39: Liquid investments | B39: 1384.35 | G39: Added to operating enterprise value.
A40: India Cements: shares held (crore) | B40: 23.241683 | G40: From the non-current investments note: 23,24,16,830 shares, a 74.99% holding.
A41: India Cements: carrying value | B41: 0 | G41: Book value in the same note. Works out to Rs 385.95 per share.
A42: India Cements: market price per share | G42: LEAVE BLANK until sourced from NSE. India Cements is LISTED, so asset consistency requires this stake at market value, not book. Blank means the model falls back to carrying value.
A43: India Cements: value used | B43: =IF(B42="",B41,B40*B42) -> 0 | G43: Market value in Rs crore is shares in crore times price in rupees.
A44: Other investments at book | B44: 6739.51 | G44: Total investments in subsidiaries, associates and others of 12,541 less the India Cements carrying value.
A45: Investments in subsidiaries and others | B45: =B43+B44 -> 6739.51 | G45: Feeds the equity bridge in all five valuation methods.
A46: Loan funds | B46: 22780.66 | G46: Deducted to reach equity value.
A47: Lease liabilities | B47: 974.43 | G47: Treated as debt.
A49: Opening position, FY2025-26 actual
A50: Grey cement sales volume (Mn.T) | B50: 140.75 | G50: From the ten year table.
A51: Realisation per tonne (Rs) | B51: 5838.36 | G51: Revenue of 82,170 crore over 140.75 Mn.T.
A52: EBITDA per tonne (Rs) | B52: 1096.91 | G52: Operating profit of 15,439 crore over 140.75 Mn.T. Note this is STANDALONE and therefore excludes India Cements, which is the weakest asset in the group.
A53: Standalone grey cement capacity (Mn.T) | B53: 172.5 | G53: DERIVED, NOT DISCLOSED: consolidated 192.3 mtpa less 5.4 overseas less India Cements 14.45 mtpa. Verify against the company investor presentation before relying on it.
A54: Operating fixed assets, CONSOLIDATED | B54: 99626.77 | G54: Consolidated PPE 80,283.38 plus CWIP 8,275.87 plus right of use 714.34 plus other intangibles 9,886.78 plus intangibles under development 466.40. AN EARLIER DRAFT OMITTED THE TWO INTANGIBLE LINES, Rs 10,353 crore in total, which added subsidiary earnings to the model without the assets that produce them and broke the equivalence of the five methods. The sanity check that catches this is on the Entity Build sheet: every consolidated line must be at least as large as its standalone counterpart.
A55: Goodwill, CONSOLIDATED | B55: 7909.05 | G55: Consolidated goodwill. Retained in invested capital for the ROIC measure but EXCLUDED from terminal reinvestment, because organic growth does not require buying more goodwill.
A56: Subsidiary revenue, base year | B56: 6341.88 | G56: Consolidated revenue of 88,511.53 less standalone 82,169.65. Principally India Cements, in which UltraTech holds 74.99%.
A57: Subsidiary EBITDA, base year | B57: 1581.23 | G57: Consolidated EBITDA of 17,020.23 less standalone 15,439.00. Implies a 24.9% margin, higher than the standalone 18.8%, which reflects the mix of businesses inside the subsidiary block rather than India Cements alone.
A58: Non-controlling interest, CONSOLIDATED | B58: 4088.9 | G58: Deducted in the bridge because consolidated cash flows include 100% of subsidiaries that UltraTech does not wholly own.
A59: Capital work in progress | B59: 7871.47 | G59: Standalone CWIP at 31 March 2026, from Note 02. Held flat in the forecast: the pipeline is assumed to be replenished as projects commission.
A60: Net working capital | B60: -5865.44 | G60: Negative, a source of funds.
A62: Every yellow cell above is a judgement. The three under Cost of capital inputs are not merely uncertain, they are unsourced placeholders, and the workbook should not be quoted until they are replaced.
A64: Terminal ROIC fade (Appendix 5A, Golden Check 6)
A65: Apply terminal ROIC fade? 1 = yes, 0 = no | B65: 0 | M65: SHIPPED AT 0. With the fade ON, FCFF, FCFE and EVA all reconcile at Rs 3,127.70 and Golden Check 6 PASSES with a terminal ROIC of 11.83% against a WACC of 11.33%. CCF and APV do not follow, because they build the terminal from the unfaded cash flow chain and would each need the boundary capital adjustment wired into them separately. Rather than ship a workbook whose five methods disagree by Rs 747 per share, the switch is set to 0. The full construction, including the implied capital and the boundary adjustment that make it work, is built and visible on the Balance Sheet sheet. Setting this cell to 1 reproduces the faded valuation.
A66: Faded terminal ROIC, as WACC plus a spread | B66: ='UTCL-Cost of Capital'!$B$16+B67 -> 0.11831182
A67: Spread over WACC in the faded terminal state | B67: 0.005
A69: WHY THIS EXISTS. Golden Check 6 in Appendix 5A asks whether terminal return on capital fades toward the cost of capital or whether the model assumes perpetual super normal rents. Without a fade this model carries a terminal ROIC of 15.8% against a WACC of 11.33%, a permanent spread of 4.5 points, which contradicts competitive convergence and also contradicts UltraTech's own record: realised ROIC FELL from 14.5% to 10.8% over four years. With the fade switched on, terminal ROIC becomes 11.83% and the value falls from Rs 5,273 to Rs 4,132. Switching the fade OFF restores the higher figure. The fade is ON by default because it is the more defensible assumption and because it moves the valuation AGAINST our own SELL recommendation, which is the conservative direction.

Sheet UTCL-P&L
A1: Line item | B1: Unit | C1: FY2026-27 | D1: FY2027-28 | E1: FY2028-29 | F1: FY2029-30 | G1: FY2030-31
A2: Grey cement capacity | B2: Mn.T | C2: ='UTCL-Assumptions'!B21 -> 186 | D2: ='UTCL-Assumptions'!C21 -> 195 | E2: ='UTCL-Assumptions'!D21 -> 205 | F2: ='UTCL-Assumptions'!E21 -> 213 | G2: ='UTCL-Assumptions'!F21 -> 220
A3: Capacity utilisation | B3: % | C3: ='UTCL-Assumptions'!B22 -> 0.82 | D3: ='UTCL-Assumptions'!C22 -> 0.835 | E3: ='UTCL-Assumptions'!D22 -> 0.845 | F3: ='UTCL-Assumptions'!E22 -> 0.855 | G3: ='UTCL-Assumptions'!F22 -> 0.86
A4: Grey cement sales volume | B4: Mn.T | C4: =C2*C3 -> 152.52 | D4: =D2*D3 -> 162.825 | E4: =E2*E3 -> 173.225 | F4: =F2*F3 -> 182.115 | G4: =G2*G3 -> 189.2
A5: EBITDA per tonne | B5: Rs/t | C5: ='UTCL-Assumptions'!$B$52*(1+'UTCL-Assumptions'!B23) -> 1184.6628 | D5: =C5*(1+'UTCL-Assumptions'!C23) -> 1255.7426 | E5: =D5*(1+'UTCL-Assumptions'!D23) -> 1305.9723 | F5: =E5*(1+'UTCL-Assumptions'!E23) -> 1345.1514 | G5: =F5*(1+'UTCL-Assumptions'!F23) -> 1378.7802
A6: Realisation per tonne | B6: Rs/t | C6: ='UTCL-Assumptions'!$B$51*(1+'UTCL-Assumptions'!B23*0.5) -> 6071.8944 | D6: =C6*(1+'UTCL-Assumptions'!C23*0.5) -> 6254.0512 | E6: =D6*(1+'UTCL-Assumptions'!D23*0.5) -> 6379.1323 | F6: =E6*(1+'UTCL-Assumptions'!E23*0.5) -> 6474.8192 | G6: =F6*(1+'UTCL-Assumptions'!F23*0.5) -> 6555.7545
A7: Standalone revenue | B7: Rs cr | C7: =C4*C6/10 -> 92608.533 | D7: =D4*D6/10 -> 101831.59 | E7: =E4*E6/10 -> 110502.52 | F7: =F4*F6/10 -> 117916.17 | G7: =G4*G6/10 -> 124034.87
A8: Standalone EBITDA | B8: Rs cr | C8: =C4*C5/10 -> 18068.477 | D8: =D4*D5/10 -> 20446.628 | E8: =E4*E5/10 -> 22622.705 | F8: =F4*F5/10 -> 24497.225 | G8: =G4*G5/10 -> 26086.522
A10: Subsidiary revenue | B10: Rs cr | C10: ='UTCL-Assumptions'!$B$56*(1+'UTCL-Assumptions'!B25) -> 6722.3928 | D10: =C10*(1+'UTCL-Assumptions'!C25) -> 7092.1244 | E10: =D10*(1+'UTCL-Assumptions'!D25) -> 7446.7306 | F10: =E10*(1+'UTCL-Assumptions'!E25) -> 7781.8335 | G10: =F10*(1+'UTCL-Assumptions'!F25) -> 8093.1068
A11: Subsidiary EBITDA margin | B11: Rs cr | C11: ='UTCL-Assumptions'!B26 -> 0.25 | D11: ='UTCL-Assumptions'!C26 -> 0.252 | E11: ='UTCL-Assumptions'!D26 -> 0.254 | F11: ='UTCL-Assumptions'!E26 -> 0.256 | G11: ='UTCL-Assumptions'!F26 -> 0.258
A12: Subsidiary EBITDA | B12: Rs cr | C12: =C10*C11 -> 1680.5982 | D12: =D10*D11 -> 1787.2153 | E12: =E10*E11 -> 1891.4696 | F12: =F10*F11 -> 1992.1494 | G12: =G10*G11 -> 2088.0216
A14: Revenue | B14: Rs cr | C14: =C7+C10 -> 99330.926 | D14: =D7+D10 -> 108923.71 | E14: =E7+E10 -> 117949.25 | F14: =F7+F10 -> 125698 | G14: =G7+G10 -> 132127.98
A15: Operating profit (EBITDA) | B15: Rs cr | C15: =C8+C12 -> 19749.075 | D15: =D8+D12 -> 22233.844 | E15: =E8+E12 -> 24514.174 | F15: =F8+F12 -> 26489.375 | G15: =G8+G12 -> 28174.543
A16: Opening productive fixed assets | B16: Rs cr | C16: ='UTCL-Assumptions'!$B$54 -> 99626.77 | D16: =C19 -> 104095.52 | E16: =D19 -> 108338.59 | F16: =E19 -> 111867.38 | G16: =F19 -> 114717.97
A17: Depreciation and amortisation | B17: Rs cr | C17: =C16*'UTCL-Assumptions'!B24 -> 5031.2515 | D17: =D16*'UTCL-Assumptions'!C24 -> 5256.9278 | E17: =E16*'UTCL-Assumptions'!D24 -> 5471.2072 | F17: =F16*'UTCL-Assumptions'!E24 -> 5649.4147 | G17: =G16*'UTCL-Assumptions'!F24 -> 5793.3721
A18: Capital expenditure | B18: Rs cr | C18: ='UTCL-Assumptions'!B27 -> 9500 | D18: ='UTCL-Assumptions'!C27 -> 9500 | E18: ='UTCL-Assumptions'!D27 -> 9000 | F18: ='UTCL-Assumptions'!E27 -> 8500 | G18: ='UTCL-Assumptions'!F27 -> 8500
A19: Closing productive fixed assets | B19: Rs cr | C19: =C16+C18-C17 -> 104095.52 | D19: =D16+D18-D17 -> 108338.59 | E19: =E16+E18-E17 -> 111867.38 | F19: =F16+F18-F17 -> 114717.97 | G19: =G16+G18-G17 -> 117424.6
A20: EBIT | B20: Rs cr | C20: =C15-C17 -> 14717.824 | D20: =D15-D17 -> 16976.916 | E20: =E15-E17 -> 19042.967 | F20: =F15-F17 -> 20839.96 | G20: =G15-G17 -> 22381.171
A21: NOPAT (EBIT at statutory tax) | B21: Rs cr | C21: =C20*(1-'UTCL-Assumptions'!$B$4) -> 11013.642 | D21: =D20*(1-'UTCL-Assumptions'!$B$4) -> 12704.166 | E21: =E20*(1-'UTCL-Assumptions'!$B$4) -> 14250.233 | F21: =F20*(1-'UTCL-Assumptions'!$B$4) -> 15594.959 | G21: =G20*(1-'UTCL-Assumptions'!$B$4) -> 16748.278
A22: Net working capital (closing) | B22: Rs cr | C22: =C14*'UTCL-Assumptions'!B28 -> -3714.9766 | D22: =D14*'UTCL-Assumptions'!C28 -> -4073.7469 | E22: =E14*'UTCL-Assumptions'!D28 -> -4411.3019 | F22: =F14*'UTCL-Assumptions'!E28 -> -4701.1054 | G22: =G14*'UTCL-Assumptions'!F28 -> -4941.5865
A23: Change in net working capital | B23: Rs cr | C23: =C22-'UTCL-Assumptions'!$B$60 -> 2150.4634 | D23: =D22-C22 -> -358.77025 | E23: =E22-D22 -> -337.55503 | F23: =F22-E22 -> -289.80344 | G23: =G22-F22 -> -240.48116
A24: FCFF | B24: Rs cr | C24: =C21+C17-C18-C23 -> 4394.43 | D24: =D21+D17-D18-D23 -> 8819.8638 | E24: =E21+E17-E18-E23 -> 11058.995 | F24: =F21+F17-F18-F23 -> 13034.177 | G24: =G21+G17-G18-G23 -> 14282.131
A26: Memo: capex as percent of revenue | B26: Rs cr | C26: =IFERROR(C18/C14,"") -> 0.095639902 | D26: =IFERROR(D18/D14,"") -> 0.087217004 | E26: =IFERROR(E18/E14,"") -> 0.076304004 | F26: =IFERROR(F18/F14,"") -> 0.067622394 | G26: =IFERROR(G18/G14,"") -> 0.064331566
A27: Memo: EBITDA margin | B27: Rs cr | C27: =IFERROR(C15/C14,"") -> 0.19882101 | D27: =IFERROR(D15/D14,"") -> 0.20412308 | E27: =IFERROR(E15/E14,"") -> 0.20783663 | F27: =IFERROR(F15/F14,"") -> 0.21073823 | G27: =IFERROR(G15/G14,"") -> 0.21323677
A29: Volume is capacity times utilisation, not a growth rate, because UltraTech has already built the capacity and is running it at roughly 82%. Growth for the next several years comes from filling existing plants. EBITDA is volume times EBITDA per tonne, the metric the industry and management actually steer by. Capex is an explicit input anchored to management guidance rather than derived from capital intensity, because scaling assets to revenue charged the company again for capacity it had already paid for. FCFF equals NOPAT less the increase in invested capital, which is what allows the EVA sheet to reconcile back to the same enterprise value.

Sheet UTCL-Balance Sheet
A1: Line item | B1: Unit | C1: FY2026-27 | D1: FY2027-28 | E1: FY2028-29 | F1: FY2029-30 | G1: FY2030-31
A2: Opening invested capital | B2: Rs cr | C2: ='UTCL-Assumptions'!$B$54+'UTCL-Assumptions'!$B$60 -> 93761.33 | D2: =C6 -> 100380.54 | E2: =D6 -> 104264.84 | F2: =E6 -> 107456.08 | G2: =F6 -> 110016.86
A3: Add: Capital expenditure | B3: Rs cr | C3: ='UTCL-P&L'!C18 -> 9500 | D3: ='UTCL-P&L'!D18 -> 9500 | E3: ='UTCL-P&L'!E18 -> 9000 | F3: ='UTCL-P&L'!F18 -> 8500 | G3: ='UTCL-P&L'!G18 -> 8500
A4: Less: Depreciation | B4: Rs cr | C4: =-'UTCL-P&L'!C17 -> -5031.2515 | D4: =-'UTCL-P&L'!D17 -> -5256.9278 | E4: =-'UTCL-P&L'!E17 -> -5471.2072 | F4: =-'UTCL-P&L'!F17 -> -5649.4147 | G4: =-'UTCL-P&L'!G17 -> -5793.3721
A5: Add: Change in net working capital | B5: Rs cr | C5: ='UTCL-P&L'!C23 -> 2150.4634 | D5: ='UTCL-P&L'!D23 -> -358.77025 | E5: ='UTCL-P&L'!E23 -> -337.55503 | F5: ='UTCL-P&L'!F23 -> -289.80344 | G5: ='UTCL-P&L'!G23 -> -240.48116
A6: Closing invested capital | B6: Rs cr | C6: =SUM(C2:C5) -> 100380.54 | D6: =SUM(D2:D5) -> 104264.84 | E6: =SUM(E2:E5) -> 107456.08 | F6: =SUM(F2:F5) -> 110016.86 | G6: =SUM(G2:G5) -> 112483.01
A8: NOPAT | B8: Rs cr | C8: ='UTCL-P&L'!C21 -> 11013.642 | D8: ='UTCL-P&L'!D21 -> 12704.166 | E8: ='UTCL-P&L'!E21 -> 14250.233 | F8: ='UTCL-P&L'!F21 -> 15594.959 | G8: ='UTCL-P&L'!G21 -> 16748.278
A9: ROIC on opening invested capital | B9: Rs cr | C9: =IFERROR(C8/C2,"") -> 0.11746465 | D9: =IFERROR(D8/D2,"") -> 0.12656004 | E9: =IFERROR(E8/E2,"") -> 0.13667342 | F9: =IFERROR(F8/F2,"") -> 0.14512868 | G9: =IFERROR(G8/G2,"") -> 0.15223374
A10: Reinvestment (change in invested capital) | B10: Rs cr | C10: =C6-C2 -> 6619.2118 | D10: =D6-D2 -> 3884.302 | E10: =E6-E2 -> 3191.2378 | F10: =F6-F2 -> 2560.7818 | G10: =G6-G2 -> 2466.1467
A11: Reinvestment rate | B11: Rs cr | C11: =IFERROR(C10/C8,"") -> 0.60100119 | D11: =IFERROR(D10/D8,"") -> 0.30575026 | E11: =IFERROR(E10/E8,"") -> 0.22394285 | F11: =IFERROR(F10/F8,"") -> 0.16420574 | G11: =IFERROR(G10/G8,"") -> 0.14724778
A13: Terminal year, steady state
A14: NOPAT in the terminal year | C14: =G8*(1+'UTCL-Assumptions'!$B$35) -> 17919.653
A15: Closing invested capital, FY2030-31 | C15: =G6 -> 112483.01
A16: Reinvestment = g x invested capital | C16: =IF('UTCL-Assumptions'!$B$65=1,C14*('UTCL-Assumptions'!$B$35/'UTCL-Assumptions'!$B$66),'UTCL-Assumptions'!$B$35*C15) -> 7867.0617
A17: Terminal FCFF | C17: =C14-C16 -> 10052.591
A18: Implied terminal ROIC | C18: =IFERROR(C14/C15,"") -> 0.15930986
A19: Implied terminal reinvestment rate | C19: =IFERROR('UTCL-Assumptions'!$B$35/C18,"") -> 0.43901865
A21: The terminal year is forced into steady state: reinvestment equals terminal growth times closing invested capital. This is not a cosmetic choice. It is the condition under which the FCFF, CCF, APV, FCFE and EVA methods all return the same value. Growing the last forecast FCFF by g instead would break the EVA reconciliation, because EVA and FCFE would then imply different reinvestment.
A23: Terminal ROIC fade, applied above
A24: Terminal ROIC before fade | C24: =C14/C15 -> 0.15930986
A25: Terminal ROIC after fade | C25: ='UTCL-Assumptions'!$B$66 -> 0.11831182
A26: Reinvestment rate = g / terminal ROIC | C26: ='UTCL-Assumptions'!$B$35/'UTCL-Assumptions'!$B$66 -> 0.59114971
A27: Fade switch (1 = on) | C27: ='UTCL-Assumptions'!$B$65 -> 0
A29: Terminal ROIC fade: implied capital and boundary adjustment
A30: Terminal ROIC before fade | C30: =C14/C15 -> 0.15930986
A31: Faded terminal ROIC (WACC plus spread) | C31: ='UTCL-Assumptions'!$B$66 -> 0.11831182
A32: Invested capital IMPLIED by the faded ROIC | C32: =C14/'UTCL-Assumptions'!$B$66 -> 151461.22
A33: Closing invested capital, last explicit year | C33: =C15 -> 112483.01
A34: Boundary capital adjustment | C34: =C33-C32 -> -38978.206
A35: Terminal reinvestment = g x implied capital | C35: ='UTCL-Assumptions'!$B$35*C32 -> 10593.197
A36: Terminal FCFF on the faded basis | C36: =C14-C35 -> 7326.4552
A38: WHY THE ADJUSTMENT IS NEEDED. A faded terminal return implies a larger capital base than the explicit forecast ends with, because the same NOPAT divided by a lower ROIC gives more capital. That step change is a real capital movement and must appear in the cash flow methods as well as in the return measure. Recognising it is what keeps FCFF, CCF, APV, FCFE and EVA equal. Golden Check 6 now PASSES: terminal ROIC is WACC plus 0.50 points rather than WACC plus 4.5.

Sheet UTCL-Cash Flow
A1: Cash flow: derived history and forecast
A3: Historical capex, derived from the ten year table
A4: Line item | B4: Unit | C4: FY22 | D4: FY23 | E4: FY24 | F4: FY25 | G4: FY26
A5: Closing net fixed assets | B5: Rs cr | C5: ='UTCL-Source Data'!H14 -> 52604 | D5: ='UTCL-Source Data'!I14 -> 63077 | E5: ='UTCL-Source Data'!J14 -> 69368 | F5: ='UTCL-Source Data'!K14 -> 83764 | G5: ='UTCL-Source Data'!L14 -> 89161
A6: Less: opening net fixed assets | B6: Rs cr | C6: =-'UTCL-Source Data'!G14 -> -49144 | D6: =-'UTCL-Source Data'!H14 -> -52604 | E6: =-'UTCL-Source Data'!I14 -> -63077 | F6: =-'UTCL-Source Data'!J14 -> -69368 | G6: =-'UTCL-Source Data'!K14 -> -83764
A7: Add: depreciation | B7: Rs cr | C7: ='UTCL-Source Data'!H7 -> 2457 | D7: ='UTCL-Source Data'!I7 -> 2773 | E7: ='UTCL-Source Data'!J7 -> 3027 | F7: ='UTCL-Source Data'!K7 -> 3739 | G7: ='UTCL-Source Data'!L7 -> 4055
A8: Derived capital expenditure | B8: Rs cr | C8: =SUM(C5:C7) -> 5917 | D8: =SUM(D5:D7) -> 13246 | E8: =SUM(E5:E7) -> 9318 | F8: =SUM(F5:F7) -> 18135 | G8: =SUM(G5:G7) -> 9452
A10: The annual report cash flow statement is not spread line by line here; capex is derived as the change in net fixed assets plus depreciation, which is the figure the valuation uses. If the full statement is required for submission it should be spread from the report and entered as blue inputs.
A14: Forecast free cash flow to the firm
A15: Line item | B15: Unit | C15: FY27 | D15: FY28 | E15: FY29 | F15: FY30 | G15: FY31
A16: Operating profit (EBITDA) | B16: Rs cr | C16: ='UTCL-P&L'!C15 -> 19749.075 | D16: ='UTCL-P&L'!D15 -> 22233.844 | E16: ='UTCL-P&L'!E15 -> 24514.174 | F16: ='UTCL-P&L'!F15 -> 26489.375 | G16: ='UTCL-P&L'!G15 -> 28174.543
A17: Less: Depreciation and amortisation | B17: Rs cr | C17: =-'UTCL-P&L'!C17 -> -5031.2515 | D17: =-'UTCL-P&L'!D17 -> -5256.9278 | E17: =-'UTCL-P&L'!E17 -> -5471.2072 | F17: =-'UTCL-P&L'!F17 -> -5649.4147 | G17: =-'UTCL-P&L'!G17 -> -5793.3721
A18: EBIT | B18: Rs cr | C18: ='UTCL-P&L'!C20 -> 14717.824 | D18: ='UTCL-P&L'!D20 -> 16976.916 | E18: ='UTCL-P&L'!E20 -> 19042.967 | F18: ='UTCL-P&L'!F20 -> 20839.96 | G18: ='UTCL-P&L'!G20 -> 22381.171
A19: NOPAT at statutory tax | B19: Rs cr | C19: ='UTCL-P&L'!C21 -> 11013.642 | D19: ='UTCL-P&L'!D21 -> 12704.166 | E19: ='UTCL-P&L'!E21 -> 14250.233 | F19: ='UTCL-P&L'!F21 -> 15594.959 | G19: ='UTCL-P&L'!G21 -> 16748.278
A20: Add: Depreciation and amortisation | B20: Rs cr | C20: ='UTCL-P&L'!C17 -> 5031.2515 | D20: ='UTCL-P&L'!D17 -> 5256.9278 | E20: ='UTCL-P&L'!E17 -> 5471.2072 | F20: ='UTCL-P&L'!F17 -> 5649.4147 | G20: ='UTCL-P&L'!G17 -> 5793.3721
A21: Less: Capital expenditure | B21: Rs cr | C21: =-'UTCL-P&L'!C18 -> -9500 | D21: =-'UTCL-P&L'!D18 -> -9500 | E21: =-'UTCL-P&L'!E18 -> -9000 | F21: =-'UTCL-P&L'!F18 -> -8500 | G21: =-'UTCL-P&L'!G18 -> -8500
A22: Less: Change in net working capital | B22: Rs cr | C22: =-'UTCL-P&L'!C23 -> -2150.4634 | D22: =-'UTCL-P&L'!D23 -> 358.77025 | E22: =-'UTCL-P&L'!E23 -> 337.55503 | F22: =-'UTCL-P&L'!F23 -> 289.80344 | G22: =-'UTCL-P&L'!G23 -> 240.48116
A23: Free cash flow to the firm | B23: Rs cr | C23: ='UTCL-P&L'!C24 -> 4394.43 | D23: ='UTCL-P&L'!D24 -> 8819.8638 | E23: ='UTCL-P&L'!E24 -> 11058.995 | F23: ='UTCL-P&L'!F24 -> 13034.177 | G23: ='UTCL-P&L'!G24 -> 14282.131

Sheet UTCL-Cost of Capital
A1: Cost of Capital
A3: Indian 10 year G-Sec yield | B3: ='UTCL-Assumptions'!$B$10 -> 0.0685 | C3: Still to be sourced from RBI.
A4: Less: sovereign default spread | B4: =-'UTCL-Assumptions'!$B$11 -> -0.0187 | C4: Damodaran, January 2026. India Baa3.
A5: Risk free rate | B5: ='UTCL-Assumptions'!$B$12 -> 0.0498
A6: India equity risk premium | B6: ='UTCL-Assumptions'!$B$13 -> 0.0708 | C6: Damodaran, January 2026: 4.23% mature market plus 2.85% India country risk premium.
A7: Unlevered beta (Building Materials) | B7: ='UTCL-Assumptions'!$B$14 -> 0.9 | C7: Damodaran Betas by Sector (Global), January 2026, 469 firms, corrected for cash.
A8: Beta (levered) | B8: ='UTCL-Assumptions'!$B$16 -> 0.94356188 | C8: Relevered on UltraTech's own market debt to equity of 6.47%.
A9: Cost of equity, CAPM | B9: =B5+B8*B6 -> 0.11660418 | C9: CAPM with the Damodaran bottom up beta.
A10: Fama French Ke, if computed | C10: Leave blank to use CAPM. Fill from the companion notebook, which regresses ULTRACEMCO on the IIM Ahmedabad India Fama French factors. A Fama French Ke is ALREADY a levered all in number, so if you use it do not relever a beta on top of it.
A11: Cost of equity (Ke) | B11: =IF(B10="",B9,B10) -> 0.11660418 | C11: Uses the Fama French figure when supplied, otherwise CAPM.
A12: Pre tax cost of debt (Kd) | B12: ='UTCL-Assumptions'!$B$17 -> 0.0834
A13: Statutory tax rate | B13: ='UTCL-Assumptions'!$B$4 -> 0.25168
A14: Target debt to enterprise value (D/V) | B14: ='UTCL-Assumptions'!$B$36 -> 0.060751
A15: Equity to enterprise value (E/V) | B15: =1-B14 -> 0.939249
A16: WACC (after tax) | B16: =B15*B11+B14*B12*(1-B13) -> 0.11331182 | C16: Weights are market value based and held constant, which implies continuous rebalancing of debt to the target ratio.
A17: Unlevered cost of capital (rho) | B17: =B15*B11+B14*B12 -> 0.11458699 | C17: Under constant rebalancing the tax shield carries the same risk as the assets, so rho is the unweighted mix of Ke and Kd.
A18: Check: rho = WACC + Kd x t x D/V | B18: =B16+B12*B13*B14 -> 0.11458699 | C18: Must equal the row above to the last decimal.
A20: Circularity: market cap weights versus iterative convergence
A21: Weights used in the WACC above | B21: Market capitalisation | C21: The tension is deliberate and disclosed: the model uses the very share price it is testing. Mohanty sanctions this only if stated, with the iterated alternative shown.
A22: D/E on market capitalisation | B22: 0.064681 | C22: Debt 20,480 over market cap 316,633.
A23: D/E on the model's own equity value | B23: 0.1478 | C23: Debt 20,480 over the DCF equity value. Solved by iteration per SSRN 413240.
A24: Relevered beta at the converged D/E | B24: 0.9996 | C24: Rises from 0.9436.
A25: Cost of equity at the converged D/E | B25: 0.11707 | C25: Rises from 11.31%.
A26: WACC at the converged D/E | B26: 0.11003 | C26: Essentially unchanged from 11.002%.
A27: Value per share, converged | B27: 4701 | C27: Against Rs 4,748 on market cap weights, a difference of 1.0%.
A29: Why the two agree: raising D/V from 6.1% to 12.9% substitutes cheaper debt into the weights, which pulls WACC down, while relevering beta from 0.9436 to 0.9996 pushes the cost of equity up. The two effects very nearly cancel. The conclusion is not that circularity does not matter, but that this particular valuation is insensitive to it, which is worth stating rather than assuming.
A33: Under the constant leverage assumption used here, the interest tax shield is discounted at rho rather than at the cost of debt. That is the assumption that makes CCF and APV agree with FCFF at WACC. If you instead assume a fixed rupee amount of debt, the tax shield should be discounted at Kd and the reconciliation changes shape.

Sheet UTCL-Beta
A1: Beta: bottom up build and live regression cross check
A2: Blue on yellow is an input. The regression block below computes itself once monthly closes are pasted in.
A4: Method used: bottom up beta
A5: Input | B5: Value | H5: Source and reasoning
A6: Unlevered beta, Building Materials | B6: 0.9 | H6: Damodaran, Betas by Sector (Global), January 2026. 469 firms. CASH CORRECTED figure, not the raw 0.86, because this model adds cash back separately at the equity bridge; the raw beta would count cash twice.
A7: Market debt to equity | B7: 0.064681 | H7: Borrowings and leases over market capitalisation, both from the company's own disclosure.
A8: Marginal tax rate | B8: 0.25168 | H8: Section 115BAA: 22% plus 10% surcharge plus 4% cess.
A9: Levered beta (Hamada) | B9: =B6*(1+(1-B8)*B7) -> 0.94356188 | H9: Unlevered x (1 + (1 - t) x D/E). This is the figure carried into the Cost of Capital sheet.
A11: Cross check: live regression beta, 60 monthly observations
A12: Regression beta (slope) | B12: =IFERROR(SLOPE(G25:G84,F25:F84),"paste prices below") -> 1.0863349
A13: R squared | B13: =IFERROR(RSQ(G25:G84,F25:F84),"") -> 0.47579215
A14: Observations | B14: =COUNT(F25:F84) -> 60
A15: Blume adjusted beta | B15: =IFERROR(0.67*B12+0.33,"") -> 1.0578444
A16: Difference vs bottom up | B16: =IFERROR(B12-B9,"") -> 0.14277302
A18: DATA POPULATED. 61 month end closes from March 2021 to March 2026 for the NIFTY 500 and for ULTRACEMCO, newest first. SOURCE NOTE, stated precisely: the series was supplied with an adjusted close column, which is a market data vendor convention rather than the NSE bhavcopy format, so it should be treated as vendor sourced rather than exchange sourced. That is acceptable for a beta regression, which needs a consistent series rather than an authoritative one, but it is why the sourcing claim elsewhere in this model is confined to the FINANCIAL STATEMENTS and the COST OF CAPITAL PARAMETERS, which come from annual reports, RBI and Damodaran respectively.
B24: Month end | C24: NIFTY 500 close | D24: ULTRACEMCO close | F24: Index return | G24: Stock return | H24: Newest month at the top. Returns are computed against the row below.
B25: 2026-03 | C25: 20528.05 | D25: 10745 | F25: =IFERROR(C25/C26-1,"") -> -0.11390413 | G25: =IFERROR(D25/D26-1,"") -> -0.15240199
B26: 2026-02 | C26: 23166.85 | D26: 12677 | F26: =IFERROR(C26/C27-1,"") -> 0.003784744 | G26: =IFERROR(D26/D27-1,"") -> -0.0013392154
B27: 2026-01 | C27: 23079.5 | D27: 12694 | F27: =IFERROR(C27/C28-1,"") -> -0.033179664 | G27: =IFERROR(D27/D28-1,"") -> 0.077223354
B28: 2025-12 | C28: 23871.55 | D28: 11784 | F28: =IFERROR(C28/C29-1,"") -> -0.0025759196 | G28: =IFERROR(D28/D29-1,"") -> 0.015862069
B29: 2025-11 | C29: 23933.2 | D29: 11600 | F29: =IFERROR(C29/C30-1,"") -> 0.0093967204 | G29: =IFERROR(D29/D30-1,"") -> -0.029044949
B30: 2025-10 | C30: 23710.4 | D30: 11947 | F30: =IFERROR(C30/C31-1,"") -> 0.0429443 | G30: =IFERROR(D30/D31-1,"") -> -0.022500409
B31: 2025-09 | C31: 22734.1 | D31: 12222 | F31: =IFERROR(C31/C32-1,"") -> 0.012070988 | G31: =IFERROR(D31/D32-1,"") -> -0.03306962
B32: 2025-08 | C32: 22462.95 | D32: 12640 | F32: =IFERROR(C32/C33-1,"") -> -0.019725114 | G32: =IFERROR(D32/D33-1,"") -> 0.031920973
B33: 2025-07 | C33: 22914.95 | D33: 12249 | F33: =IFERROR(C33/C34-1,"") -> -0.029734685 | G33: =IFERROR(D33/D34-1,"") -> 0.012900025
B34: 2025-06 | C34: 23617.2 | D34: 12093 | F34: =IFERROR(C34/C35-1,"") -> 0.035753521 | G34: =IFERROR(D34/D35-1,"") -> 0.078768956
B35: 2025-05 | C35: 22801.95 | D35: 11210 | F35: =IFERROR(C35/C36-1,"") -> 0.035038504 | G35: =IFERROR(D35/D36-1,"") -> -0.037024311
B36: 2025-04 | C36: 22030.05 | D36: 11641 | F36: =IFERROR(C36/C37-1,"") -> 0.032357758 | G36: =IFERROR(D36/D37-1,"") -> 0.01142095
... B84: 2021-04 | C84: 12364.35 | D84: 6278.95 | F84: =IFERROR(C84/C85-1,"") -> 0.0041133047 | G84: =IFERROR(D84/D85-1,"") -> -0.06812161
B85: 2021-03 | C85: 12313.7 | D85: 6737.95
A87: Reading the result. If the regression beta lands close to the bottom up figure, report both and keep the bottom up number, which is more stable. If it differs materially, say which you adopt and why. Note that the sensitivity work on the Sensitivity sheet shows the valuation conclusion does not turn on beta: even a beta of 0.70 leaves the shares far above our value.
A89: Which beta this model uses, and why
A90: Bottom up beta (USED in the model) | B90: 0.9436
A91: Regression beta, NIFTY 500, 60 months | B91: 1.0863
A92: Regression R squared | B92: 0.476
A93: Difference, regression less bottom up | B93: 0.1427
A95: THE CHOICE AND ITS DIRECTION. The model uses the BOTTOM UP beta. Three reasons. First, it is estimated from 469 sector firms rather than from one noisy series: the regression R squared is 0.48, so most of the variation in the stock is not explained by the index at all. Second, bottom up betas are more stable across estimation windows, which matters when the choice of window is itself a judgement. Third and most important, the regression beta of 1.0863 is HIGHER than the bottom up 0.9436, which would raise the cost of capital and LOWER our valuation. Since our recommendation is a SELL, using the lower beta works AGAINST our own conclusion. That is the conservative choice and it forecloses any suggestion that a beta was selected to flatter the answer. The Sensitivity sheet shows the value at the regression beta.

Sheet UTCL-FCFF valuation
A1: Line item | B1: Unit | C1: FY2026-27 | D1: FY2027-28 | E1: FY2028-29 | F1: FY2029-30 | G1: FY2030-31 | H1: Terminal
A2: FCFF | B2: Rs cr | C2: ='UTCL-P&L'!C24 -> 4394.43 | D2: ='UTCL-P&L'!D24 -> 8819.8638 | E2: ='UTCL-P&L'!E24 -> 11058.995 | F2: ='UTCL-P&L'!F24 -> 13034.177 | G2: ='UTCL-P&L'!G24 -> 14282.131 | H2: ='UTCL-Balance Sheet'!C17 -> 10052.591
A3: Discount factor at WACC | B3: Rs cr | C3: =1/(1+'UTCL-Cost of Capital'!$B$16)^1 -> 0.89822095 | D3: =1/(1+'UTCL-Cost of Capital'!$B$16)^2 -> 0.80680087 | E3: =1/(1+'UTCL-Cost of Capital'!$B$16)^3 -> 0.72468544 | F3: =1/(1+'UTCL-Cost of Capital'!$B$16)^4 -> 0.65092764 | G3: =1/(1+'UTCL-Cost of Capital'!$B$16)^5 -> 0.58467684
A4: Present value of FCFF | B4: Rs cr | C4: =C2*C3 -> 3947.1691 | D4: =D2*D3 -> 7115.8737 | E4: =E2*E3 -> 8014.2929 | F4: =F2*F3 -> 8484.3062 | G4: =G2*G3 -> 8350.4315
A6: Sum of PV of explicit FCFF | C6: =SUM(C4:G4) -> 35912.073
A7: Terminal value at FY2030-31 | C7: =IF('UTCL-Assumptions'!$B$65=1,('UTCL-Balance Sheet'!C36/('UTCL-Cost of Capital'!$B$16-'UTCL-Assumptions'!$B$35))+'UTCL-Balance Sheet'!C34,H2/('UTCL-Cost of Capital'!$B$16-'UTCL-Assumptions'!$B$35)) -> 231777
A8: PV of terminal value | C8: =C7*G3 -> 135514.64
A9: Enterprise value of operations | C9: =C6+C8 -> 171426.72
A10: Add: Liquid investments | C10: ='UTCL-Assumptions'!$B$39 -> 1384.35
A11: Add: Investments in subsidiaries and others | C11: ='UTCL-Assumptions'!$B$45 -> 6739.51
A12: Less: Loan funds | C12: =-'UTCL-Assumptions'!$B$46 -> -22780.66
A13: Less: Lease liabilities | C13: =-'UTCL-Assumptions'!$B$47 -> -974.43
A14: Equity value | C14: =SUM(C9:C13)-'UTCL-Assumptions'!$B$58 -> 151706.59
A15: Value per share (Rs) | C15: =C14/'UTCL-Assumptions'!$B$5 -> 5148.1806
A16: Terminal value as percent of enterprise value | C16: =C8/C9 -> 0.79051064
A17: Implied terminal EV/EBITDA | C17: =C7/('UTCL-P&L'!G15*(1+'UTCL-Assumptions'!$B$35)) -> 7.6887195
A19: The implied terminal EV/EBITDA is the multiplier consistency check.
A21: Reverse cross-check: what terminal growth would the peer exit multiple require?
A22: Assumed exit EV/EBITDA | B22: Implied terminal g | D22: Verdict
A23: 19.05 | B23: 0.0978 | D23: Peer median. Implies g of 9.8% against a WACC of 11.0% and nominal GDP of 10.8%: UltraTech would have to grow at almost the whole economy's rate forever with a near zero spread over its cost of capital.
A24: 15 | B24: 0.0935 | D24: Still requires g close to nominal GDP.
A25: 12 | B25: 0.0877 | D25: Requires g of 8.8%, above any defensible mature growth rate.
A26: 10 | B26: 0.0809 | D26: Requires g of 8.1%.
A27: 8 | B27: 0.0679 | D27: Requires g of 6.8%, roughly 63% of nominal GDP. The first figure in this table that is arguable.
A28: 6.8 | B28: 0.05 | D28: The model's own base case, g = 5%, or 46% of nominal GDP.
A30: This is the bracketing the method asks for, and it does NOT bracket cleanly. Our g of 5% implies 6.8x; the peer multiple of 19.05x implies g of 9.8%. The truth lies between, but note what the peer multiple demands: growth at roughly 91% of nominal GDP in perpetuity from a company whose realisation has compounded at 2.0% over ten years. The position this model takes is that the peer multiple, not the terminal assumption, is the implausible end of the range. That is a position, not a dodge, and the report must defend it.

Sheet UTCL-CCF valuation
A1: Line item | B1: Unit | C1: FY2026-27 | D1: FY2027-28 | E1: FY2028-29 | F1: FY2029-30 | G1: FY2030-31 | H1: Terminal
A2: Enterprise value at each year end | B2: Rs cr | C2: =(D2+'UTCL-P&L'!D24)/(1+'UTCL-Cost of Capital'!$B$16) -> 186456.96 | D2: =(E2+'UTCL-P&L'!E24)/(1+'UTCL-Cost of Capital'!$B$16) -> 198764.87 | E2: =(F2+'UTCL-P&L'!F24)/(1+'UTCL-Cost of Capital'!$B$16) -> 210228.29 | F2: =(G2+'UTCL-P&L'!G24)/(1+'UTCL-Cost of Capital'!$B$16) -> 221015.46 | G2: ='UTCL-FCFF valuation'!C7 -> 231777
A3: Enterprise value at valuation date | B3: =(C2+'UTCL-P&L'!C24)/(1+'UTCL-Cost of Capital'!$B$16) -> 171426.72
A4: Debt at target ratio, opening | B4: Rs cr | C4: =$B$3*'UTCL-Cost of Capital'!$B$14 -> 10414.344 | D4: =C2*'UTCL-Cost of Capital'!$B$14 -> 11327.447 | E4: =D2*'UTCL-Cost of Capital'!$B$14 -> 12075.165 | F4: =E2*'UTCL-Cost of Capital'!$B$14 -> 12771.579 | G4: =F2*'UTCL-Cost of Capital'!$B$14 -> 13426.91
A5: Interest on opening debt | B5: Rs cr | C5: =C4*'UTCL-Cost of Capital'!$B$12 -> 868.55632 | D5: =D4*'UTCL-Cost of Capital'!$B$12 -> 944.70906 | E5: =E4*'UTCL-Cost of Capital'!$B$12 -> 1007.0687 | F5: =F4*'UTCL-Cost of Capital'!$B$12 -> 1065.1497 | G5: =G4*'UTCL-Cost of Capital'!$B$12 -> 1119.8043
A6: Interest tax shield | B6: Rs cr | C6: =C5*'UTCL-Cost of Capital'!$B$13 -> 218.59826 | D6: =D5*'UTCL-Cost of Capital'!$B$13 -> 237.76438 | E6: =E5*'UTCL-Cost of Capital'!$B$13 -> 253.45906 | F6: =F5*'UTCL-Cost of Capital'!$B$13 -> 268.07687 | G6: =G5*'UTCL-Cost of Capital'!$B$13 -> 281.83235 | H6: =G2*'UTCL-Cost of Capital'!$B$14*'UTCL-Cost of Capital'!$B$12*'UTCL-Cost of Capital'!$B$13 -> 295.55514
A7: Capital cash flow (FCFF + tax shield) | B7: Rs cr | C7: ='UTCL-P&L'!C24+C6 -> 4613.0282 | D7: ='UTCL-P&L'!D24+D6 -> 9057.6281 | E7: ='UTCL-P&L'!E24+E6 -> 11312.454 | F7: ='UTCL-P&L'!F24+F6 -> 13302.254 | G7: ='UTCL-P&L'!G24+G6 -> 14563.964 | H7: ='UTCL-FCFF valuation'!H2+H6 -> 10348.146
A8: Discount factor at rho | B8: Rs cr | C8: =1/(1+'UTCL-Cost of Capital'!$B$17)^1 -> 0.89719332 | D8: =1/(1+'UTCL-Cost of Capital'!$B$17)^2 -> 0.80495584 | E8: =1/(1+'UTCL-Cost of Capital'!$B$17)^3 -> 0.722201 | F8: =1/(1+'UTCL-Cost of Capital'!$B$17)^4 -> 0.64795391 | G8: =1/(1+'UTCL-Cost of Capital'!$B$17)^5 -> 0.58133992
A9: Present value of CCF | B9: Rs cr | C9: =C7*C8 -> 4138.7781 | D9: =D7*D8 -> 7290.9907 | E9: =E7*E8 -> 8169.8659 | F9: =F7*F8 -> 8619.2475 | G9: =G7*G8 -> 8466.6135
A11: Sum of PV of explicit CCF | C11: =SUM(C9:G9) -> 36685.496
A12: Terminal value at rho | C12: =H7/('UTCL-Cost of Capital'!$B$17-'UTCL-Assumptions'!$B$35) -> 231777
A13: PV of terminal value | C13: =C12*G8 -> 134741.22
A14: Enterprise value of operations | C14: =C11+C13 -> 171426.72
A15: Equity value | C15: =C14+'UTCL-Assumptions'!$B$39+'UTCL-Assumptions'!$B$45-'UTCL-Assumptions'!$B$46-'UTCL-Assumptions'!$B$47-'UTCL-Assumptions'!$B$58 -> 151706.59
A16: Value per share (Rs) | C16: =C15/'UTCL-Assumptions'!$B$5 -> 5148.1806

Sheet UTCL-APV valuation
A1: Line item | B1: Unit | C1: FY2026-27 | D1: FY2027-28 | E1: FY2028-29 | F1: FY2029-30 | G1: FY2030-31 | H1: Terminal
A2: FCFF (unlevered cash flow) | B2: Rs cr | C2: ='UTCL-P&L'!C24 -> 4394.43 | D2: ='UTCL-P&L'!D24 -> 8819.8638 | E2: ='UTCL-P&L'!E24 -> 11058.995 | F2: ='UTCL-P&L'!F24 -> 13034.177 | G2: ='UTCL-P&L'!G24 -> 14282.131 | H2: ='UTCL-FCFF valuation'!H2 -> 10052.591
A3: Discount factor at rho | B3: Rs cr | C3: =1/(1+'UTCL-Cost of Capital'!$B$17)^1 -> 0.89719332 | D3: =1/(1+'UTCL-Cost of Capital'!$B$17)^2 -> 0.80495584 | E3: =1/(1+'UTCL-Cost of Capital'!$B$17)^3 -> 0.722201 | F3: =1/(1+'UTCL-Cost of Capital'!$B$17)^4 -> 0.64795391 | G3: =1/(1+'UTCL-Cost of Capital'!$B$17)^5 -> 0.58133992
A4: PV of FCFF at rho | B4: Rs cr | C4: =C2*C3 -> 3942.6532 | D4: =D2*D3 -> 7099.6009 | E4: =E2*E3 -> 7986.8175 | F4: =F2*F3 -> 8445.546 | G4: =G2*G3 -> 8302.7731
A5: Interest tax shield | B5: Rs cr | C5: ='UTCL-CCF valuation'!C6 -> 218.59826 | D5: ='UTCL-CCF valuation'!D6 -> 237.76438 | E5: ='UTCL-CCF valuation'!E6 -> 253.45906 | F5: ='UTCL-CCF valuation'!F6 -> 268.07687 | G5: ='UTCL-CCF valuation'!G6 -> 281.83235 | H5: ='UTCL-CCF valuation'!H6 -> 295.55514
A6: PV of tax shield at rho | B6: Rs cr | C6: =C5*C3 -> 196.12489 | D6: =D5*D3 -> 191.38982 | E6: =E5*E3 -> 183.04839 | F6: =F5*F3 -> 173.70146 | G6: =G5*G3 -> 163.8404
A8: Sum of PV of explicit FCFF | C8: =SUM(C4:G4) -> 35777.391
A9: Terminal unlevered value | C9: =H2/('UTCL-Cost of Capital'!$B$17-'UTCL-Assumptions'!$B$35) -> 225157.17
A10: Unlevered enterprise value (Vu) | C10: =C8+C9*G3 -> 166670.24
A11: Sum of PV of explicit tax shields | C11: =SUM(C6:G6) -> 908.10496
A12: Terminal value of tax shield | C12: =H5/('UTCL-Cost of Capital'!$B$17-'UTCL-Assumptions'!$B$35) -> 6619.8217
A13: PV of interest tax shield | C13: =C11+C12*G3 -> 4756.4716
A14: Enterprise value of operations | C14: =C10+C13 -> 171426.72
A15: Equity value | C15: =C14+'UTCL-Assumptions'!$B$39+'UTCL-Assumptions'!$B$45-'UTCL-Assumptions'!$B$46-'UTCL-Assumptions'!$B$47-'UTCL-Assumptions'!$B$58 -> 151706.59
A16: Value per share (Rs) | C16: =C15/'UTCL-Assumptions'!$B$5 -> 5148.1806
A18: The tax shield is worth only a small fraction of enterprise value here because UltraTech carries very little debt relative to its size. That is a finding, not a rounding error: the company is not using leverage to create value.

Sheet UTCL-FCFE valuation
A1: Line item | B1: Unit | C1: FY2026-27 | D1: FY2027-28 | E1: FY2028-29 | F1: FY2029-30 | G1: FY2030-31
A2: FCFF | B2: Rs cr | C2: ='UTCL-P&L'!C24 -> 4394.43 | D2: ='UTCL-P&L'!D24 -> 8819.8638 | E2: ='UTCL-P&L'!E24 -> 11058.995 | F2: ='UTCL-P&L'!F24 -> 13034.177 | G2: ='UTCL-P&L'!G24 -> 14282.131
A3: Less: Interest after tax | B3: Rs cr | C3: =-'UTCL-CCF valuation'!C5*(1-'UTCL-Cost of Capital'!$B$13) -> -649.95807 | D3: =-'UTCL-CCF valuation'!D5*(1-'UTCL-Cost of Capital'!$B$13) -> -706.94468 | E3: =-'UTCL-CCF valuation'!E5*(1-'UTCL-Cost of Capital'!$B$13) -> -753.60968 | F3: =-'UTCL-CCF valuation'!F5*(1-'UTCL-Cost of Capital'!$B$13) -> -797.0728 | G3: =-'UTCL-CCF valuation'!G5*(1-'UTCL-Cost of Capital'!$B$13) -> -837.97197
A4: Add: Net new borrowing | B4: Rs cr | C4: ='UTCL-CCF valuation'!C2*'UTCL-Cost of Capital'!$B$14-'UTCL-CCF valuation'!C4 -> 913.10234 | D4: ='UTCL-CCF valuation'!D2*'UTCL-Cost of Capital'!$B$14-'UTCL-CCF valuation'!D4 -> 747.7181 | E4: ='UTCL-CCF valuation'!E2*'UTCL-Cost of Capital'!$B$14-'UTCL-CCF valuation'!E4 -> 696.41392 | F4: ='UTCL-CCF valuation'!F2*'UTCL-Cost of Capital'!$B$14-'UTCL-CCF valuation'!F4 -> 655.33158 | G4: ='UTCL-CCF valuation'!G2*'UTCL-Cost of Capital'!$B$14-'UTCL-CCF valuation'!G4 -> 653.77393
A5: FCFE | B5: Rs cr | C5: =SUM(C2:C4) -> 4657.5743 | D5: =SUM(D2:D4) -> 8860.6372 | E5: =SUM(E2:E4) -> 11001.8 | F5: =SUM(F2:F4) -> 12892.436 | G5: =SUM(G2:G4) -> 14097.933
A6: Discount factor at Ke | B6: Rs cr | C6: =1/(1+'UTCL-Cost of Capital'!$B$11)^1 -> 0.8955725 | D6: =1/(1+'UTCL-Cost of Capital'!$B$11)^2 -> 0.80205011 | E6: =1/(1+'UTCL-Cost of Capital'!$B$11)^3 -> 0.71829402 | F6: =1/(1+'UTCL-Cost of Capital'!$B$11)^4 -> 0.64328437 | G6: =1/(1+'UTCL-Cost of Capital'!$B$11)^5 -> 0.5761078
A7: PV of FCFE | B7: Rs cr | C7: =C5*C6 -> 4171.1954 | D7: =D5*D6 -> 7106.675 | E7: =E5*E6 -> 7902.5268 | F7: =F5*F6 -> 8293.5025 | G7: =G5*G6 -> 8121.9293
A9: Sum of PV of explicit FCFE | C9: =SUM(C7:G7) -> 35595.829
A10: Terminal equity value at FY2030-31 | C10: ='UTCL-FCFF valuation'!C7*(1-'UTCL-Cost of Capital'!$B$14) -> 217696.31
A11: PV of terminal equity value | C11: =C10*G6 -> 125416.54
A12: Equity value of operations | C12: =C9+C11 -> 161012.37
A13: Add: Liquid investments | C13: ='UTCL-Assumptions'!$B$39 -> 1384.35
A14: Add: Investments in subsidiaries and others | C14: ='UTCL-Assumptions'!$B$45 -> 6739.51
A15: Less: Debt in excess of the target level | C15: =-('UTCL-Assumptions'!$B$46+'UTCL-Assumptions'!$B$47-'UTCL-CCF valuation'!C4) -> -13340.746
A16: Equity value | C16: =SUM(C12:C15)-'UTCL-Assumptions'!$B$58 -> 151706.59
A17: Value per share (Rs) | C17: =C16/'UTCL-Assumptions'!$B$5 -> 5148.1806
A19: FCFE is built on the target debt schedule, not on the actual book debt. The difference between the two is removed on the line above so that FCFE reconciles to the other four methods. If you prefer to model actual debt, the constant leverage assumption must be dropped and the tax shield rediscounted at Kd.

Sheet UTCL-EVA
A1: Line item | B1: Unit | C1: FY2026-27 | D1: FY2027-28 | E1: FY2028-29 | F1: FY2029-30 | G1: FY2030-31 | H1: Terminal
A2: NOPAT | B2: Rs cr | C2: ='UTCL-Balance Sheet'!C8 -> 11013.642 | D2: ='UTCL-Balance Sheet'!D8 -> 12704.166 | E2: ='UTCL-Balance Sheet'!E8 -> 14250.233 | F2: ='UTCL-Balance Sheet'!F8 -> 15594.959 | G2: ='UTCL-Balance Sheet'!G8 -> 16748.278 | H2: ='UTCL-Balance Sheet'!C14 -> 17919.653
A3: Opening invested capital | B3: Rs cr | C3: ='UTCL-Balance Sheet'!C2 -> 93761.33 | D3: ='UTCL-Balance Sheet'!D2 -> 100380.54 | E3: ='UTCL-Balance Sheet'!E2 -> 104264.84 | F3: ='UTCL-Balance Sheet'!F2 -> 107456.08 | G3: ='UTCL-Balance Sheet'!G2 -> 110016.86 | H3: =IF('UTCL-Assumptions'!$B$65=1,'UTCL-Balance Sheet'!C32,'UTCL-Balance Sheet'!C15) -> 112483.01
A4: Capital charge (WACC x opening IC) | B4: Rs cr | C4: =C3*'UTCL-Cost of Capital'!$B$16 -> 10624.267 | D4: =D3*'UTCL-Cost of Capital'!$B$16 -> 11374.302 | E4: =E3*'UTCL-Cost of Capital'!$B$16 -> 11814.44 | F4: =F3*'UTCL-Cost of Capital'!$B$16 -> 12176.045 | G4: =G3*'UTCL-Cost of Capital'!$B$16 -> 12466.211 | H4: =H3*'UTCL-Cost of Capital'!$B$16 -> 12745.655
A5: Economic value added | B5: Rs cr | C5: =C2-C4 -> 389.37457 | D5: =D2-D4 -> 1329.8635 | E5: =E2-E4 -> 2435.7935 | F5: =F2-F4 -> 3418.9144 | G5: =G2-G4 -> 4282.0667 | H5: =H2-H4 -> 5173.9977
A6: Discount factor at WACC | B6: Rs cr | C6: =1/(1+'UTCL-Cost of Capital'!$B$16)^1 -> 0.89822095 | D6: =1/(1+'UTCL-Cost of Capital'!$B$16)^2 -> 0.80680087 | E6: =1/(1+'UTCL-Cost of Capital'!$B$16)^3 -> 0.72468544 | F6: =1/(1+'UTCL-Cost of Capital'!$B$16)^4 -> 0.65092764 | G6: =1/(1+'UTCL-Cost of Capital'!$B$16)^5 -> 0.58467684
A7: PV of EVA | B7: Rs cr | C7: =C5*C6 -> 349.7444 | D7: =D5*D6 -> 1072.935 | E7: =E5*E6 -> 1765.1841 | F7: =F5*F6 -> 2225.4659 | G7: =G5*G6 -> 2503.6252
A9: Opening invested capital at valuation date | C9: =C3 -> 93761.33
A10: Sum of PV of explicit EVA | C10: =SUM(C7:G7) -> 7916.9546
A11: Terminal value of EVA | C11: =H5/('UTCL-Cost of Capital'!$B$16-'UTCL-Assumptions'!$B$35) -> 119293.99
A12: PV of terminal EVA | C12: =C11*G6 -> 69748.431
A13: Enterprise value of operations | C13: =C9+C10+C12 -> 171426.72
A14: Equity value | C14: =C13+'UTCL-Assumptions'!$B$39+'UTCL-Assumptions'!$B$45-'UTCL-Assumptions'!$B$46-'UTCL-Assumptions'!$B$47-'UTCL-Assumptions'!$B$58 -> 151706.59
A15: Value per share (Rs) | C15: =C14/'UTCL-Assumptions'!$B$5 -> 5148.1806
A17: EVA reconciles to FCFF only because FCFF was defined as NOPAT less the change in invested capital, and because the terminal year is a true steady state. Both conditions are necessary.

Sheet UTCL-Reconciliation
A1: Reconciliation of the five valuation methods
A2: All five must return the same enterprise and equity value. Any difference is an error, not a modelling choice.
A4: Method | B4: Discount rate | C4: Enterprise value | D4: Value per share | E4: Difference vs FCFF
A5: FCFF | B5: WACC | C5: ='UTCL-FCFF valuation'!C9 -> 171426.72 | D5: ='UTCL-FCFF valuation'!C15 -> 5148.1806 | E5: =IFERROR(D5-D5,"") -> 0
A6: CCF | B6: rho | C6: ='UTCL-CCF valuation'!C14 -> 171426.72 | D6: ='UTCL-CCF valuation'!C16 -> 5148.1806 | E6: =IFERROR(D6-D5,"") -> 0
A7: APV | B7: rho | C7: ='UTCL-APV valuation'!C14 -> 171426.72 | D7: ='UTCL-APV valuation'!C16 -> 5148.1806 | E7: =IFERROR(D7-D5,"") -> 0
A8: EVA | B8: WACC | C8: ='UTCL-EVA'!C13 -> 171426.72 | D8: ='UTCL-EVA'!C15 -> 5148.1806 | E8: =IFERROR(D8-D5,"") -> 0
A9: FCFE | B9: Ke | C9: equity method | D9: ='UTCL-FCFE valuation'!C17 -> 5148.1806 | E9: =IFERROR(D9-D5,"") -> 0
A11: Maximum absolute difference | D11: =MAX(ABS(E5),ABS(E6),ABS(E7),ABS(E8),ABS(E9)) -> 0
A12: Status | D12: =IF(D11<0.01,"RECONCILED","DOES NOT RECONCILE") -> RECONCILED
A14: The five methods agreeing is not a coincidence to be admired, it is the minimum standard: they are the same model rearranged. Agreement proves internal consistency. It says nothing about whether the assumptions are right.

Sheet UTCL-Terminal
A1: Terminal value: Gordon and exit multiple cross check
A3: Growth decomposition, built multiplicatively
A4: Long run real GDP growth | B4: ='UTCL-Assumptions'!B31 -> 0.065 | D4: Owned assumption.
A5: Long run inflation | B5: ='UTCL-Assumptions'!B32 -> 0.04 | D5: RBI CPI target.
A6: Nominal GDP growth | B6: ='UTCL-Assumptions'!B33 -> 0.1076 | D6: (1+real)(1+inflation)-1, NOT real plus inflation.
A7: Terminal g as a fraction of nominal GDP | B7: ='UTCL-Assumptions'!B34 -> 0.65 | D7: The editable driver.
A8: Terminal growth rate | B8: ='UTCL-Assumptions'!B35 -> 0.06994 | D8: Derived, not typed.
A10: Method A: Gordon growth on a steady state terminal year
A11: NOPAT in the terminal year | B11: ='UTCL-Balance Sheet'!C14 -> 17919.653
A12: Closing invested capital | B12: ='UTCL-Balance Sheet'!C15 -> 112483.01
A13: Reinvestment = g x invested capital | B13: ='UTCL-Balance Sheet'!C16 -> 7867.0617
A14: Terminal FCFF | B14: ='UTCL-Balance Sheet'!C17 -> 10052.591
A15: Implied terminal ROIC | B15: ='UTCL-Balance Sheet'!C18 -> 0.15930986
A16: Implied reinvestment rate | B16: ='UTCL-Balance Sheet'!C19 -> 0.43901865
A17: Terminal value, Gordon | B17: ='UTCL-FCFF valuation'!C7 -> 231777
A19: Method B: exit multiple cross check
A20: Implied exit EV/EBITDA from Method A | B20: ='UTCL-FCFF valuation'!C17 -> 7.6887195
A21: Peer median EV/EBITDA | B21: 19.05
A22: Terminal growth the peer multiple would require | B22: 0.0978
A24: MULTIPLIER CONSISTENCY: the two methods do NOT bracket each other. Method A implies about 6.4x against a peer median of 19.05x. Solving the peer multiple back for growth gives 9.8% in perpetuity against nominal GDP of 10.76%, so the peer multiple requires growth at roughly 91% of the whole economy forever. We take the position that the peer multiple is the implausible end and hedge by weighting a 10.0x exit case at half the target price in the report. Recorded as a PARTIAL on the Dashboard rather than smoothed over.
A27: MULTIPLIER CONSISTENCY: is the implied multiple an outcome of our own fundamentals?
A28: The test is NOT whether our multiple equals the peer multiple. It is whether the multiple our model implies is arithmetically consistent with the growth, return on capital and discount rate the model itself uses. A multiple is an OUTCOME of those three, never an input. If the two agree, the model is internally consistent and the multiple can be reported as a result.
A31: Terminal NOPAT divided by terminal EBITDA | B31: ='UTCL-Balance Sheet'!C14/('UTCL-P&L'!G15*(1+'UTCL-Assumptions'!$B$35)) -> 0.59444719
A32: Terminal ROIC | B32: ='UTCL-Balance Sheet'!C31 -> 0.11831182
A33: Terminal growth rate g | B33: ='UTCL-Assumptions'!$B$35 -> 0.06994
A34: Reinvestment rate = g / ROIC | B34: =B33/B32 -> 0.59114971
A35: WACC | B35: ='UTCL-Cost of Capital'!$B$16 -> 0.11331182
A36: JUSTIFIED EV/EBITDA = (NOPAT/EBITDA)(1 - g/ROIC)/(WACC - g) | B36: =B31*(1-B34)/(B35-B33) -> 5.6036359
A37: Model implied exit EV/EBITDA | B37: ='UTCL-FCFF valuation'!C17 -> 7.6887195
A38: Difference | B38: =B36-B37 -> -2.0850836
A39: VERDICT | B39: =IF(ABS(B38)<0.25,"PASS: the multiple is consistent with our own fundamentals","REVIEW") -> REVIEW
A41: On this test the model PASSES. The separate observation that the PEER multiple of about 19x implies perpetual growth above nominal GDP is a finding about the peer set, reported in the relative valuation section, not a failure of internal consistency in this model. Conflating the two would require us to adopt a multiple we have shown to be arithmetically impossible.

Sheet UTCL-Sensitivity
A1: Sensitivity
A3: Beta sensitivity. Bottom up beta is 0.9436; Damodaran unlevered range across building materials and construction supplies is 0.84 to 0.92
A4: Beta | B4: Cost of equity | C4: WACC
A5: 0.6 | B5: ='UTCL-Cost of Capital'!$B$5+A5*'UTCL-Cost of Capital'!$B$6 -> 0.09228 | C5: =(1-'UTCL-Cost of Capital'!$B$14)*B5+'UTCL-Cost of Capital'!$B$14*'UTCL-Cost of Capital'!$B$12*(1-'UTCL-Cost of Capital'!$B$13) -> 0.090465361
A6: 0.7 | B6: ='UTCL-Cost of Capital'!$B$5+A6*'UTCL-Cost of Capital'!$B$6 -> 0.09936 | C6: =(1-'UTCL-Cost of Capital'!$B$14)*B6+'UTCL-Cost of Capital'!$B$14*'UTCL-Cost of Capital'!$B$12*(1-'UTCL-Cost of Capital'!$B$13) -> 0.097115244
A7: 0.8 | B7: ='UTCL-Cost of Capital'!$B$5+A7*'UTCL-Cost of Capital'!$B$6 -> 0.10644 | C7: =(1-'UTCL-Cost of Capital'!$B$14)*B7+'UTCL-Cost of Capital'!$B$14*'UTCL-Cost of Capital'!$B$12*(1-'UTCL-Cost of Capital'!$B$13) -> 0.10376513
A8: 0.9 | B8: ='UTCL-Cost of Capital'!$B$5+A8*'UTCL-Cost of Capital'!$B$6 -> 0.11352 | C8: =(1-'UTCL-Cost of Capital'!$B$14)*B8+'UTCL-Cost of Capital'!$B$14*'UTCL-Cost of Capital'!$B$12*(1-'UTCL-Cost of Capital'!$B$13) -> 0.11041501
A9: 1 | B9: ='UTCL-Cost of Capital'!$B$5+A9*'UTCL-Cost of Capital'!$B$6 -> 0.1206 | C9: =(1-'UTCL-Cost of Capital'!$B$14)*B9+'UTCL-Cost of Capital'!$B$14*'UTCL-Cost of Capital'!$B$12*(1-'UTCL-Cost of Capital'!$B$13) -> 0.11706489
A10: 1.1 | B10: ='UTCL-Cost of Capital'!$B$5+A10*'UTCL-Cost of Capital'!$B$6 -> 0.12768 | C10: =(1-'UTCL-Cost of Capital'!$B$14)*B10+'UTCL-Cost of Capital'!$B$14*'UTCL-Cost of Capital'!$B$12*(1-'UTCL-Cost of Capital'!$B$13) -> 0.12371478
A11: 1.2 | B11: ='UTCL-Cost of Capital'!$B$5+A11*'UTCL-Cost of Capital'!$B$6 -> 0.13476 | C11: =(1-'UTCL-Cost of Capital'!$B$14)*B11+'UTCL-Cost of Capital'!$B$14*'UTCL-Cost of Capital'!$B$12*(1-'UTCL-Cost of Capital'!$B$13) -> 0.13036466
A13: To read the value impact, change the beta cell on the Assumptions sheet and watch the Summary. A one point move in beta changes the cost of equity by six hundred basis points here, which moves the answer by roughly a third. Until beta is settled from real price history, treat the output as a band and not as a point estimate.
A15: Scenario comparison. Change the yellow cells on Assumptions to reproduce each column.
A16: Driver | B16: Conservative | C16: Base (this model) | D16: Sell side view
A17: Utilisation, FY27 to FY31 | B17: 81.0% to 84.0% | C17: 82.0% to 86.0% | D17: 83.0% to 88.5%
A18: EBITDA per tonne growth | B18: 5,4,3,2,2% | C18: 8,6,4,3,2.5% | D18: 12.4,13.6,3,2,2%
A19: EBITDA per tonne by FY2030-31 | B19: Rs 1,284 | C19: Rs 1,379 | D19: Rs 1,501
A20: Capacity by FY2030-31 | B20: 220 Mn.T | C20: 220 Mn.T | D20: 241 Mn.T
A21: Capex per year | B21: 9,500 to 8,500 | C21: 9,500 to 8,500 | D21: 10,000 to 11,500
A22: Terminal ROIC | B22: 13.6% | C22: 15.5% | D22: 18.3%
A23: VALUE PER SHARE | B23: Rs 3,922 | C23: Rs 4,748 | D23: Rs 6,280
A24: Gap to market price of Rs 10,745 | B24: minus 63% | C24: minus 56% | D24: minus 42%
A26: The sell side column reproduces a broker BUY note of October 2025 carrying a target of Rs 15,000. Two things about it. First, that target is not a discounted cash flow at all: it is 19 times EV/EBITDA applied to the average of two forecast years, so it assumes the multiple rather than testing it. Second, the stock fell from Rs 12,370 at the date of that note to Rs 10,745 by 30 March 2026, so the market did not validate the call. Their FACTS are used here (capacity schedule, utilisation, capex guidance, and the split showing core assets at Rs 966 per tonne against India Cements at Rs 386 and Kesoram at Rs 755). Their FORECAST is not. Even on their own operating assumptions the discounted cash flow lands 42% below the traded price.
A32: WACC against terminal growth: LIVE two way table, value per share in Rs
A33: WACC \ terminal g | B33: 4.0% | C33: 4.5% | D33: 5.0% | E33: 5.5% | F33: 6.0% | G33: 6.5%
A34: 0.09 | B34: =IF($A34<=0.04,"",(('UTCL-P&L'!C17/(1+$A34)^1+'UTCL-P&L'!D17/(1+$A34)^2+'UTCL-P&L'!E17/(1+$A34)^3+'UTCL-P&L'!F17/(1+$A34)^4+'UTCL-P&L'!G17/(1+$A34)^5+(('UTCL-P&L'!G14*(1+0.04))-0.04*'UTCL-Balance Sheet'!G6)/($A34-0.04)/(1+$A34)^5)+'UTCL-Assumptions'!$B$39+'UTCL-Assumptions'!$B$45-'UTCL-Assumptions'!$B$46-'UTCL-Assumptions'!$B$47)/'UTCL-Assumptions'!$B$5) -> 58812.891 | C34: =IF($A34<=0.045,"",(('UTCL-P&L'!C17/(1+$A34)^1+'UTCL-P&L'!D17/(1+$A34)^2+'UTCL-P&L'!E17/(1+$A34)^3+'UTCL-P&L'!F17/(1+$A34)^4+'UTCL-P&L'!G17/(1+$A34)^5+(('UTCL-P&L'!G14*(1+0.045))-0.045*'UTCL-Balance Sheet'!G6)/($A34-0.045)/(1+$A34)^5)+'UTCL-Assumptions'!$B$39+'UTCL-Assumptions'!$B$45-'UTCL-Assumptions'!$B$46-'UTCL-Assumptions'!$B$47)/'UTCL-Assumptions'!$B$5) -> 65375.432 | D34: =IF($A34<=0.05,"",(('UTCL-P&L'!C17/(1+$A34)^1+'UTCL-P&L'!D17/(1+$A34)^2+'UTCL-P&L'!E17/(1+$A34)^3+'UTCL-P&L'!F17/(1+$A34)^4+'UTCL-P&L'!G17/(1+$A34)^5+(('UTCL-P&L'!G14*(1+0.05))-0.05*'UTCL-Balance Sheet'!G6)/($A34-0.05)/(1+$A34)^5)+'UTCL-Assumptions'!$B$39+'UTCL-Assumptions'!$B$45-'UTCL-Assumptions'!$B$46-'UTCL-Assumptions'!$B$47)/'UTCL-Assumptions'!$B$5) -> 73578.608 | E34: =IF($A34<=0.055,"",(('UTCL-P&L'!C17/(1+$A34)^1+'UTCL-P&L'!D17/(1+$A34)^2+'UTCL-P&L'!E17/(1+$A34)^3+'UTCL-P&L'!F17/(1+$A34)^4+'UTCL-P&L'!G17/(1+$A34)^5+(('UTCL-P&L'!G14*(1+0.055))-0.055*'UTCL-Balance Sheet'!G6)/($A34-0.055)/(1+$A34)^5)+'UTCL-Assumptions'!$B$39+'UTCL-Assumptions'!$B$45-'UTCL-Assumptions'!$B$46-'UTCL-Assumptions'!$B$47)/'UTCL-Assumptions'!$B$5) -> 84125.549 | F34: =IF($A34<=0.06,"",(('UTCL-P&L'!C17/(1+$A34)^1+'UTCL-P&L'!D17/(1+$A34)^2+'UTCL-P&L'!E17/(1+$A34)^3+'UTCL-P&L'!F17/(1+$A34)^4+'UTCL-P&L'!G17/(1+$A34)^5+(('UTCL-P&L'!G14*(1+0.06))-0.06*'UTCL-Balance Sheet'!G6)/($A34-0.06)/(1+$A34)^5)+'UTCL-Assumptions'!$B$39+'UTCL-Assumptions'!$B$45-'UTCL-Assumptions'!$B$46-'UTCL-Assumptions'!$B$47)/'UTCL-Assumptions'!$B$5) -> 98188.137 | G34: =IF($A34<=0.065,"",(('UTCL-P&L'!C17/(1+$A34)^1+'UTCL-P&L'!D17/(1+$A34)^2+'UTCL-P&L'!E17/(1+$A34)^3+'UTCL-P&L'!F17/(1+$A34)^4+'UTCL-P&L'!G17/(1+$A34)^5+(('UTCL-P&L'!G14*(1+0.065))-0.065*'UTCL-Balance Sheet'!G6)/($A34-0.065)/(1+$A34)^5)+'UTCL-Assumptions'!$B$39+'UTCL-Assumptions'!$B$45-'UTCL-Assumptions'!$B$46-'UTCL-Assumptions'!$B$47)/'UTCL-Assumptions'!$B$5) -> 117875.76
A35: 0.1 | B35: =IF($A35<=0.04,"",(('UTCL-P&L'!C17/(1+$A35)^1+'UTCL-P&L'!D17/(1+$A35)^2+'UTCL-P&L'!E17/(1+$A35)^3+'UTCL-P&L'!F17/(1+$A35)^4+'UTCL-P&L'!G17/(1+$A35)^5+(('UTCL-P&L'!G14*(1+0.04))-0.04*'UTCL-Balance Sheet'!G6)/($A35-0.04)/(1+$A35)^5)+'UTCL-Assumptions'!$B$39+'UTCL-Assumptions'!$B$45-'UTCL-Assumptions'!$B$46-'UTCL-Assumptions'!$B$47)/'UTCL-Assumptions'!$B$5) -> 46841.896 | C35: =IF($A35<=0.045,"",(('UTCL-P&L'!C17/(1+$A35)^1+'UTCL-P&L'!D17/(1+$A35)^2+'UTCL-P&L'!E17/(1+$A35)^3+'UTCL-P&L'!F17/(1+$A35)^4+'UTCL-P&L'!G17/(1+$A35)^5+(('UTCL-P&L'!G14*(1+0.045))-0.045*'UTCL-Balance Sheet'!G6)/($A35-0.045)/(1+$A35)^5)+'UTCL-Assumptions'!$B$39+'UTCL-Assumptions'!$B$45-'UTCL-Assumptions'!$B$46-'UTCL-Assumptions'!$B$47)/'UTCL-Assumptions'!$B$5) -> 51122.908 | D35: =IF($A35<=0.05,"",(('UTCL-P&L'!C17/(1+$A35)^1+'UTCL-P&L'!D17/(1+$A35)^2+'UTCL-P&L'!E17/(1+$A35)^3+'UTCL-P&L'!F17/(1+$A35)^4+'UTCL-P&L'!G17/(1+$A35)^5+(('UTCL-P&L'!G14*(1+0.05))-0.05*'UTCL-Balance Sheet'!G6)/($A35-0.05)/(1+$A35)^5)+'UTCL-Assumptions'!$B$39+'UTCL-Assumptions'!$B$45-'UTCL-Assumptions'!$B$46-'UTCL-Assumptions'!$B$47)/'UTCL-Assumptions'!$B$5) -> 56260.122 | E35: =IF($A35<=0.055,"",(('UTCL-P&L'!C17/(1+$A35)^1+'UTCL-P&L'!D17/(1+$A35)^2+'UTCL-P&L'!E17/(1+$A35)^3+'UTCL-P&L'!F17/(1+$A35)^4+'UTCL-P&L'!G17/(1+$A35)^5+(('UTCL-P&L'!G14*(1+0.055))-0.055*'UTCL-Balance Sheet'!G6)/($A35-0.055)/(1+$A35)^5)+'UTCL-Assumptions'!$B$39+'UTCL-Assumptions'!$B$45-'UTCL-Assumptions'!$B$46-'UTCL-Assumptions'!$B$47)/'UTCL-Assumptions'!$B$5) -> 62538.938 | F35: =IF($A35<=0.06,"",(('UTCL-P&L'!C17/(1+$A35)^1+'UTCL-P&L'!D17/(1+$A35)^2+'UTCL-P&L'!E17/(1+$A35)^3+'UTCL-P&L'!F17/(1+$A35)^4+'UTCL-P&L'!G17/(1+$A35)^5+(('UTCL-P&L'!G14*(1+0.06))-0.06*'UTCL-Balance Sheet'!G6)/($A35-0.06)/(1+$A35)^5)+'UTCL-Assumptions'!$B$39+'UTCL-Assumptions'!$B$45-'UTCL-Assumptions'!$B$46-'UTCL-Assumptions'!$B$47)/'UTCL-Assumptions'!$B$5) -> 70387.46 | G35: =IF($A35<=0.065,"",(('UTCL-P&L'!C17/(1+$A35)^1+'UTCL-P&L'!D17/(1+$A35)^2+'UTCL-P&L'!E17/(1+$A35)^3+'UTCL-P&L'!F17/(1+$A35)^4+'UTCL-P&L'!G17/(1+$A35)^5+(('UTCL-P&L'!G14*(1+0.065))-0.065*'UTCL-Balance Sheet'!G6)/($A35-0.065)/(1+$A35)^5)+'UTCL-Assumptions'!$B$39+'UTCL-Assumptions'!$B$45-'UTCL-Assumptions'!$B$46-'UTCL-Assumptions'!$B$47)/'UTCL-Assumptions'!$B$5) -> 80478.415
A36: 0.11 | B36: =IF($A36<=0.04,"",(('UTCL-P&L'!C17/(1+$A36)^1+'UTCL-P&L'!D17/(1+$A36)^2+'UTCL-P&L'!E17/(1+$A36)^3+'UTCL-P&L'!F17/(1+$A36)^4+'UTCL-P&L'!G17/(1+$A36)^5+(('UTCL-P&L'!G14*(1+0.04))-0.04*'UTCL-Balance Sheet'!G6)/($A36-0.04)/(1+$A36)^5)+'UTCL-Assumptions'!$B$39+'UTCL-Assumptions'!$B$45-'UTCL-Assumptions'!$B$46-'UTCL-Assumptions'!$B$47)/'UTCL-Assumptions'!$B$5) -> 38385.865 | C36: =IF($A36<=0.045,"",(('UTCL-P&L'!C17/(1+$A36)^1+'UTCL-P&L'!D17/(1+$A36)^2+'UTCL-P&L'!E17/(1+$A36)^3+'UTCL-P&L'!F17/(1+$A36)^4+'UTCL-P&L'!G17/(1+$A36)^5+(('UTCL-P&L'!G14*(1+0.045))-0.045*'UTCL-Balance Sheet'!G6)/($A36-0.045)/(1+$A36)^5)+'UTCL-Assumptions'!$B$39+'UTCL-Assumptions'!$B$45-'UTCL-Assumptions'!$B$46-'UTCL-Assumptions'!$B$47)/'UTCL-Assumptions'!$B$5) -> 41357.758 | D36: =IF($A36<=0.05,"",(('UTCL-P&L'!C17/(1+$A36)^1+'UTCL-P&L'!D17/(1+$A36)^2+'UTCL-P&L'!E17/(1+$A36)^3+'UTCL-P&L'!F17/(1+$A36)^4+'UTCL-P&L'!G17/(1+$A36)^5+(('UTCL-P&L'!G14*(1+0.05))-0.05*'UTCL-Balance Sheet'!G6)/($A36-0.05)/(1+$A36)^5)+'UTCL-Assumptions'!$B$39+'UTCL-Assumptions'!$B$45-'UTCL-Assumptions'!$B$46-'UTCL-Assumptions'!$B$47)/'UTCL-Assumptions'!$B$5) -> 44824.968 | E36: =IF($A36<=0.055,"",(('UTCL-P&L'!C17/(1+$A36)^1+'UTCL-P&L'!D17/(1+$A36)^2+'UTCL-P&L'!E17/(1+$A36)^3+'UTCL-P&L'!F17/(1+$A36)^4+'UTCL-P&L'!G17/(1+$A36)^5+(('UTCL-P&L'!G14*(1+0.055))-0.055*'UTCL-Balance Sheet'!G6)/($A36-0.055)/(1+$A36)^5)+'UTCL-Assumptions'!$B$39+'UTCL-Assumptions'!$B$45-'UTCL-Assumptions'!$B$46-'UTCL-Assumptions'!$B$47)/'UTCL-Assumptions'!$B$5) -> 48922.579 | F36: =IF($A36<=0.06,"",(('UTCL-P&L'!C17/(1+$A36)^1+'UTCL-P&L'!D17/(1+$A36)^2+'UTCL-P&L'!E17/(1+$A36)^3+'UTCL-P&L'!F17/(1+$A36)^4+'UTCL-P&L'!G17/(1+$A36)^5+(('UTCL-P&L'!G14*(1+0.06))-0.06*'UTCL-Balance Sheet'!G6)/($A36-0.06)/(1+$A36)^5)+'UTCL-Assumptions'!$B$39+'UTCL-Assumptions'!$B$45-'UTCL-Assumptions'!$B$46-'UTCL-Assumptions'!$B$47)/'UTCL-Assumptions'!$B$5) -> 53839.712 | G36: =IF($A36<=0.065,"",(('UTCL-P&L'!C17/(1+$A36)^1+'UTCL-P&L'!D17/(1+$A36)^2+'UTCL-P&L'!E17/(1+$A36)^3+'UTCL-P&L'!F17/(1+$A36)^4+'UTCL-P&L'!G17/(1+$A36)^5+(('UTCL-P&L'!G14*(1+0.065))-0.065*'UTCL-Balance Sheet'!G6)/($A36-0.065)/(1+$A36)^5)+'UTCL-Assumptions'!$B$39+'UTCL-Assumptions'!$B$45-'UTCL-Assumptions'!$B$46-'UTCL-Assumptions'!$B$47)/'UTCL-Assumptions'!$B$5) -> 59849.541
A37: 0.12 | B37: =IF($A37<=0.04,"",(('UTCL-P&L'!C17/(1+$A37)^1+'UTCL-P&L'!D17/(1+$A37)^2+'UTCL-P&L'!E17/(1+$A37)^3+'UTCL-P&L'!F17/(1+$A37)^4+'UTCL-P&L'!G17/(1+$A37)^5+(('UTCL-P&L'!G14*(1+0.04))-0.04*'UTCL-Balance Sheet'!G6)/($A37-0.04)/(1+$A37)^5)+'UTCL-Assumptions'!$B$39+'UTCL-Assumptions'!$B$45-'UTCL-Assumptions'!$B$46-'UTCL-Assumptions'!$B$47)/'UTCL-Assumptions'!$B$5) -> 32121.599 | C37: =IF($A37<=0.045,"",(('UTCL-P&L'!C17/(1+$A37)^1+'UTCL-P&L'!D17/(1+$A37)^2+'UTCL-P&L'!E17/(1+$A37)^3+'UTCL-P&L'!F17/(1+$A37)^4+'UTCL-P&L'!G17/(1+$A37)^5+(('UTCL-P&L'!G14*(1+0.045))-0.045*'UTCL-Balance Sheet'!G6)/($A37-0.045)/(1+$A37)^5)+'UTCL-Assumptions'!$B$39+'UTCL-Assumptions'!$B$45-'UTCL-Assumptions'!$B$46-'UTCL-Assumptions'!$B$47)/'UTCL-Assumptions'!$B$5) -> 34279.607 | D37: =IF($A37<=0.05,"",(('UTCL-P&L'!C17/(1+$A37)^1+'UTCL-P&L'!D17/(1+$A37)^2+'UTCL-P&L'!E17/(1+$A37)^3+'UTCL-P&L'!F17/(1+$A37)^4+'UTCL-P&L'!G17/(1+$A37)^5+(('UTCL-P&L'!G14*(1+0.05))-0.05*'UTCL-Balance Sheet'!G6)/($A37-0.05)/(1+$A37)^5)+'UTCL-Assumptions'!$B$39+'UTCL-Assumptions'!$B$45-'UTCL-Assumptions'!$B$46-'UTCL-Assumptions'!$B$47)/'UTCL-Assumptions'!$B$5) -> 36745.902 | E37: =IF($A37<=0.055,"",(('UTCL-P&L'!C17/(1+$A37)^1+'UTCL-P&L'!D17/(1+$A37)^2+'UTCL-P&L'!E17/(1+$A37)^3+'UTCL-P&L'!F17/(1+$A37)^4+'UTCL-P&L'!G17/(1+$A37)^5+(('UTCL-P&L'!G14*(1+0.055))-0.055*'UTCL-Balance Sheet'!G6)/($A37-0.055)/(1+$A37)^5)+'UTCL-Assumptions'!$B$39+'UTCL-Assumptions'!$B$45-'UTCL-Assumptions'!$B$46-'UTCL-Assumptions'!$B$47)/'UTCL-Assumptions'!$B$5) -> 39591.626 | F37: =IF($A37<=0.06,"",(('UTCL-P&L'!C17/(1+$A37)^1+'UTCL-P&L'!D17/(1+$A37)^2+'UTCL-P&L'!E17/(1+$A37)^3+'UTCL-P&L'!F17/(1+$A37)^4+'UTCL-P&L'!G17/(1+$A37)^5+(('UTCL-P&L'!G14*(1+0.06))-0.06*'UTCL-Balance Sheet'!G6)/($A37-0.06)/(1+$A37)^5)+'UTCL-Assumptions'!$B$39+'UTCL-Assumptions'!$B$45-'UTCL-Assumptions'!$B$46-'UTCL-Assumptions'!$B$47)/'UTCL-Assumptions'!$B$5) -> 42911.639 | G37: =IF($A37<=0.065,"",(('UTCL-P&L'!C17/(1+$A37)^1+'UTCL-P&L'!D17/(1+$A37)^2+'UTCL-P&L'!E17/(1+$A37)^3+'UTCL-P&L'!F17/(1+$A37)^4+'UTCL-P&L'!G17/(1+$A37)^5+(('UTCL-P&L'!G14*(1+0.065))-0.065*'UTCL-Balance Sheet'!G6)/($A37-0.065)/(1+$A37)^5)+'UTCL-Assumptions'!$B$39+'UTCL-Assumptions'!$B$45-'UTCL-Assumptions'!$B$46-'UTCL-Assumptions'!$B$47)/'UTCL-Assumptions'!$B$5) -> 46835.29
A38: 0.13 | B38: =IF($A38<=0.04,"",(('UTCL-P&L'!C17/(1+$A38)^1+'UTCL-P&L'!D17/(1+$A38)^2+'UTCL-P&L'!E17/(1+$A38)^3+'UTCL-P&L'!F17/(1+$A38)^4+'UTCL-P&L'!G17/(1+$A38)^5+(('UTCL-P&L'!G14*(1+0.04))-0.04*'UTCL-Balance Sheet'!G6)/($A38-0.04)/(1+$A38)^5)+'UTCL-Assumptions'!$B$39+'UTCL-Assumptions'!$B$45-'UTCL-Assumptions'!$B$46-'UTCL-Assumptions'!$B$47)/'UTCL-Assumptions'!$B$5) -> 27314.303 | C38: =IF($A38<=0.045,"",(('UTCL-P&L'!C17/(1+$A38)^1+'UTCL-P&L'!D17/(1+$A38)^2+'UTCL-P&L'!E17/(1+$A38)^3+'UTCL-P&L'!F17/(1+$A38)^4+'UTCL-P&L'!G17/(1+$A38)^5+(('UTCL-P&L'!G14*(1+0.045))-0.045*'UTCL-Balance Sheet'!G6)/($A38-0.045)/(1+$A38)^5)+'UTCL-Assumptions'!$B$39+'UTCL-Assumptions'!$B$45-'UTCL-Assumptions'!$B$46-'UTCL-Assumptions'!$B$47)/'UTCL-Assumptions'!$B$5) -> 28935.645 | D38: =IF($A38<=0.05,"",(('UTCL-P&L'!C17/(1+$A38)^1+'UTCL-P&L'!D17/(1+$A38)^2+'UTCL-P&L'!E17/(1+$A38)^3+'UTCL-P&L'!F17/(1+$A38)^4+'UTCL-P&L'!G17/(1+$A38)^5+(('UTCL-P&L'!G14*(1+0.05))-0.05*'UTCL-Balance Sheet'!G6)/($A38-0.05)/(1+$A38)^5)+'UTCL-Assumptions'!$B$39+'UTCL-Assumptions'!$B$45-'UTCL-Assumptions'!$B$46-'UTCL-Assumptions'!$B$47)/'UTCL-Assumptions'!$B$5) -> 30759.655 | E38: =IF($A38<=0.055,"",(('UTCL-P&L'!C17/(1+$A38)^1+'UTCL-P&L'!D17/(1+$A38)^2+'UTCL-P&L'!E17/(1+$A38)^3+'UTCL-P&L'!F17/(1+$A38)^4+'UTCL-P&L'!G17/(1+$A38)^5+(('UTCL-P&L'!G14*(1+0.055))-0.055*'UTCL-Balance Sheet'!G6)/($A38-0.055)/(1+$A38)^5)+'UTCL-Assumptions'!$B$39+'UTCL-Assumptions'!$B$45-'UTCL-Assumptions'!$B$46-'UTCL-Assumptions'!$B$47)/'UTCL-Assumptions'!$B$5) -> 32826.867 | F38: =IF($A38<=0.06,"",(('UTCL-P&L'!C17/(1+$A38)^1+'UTCL-P&L'!D17/(1+$A38)^2+'UTCL-P&L'!E17/(1+$A38)^3+'UTCL-P&L'!F17/(1+$A38)^4+'UTCL-P&L'!G17/(1+$A38)^5+(('UTCL-P&L'!G14*(1+0.06))-0.06*'UTCL-Balance Sheet'!G6)/($A38-0.06)/(1+$A38)^5)+'UTCL-Assumptions'!$B$39+'UTCL-Assumptions'!$B$45-'UTCL-Assumptions'!$B$46-'UTCL-Assumptions'!$B$47)/'UTCL-Assumptions'!$B$5) -> 35189.394 | G38: =IF($A38<=0.065,"",(('UTCL-P&L'!C17/(1+$A38)^1+'UTCL-P&L'!D17/(1+$A38)^2+'UTCL-P&L'!E17/(1+$A38)^3+'UTCL-P&L'!F17/(1+$A38)^4+'UTCL-P&L'!G17/(1+$A38)^5+(('UTCL-P&L'!G14*(1+0.065))-0.065*'UTCL-Balance Sheet'!G6)/($A38-0.065)/(1+$A38)^5)+'UTCL-Assumptions'!$B$39+'UTCL-Assumptions'!$B$45-'UTCL-Assumptions'!$B$46-'UTCL-Assumptions'!$B$47)/'UTCL-Assumptions'!$B$5) -> 37915.387
A40: Fully live: these cells recompute from the forecast FCFs and the steady state terminal formula, they are not pasted values. The shaded cell is the base case. Market price is Rs 10,745. No combination of a defensible WACC and a terminal growth rate below WACC reaches it, which is the point of showing the whole grid rather than one number.

Sheet UTCL-Relative Valuation
A1: Relative Valuation: UltraTech Cement
A2: Peer multiples are an OUTCOME to check the DCF against, never the thing that sets the value. Read this sheet after the DCF, not before.
A4: Line item | B4: Unit | C4: UltraTech | D4: Ambuja | E4: Shree | F4: JK | G4: Ramco
C5: SUBJECT | D5: Peer | E5: Peer | F5: Peer | G5: Peer
A6: Market capitalisation | B6: Rs cr | C6: 316633 | D6: 99095 | E6: 83058 | F6: 39252 | G6: 21939
A7: Net debt | B7: Rs cr | C7: 16443.97 | D7: -92.67 | E7: -6157.3 | F7: 5717.1 | G7: 3644.32
A8: Non-controlling interest | B8: Rs cr | C8: 0 | D8: 12498.92 | E8: 0 | F8: 0 | G8: 0
A9: EBITDA | B9: Rs cr | C9: 15816.65 | D9: 6558.99 | E9: 4036.63 | F9: 2283.94 | G9: 1347.74
A10: Revenue | B10: Rs cr | C10: 86069.88 | D10: 40446.04 | E10: 19985.22 | F10: 13621.38 | G10: 9211.41
A11: Normalised PAT | B11: Rs cr | C11: 7761.6 | D11: 2259.74 | E11: 1533.67 | F11: 1096.29 | G11: 178.45
A12: Net worth | B12: Rs cr | C12: 74663.37 | D12: 59347.32 | E12: 22511.6 | F12: 6960.68 | G12: 8142.37
A13: Diluted shares (crore) | B13: cr | C13: 29.468 | D13: 247.18 | E13: 3.608 | F13: 7.727 | G13: 23.63
A14: Basis of accounts | C14: Standalone TTM to Jun-26 | D14: CONSOLIDATED FY2025-26 | E14: Standalone TTM to Jun-26 | F14: Standalone TTM to Jun-26 | G14: Standalone TTM to Jun-26
A15: Enterprise value | C15: =C6+C8+C7 -> 333076.97 | D15: =D6+D8+D7 -> 111501.25 | E15: =E6+E8+E7 -> 76900.7 | F15: =F6+F8+F7 -> 44969.1 | G15: =G6+G8+G7 -> 25583.32
A17: Multiples
A18: EV/EBITDA | C18: =C15/C9 -> 21.058629 | D18: =D15/D9 -> 16.999759 | E18: =E15/E9 -> 19.050718 | F18: =F15/F9 -> 19.689265 | G18: =G15/G9 -> 18.982385
A19: EV/Sales | C19: =C15/C10 -> 3.8698436 | D19: =D15/D10 -> 2.7567903 | E19: =E15/E10 -> 3.8478786 | F19: =F15/F10 -> 3.3013615 | G19: =G15/G10 -> 2.7773511
A20: P/E (normalised) | C20: =C6/C11 -> 40.79481 | D20: =D6/D11 -> 43.85239 | E20: =E6/E11 -> 54.15637 | F20: =F6/F11 -> 35.804395 | G20: =G6/G11 -> 122.942
A21: P/B | C21: =C6/C12 -> 4.2408078 | D21: =D6/D12 -> 1.6697468 | E21: =E6/E12 -> 3.6895645 | F21: =F6/F12 -> 5.6391042 | G21: =G6/G12 -> 2.6944244
A22: ROE | C22: =C11/C12 -> 0.10395459 | D22: =D11/D12 -> 0.03807653 | E22: =E11/E12 -> 0.068127987 | F22: =F11/F12 -> 0.15749754 | G22: =G11/G12 -> 0.021916223
A23: Revenue growth | C23: 0.047 | D23: 0 | E23: 0.035 | F23: 0.052 | G23: 0.022
A25: Peer statistics (peers only, subject excluded)
A26: Multiple | C26: Min | D26: P25 | E26: Median | F26: P75 | G26: Max | H26: Mcap weighted
A27: EV/EBITDA | C27: =MIN(D18:G18) -> 16.999759 | D27: =QUARTILE(D18:G18,1) -> 18.486729 | E27: =MEDIAN(D18:G18) -> 19.016552 | F27: =QUARTILE(D18:G18,3) -> 19.210355 | G27: =MAX(D18:G18) -> 19.689265 | H27: =(D6*D18+E6*E18+F6*F18+G6*G18)/(D6+E6+F6+G6) -> 18.312361
A28: EV/Sales | C28: =MIN(D19:G19) -> 2.7567903 | D28: =QUARTILE(D19:G19,1) -> 2.7722109 | E28: =MEDIAN(D19:G19) -> 3.0393563 | F28: =QUARTILE(D19:G19,3) -> 3.4379908 | G28: =MAX(D19:G19) -> 3.8478786 | H28: =(D6*D19+E6*E19+F6*F19+G6*G19)/(D6+E6+F6+G6) -> 3.2188942
A29: P/E (normalised) | C29: =MIN(D20:G20) -> 35.804395 | D29: =QUARTILE(D20:G20,1) -> 41.840391 | E29: =MEDIAN(D20:G20) -> 49.00438 | F29: =QUARTILE(D20:G20,3) -> 71.352778 | G29: =MAX(D20:G20) -> 122.942 | H29: =(D6*D20+E6*E20+F6*F20+G6*G20)/(D6+E6+F6+G6) -> 53.201604
A30: P/B | C30: =MIN(D21:G21) -> 1.6697468 | D30: =QUARTILE(D21:G21,1) -> 2.438255 | E30: =MEDIAN(D21:G21) -> 3.1919944 | F30: =QUARTILE(D21:G21,3) -> 4.1769494 | G30: =MAX(D21:G21) -> 5.6391042 | H30: =(D6*D21+E6*E21+F6*F21+G6*G21)/(D6+E6+F6+G6) -> 3.0917981
A32: Implied value of UltraTech Cement
A33: Basis | C33: Peer P25 | D33: Peer median | E33: Peer P75 | F33: Mcap weighted
A34: Peer EV/EBITDA applied | C34: =D27 -> 18.486729 | D34: =E27 -> 19.016552 | E34: =F27 -> 19.210355 | F34: =H27 -> 18.312361
A35: Implied equity value | C35: =C34*C9-C7-C8 -> 275954.15 | D35: =D34*C9-C7-C8 -> 284334.17 | E35: =E34*C9-C7-C8 -> 287399.49 | F35: =F34*C9-C7-C8 -> 273196.24
A36: Implied price per share (EV/EBITDA) | C36: =C35/C13 -> 9364.5361 | D36: =D35/C13 -> 9648.9131 | E36: =E35/C13 -> 9752.935 | F36: =F35/C13 -> 9270.9461
A38: Peer P/E applied | C38: =D29 -> 41.840391 | D38: =E29 -> 49.00438 | E38: =F29 -> 71.352778 | F38: =H29 -> 53.201604
A39: Implied equity value | C39: =C38*C11 -> 324748.38 | D39: =D38*C11 -> 380352.4 | E39: =E38*C11 -> 553811.72 | F39: =F38*C11 -> 412929.57
A40: Implied price per share (P/E) | C40: =C39/C13 -> 11020.374 | D40: =D39/C13 -> 12907.303 | E40: =E39/C13 -> 18793.665 | F40: =F39/C13 -> 14012.813
A42: Peer P/B applied | C42: =D30 -> 2.438255 | D42: =E30 -> 3.1919944 | E42: =F30 -> 4.1769494 | F42: =H30 -> 3.0917981
A43: Implied equity value | C43: =C42*C12 -> 182048.33 | D43: =D42*C12 -> 238325.06 | E43: =E42*C12 -> 311865.12 | F43: =F42*C12 -> 230844.06
A44: Implied price per share (P/B) | C44: =C43/C13 -> 6177.8313 | D44: =D43/C13 -> 8087.5886 | E44: =E43/C13 -> 10583.179 | F44: =F43/C13 -> 7833.72
A46: Where the DCF sits against the peer set
A47: Approach | C47: Value per share | D47: Gap to market
A48: DCF (this workbook, all five methods) | C48: 4747.5637 | D48: =IFERROR(C48/$C$52-1,"") -> -0.55815984
A49: Relative: peer median EV/EBITDA | C49: =D36 -> 9648.9131 | D49: =IFERROR(C49/$C$52-1,"") -> -0.10200734
A50: Relative: peer median P/E | C50: =D40 -> 12907.303 | D50: =IFERROR(C50/$C$52-1,"") -> 0.20124027
A51: Relative: peer median P/B | C51: =D44 -> 8087.5886 | D51: =IFERROR(C51/$C$52-1,"") -> -0.24731469
A52: Market price | C52: 10744.98
A54: DCF implied EV/EBITDA | C54: =(C48*C13+C7+C8)/C9 -> 9.8848477 | E54: Compare with the peer median above. This is the multiplier consistency check.
A56: CAUTION ON THE P/B ROW ABOVE. Applying a peer P/B to a company whose ROE differs sharply from the peer set is not a valuation, it is a category error. Across these five companies P/B tracks ROE closely: JK Cement at 5.6x on a 16% ROE, Shree at 3.7x on 7%, Ambuja at 1.7x on 4%. A company earning a lower return SHOULD trade at a lower multiple of book. The implied P/B values are shown for completeness and because the pairing itself is the diagnostic, but they should NOT be carried into a conclusion without adjusting for the ROE difference.
A61: The DCF value of about Rs 4,747 implies an EV/EBITDA far below the peer median. UltraTech trades ABOVE its peers at 21.1x against a median near 19x, so relative valuation and the DCF point the SAME way here: expensive. The two relative measures bracket the market price, which is the honest read, and the P/E figure is pulled upward by Ramco at 123x, whose normalised earnings are depressed by exceptional gains.
A65: READ THIS ALONGSIDE THE DCF, NOT INSTEAD OF IT. A multiple tells you where a company sits among its peers. It cannot tell you whether the peers are right. The entire Indian cement set trades at roughly 19x EBITDA and 47x normalised earnings while this workbook's DCF implies about 6x. Either the sector is richly rated or the model is too pessimistic on a cyclical recovery. Take a position on that in the report rather than averaging the two approaches together.
A70: BASIS WARNING. Ambuja is carried on a CONSOLIDATED basis and every other company on a standalone basis. This is necessary, not sloppy: Ambuja held 50.05% of the listed ACC plus majority stakes in Orient, Sanghi and Penna at the valuation date, so its market capitalisation prices the whole group while its standalone EBITDA excludes ACC entirely. Dividing one by the other printed 35x. On a consolidated basis with the non-controlling interest added to enterprise value it is 17x. For the other four companies standalone and consolidated differ by under 10%, so the problem does not arise. Ambuja is also one quarter behind the others, on FY2025-26 rather than TTM to June 2026, because its consolidated Q1 filing is a scanned image from which finance costs could not be read reliably and guessing them was rejected.
A73: THE MULTIPLE VERSUS THE RETURN: why a lower EV/EBITDA does not mean cheap
A74: This block answers the obvious objection to a SELL on Ambuja: it trades BELOW the peer median on EV/EBITDA, so how can it be expensive? The answer is that EV/EBITDA measures what you pay for a stream of operating profit and says nothing about how much CAPITAL was consumed to produce it. Ambuja bought its EBITDA and capitalised Rs 22,979 crore of goodwill doing so; UltraTech largely built its own. The multiple cannot see that difference. Enterprise value to invested capital can, and so can price to book.
A78: Measure | C78: UltraTech | D78: Ambuja | F78: Ambuja as a percent of UltraTech
A79: Enterprise value (Rs cr) | C79: 333077 | D79: 111501 | F79: =D79/C79 -> 0.33476043
A80: Invested capital (Rs cr) | C80: 86090 | D80: 67208 | F80: =D80/C80 -> 0.78067139
A81: EBITDA (Rs cr) | C81: 15439 | D81: 6559 | F81: =D81/C81 -> 0.42483321
A82: EV / EBITDA | C82: =C79/C81 -> 21.573742 | D82: =D79/D81 -> 16.999695 | F82: =D82/C82 -> 0.78798083
A83: EV / Invested capital | C83: =C79/C80 -> 3.8689395 | D83: =D79/D80 -> 1.6590436 | F83: =D83/C83 -> 0.42881094
A84: ROIC today | C84: 0.108 | D84: 0.033 | F84: =D84/C84 -> 0.30555556
A85: ROIC, our terminal year | C85: 0.158 | D85: 0.09 | F85: =D85/C85 -> 0.56962025
A86: Return on equity | C86: 0.104 | D86: 0.038 | F86: =D86/C86 -> 0.36538462
A87: Price to book | C87: 4.24 | D87: 1.67 | F87: =D87/C87 -> 0.39386792
A89: READ THE THREE HIGHLIGHTED ROWS TOGETHER. Ambuja is priced at about 79% of UltraTech's EV/EBITDA, so it looks roughly a fifth cheaper. It is priced at about 43% of UltraTech's enterprise value per rupee of invested capital. But it earns only about 31% of UltraTech's return on that capital. The discount is nowhere near large enough for the gap in returns, and that is the whole answer: the cheaper stock is the larger SELL.
A93: What return on capital each company's price requires
A94: Steady state identity: EV/IC = (ROIC - g) / (WACC - g) | C94: UltraTech | D94: Ambuja | F94: Verdict
A95: Terminal growth g | C95: 0.0699 | D95: 0.0699
A96: WACC | C96: 0.11331 | D96: 0.11375
A97: ROIC today | C97: 0.108 | D97: 0.033
A98: ROIC, our terminal year | C98: 0.158 | D98: 0.09
A99: JUSTIFIED EV/IC on today's ROIC | C99: =(C97-C95)/(C96-C95) -> 0.87767795 | D99: =(D97-D95)/(D96-D95) -> -0.84150513
A100: JUSTIFIED EV/IC on terminal ROIC | C100: =(C98-C95)/(C96-C95) -> 2.0294863 | D100: =(D98-D95)/(D96-D95) -> 0.45838084
A101: ACTUAL EV/IC at the traded price | C101: =C79/C80 -> 3.8689395 | D101: =D79/D80 -> 1.6590436
A102: Actual as a multiple of justified (terminal ROIC) | C102: =C101/C100 -> 1.9063639 | D102: =D101/D100 -> 3.6193562
A104: THE DECISIVE NUMBERS. On our terminal returns, UltraTech's price is about 1.9 times what its return on capital justifies and Ambuja's is about 3.6 times. On TODAY'S return on capital Ambuja's justified multiple is NEGATIVE: at a 3.3% return and 7.0% growth, every rupee reinvested destroys value, so no positive multiple of invested capital is warranted at all. This is the sharpest statement of the investment case and it explains why the two SELL recommendations are consistent rather than contradictory. We are not claiming Ambuja is mispriced against its sector. We are claiming the SECTOR is mispriced against the cash it generates, and Ambuja is the member with the weakest returns. Note that UltraTech is itself one of the peers in the median: our own model says it is 51% overvalued, so a peer median built from such companies cannot be used to argue that anything is cheap.

Sheet UTCL-Dashboard
A1: Consistency Dashboard
A2: Audit checklist run before submission. PASS, PARTIAL and FAIL recorded honestly; a PARTIAL is a known gap, not a rounding issue.
A4: The five consistencies
A5: # | B5: Consistency | C5: Verdict | D5: Evidence and remaining gap
A6: 1 | B6: Assumptions | C6: PASS | D6: Growth requires reinvestment throughout. Volume is capacity times utilisation, so growth is tied to physical assets. Capex is an explicit input, never held flat while sales grow. Terminal year forced to steady state with reinvestment = g x invested capital, which is what makes EVA reconcile.
A7: 2 | B7: Risk | C7: PASS | D7: Firm flows at firm rates, equity flows at the cost of equity: FCFF at WACC, CCF and APV at the unlevered rho, FCFE at Ke, EVA at WACC. Debt policy is stated as constant D/V with continuous rebalancing (Harris-Pringle, Case 2), so the interest tax shield is discounted at rho and beta is unlevered as bL x E/(D+E). The same case is used in the unlever, the relever and the shield everywhere.
A8: 3 | B8: Asset | C8: PASS | D8: Other income is excluded from EBITDA, so surplus cash and investments are non-operating and added back once at the bridge. The unlevered beta used is Damodaran's CASH CORRECTED 0.90, not the raw 0.86, precisely because cash is added separately; using the raw figure would count cash twice. The India Cements stake is now isolated on the Assumptions sheet: 23,241,683 shares at a carrying value of Rs 8,970.17 crore, with a market price cell that overrides book once sourced from NSE. Until then the model falls back to carrying value and the Source Log flags it as an open item. Sensitivity: each Rs 100 on the ICEM price moves UltraTech by about Rs 79 per share.
A9: 4 | B9: Liability | C9: PASS | D9: Loan funds of 19,617 and lease liabilities of 863 are both inside the WACC weights and both subtracted in the bridge. Deferred tax liabilities of 8,506 are in neither, treated as non interest bearing, and are excluded from invested capital on both sides. Nothing appears twice and nothing is missing.
A10: 5 | B10: Multiplier | C10: PARTIAL | D10: The terminal EV/EBITDA implied by g = 5% and WACC = 11.0% is about 6.8x against peers at 19.0x to 19.7x, so the two do not bracket cleanly. The reverse cross-check is now built on the FCFF sheet and it sharpens the question rather than dissolving it: a 19.05x exit multiple requires terminal growth of 9.8% against a WACC of 11.0% and nominal GDP of 10.8%, meaning growth at roughly 91% of the whole economy in perpetuity from a company whose realisation has compounded at 2.0% over ten years. The model takes the position that the peer multiple is the implausible end of the range, and says so. Upgraded from FAIL because a defensible position is now recorded and evidenced; it remains PARTIAL because the gap is real.
A12: Audit checklist, mohanty_method.md section 13
A13: # | B13: Check | C13: Verdict | D13: Evidence and remaining gap
A14: 1 | B14: FCF and FCFE reconcile within 0.5% | C14: PASS | D14: All five methods return Rs 4,747.5637 per share. Maximum difference across methods is zero to six decimal places. See the Reconciliation sheet.
A15: 2 | B15: WACC recomputes; weights market value or converged; circularity documented | C15: PASS | D15: Weights are market value based, and the tension is disclosed: the model uses the price it is testing. The iterative alternative per SSRN 413240 is solved on the Cost-of-Capital sheet and converges to Rs 4,701, a 1.0% difference, because a rising D/V and a rising relevered beta almost exactly offset.
A16: 3 | B16: Debt grows at g where constant WACC and D/E are assumed | C16: PASS | D16: Debt is set to D/V times enterprise value at every date, so it grows with the firm. The net new borrowing line is visible on the FCFE sheet, which is the reconciliation Mohanty tests for.
A17: 4 | B17: Cash and investments: one treatment in NOPAT, beta and bridge | C17: PASS | D17: Consistent in flows, beta and bridge. The listed India Cements stake is isolated with a market price override; blank means book, and the Source Log carries it as an open item rather than an unstated approximation.
A18: 5 | B18: Every liability in the WACC is subtracted in the bridge | C18: PASS | D18: Verified line by line. Debt and leases in both, deferred tax in neither.
A19: 6 | B19: Terminal: g < WACC, g built multiplicatively, reinvestment = g/RONIC, exit multiple sane | C19: PARTIAL | D19: g = 5% is comfortably below WACC = 11.0%, and reinvestment = g/RONIC = 32.2% holds exactly. g is now BUILT multiplicatively on the Assumptions sheet: (1+6.5% real)(1+4.0% inflation)-1 = 10.76% nominal, taken at 46.5% to give 5.0%, with the fraction as the editable driver rather than g itself. Remaining item is the implied exit multiple, see multiplier consistency above, where a position is now recorded.
A20: 7 | B20: Tax: marginal statutory in NOPAT and Kd; cash rate divergence modelled | C20: PASS | D20: Section 115BAA at 25.168% used in NOPAT and in after tax Kd. Checked against the reported effective rate: FY2025-26 tax of 2,622 on PBT after exceptionals of 10,027 is 26.1%, materially in line with statutory, so no migration path is required. This was verified, not assumed.
A21: 8 | B21: No DDT adjustment on post FY2020 flows | C21: PASS | D21: None applied anywhere. DDT was abolished with effect from FY2020-21.
A22: 9 | B22: Every input traces to the Source Log; zero aggregator numbers | C22: PARTIAL | D22: A Source Log sheet now exists and every input traces to a row on it. No aggregator data anywhere: no moneycontrol, screener.in or Yahoo. Financials come from the company's own integrated report, market data from NSE and the company's shareholder information section, beta and equity risk premium from Damodaran. THREE GAPS: the Indian 10 year G-Sec yield is still a placeholder and must come from RBI or FBIL; standalone capacity of 172.5 Mn.T is derived, not disclosed; and the capacity schedule, utilisation and capex guidance reach this model through a broker note relaying an earnings call, so they must be re-sourced from the call transcript itself.
A23: 10 | B23: Sensitivity tables live linked | C23: PASS | D23: The WACC by terminal growth table on the Sensitivity sheet recomputes from the forecast cash flows; it is not pasted values. Change any driver and the grid moves. The beta table is live. The three column scenario table is documented rather than live, by design.
A25: Workflow phases not yet complete
B26: Phase 9, relative valuation | D26: The DCF implied EV/EBITDA and P/E are now carried into the comps workbook Output sheet and shown beside the peer median and the traded multiple, which is the exhibit the method asks for.
B27: Phase 10, catalysts | D27: Written into the Summary conclusion. A gap this size cannot be presented as mispricing without naming what would force a reprice.
B28: Two company structure | D28: Both UltraTech and Ambuja are single product cement producers, which makes both the EASY pick. The course pairs one easy with one difficult company. Consider whether the second name should be replaced with a genuinely hard one, a bank, an NBFC or a multi segment platform, or be prepared to argue that Ambuja's amalgamation accounting and tax distortions make it the difficult case.
A31: The 7 Golden Sanity Checks (Mohanty, Appendix 5A)
A32: # | B32: Check | C32: Verdict | D32: Evidence
A33: 1 | B33: Revenue growth plausible against GDP and TAM | C33: PASS | D33: Revenue CAGR of 8.6% against nominal GDP of 10.76% and industry demand growth of 6 to 7%. We forecast the company growing slightly ahead of industry volume but below nominal GDP, which is the right shape for a mature share leader. The ten year actual of 14.7% was inflated by four acquisitions and is deliberately not extrapolated.
A34: 2 | B34: Physical capacity supports projected volume | C34: PASS | D34: Volume is BUILT as capacity times utilisation rather than assumed, so the check is structural rather than after the fact. Capacity rises 186 to 220 Mn.T in line with announced expansion; utilisation rises 82.0% to 86.0%. Peak forecast volume of 189.2 Mn.T sits inside capacity of 220 Mn.T at all times.
A35: 3 | B35: Capex is sufficient to build the projected capacity | C35: PARTIAL | D35: Total capex of Rs 45,000 cr less maintenance of Rs 23,676 cr leaves growth capex of Rs 21,324 cr against capacity addition of 47.5 Mn.T, or about Rs 4,489 per tonne. Indian brownfield cement capacity typically costs Rs 5,000 to 7,000 per tonne. Our capex is therefore LIGHT relative to the capacity we assume, by perhaps Rs 3,000 to 6,000 cr over five years. Correcting it would LOWER our value further, so the direction is against us and the SELL is unaffected, but the inconsistency is real and is recorded rather than hidden.
A36: 4 | B36: Margin expansion realism | C36: PASS | D36: EBITDA margin rises 18.8% to 21.0%. That is above the ten year average of roughly 19 to 21% but below the 25.4% peak of FY2020-21, which was a fuel cost windfall. Management has guided a Rs 300 per tonne cost saving and we take about two thirds of it. No unprecedented margin is assumed.
A37: 5 | B37: Working capital sanity | C37: PASS | D37: Net working capital held at minus 3.7% of revenue, which is the FY2025-26 actual and close to the ten year average. Cash is not manufactured by shrinking working capital: the ratio is flat across the forecast, contributing only Rs 300 to 400 cr a year.
A38: 6 | B38: Terminal ROIC fades toward WACC | C38: FAIL | D38: TERMINAL ROIC OF 15.5% AGAINST A WACC OF 11.33% IS A PERMANENT SPREAD OF 4.19 PERCENTAGE POINTS IN PERPETUITY. That assumes UltraTech earns super normal returns forever, which contradicts competitive convergence and is exactly what this check exists to catch. The spread is also inconsistent with the company's own record: realised ROIC has FALLEN from 14.5% to 10.8% over four years. Fading terminal ROIC toward WACC would reduce our value materially. We have not done so, which means our valuation is if anything too GENEROUS and the SELL recommendation is conservative. This is the single most important self criticism in the model.
A39: 7 | B39: Terminal value dominance | C39: PASS | D39: Terminal value is 76% of enterprise value, below the 80 to 90% threshold at which this check demands scrutiny. It is nonetheless high and reflects the thin free cash flow of the explicit period.
A41: Applied from Prof. Mohanty's own audit framework, Appendix 5A of Book 29. Two checks are recorded as less than a full pass and both are stated in the direction that is against us: the capex to capacity check suggests our capital spending may be LIGHT, and the terminal ROIC fade check finds a permanent 4.19 point spread over the cost of capital that competitive convergence would erode. Correcting either would LOWER our valuation, which means the SELL recommendation is conservative rather than aggressive.

Sheet UTCL-Summary
A1: UltraTech Cement Ltd: Valuation Summary
A2: Standalone. Rs crore and Rs per share. Valuation date 31 March 2026.
A4: Market
A5: Market price per share (30-Mar-2026) | B5: ='UTCL-Assumptions'!$B$6 -> 10745
A6: Market capitalisation | B6: ='UTCL-Assumptions'!$B$7 -> 316633
A7: Shares outstanding (crore) | B7: ='UTCL-Assumptions'!$B$5 -> 29.468
A9: Discounted cash flow methods
A10: Method | B10: Discount rate | C10: Rate | D10: Value per share | E10: Upside / (downside)
A11: FCFF | B11: WACC | C11: ='UTCL-Cost of Capital'!$B$16 -> 0.11331182 | D11: ='UTCL-FCFF valuation'!C15 -> 5148.1806 | E11: =IFERROR(D11/$B$5-1,"") -> -0.52087663
A12: CCF | B12: Unlevered rho | C12: ='UTCL-Cost of Capital'!$B$17 -> 0.11458699 | D12: ='UTCL-CCF valuation'!C16 -> 5148.1806 | E12: =IFERROR(D12/$B$5-1,"") -> -0.52087663
A13: APV | B13: Unlevered rho | C13: ='UTCL-Cost of Capital'!$B$17 -> 0.11458699 | D13: ='UTCL-APV valuation'!C16 -> 5148.1806 | E13: =IFERROR(D13/$B$5-1,"") -> -0.52087663
A14: FCFE | B14: Cost of equity | C14: ='UTCL-Cost of Capital'!$B$11 -> 0.11660418 | D14: ='UTCL-FCFE valuation'!C17 -> 5148.1806 | E14: =IFERROR(D14/$B$5-1,"") -> -0.52087663
A15: EVA | B15: WACC | C15: ='UTCL-Cost of Capital'!$B$16 -> 0.11331182 | D15: ='UTCL-EVA'!C15 -> 5148.1806 | E15: =IFERROR(D15/$B$5-1,"") -> -0.52087663
A16: All five methods (must be identical) | D16: =IF(MAX(D11:D15)-MIN(D11:D15)<0.01,D11,"CHECK RECONCILIATION") -> 5148.1806
A18: What the market price is implying: read this before concluding anything
A19: Market enterprise value | B19: =$B$6+'UTCL-Assumptions'!$B$46+'UTCL-Assumptions'!$B$47-'UTCL-Assumptions'!$B$39-'UTCL-Assumptions'!$B$45 -> 332264.23
A20: Model enterprise value of operations | B20: ='UTCL-FCFF valuation'!C9 -> 171426.72
A21: Market EV / FY2025-26 EBITDA | B21: =$B$19/'UTCL-Source Data'!L5 -> 21.521098
A22: Model EV / FY2025-26 EBITDA | B22: =$B$20/'UTCL-Source Data'!L5 -> 11.103486
A23: Model implied terminal EV/EBITDA | B23: ='UTCL-FCFF valuation'!C17 -> 7.6887195
A24: Terminal value as percent of enterprise value | B24: ='UTCL-FCFF valuation'!C16 -> 0.79051064
A26: The gap between the market EV/EBITDA and the model EV/EBITDA is the single most useful diagnostic in this workbook. A large gap means either the market disagrees with the forecast, or the cost of capital is wrong, or the terminal assumptions are wrong. Given that the risk free rate, the equity risk premium and beta are still placeholders, the cost of capital is the first place to look.
A30: Football field
B31: Low | C31: High | D31: Band width
A32: DCF, all five methods | B32: =MIN(D11:D15) -> 5148.1806 | C32: =MAX(D11:D15) -> 5148.1806 | D32: =C32-B32 -> 0
A33: Relative valuation (peer median, TTM) | B33: 9667.25 | C33: 14264.33 | D33: =C33-B33 -> 4597.08 | F33: From the comps workbook: EV/EBITDA at the 19.05x peer median gives 9,667; P/E at 54.16x gives 14,264.
A34: Market price | B34: =$B$5 -> 10745
A36: Conclusion
A37: The five methods reconcile exactly, so the model is internally consistent. What it is not is reconcilable with the market price, and that divergence is the finding rather than a defect to be tuned away. The base case gives about Rs 4,750 per share against a traded Rs 10,745. Three tests say the discount rate is not the explanation. Replacing an invented cost of capital with Damodaran's sourced beta and India equity risk premium moved the answer by only a few hundred rupees. A reverse DCF shows the market price requires a WACC near 7.3%, which for a company 94% funded by equity implies an equity risk premium close to zero. And holding the cost of capital while solving on growth instead requires roughly 29% revenue growth every year for five years, against a ten year actual of 14.7% that was itself inflated by four large acquisitions. The forecast is built the way the industry is actually run. Volume is capacity times utilisation rather than a growth rate, because UltraTech has already built the capacity and is filling only about 82% of it, so several years of growth require little new capital. EBITDA is volume times EBITDA per tonne, the metric management steers by. Capex is an explicit input anchored to management's own guidance of roughly Rs 10,000 crore a year. An earlier version of this model scaled fixed assets to revenue, which charged the company a second time for capacity it had already paid for and understated value by roughly a third. That correction is the single largest revision made during the build. What still constrains the value is returns. ROIC rises from 12.0% to 15.2% across the forecast against a WACC of 11.0%, so the company does create economic value, but not enough to support 3.7 times invested capital and 20.7 times EBITDA. The history explains why. Volume has compounded at 12.5% over ten years while realisation managed only 2.0% and fell 6.1% in FY2024-25. UltraTech buys growth with capital rather than earning it through price. Reported ROIC slid from 14.5% in FY2021-22 to 10.8% in FY2025-26, and the acquired assets are the visible drag: management disclosed core operating assets at about Rs 966 per tonne of EBITDA against India Cements at Rs 386 and Kesoram at Rs 755. The bull case is therefore specific and testable: that integration lifts the blended EBITDA per tonne materially, that utilisation climbs as recently added capacity ramps, and that cement pricing recovers from a cyclical trough. The Sensitivity sheet prices that case. Even adopting a sell side house's own operating trajectory in full, which has EBITDA per tonne rising 54% in three years, the discounted cash flow reaches only about Rs 6,280, still 42% below the traded price. No assumption set grounded in this company's own ten year record closes the gap. Relative valuation says something different and should not be averaged in. Against peers UltraTech is fairly priced, 10% below on EV/EBITDA and 33% above on P/E. The DCF says the peers and UltraTech together look expensive against cash flows. Both can be true, because they answer different questions. The honest conclusion is that UltraTech is reasonably valued relative to Indian cement and expensive relative to the cash it generates, and that anyone paying the current price is underwriting a return on capital this company has not earned since FY2021-22. Catalysts, because a gap this size cannot be presented as mispricing without naming what would close it. On the bull side: completion of the India Cements and Kesoram brand and cost integration, which management expects to lift those assets from Rs 386 and Rs 755 per tonne of EBITDA toward the Rs 966 the core assets already earn; quarterly EBITDA per tonne prints that confirm or refute the guided Rs 300 per tonne cost saving; the green power share moving from 42% toward 65%; and a cement price recovery after realisation fell 6.1% in FY2024-25. On the bear side: capacity additions across the industry outrunning demand and holding utilisation near 80%, which would keep ROIC pinned near the cost of capital. The single most informative disclosure to watch is blended EBITDA per tonne, because it is the one number that separates the DCF from the market price. If it reaches the sell side's Rs 1,423 by FY2027-28 the gap narrows materially; if it stalls near Rs 1,200 the DCF view strengthens. Caveats, stated plainly rather than buried. The Indian 10 year G-Sec yield is still a placeholder and must come from RBI. Standalone capacity of 172.5 Mn.T is derived, not disclosed, and should be checked against the company's investor presentation. The capacity schedule, utilisation and capex guidance reach this model through a broker note relaying an earnings call, so they should be re-sourced from the call itself. The explicit forecast runs five years, which is short for a company mid expansion. And the model implied terminal EV/EBITDA sits far below anything cement has traded at, which is the multiplier consistency check refusing to stay quiet, and it is recorded as a FAIL on the Consistency Dashboard rather than smoothed over. Finally, the terminal growth rate of 5% was chosen rather than built multiplicatively from real GDP and inflation as the method requires: RBI's 4% inflation target with 6.5% real growth implies 10.76% nominal, so 5% embeds a deliberate view that a mature cement producer grows well below the economy. Justify that in a paragraph.
